Workbook

Sheet Dashboard
A1: GreetHub - Dashboard
A2: ="Scenario: "&Scenarios!B3&" (change on Scenarios sheet)" -> Scenario: Base (change on Scenarios sheet)
A3: Core KPIs below exclude the Kiosk and Agent programs. Side-by-side four-scenario comparison starts at row 52.
A4: KPI | B4: Value
A5: Break-even month (sustained) | B5: =Scenarios!$B$16 -> Not within 36 mo
A6: Cash payback month | B6: =Scenarios!$B$18 -> Not within 36 mo
A7: Month 12 net revenue | B7: =Scenarios!$B$19 -> 5358.0897
A8: Month 12 net income | B8: =Scenarios!$B$20 -> -5222.6607
A9: Month 36 net revenue | B9: =Scenarios!$B$21 -> 10226.959
A10: Month 36 net income | B10: =Scenarios!$B$22 -> -3115.9759
A11: Cash balance, month 36 | B11: =Scenarios!$B$27 -> -267461.65
A12: Peak funding need | B12: =Scenarios!$B$29 -> 297461.65
A13: Blended CAC | B13: =Scenarios!$B$31 -> 39.57446
A14: LTV per customer | B14: =Scenarios!$B$33 -> 25.834126
A15: LTV : blended CAC | B15: =Scenarios!$B$34 -> 0.65279796
A16: Orders, 36 months | B16: =Scenarios!$B$30 -> 9471.4107
A18: Annual summary | B18: Year 1 | C18: Year 2 | D18: Year 3
A19: Visits | B19: =Forecast!AO30 -> 156723.25 | C19: =Forecast!AP30 -> 192681.08 | D19: =Forecast!AQ30 -> 216934.53
A20: New-customer orders | B20: =Forecast!AO40 -> 1716.0527 | C20: =Forecast!AP40 -> 2130.2096 | D20: =Forecast!AQ40 -> 2412.2928
A21: Total orders | B21: =Forecast!AO43 -> 2007.4148 | C21: =Forecast!AP43 -> 3155.7292 | D21: =Forecast!AQ43 -> 4308.2667
A22: Net revenue | B22: =Forecast!AO60 -> 57322.61 | C22: =Forecast!AP60 -> 90113.233 | D22: =Forecast!AQ60 -> 123024.45
A23: Gross profit | B23: =Forecast!AO71 -> 27389.167 | C23: =Forecast!AP71 -> 44123.404 | D23: =Forecast!AQ71 -> 61155.744
A24: Marketing | B24: =Forecast!AO74 -> 82559.645 | C24: =Forecast!AP74 -> 82559.645 | D24: =Forecast!AQ74 -> 82559.645
A25: Operating costs | B25: =Forecast!AO75 -> 15007.28 | C25: =Forecast!AP75 -> 19251.011 | D25: =Forecast!AQ75 -> 20586.74
A26: Net income | B26: =Forecast!AO77 -> -197783.76 | C26: =Forecast!AP77 -> -57687.253 | D26: =Forecast!AQ77 -> -41990.642
A27: Ending cash | B27: =Forecast!AO80 -> -167783.76 | C27: =Forecast!AP80 -> -225471.01 | D27: =Forecast!AQ80 -> -267461.65
A29: Contribution margin per item | B29: CM $ | C29: CM %
A30: ='Unit Economics'!A5 -> Card - Digital e-card/PDF | B30: ='Unit Economics'!N5 -> 3.1930555 | C30: ='Unit Economics'!O5 -> 0.82501499
A31: ='Unit Economics'!A6 -> Card - Printed 5x7 folded | B31: ='Unit Economics'!N6 -> 4.4452865 | C31: ='Unit Economics'!O6 -> 0.4290581
A32: ='Unit Economics'!A7 -> Book - Digital flipbook/PDF | B32: ='Unit Economics'!N7 -> 17.176965 | C32: ='Unit Economics'!O7 -> 0.88585347
A33: ='Unit Economics'!A8 -> Book - Hardcover 8.5x8.5, 24pp | B33: ='Unit Economics'!N8 -> 21.418305 | C33: ='Unit Economics'!O8 -> 0.49741451
A34: ='Unit Economics'!A9 -> Book - Hardcover 8.5x8.5, 32pp | B34: ='Unit Economics'!N9 -> 27.836268 | C34: ='Unit Economics'!O9 -> 0.52760903
A52: Scenario comparison (36 months) | B52: Core only | C52: Core + Agent | D52: Core + Kiosk | E52: Everything
A53: Cumulative cash, month 12 | B53: =Compare!B52 -> -167783.76 | C53: =Compare!C52 -> -243297.94 | D53: =Compare!D52 -> -202398.76 | E53: =Compare!E52 -> -277912.94
A54: Cumulative cash, month 24 | B54: =Compare!B53 -> -225471.01 | C54: =Compare!C53 -> -313435.37 | D54: =Compare!D53 -> -260086.01 | E54: =Compare!E53 -> -348050.37
A55: Cumulative cash, month 36 | B55: =Compare!B54 -> -267461.65 | C55: =Compare!C54 -> -357652.27 | D55: =Compare!D54 -> -302076.65 | E55: =Compare!E54 -> -392267.27
A56: Peak funding need | B56: =Compare!B56 -> 297461.65 | C56: =Compare!C56 -> 387652.27 | D56: =Compare!D56 -> 332076.65 | E56: =Compare!E56 -> 422267.27
A57: Break-even month (sustained, net income) | B57: =Compare!B57 -> Not within 36 mo | C57: =Compare!C57 -> Not within 36 mo | D57: =Compare!D57 -> Not within 36 mo | E57: =Compare!E57 -> Not within 36 mo
A58: Total R&D spend | B58: =Compare!B58 -> 107100 | C58: =Compare!C58 -> 190800 | D58: =Compare!D58 -> 141715 | E58: =Compare!E58 -> 225415
A59: Cumulative net income | B59: =Compare!B59 -> -297461.65 | C59: =Compare!C59 -> -387652.27 | D59: =Compare!D59 -> -332076.65 | E59: =Compare!E59 -> -422267.27
A60: ="Case: "&Scenarios!B3&" | Market-adjusted: "&IF(Scenarios!B44=1,"ON","off") -> Case: Base | Market-adjusted: off

Sheet Inputs
A1: GreetHub - Inputs (all business assumptions live here)
A2: Blue = input you can edit. Black = formula. Yellow fill = slot reserved for CMO/CTO data. Status: SOURCED / ESTIMATE / GUESS. Printer prices are ESTIMATES to verify against live Lulu / Prodigi / Gelato price sheets.
A3: Legend: | B3: Input | C3: Formula | D3: CMO / CTO data
A5: 1. General
A6: Assumption | B6: Value | C6: Unit | D6: Status | E6: Sensible range | F6: Notes / source
A7: Launch month (month 1) | B7: 46327 | C7: date | D7: SOURCED | E7: any | F7: CMO launch assumption: November 2026. Drives seasonality alignment.
A8: Opening cash (founder capital) | B8: 30000 | C8: $ | D8: GUESS | E8: $10k-100k | F8: Starting cash balance; also sets funding need.
A9: Items per paid order | B9: 1.15 | C9: items | D9: GUESS | E9: 1.0-1.5 | F9: Card+book bundles; Stripe $0.30 is per order, not per item.
A10: 2. Funnel (visitor -> sign-up -> creator start -> purchase)
A11: Assumption | B11: Value | C11: Unit | D11: Status | E11: Sensible range | F11: Notes / source
A12: Organic/referral visitor -> sign-up rate | B12: 0.07 | C12: % of visits | D12: GUESS | E12: 3%-12% | F12: Paid channels use per-channel CMO rates in section 7. Matches CMO range (4-9%).
A13: Sign-up -> creator start rate (all sources) | B13: 0.6 | C13: % of sign-ups | D13: GUESS | E13: 40%-80% | F13: Sign-ups who begin a brief; drives token cost of unpaid starts.
A14: Organic: creator start -> purchase rate | B14: 0.25 | C14: % of starts | D14: GUESS | E14: 12%-40% | F14: 0.60 x 0.25 = 15% sign-up -> purchase, in line with CMO channel rates (9-20%). Paid channels use CMO signup->purchase directly.
A15: Share of visitors who run a free guest preview | B15: 0.15 | C15: % of visits | D15: GUESS | E15: 5%-30% | F15: Guest previews cost tokens and earn no revenue (cost line in Forecast).
A16: Seasonality sensitivity of purchase conversion | B16: 0.5 | C16: 0-1 | D16: GUESS | E16: 0-1 | F16: 0 = season only changes traffic; 1 = conversion moves fully with season index.
A17: Token cost incurred before an unpaid creator start abandons | B17: 0.35 | C17: % of full cost | D17: ESTIMATE | E17: 20%-60% | F17: The model-sheet approval gate caps waste (PLAN.md).
A18: 3. Traffic
A19: Assumption | B19: Value | C19: Unit | D19: Status | E19: Sensible range | F19: Notes / source
A20: Organic visits, month 1 (before seasonality) | B20: 2000 | C20: visits | D20: GUESS | E20: 500-8,000 | F20: Brand/social/referral at launch.
A21: Organic monthly growth, month 2 | B21: 0.12 | C21: % / mo | D21: GUESS | E21: 5%-20% | F21: Compounds, then decays (next row).
A22: Organic growth decay factor per month | B22: 0.93 | C22: x | D22: GUESS | E22: 0.88-0.98 | F22: growth_t = g x decay^(t-1). 0.93 -> ~5x organic by month 36.
A23: Recipient referral visits per item sold (prior month) | B23: 0.3 | C23: visits/item | D23: GUESS | E23: 0.1-0.8 | F23: Card/book recipients open the 'made with GreetHub' link.
A24: 4. Marketing budget (paid visits = budget / CPC)
A25: Assumption | B25: Value | C25: Unit | D25: Status | E25: Sensible range | F25: Notes / source
A26: Monthly marketing budget, month 1 | B26: =SUM(B57:B62) -> 6500 | C26: $ / mo | D26: CMO PLAN (spend decision; CAC inputs mostly GUESS) | E26: $1k-15k | F26: Sum of CMO channel budgets (section 7), $6.5k/mo = $19.5k per 90 days. Overwrite with a number to test.
A27: Budget monthly growth | B27: 0 | C27: % / mo | D27: GUESS | E27: 0%-10% | F27: Compounds until cap. Growth only pays if contribution per order beats CAC.
A28: Budget cap | B28: 20000 | C28: $ / mo | D28: GUESS | E28: $5k-100k | F28: Ceiling on base monthly budget.
A29: Budget follows season index | B29: 0.5 | C29: 0-1 | D29: GUESS | E29: 0-1 | F29: 1 = budget scales fully with season index.
A30: 5. Repeat, refunds, re-rolls, payments
A31: Assumption | B31: Value | C31: Unit | D31: Status | E31: Sensible range | F31: Notes / source
A32: Repeat orders per existing customer per year | B32: 0.35 | C32: orders/yr | D32: GUESS | E32: 0.15-0.8 | F32: Occasion-driven; applied to cumulative customers.
A33: Customer lifetime used for LTV | B33: 2 | C33: years | D33: GUESS | E33: 1-3 | F33: LTV = contribution per order x (1 + repeat x lifetime).
A34: Re-roll rate, cards (extra renders over base) | B34: 0.2 | C34: % of renders | D34: GUESS (n=10) | E34: 20%-50% | F34: Only 10 first-attempt 2K page renders exist: 5/10 passed QA first time (95% CI 24-76%); 3 of the 5 fails were QA bugs since fixed (Model evals, 2026-10-12). Run 20% and 50%. Now flows through to measured token totals (Model Costs col J).
A35: Re-roll rate, books (extra renders over base) | B35: 0.2 | C35: % of renders | D35: GUESS (n=10) | E35: 20%-50% | F35: Only 10 first-attempt 2K page renders exist: 5/10 passed QA first time (95% CI 24-76%); 3 of the 5 fails were QA bugs since fixed (Model evals, 2026-10-12). Run 20% and 50%. Now flows through to measured token totals (Model Costs col J).
A36: Refund rate (share of revenue refunded) | B36: 0.03 | C36: % of revenue | D36: GUESS | E36: 1%-6% | F36: Token cost is sunk on refund.
A37: Reprint rate (printed items reshipped) | B37: 0.04 | C37: % of printed | D37: GUESS | E37: 2%-8% | F37: Print defects, transit damage. Costs print + shipping again.
A38: Chargeback rate | B38: 0.003 | C38: % of orders | D38: ESTIMATE | E38: 0.1%-1%
A39: Chargeback fee | B39: 15 | C39: $ / dispute | D39: SOURCED | E39: $15 | F39: Stripe dispute fee (US) - verify.
A40: Stripe fee, percentage | B40: 0.029 | C40: % of charge | D40: SOURCED | E40: 2.9% | F40: Owner brief / Stripe standard US card rate.
A41: Stripe fee, fixed | B41: 0.3 | C41: $ / order | D41: SOURCED | E41: $0.30 | F41: Owner brief / Stripe standard US card rate.
A42: OpenRouter credit-purchase fee on token spend | B42: 0.055 | C42: % of tokens | D42: ESTIMATE | E42: 0-8% | F42: OpenRouter charges a fee when buying credits - verify.
A43: Share of printed items where postage fee is charged | B43: 0.9 | C43: % of printed | D43: GUESS | E43: 50%-100% | F43: Rest = free-shipping promos.
A45: 6. SKU table: launch prices, mix, print and shipping costs (ESTIMATES - verify against live printer price sheets)
A46: SKU | B46: Product line | C46: Format | D46: Printed? (1/0) | E46: List price ($) | F46: Postage fee charged ($) | G46: Mix (% of items) | H46: Print cost est. ($) | I46: Shipping cost est. ($) | J46: Fulfilment partner | K46: Pricing reasoning
A47: Card - Digital e-card/PDF | B47: Card | C47: Digital | D47: 0 | E47: 3.99 | F47: 0 | G47: 0.14 | H47: 0 | I47: 0 | J47: None (instant delivery) | K47: Impulse price; near-pure margin, upsell path to print.
A48: Card - Printed 5x7 folded | B48: Card | C48: Printed | D48: 1 | E48: 7.99 | F48: 2.99 | G48: 0.4 | H48: 3.25 | I48: 1.6 | J48: Prodigi / Gelato | K48: Retail premium cards sell $5-8; personalised justifies the top. Postage option $2.99 covers ~2x shipping cost.
A49: Book - Digital flipbook/PDF | B49: Book | C49: Digital | D49: 0 | E49: 19.99 | F49: 0 | G49: 0.08 | H49: 0 | I49: 0 | J49: None (instant delivery) | K49: Anchors printed price at about half.
A50: Book - Hardcover 8.5x8.5, 24pp | B50: Book | C50: Printed | D50: 1 | E50: 39 | F50: 5.99 | G50: 0.15 | H50: 12.5 | I50: 5.5 | J50: Lulu | K50: Personalised hardcovers sell ~$35-45. Lulu 24pp casewrap est ~$12.50.
A51: Book - Hardcover 8.5x8.5, 32pp | B51: Book | C51: Printed | D51: 1 | E51: 49 | F51: 5.99 | G51: 0.23 | H51: 14.5 | I51: 6 | J51: Lulu | K51: +8 pages: +$2 print, +4 renders (~$0.5); +$10 price keeps margin %.
A52: Mix check (must equal 100%) | G52: =SUM(G47:G51) -> 1 | H52: =IF(ABS(G52-1)<0.0001,"OK","MIX MUST SUM TO 100%") -> OK
A53: Print/shipping costs are ESTIMATES from memory of public Lulu / Prodigi / Gelato calculators for US delivery. Verify on live sheets before launch. CMO copy tokens: {card_digital}, {card_printed}, {book_digital}, {book_24}, {book_32} map to the list prices above.
A55: 7. Marketing channels - re-imported 2026-10-12 from docs/cmo/channel-assumptions.csv. Only Google and Meta CPC are sourced (secondary benchmarks); every CTR, conversion rate and other CPC is a GUESS (column K).
A56: Channel | B56: Monthly budget base ($) | C56: CPC low | D56: CPC base | E56: CPC high | F56: CTR base | G56: Visitor -> sign-up | H56: Sign-up -> purchase | I56: CAC base (formula) | J56: Budget share (formula) | K56: Evidence (CMO csv, re-imported 2026-10-12)
A57: meta_instagram_ads | B57: 2000 | C57: 0.55 | D57: 0.85 | E57: 1.4 | F57: 0.011 | G57: 0.07 | H57: 0.14 | I57: =IFERROR(D57/(G57*H57),0) -> 86.734694 | J57: =B57/SUM($B$57:$B$62) -> 0.30769231 | K57: cpc: sourced-secondary (e-commerce Meta CPC about $0.87, MHI dataset via webtonic.io, read 2026-10-11 per docs/market/02); ctr: guess (benchmark median 1.93%, we keep 1.1% for an unknown brand); conversion: guess
A58: pinterest_ads | B58: 800 | C58: 0.3 | D58: 0.55 | E58: 0.95 | F58: 0.006 | G58: 0.06 | H58: 0.15 | I58: =IFERROR(D58/(G58*H58),0) -> 61.111111 | J58: =B58/SUM($B$57:$B$62) -> 0.12307692 | K58: all guess (no benchmark found, docs/market/02 2026-10-11)
A59: google_search | B59: 800 | C59: 2.5 | D59: 4.14 | E59: 5.5 | F59: 0.045 | G59: 0.09 | H59: 0.2 | I59: =IFERROR(D59/(G59*H59),0) -> 230 | J59: =B59/SUM($B$57:$B$62) -> 0.12307692 | K59: cpc: sourced-secondary (Shopping, Collectibles and Gifts $4.14, range $2.50-5.50, WordStream/LocaliQ via wemakeitlab.com, read 2026-10-11 per docs/market/02); ctr and conversion: guess
A60: tiktok_ads | B60: 300 | C60: 0.3 | D60: 0.6 | E60: 1.1 | F60: 0.008 | G60: 0.04 | H60: 0.09 | I60: =IFERROR(D60/(G60*H60),0) -> 166.66667 | J60: =B60/SUM($B$57:$B$62) -> 0.046153846 | K60: all guess (no benchmark found)
A61: creators_affiliate | B61: 1400 | C61: 0.7 | D61: 1.2 | E61: 2.2 | F61: 0.02 | G61: 0.08 | H61: 0.16 | I61: =IFERROR(D61/(G61*H61),0) -> 93.75 | J61: =B61/SUM($B$57:$B$62) -> 0.21538462 | K61: all guess (no benchmark found); effective cost per visit = fees plus gifted books / tracked clicks
A62: occasion_seo_content | B62: 1200 | C62: 0.2 | D62: 0.35 | E62: 0.7 | F62: 0.03 | G62: 0.07 | H62: 0.15 | I62: =IFERROR(D62/(G62*H62),0) -> 33.333333 | J62: =B62/SUM($B$57:$B$62) -> 0.18461538 | K62: all guess; effective cost per visit = content and tooling spend / organic visits
A63: Total / check | B63: =SUM(B57:B62) -> 6500 | J63: =SUM(J57:J62) -> 1
A64: Scenario: Low uses CPC high, Base uses CPC base, High uses CPC low. Channel conversion held constant across scenarios except the conversion lever. CMO notes: blended CAC ~$76 at base; SEO ~$33, TikTok ~$167. Sensible ranges: CPC $0.2-3.0; sign-up 3-10%; sign-up->purchase 8-20%.
A66: 8. Seasonality index by calendar month (1.00 = average; birthdays steady underneath)
A67: Calendar month | B67: Index | C67: Driver
A68: Jan | B68: 0.7 | C68: Post-holiday trough; birthdays only
A69: Feb | B69: 1.3 | C69: Valentine's Day
A70: Mar | B70: 0.85 | C70: Birthdays; Easter lead
A71: Apr | B71: 0.9 | C71: Easter / spring
A72: May | B72: 1.4 | C72: Mother's Day
A73: Jun | B73: 1.05 | C73: Father's Day, graduations, weddings
A74: Jul | B74: 0.85 | C74: Summer trough
A75: Aug | B75: 0.9 | C75: Back to school
A76: Sep | B76: 0.95 | C76: Grandparents Day, holiday SEO build
A77: Oct | B77: 1 | C77: Halloween, holiday lead
A78: Nov | B78: 1.3 | C78: Holiday shopping starts
A79: Dec | B79: 1.9 | C79: Christmas (print cutoffs ~Dec 15)
A80: Average index | B80: =AVERAGE(B68:B79) -> 1.0916667
A82: 9. Scenario levers (selector on the Scenarios sheet picks a column). CPC scenarios come from the CMO low/base/high CPC columns.
A83: Lever | B83: Applies to | C83: Low | D83: Base | E83: High | F83: Notes
A84: Organic traffic multiplier | B84: organic + referral visits | C84: 0.6 | D84: 1 | E84: 1.5 | F84: GUESS
A85: Purchase conversion multiplier | B85: sign-up/start -> purchase | C85: 0.7 | D85: 1 | E85: 1.3 | F85: GUESS
A86: Repeat purchase multiplier | B86: repeat orders | C86: 0.6 | D86: 1 | E86: 1.4 | F86: GUESS
A87: Token cost multiplier | B87: all model costs | C87: 1.4 | D87: 1 | E87: 0.85 | F87: GUESS
A88: Refund / reprint multiplier | B88: refund and reprint rates | C88: 1.5 | D88: 1 | E88: 0.7 | F88: GUESS
A89: Marketing budget multiplier | B89: monthly budget | C89: 1 | D89: 1 | E89: 1 | F89: GUESS
A90: Print + shipping cost multiplier | B90: printer and carrier costs | C90: 1.1 | D90: 1 | E90: 0.95 | F90: GUESS
A92: 10. Operating costs (monthly). Cost = fixed + variable per 1,000 units of driver
A93: Opex line | B93: Fixed ($/mo) | C93: Variable ($ per 1,000 units) | D93: Driver code (1 visits, 2 sign-ups, 3 orders, 4 revenue $) | E93: Status | F93: Basis
A94: Vercel (Pro) | B94: 20 | C94: 0.5 | D94: 1 | E94: ESTIMATE | F94: Pro $20/seat; bandwidth overage grows with visits - verify plan.
A95: Supabase (Pro + compute) | B95: 35 | C95: 20 | D95: 2 | E95: ESTIMATE | F95: Pro $25 + small compute add-on; storage grows with sign-ups.
A96: Resend (email) | B96: 20 | C96: 0.5 | D96: 3 | E96: ESTIMATE | F96: Pro plan $20 up to 50k emails.
A97: Domain | B97: 1.67 | C97: 0 | D97: 1 | E97: ESTIMATE | F97: ~$20/yr amortised.
A98: Stripe Tax | B98: 0 | C98: 3 | D98: 4 | E98: ESTIMATE | F98: 0.5% per transaction x ~60% of sales in registered states = $3 per $1,000. Tax collected is pass-through.
A99: Monitoring (Sentry + uptime) | B99: 26 | C99: 0 | D99: 1 | E99: ESTIMATE | F99: Sentry Team ~$26.
A100: OpenRouter base (dev/QA/pipeline testing) | B100: 75 | C100: 0 | D100: 1 | E100: GUESS | F100: Non-customer token spend: regression tests, prompt tuning.
A101: Design and dev tools | B101: 40 | C101: 0 | D101: 1 | E101: GUESS | F101: Figma, fonts, misc SaaS.
A102: Legal / LLC upkeep and accounting | B102: 150 | C102: 0 | D102: 1 | E102: GUESS | F102: Registered agent, bookkeeping, annual report amortised.
A103: Insurance (GL + cyber) | B103: 95 | C103: 0 | D103: 1 | E103: GUESS | F103: Small-business package; quote needed.
A104: Support (helpdesk + hourly help) | B104: 25 | C104: 900 | D104: 3 | E104: GUESS | F104: Helpdesk $25 + ~$0.90 of support labour per order.
A105: Founder / contractor pay (optional) | B105: 0 | C105: 0 | D105: 1 | E105: GUESS | F105: Zero by default; enter pay to see a sustainable-business break-even.
A107: 11. One-time launch costs (charged in month 1)
...

Sheet Scenarios
A1: Scenarios - selector drives the whole model
A3: Select scenario | B3: Base | C3: <- choose Low / Base / High (only control cell outside Inputs)
A4: Scenario index (1=Low, 2=Base, 3=High) | B4: =MATCH(B3,Inputs!$C$83:$E$83,0) -> 2
A6: Active lever | B6: Active value
A7: Organic traffic multiplier | B7: =INDEX(Inputs!$C$84:$E$84,$B$4) -> 1
A8: Purchase conversion multiplier | B8: =INDEX(Inputs!$C$85:$E$85,$B$4) -> 1
A9: Repeat purchase multiplier | B9: =INDEX(Inputs!$C$86:$E$86,$B$4) -> 1
A10: Token cost multiplier | B10: =INDEX(Inputs!$C$87:$E$87,$B$4) -> 1
A11: Refund / reprint multiplier | B11: =INDEX(Inputs!$C$88:$E$88,$B$4) -> 1
A12: Marketing budget multiplier | B12: =INDEX(Inputs!$C$89:$E$89,$B$4) -> 1
A13: Print + shipping cost multiplier | B13: =INDEX(Inputs!$C$90:$E$90,$B$4) -> 1
A15: Headline KPIs (selected scenario) | B15: Value | C15: Note
A16: Break-even month (sustained: trailing-3M profit stays >= 0) | B16: =IF(COUNT(Forecast!$D$85:$AM$85)=0,"Not within 36 mo",MIN(Forecast!$D$85:$AM$85)) -> Not within 36 mo | C16: Month # from launch
A17: First profitable month | B17: =IF(COUNT(Forecast!$D$84:$AM$84)=0,"Not within 36 mo",MIN(Forecast!$D$84:$AM$84)) -> Not within 36 mo | C17: May be a seasonal one-off
A18: Cash payback month (cumulative net income >= 0) | B18: =IF(COUNT(Forecast!$D$86:$AM$86)=0,"Not within 36 mo",MIN(Forecast!$D$86:$AM$86)) -> Not within 36 mo
A19: Month 12 net revenue | B19: =Forecast!O60 -> 5358.0897
A20: Month 12 net income | B20: =Forecast!O77 -> -5222.6607
A21: Month 36 net revenue | B21: =Forecast!AM60 -> 10226.959
A22: Month 36 net income | B22: =Forecast!AM77 -> -3115.9759
A23: Year 1 net revenue | B23: =Forecast!AO60 -> 57322.61
A24: Year 1 net income | B24: =Forecast!AO77 -> -197783.76
A25: Year 3 net revenue | B25: =Forecast!AQ60 -> 123024.45
A26: Year 3 net income | B26: =Forecast!AQ77 -> -41990.642
A27: Cash balance, month 36 | B27: =Forecast!AM80 -> -267461.65
A28: Lowest cash balance | B28: =MIN(Forecast!C80:AM80) -> -267461.65
A29: Peak funding need (opening cash minus lowest cash) | B29: =MAX(0,Inputs!$B$8-$B$28) -> 297461.65
A30: Total orders, 36 months | B30: =SUM(Forecast!$D$43:$AM$43) -> 9471.4107
A31: Blended CAC, 36 months ($ per new customer) | B31: =IFERROR(SUM(Forecast!$D$74:$AM$74)/SUM(Forecast!$D$40:$AM$40),0) -> 39.57446
A32: Paid CAC, steady state ($) | B32: ='Unit Economics'!$B$28 -> 70.375775
A33: LTV per customer (contribution $) | B33: ='Unit Economics'!$B$25 -> 25.834126
A34: LTV : blended CAC | B34: =IFERROR($B$33/$B$31,0) -> 0.65279796 | C34: Healthy >= 3x
A35: LTV : paid CAC | B35: =IFERROR($B$33/$B$32,0) -> 0.36708834
A36: Blended contribution margin per order ($) | B36: ='Unit Economics'!$B$23 -> 15.196545
A37: Gross margin, Year 3 | B37: =Forecast!AQ72 -> 0.49710236
A38: Guest preview cost, 36 months ($, no revenue) | B38: =SUM(Forecast!$D$63:$AM$63) -> 6175.0332
A41: Program and cost switches (v2). Second set of controls outside Inputs; blue cells with yellow fill are the only edit points.
A42: Include Kiosk program (0/1) | B42: 0 | C42: B42: adds the Kiosk sheet to the selected view. Off by default (kiosk/08). The Dashboard comparison always shows all four.
A43: Include Agent Channel (0/1) | B43: 0 | C43: B43: adds the Agent Channel sheet to the selected view.
A44: Market-adjusted (0/1) | B44: 0 | C44: B44: applies Inputs section 12 (Google CPC $4.14, free card postage at $8.99, digital book $14.99, books $44.99 / $54.99 all-in). Changes core results.
A45: Include v2 new cost lines (0/1) | B45: 1 | C45: B45: Inputs sections 13 and 14 (security, data, support, legal, insurance, accountant). Set 0 to see the original cost base.
A46: Include core launch engineering (0/1) | B46: 1 | C46: B46: R&D sheet block (a). Set 0 to see the original cost base.
A47: Count agent CAC avoided as a cash benefit (0/1) | B47: 0 | C47: B47: off by default; avoided CAC is not cash unless marketing spend is actually cut.
A50: Program-inclusive KPIs for the selected switches (from Compare). Core-only KPIs above are unchanged.
A51: Cumulative cash, month 12 | B51: =Compare!$F$52 -> -167783.76
A52: Cumulative cash, month 24 | B52: =Compare!$F$53 -> -225471.01
A53: Cumulative cash, month 36 | B53: =Compare!$F$54 -> -267461.65
A54: Peak funding need (opening cash minus lowest cash) | B54: =Compare!$F$56 -> 297461.65
A55: Break-even month (sustained) | B55: =Compare!$F$57 -> Not within 36 mo
A56: Total R&D spend, 36 months | B56: =Compare!$F$58 -> 107100

Sheet Compare
A1: Compare - four scenarios by month (cumulative cash, net income, R&D)
A2: Core = Forecast (incl. v2 cost lines and core launch engineering per switches). Agent and Kiosk are the gross standalone streams. Selected = Scenarios switches B42/B43. Market-adjusted (B44) and Low/Base/High (B3) apply to every column.
A4: Line | B4: Unit | C4: Opening / total | D4: M1 | E4: M2 | F4: M3 | G4: M4 | H4: M5 | I4: M6 | J4: M7 | K4: M8 | L4: M9 | M4: M10 | N4: M11 | O4: M12 | P4: M13 | Q4: M14 | R4: M15 | S4: M16 | T4: M17 | U4: M18 | V4: M19 | W4: M20 | X4: M21 | Y4: M22 | Z4: M23 | AA4: M24 | AB4: M25 | AC4: M26 | AD4: M27 | AE4: M28 | AF4: M29 | AG4: M30 | AH4: M31 | AI4: M32 | AJ4: M33 | AK4: M34 | AL4: M35 | AM4: M36 | AN4: 36-mo total | AO4: Year 1 | AP4: Year 2 | AQ4: Year 3
A5: Month # | B5: # | D5: =Forecast!D6 -> 1 | E5: =Forecast!E6 -> 2 | F5: =Forecast!F6 -> 3 | G5: =Forecast!G6 -> 4 | H5: =Forecast!H6 -> 5 | I5: =Forecast!I6 -> 6 | J5: =Forecast!J6 -> 7 | K5: =Forecast!K6 -> 8 | ... AM5: =Forecast!AM6 -> 36
A6: STREAMS (net income unless noted)
A7: Core net income (Forecast row 77 = cash; no working capital) | B7: $ | D7: =Forecast!D77 -> -62740.91 | E7: =Forecast!E77 -> -54192.56 | F7: =Forecast!F77 -> -24287.991 | G7: =Forecast!G77 -> -12698.507 | H7: =Forecast!H77 -> -5564.125 | I7: =Forecast!I77 -> -5569.5702 | J7: =Forecast!J77 -> -5989.7197 | K7: =Forecast!K77 -> -5595.7554 | ... AM7: =Forecast!AM77 -> -3115.9759 | AN7: =SUM(D7:AM7) -> -297461.65 | AO7: =SUM(D7:O7) -> -197783.76 | AP7: =SUM(P7:AA7) -> -57687.253 | AQ7: =SUM(AB7:AM7) -> -41990.642
A8: Agent Channel net income = cash | B8: $ | D8: ='Agent Channel'!D38 -> -18000 | E8: ='Agent Channel'!E38 -> -11250 | F8: ='Agent Channel'!F38 -> -11250 | G8: ='Agent Channel'!G38 -> -8700 | H8: ='Agent Channel'!H38 -> -8700 | I8: ='Agent Channel'!I38 -> 0 | J8: ='Agent Channel'!J38 -> 0 | K8: ='Agent Channel'!K38 -> -293.95312 | ... AM8: ='Agent Channel'!AM38 -> -170.8087 | AN8: =SUM(D8:AM8) -> -90190.615 | AO8: =SUM(D8:O8) -> -75514.182 | AP8: =SUM(P8:AA8) -> -12450.174 | AQ8: =SUM(AB8:AM8) -> -2226.2591
A9: Kiosk net income (after depreciation) | B9: $ | D9: =Kiosk!D44 -> 0 | E9: =Kiosk!E44 -> 0 | F9: =Kiosk!F44 -> 0 | G9: =Kiosk!G44 -> 0 | H9: =Kiosk!H44 -> 0 | I9: =Kiosk!I44 -> 0 | J9: =Kiosk!J44 -> -11538.333 | K9: =Kiosk!K44 -> -11538.333 | ... AM9: =Kiosk!AM44 -> 0 | AN9: =SUM(D9:AM9) -> -34615 | AO9: =SUM(D9:O9) -> -34615 | AP9: =SUM(P9:AA9) -> 0 | AQ9: =SUM(AB9:AM9) -> 0
A10: Kiosk net cash flow (after capex) | B10: $ | D10: =Kiosk!D45 -> 0 | E10: =Kiosk!E45 -> 0 | F10: =Kiosk!F45 -> 0 | G10: =Kiosk!G45 -> 0 | H10: =Kiosk!H45 -> 0 | I10: =Kiosk!I45 -> 0 | J10: =Kiosk!J45 -> -11538.333 | K10: =Kiosk!K45 -> -11538.333 | ... AM10: =Kiosk!AM45 -> 0 | AN10: =SUM(D10:AM10) -> -34615 | AO10: =SUM(D10:O10) -> -34615 | AP10: =SUM(P10:AA10) -> 0 | AQ10: =SUM(AB10:AM10) -> 0
A11: R&D: core launch engineering in forecast | B11: $ | D11: ='R&D'!D13 -> 40650 | E11: ='R&D'!E13 -> 44130 | F11: ='R&D'!F13 -> 18840 | G11: ='R&D'!G13 -> 3480 | H11: ='R&D'!H13 -> 0 | I11: ='R&D'!I13 -> 0 | J11: ='R&D'!J13 -> 0 | K11: ='R&D'!K13 -> 0 | ... AM11: ='R&D'!AM13 -> 0 | AN11: =SUM(D11:AM11) -> 107100 | AO11: =SUM(D11:O11) -> 107100 | AP11: =SUM(P11:AA11) -> 0 | AQ11: =SUM(AB11:AM11) -> 0
A12: R&D: agent / AI-platform | B12: $ | D12: ='R&D'!D28 -> 18000 | E12: ='R&D'!E28 -> 11250 | F12: ='R&D'!F28 -> 11250 | G12: ='R&D'!G28 -> 8700 | H12: ='R&D'!H28 -> 8700 | I12: ='R&D'!I28 -> 0 | J12: ='R&D'!J28 -> 0 | K12: ='R&D'!K28 -> 0 | ... AM12: ='R&D'!AM28 -> 0 | AN12: =SUM(D12:AM12) -> 83700 | AO12: =SUM(D12:O12) -> 74100 | AP12: =SUM(P12:AA12) -> 9600 | AQ12: =SUM(AB12:AM12) -> 0
A13: R&D: kiosk program | B13: $ | D13: ='R&D'!D45 -> 0 | E13: ='R&D'!E45 -> 0 | F13: ='R&D'!F45 -> 0 | G13: ='R&D'!G45 -> 0 | H13: ='R&D'!H45 -> 0 | I13: ='R&D'!I45 -> 0 | J13: ='R&D'!J45 -> 11538.333 | K13: ='R&D'!K45 -> 11538.333 | ... AM13: ='R&D'!AM45 -> 0 | AN13: =SUM(D13:AM13) -> 34615 | AO13: =SUM(D13:O13) -> 34615 | AP13: =SUM(P13:AA13) -> 0 | AQ13: =SUM(AB13:AM13) -> 0
A14: SCENARIO: CORE ONLY
A15: Core only: net income | B15: $ | D15: =D7+0*D8+0*D9 -> -62740.91 | E15: =E7+0*E8+0*E9 -> -54192.56 | F15: =F7+0*F8+0*F9 -> -24287.991 | G15: =G7+0*G8+0*G9 -> -12698.507 | H15: =H7+0*H8+0*H9 -> -5564.125 | I15: =I7+0*I8+0*I9 -> -5569.5702 | J15: =J7+0*J8+0*J9 -> -5989.7197 | K15: =K7+0*K8+0*K9 -> -5595.7554 | ... AM15: =AM7+0*AM8+0*AM9 -> -3115.9759 | AN15: =SUM(D15:AM15) -> -297461.65 | AO15: =SUM(D15:O15) -> -197783.76 | AP15: =SUM(P15:AA15) -> -57687.253 | AQ15: =SUM(AB15:AM15) -> -41990.642
A16: Core only: net cash flow | B16: $ | D16: =D7+0*D8+0*D10 -> -62740.91 | E16: =E7+0*E8+0*E10 -> -54192.56 | F16: =F7+0*F8+0*F10 -> -24287.991 | G16: =G7+0*G8+0*G10 -> -12698.507 | H16: =H7+0*H8+0*H10 -> -5564.125 | I16: =I7+0*I8+0*I10 -> -5569.5702 | J16: =J7+0*J8+0*J10 -> -5989.7197 | K16: =K7+0*K8+0*K10 -> -5595.7554 | ... AM16: =AM7+0*AM8+0*AM10 -> -3115.9759 | AN16: =SUM(D16:AM16) -> -297461.65 | AO16: =SUM(D16:O16) -> -197783.76 | AP16: =SUM(P16:AA16) -> -57687.253 | AQ16: =SUM(AB16:AM16) -> -41990.642
A17: Core only: cumulative cash balance | B17: $ | C17: =Inputs!$B$8 -> 30000 | D17: =C17+D16 -> -32740.91 | E17: =D17+E16 -> -86933.47 | F17: =E17+F16 -> -111221.46 | G17: =F17+G16 -> -123919.97 | H17: =G17+H16 -> -129484.09 | I17: =H17+I16 -> -135053.66 | J17: =I17+J16 -> -141043.38 | K17: =J17+K16 -> -146639.14 | ... AM17: =AL17+AM16 -> -267461.65
A18: Core only: R&D spend | B18: $ | D18: =D11+0*D12+0*D13 -> 40650 | E18: =E11+0*E12+0*E13 -> 44130 | F18: =F11+0*F12+0*F13 -> 18840 | G18: =G11+0*G12+0*G13 -> 3480 | H18: =H11+0*H12+0*H13 -> 0 | I18: =I11+0*I12+0*I13 -> 0 | J18: =J11+0*J12+0*J13 -> 0 | K18: =K11+0*K12+0*K13 -> 0 | ... AM18: =AM11+0*AM12+0*AM13 -> 0 | AN18: =SUM(D18:AM18) -> 107100 | AO18: =SUM(D18:O18) -> 107100 | AP18: =SUM(P18:AA18) -> 0 | AQ18: =SUM(AB18:AM18) -> 0
A19: Core only: trailing 3-month net income | B19: $ | D19: =SUM(D15) -> -62740.91 | E19: =SUM(D15:E15) -> -116933.47 | F19: =SUM(D15:F15) -> -141221.46 | G19: =SUM(E15:G15) -> -91179.058 | H19: =SUM(F15:H15) -> -42550.623 | I19: =SUM(G15:I15) -> -23832.202 | J19: =SUM(H15:J15) -> -17123.415 | K19: =SUM(I15:K15) -> -17155.045 | L19: =SUM(J15:L15) -> -16917.997 | M19: =SUM(K15:M15) -> -16241.434 | ... AM19: =SUM(AK15:AM15) -> -9871.7615
A20: Core only: flag sustained break-even (all later T3M >= 0) | B20: month | D20: =IF(MIN(D19:$AM19)>=0,D$5,"") | E20: =IF(MIN(E19:$AM19)>=0,E$5,"") | F20: =IF(MIN(F19:$AM19)>=0,F$5,"") | G20: =IF(MIN(G19:$AM19)>=0,G$5,"") | H20: =IF(MIN(H19:$AM19)>=0,H$5,"") | I20: =IF(MIN(I19:$AM19)>=0,I$5,"") | J20: =IF(MIN(J19:$AM19)>=0,J$5,"") | K20: =IF(MIN(K19:$AM19)>=0,K$5,"") | ... AM20: =IF(MIN(AM19:$AM19)>=0,AM$5,"")
A21: SCENARIO: CORE + AGENT CHANNEL
A22: Core + Agent Channel: net income | B22: $ | D22: =D7+1*D8+0*D9 -> -80740.91 | E22: =E7+1*E8+0*E9 -> -65442.56 | F22: =F7+1*F8+0*F9 -> -35537.991 | G22: =G7+1*G8+0*G9 -> -21398.507 | H22: =H7+1*H8+0*H9 -> -14264.125 | I22: =I7+1*I8+0*I9 -> -5569.5702 | J22: =J7+1*J8+0*J9 -> -5989.7197 | K22: =K7+1*K8+0*K9 -> -5889.7086 | ... AM22: =AM7+1*AM8+0*AM9 -> -3286.7846 | AN22: =SUM(D22:AM22) -> -387652.27 | AO22: =SUM(D22:O22) -> -273297.94 | AP22: =SUM(P22:AA22) -> -70137.427 | AQ22: =SUM(AB22:AM22) -> -44216.901
A23: Core + Agent Channel: net cash flow | B23: $ | D23: =D7+1*D8+0*D10 -> -80740.91 | E23: =E7+1*E8+0*E10 -> -65442.56 | F23: =F7+1*F8+0*F10 -> -35537.991 | G23: =G7+1*G8+0*G10 -> -21398.507 | H23: =H7+1*H8+0*H10 -> -14264.125 | I23: =I7+1*I8+0*I10 -> -5569.5702 | J23: =J7+1*J8+0*J10 -> -5989.7197 | K23: =K7+1*K8+0*K10 -> -5889.7086 | ... AM23: =AM7+1*AM8+0*AM10 -> -3286.7846 | AN23: =SUM(D23:AM23) -> -387652.27 | AO23: =SUM(D23:O23) -> -273297.94 | AP23: =SUM(P23:AA23) -> -70137.427 | AQ23: =SUM(AB23:AM23) -> -44216.901
A24: Core + Agent Channel: cumulative cash balance | B24: $ | C24: =Inputs!$B$8 -> 30000 | D24: =C24+D23 -> -50740.91 | E24: =D24+E23 -> -116183.47 | F24: =E24+F23 -> -151721.46 | G24: =F24+G23 -> -173119.97 | H24: =G24+H23 -> -187384.09 | I24: =H24+I23 -> -192953.66 | J24: =I24+J23 -> -198943.38 | K24: =J24+K23 -> -204833.09 | ... AM24: =AL24+AM23 -> -357652.27
A25: Core + Agent Channel: R&D spend | B25: $ | D25: =D11+1*D12+0*D13 -> 58650 | E25: =E11+1*E12+0*E13 -> 55380 | F25: =F11+1*F12+0*F13 -> 30090 | G25: =G11+1*G12+0*G13 -> 12180 | H25: =H11+1*H12+0*H13 -> 8700 | I25: =I11+1*I12+0*I13 -> 0 | J25: =J11+1*J12+0*J13 -> 0 | K25: =K11+1*K12+0*K13 -> 0 | ... AM25: =AM11+1*AM12+0*AM13 -> 0 | AN25: =SUM(D25:AM25) -> 190800 | AO25: =SUM(D25:O25) -> 181200 | AP25: =SUM(P25:AA25) -> 9600 | AQ25: =SUM(AB25:AM25) -> 0
A26: Core + Agent Channel: trailing 3-month net income | B26: $ | D26: =SUM(D22) -> -80740.91 | E26: =SUM(D22:E22) -> -146183.47 | F26: =SUM(D22:F22) -> -181721.46 | G26: =SUM(E22:G22) -> -122379.06 | H26: =SUM(F22:H22) -> -71200.623 | I26: =SUM(G22:I22) -> -41232.202 | J26: =SUM(H22:J22) -> -25823.415 | K26: =SUM(I22:K22) -> -17448.998 | L26: =SUM(J22:L22) -> -23200.108 | M26: =SUM(K22:M22) -> -28506.15 | ... AM26: =SUM(AK22:AM22) -> -10391.205
A27: Core + Agent Channel: flag sustained break-even (all later T3M >= 0) | B27: month | D27: =IF(MIN(D26:$AM26)>=0,D$5,"") | E27: =IF(MIN(E26:$AM26)>=0,E$5,"") | F27: =IF(MIN(F26:$AM26)>=0,F$5,"") | G27: =IF(MIN(G26:$AM26)>=0,G$5,"") | H27: =IF(MIN(H26:$AM26)>=0,H$5,"") | I27: =IF(MIN(I26:$AM26)>=0,I$5,"") | J27: =IF(MIN(J26:$AM26)>=0,J$5,"") | K27: =IF(MIN(K26:$AM26)>=0,K$5,"") | ... AM27: =IF(MIN(AM26:$AM26)>=0,AM$5,"")
A28: SCENARIO: CORE + KIOSK
A29: Core + Kiosk: net income | B29: $ | D29: =D7+0*D8+1*D9 -> -62740.91 | E29: =E7+0*E8+1*E9 -> -54192.56 | F29: =F7+0*F8+1*F9 -> -24287.991 | G29: =G7+0*G8+1*G9 -> -12698.507 | H29: =H7+0*H8+1*H9 -> -5564.125 | I29: =I7+0*I8+1*I9 -> -5569.5702 | J29: =J7+0*J8+1*J9 -> -17528.053 | K29: =K7+0*K8+1*K9 -> -17134.089 | ... AM29: =AM7+0*AM8+1*AM9 -> -3115.9759 | AN29: =SUM(D29:AM29) -> -332076.65 | AO29: =SUM(D29:O29) -> -232398.76 | AP29: =SUM(P29:AA29) -> -57687.253 | AQ29: =SUM(AB29:AM29) -> -41990.642
A30: Core + Kiosk: net cash flow | B30: $ | D30: =D7+0*D8+1*D10 -> -62740.91 | E30: =E7+0*E8+1*E10 -> -54192.56 | F30: =F7+0*F8+1*F10 -> -24287.991 | G30: =G7+0*G8+1*G10 -> -12698.507 | H30: =H7+0*H8+1*H10 -> -5564.125 | I30: =I7+0*I8+1*I10 -> -5569.5702 | J30: =J7+0*J8+1*J10 -> -17528.053 | K30: =K7+0*K8+1*K10 -> -17134.089 | ... AM30: =AM7+0*AM8+1*AM10 -> -3115.9759 | AN30: =SUM(D30:AM30) -> -332076.65 | AO30: =SUM(D30:O30) -> -232398.76 | AP30: =SUM(P30:AA30) -> -57687.253 | AQ30: =SUM(AB30:AM30) -> -41990.642
A31: Core + Kiosk: cumulative cash balance | B31: $ | C31: =Inputs!$B$8 -> 30000 | D31: =C31+D30 -> -32740.91 | E31: =D31+E30 -> -86933.47 | F31: =E31+F30 -> -111221.46 | G31: =F31+G30 -> -123919.97 | H31: =G31+H30 -> -129484.09 | I31: =H31+I30 -> -135053.66 | J31: =I31+J30 -> -152581.72 | K31: =J31+K30 -> -169715.81 | ... AM31: =AL31+AM30 -> -302076.65
A32: Core + Kiosk: R&D spend | B32: $ | D32: =D11+0*D12+1*D13 -> 40650 | E32: =E11+0*E12+1*E13 -> 44130 | F32: =F11+0*F12+1*F13 -> 18840 | G32: =G11+0*G12+1*G13 -> 3480 | H32: =H11+0*H12+1*H13 -> 0 | I32: =I11+0*I12+1*I13 -> 0 | J32: =J11+0*J12+1*J13 -> 11538.333 | K32: =K11+0*K12+1*K13 -> 11538.333 | ... AM32: =AM11+0*AM12+1*AM13 -> 0 | AN32: =SUM(D32:AM32) -> 141715 | AO32: =SUM(D32:O32) -> 141715 | AP32: =SUM(P32:AA32) -> 0 | AQ32: =SUM(AB32:AM32) -> 0
A33: Core + Kiosk: trailing 3-month net income | B33: $ | D33: =SUM(D29) -> -62740.91 | E33: =SUM(D29:E29) -> -116933.47 | F33: =SUM(D29:F29) -> -141221.46 | G33: =SUM(E29:G29) -> -91179.058 | H33: =SUM(F29:H29) -> -42550.623 | I33: =SUM(G29:I29) -> -23832.202 | J33: =SUM(H29:J29) -> -28661.748 | K33: =SUM(I29:K29) -> -40231.712 | L33: =SUM(J29:L29) -> -51532.997 | M33: =SUM(K29:M29) -> -39318.1 | ... AM33: =SUM(AK29:AM29) -> -9871.7615
A34: Core + Kiosk: flag sustained break-even (all later T3M >= 0) | B34: month | D34: =IF(MIN(D33:$AM33)>=0,D$5,"") | E34: =IF(MIN(E33:$AM33)>=0,E$5,"") | F34: =IF(MIN(F33:$AM33)>=0,F$5,"") | G34: =IF(MIN(G33:$AM33)>=0,G$5,"") | H34: =IF(MIN(H33:$AM33)>=0,H$5,"") | I34: =IF(MIN(I33:$AM33)>=0,I$5,"") | J34: =IF(MIN(J33:$AM33)>=0,J$5,"") | K34: =IF(MIN(K33:$AM33)>=0,K$5,"") | ... AM34: =IF(MIN(AM33:$AM33)>=0,AM$5,"")
A35: SCENARIO: EVERYTHING
A36: Everything: net income | B36: $ | D36: =D7+1*D8+1*D9 -> -80740.91 | E36: =E7+1*E8+1*E9 -> -65442.56 | F36: =F7+1*F8+1*F9 -> -35537.991 | G36: =G7+1*G8+1*G9 -> -21398.507 | H36: =H7+1*H8+1*H9 -> -14264.125 | I36: =I7+1*I8+1*I9 -> -5569.5702 | J36: =J7+1*J8+1*J9 -> -17528.053 | K36: =K7+1*K8+1*K9 -> -17428.042 | ... AM36: =AM7+1*AM8+1*AM9 -> -3286.7846 | AN36: =SUM(D36:AM36) -> -422267.27 | AO36: =SUM(D36:O36) -> -307912.94 | AP36: =SUM(P36:AA36) -> -70137.427 | AQ36: =SUM(AB36:AM36) -> -44216.901
A37: Everything: net cash flow | B37: $ | D37: =D7+1*D8+1*D10 -> -80740.91 | E37: =E7+1*E8+1*E10 -> -65442.56 | F37: =F7+1*F8+1*F10 -> -35537.991 | G37: =G7+1*G8+1*G10 -> -21398.507 | H37: =H7+1*H8+1*H10 -> -14264.125 | I37: =I7+1*I8+1*I10 -> -5569.5702 | J37: =J7+1*J8+1*J10 -> -17528.053 | K37: =K7+1*K8+1*K10 -> -17428.042 | ... AM37: =AM7+1*AM8+1*AM10 -> -3286.7846 | AN37: =SUM(D37:AM37) -> -422267.27 | AO37: =SUM(D37:O37) -> -307912.94 | AP37: =SUM(P37:AA37) -> -70137.427 | AQ37: =SUM(AB37:AM37) -> -44216.901
A38: Everything: cumulative cash balance | B38: $ | C38: =Inputs!$B$8 -> 30000 | D38: =C38+D37 -> -50740.91 | E38: =D38+E37 -> -116183.47 | F38: =E38+F37 -> -151721.46 | G38: =F38+G37 -> -173119.97 | H38: =G38+H37 -> -187384.09 | I38: =H38+I37 -> -192953.66 | J38: =I38+J37 -> -210481.72 | K38: =J38+K37 -> -227909.76 | ... AM38: =AL38+AM37 -> -392267.27
A39: Everything: R&D spend | B39: $ | D39: =D11+1*D12+1*D13 -> 58650 | E39: =E11+1*E12+1*E13 -> 55380 | F39: =F11+1*F12+1*F13 -> 30090 | G39: =G11+1*G12+1*G13 -> 12180 | H39: =H11+1*H12+1*H13 -> 8700 | I39: =I11+1*I12+1*I13 -> 0 | J39: =J11+1*J12+1*J13 -> 11538.333 | K39: =K11+1*K12+1*K13 -> 11538.333 | ... AM39: =AM11+1*AM12+1*AM13 -> 0 | AN39: =SUM(D39:AM39) -> 225415 | AO39: =SUM(D39:O39) -> 215815 | AP39: =SUM(P39:AA39) -> 9600 | AQ39: =SUM(AB39:AM39) -> 0
A40: Everything: trailing 3-month net income | B40: $ | D40: =SUM(D36) -> -80740.91 | E40: =SUM(D36:E36) -> -146183.47 | F40: =SUM(D36:F36) -> -181721.46 | G40: =SUM(E36:G36) -> -122379.06 | H40: =SUM(F36:H36) -> -71200.623 | I40: =SUM(G36:I36) -> -41232.202 | J40: =SUM(H36:J36) -> -37361.748 | K40: =SUM(I36:K36) -> -40525.665 | L40: =SUM(J36:L36) -> -57815.108 | M40: =SUM(K36:M36) -> -51582.816 | ... AM40: =SUM(AK36:AM36) -> -10391.205
A41: Everything: flag sustained break-even (all later T3M >= 0) | B41: month | D41: =IF(MIN(D40:$AM40)>=0,D$5,"") | E41: =IF(MIN(E40:$AM40)>=0,E$5,"") | F41: =IF(MIN(F40:$AM40)>=0,F$5,"") | G41: =IF(MIN(G40:$AM40)>=0,G$5,"") | H41: =IF(MIN(H40:$AM40)>=0,H$5,"") | I41: =IF(MIN(I40:$AM40)>=0,I$5,"") | J41: =IF(MIN(J40:$AM40)>=0,J$5,"") | K41: =IF(MIN(K40:$AM40)>=0,K$5,"") | ... AM41: =IF(MIN(AM40:$AM40)>=0,AM$5,"")
A42: SCENARIO: SELECTED BY SCENARIOS SWITCHES
A43: Selected by Scenarios switches: net income | B43: $ | D43: =D7+Scenarios!$B$43*D8+Scenarios!$B$42*D9 -> -62740.91 | E43: =E7+Scenarios!$B$43*E8+Scenarios!$B$42*E9 -> -54192.56 | F43: =F7+Scenarios!$B$43*F8+Scenarios!$B$42*F9 -> -24287.991 | G43: =G7+Scenarios!$B$43*G8+Scenarios!$B$42*G9 -> -12698.507 | H43: =H7+Scenarios!$B$43*H8+Scenarios!$B$42*H9 -> -5564.125 | I43: =I7+Scenarios!$B$43*I8+Scenarios!$B$42*I9 -> -5569.5702 | J43: =J7+Scenarios!$B$43*J8+Scenarios!$B$42*J9 -> -5989.7197 | K43: =K7+Scenarios!$B$43*K8+Scenarios!$B$42*K9 -> -5595.7554 | ... AM43: =AM7+Scenarios!$B$43*AM8+Scenarios!$B$42*AM9 -> -3115.9759 | AN43: =SUM(D43:AM43) -> -297461.65 | AO43: =SUM(D43:O43) -> -197783.76 | AP43: =SUM(P43:AA43) -> -57687.253 | AQ43: =SUM(AB43:AM43) -> -41990.642
A44: Selected by Scenarios switches: net cash flow | B44: $ | D44: =D7+Scenarios!$B$43*D8+Scenarios!$B$42*D10 -> -62740.91 | E44: =E7+Scenarios!$B$43*E8+Scenarios!$B$42*E10 -> -54192.56 | F44: =F7+Scenarios!$B$43*F8+Scenarios!$B$42*F10 -> -24287.991 | G44: =G7+Scenarios!$B$43*G8+Scenarios!$B$42*G10 -> -12698.507 | H44: =H7+Scenarios!$B$43*H8+Scenarios!$B$42*H10 -> -5564.125 | I44: =I7+Scenarios!$B$43*I8+Scenarios!$B$42*I10 -> -5569.5702 | J44: =J7+Scenarios!$B$43*J8+Scenarios!$B$42*J10 -> -5989.7197 | K44: =K7+Scenarios!$B$43*K8+Scenarios!$B$42*K10 -> -5595.7554 | ... AM44: =AM7+Scenarios!$B$43*AM8+Scenarios!$B$42*AM10 -> -3115.9759 | AN44: =SUM(D44:AM44) -> -297461.65 | AO44: =SUM(D44:O44) -> -197783.76 | AP44: =SUM(P44:AA44) -> -57687.253 | AQ44: =SUM(AB44:AM44) -> -41990.642
A45: Selected by Scenarios switches: cumulative cash balance | B45: $ | C45: =Inputs!$B$8 -> 30000 | D45: =C45+D44 -> -32740.91 | E45: =D45+E44 -> -86933.47 | F45: =E45+F44 -> -111221.46 | G45: =F45+G44 -> -123919.97 | H45: =G45+H44 -> -129484.09 | I45: =H45+I44 -> -135053.66 | J45: =I45+J44 -> -141043.38 | K45: =J45+K44 -> -146639.14 | ... AM45: =AL45+AM44 -> -267461.65
A46: Selected by Scenarios switches: R&D spend | B46: $ | D46: =D11+Scenarios!$B$43*D12+Scenarios!$B$42*D13 -> 40650 | E46: =E11+Scenarios!$B$43*E12+Scenarios!$B$42*E13 -> 44130 | F46: =F11+Scenarios!$B$43*F12+Scenarios!$B$42*F13 -> 18840 | G46: =G11+Scenarios!$B$43*G12+Scenarios!$B$42*G13 -> 3480 | H46: =H11+Scenarios!$B$43*H12+Scenarios!$B$42*H13 -> 0 | I46: =I11+Scenarios!$B$43*I12+Scenarios!$B$42*I13 -> 0 | J46: =J11+Scenarios!$B$43*J12+Scenarios!$B$42*J13 -> 0 | K46: =K11+Scenarios!$B$43*K12+Scenarios!$B$42*K13 -> 0 | ... AM46: =AM11+Scenarios!$B$43*AM12+Scenarios!$B$42*AM13 -> 0 | AN46: =SUM(D46:AM46) -> 107100 | AO46: =SUM(D46:O46) -> 107100 | AP46: =SUM(P46:AA46) -> 0 | AQ46: =SUM(AB46:AM46) -> 0
A47: Selected by Scenarios switches: trailing 3-month net income | B47: $ | D47: =SUM(D43) -> -62740.91 | E47: =SUM(D43:E43) -> -116933.47 | F47: =SUM(D43:F43) -> -141221.46 | G47: =SUM(E43:G43) -> -91179.058 | H47: =SUM(F43:H43) -> -42550.623 | I47: =SUM(G43:I43) -> -23832.202 | J47: =SUM(H43:J43) -> -17123.415 | K47: =SUM(I43:K43) -> -17155.045 | L47: =SUM(J43:L43) -> -16917.997 | M47: =SUM(K43:M43) -> -16241.434 | ... AM47: =SUM(AK43:AM43) -> -9871.7615
A48: Selected by Scenarios switches: flag sustained break-even (all later T3M >= 0) | B48: month | D48: =IF(MIN(D47:$AM47)>=0,D$5,"") | E48: =IF(MIN(E47:$AM47)>=0,E$5,"") | F48: =IF(MIN(F47:$AM47)>=0,F$5,"") | G48: =IF(MIN(G47:$AM47)>=0,G$5,"") | H48: =IF(MIN(H47:$AM47)>=0,H$5,"") | I48: =IF(MIN(I47:$AM47)>=0,I$5,"") | J48: =IF(MIN(J47:$AM47)>=0,J$5,"") | K48: =IF(MIN(K47:$AM47)>=0,K$5,"") | ... AM48: =IF(MIN(AM47:$AM47)>=0,AM$5,"")
A50: HEADLINE METRICS
A51: Metric | B51: Core only | C51: Core + Agent Channel | D51: Core + Kiosk | E51: Everything | F51: Selected by Scenarios switches
A52: Cumulative cash, month 12 | B52: =O17 -> -167783.76 | C52: =O24 -> -243297.94 | D52: =O31 -> -202398.76 | E52: =O38 -> -277912.94 | F52: =O45 -> -167783.76
A53: Cumulative cash, month 24 | B53: =AA17 -> -225471.01 | C53: =AA24 -> -313435.37 | D53: =AA31 -> -260086.01 | E53: =AA38 -> -348050.37 | F53: =AA45 -> -225471.01
A54: Cumulative cash, month 36 | B54: =AM17 -> -267461.65 | C54: =AM24 -> -357652.27 | D54: =AM31 -> -302076.65 | E54: =AM38 -> -392267.27 | F54: =AM45 -> -267461.65
A55: Lowest cash balance (incl. opening) | B55: =MIN(C17:AM17) -> -267461.65 | C55: =MIN(C24:AM24) -> -357652.27 | D55: =MIN(C31:AM31) -> -302076.65 | E55: =MIN(C38:AM38) -> -392267.27 | F55: =MIN(C45:AM45) -> -267461.65
A56: Peak funding need (opening cash minus lowest cash) | B56: =MAX(0,Inputs!$B$8-B55) -> 297461.65 | C56: =MAX(0,Inputs!$B$8-C55) -> 387652.27 | D56: =MAX(0,Inputs!$B$8-D55) -> 332076.65 | E56: =MAX(0,Inputs!$B$8-E55) -> 422267.27 | F56: =MAX(0,Inputs!$B$8-F55) -> 297461.65
A57: Break-even month (sustained trailing-3M net income >= 0) | B57: =IF(COUNT(D20:AM20)=0,"Not within 36 mo",MIN(D20:AM20)) -> Not within 36 mo | C57: =IF(COUNT(D27:AM27)=0,"Not within 36 mo",MIN(D27:AM27)) -> Not within 36 mo | D57: =IF(COUNT(D34:AM34)=0,"Not within 36 mo",MIN(D34:AM34)) -> Not within 36 mo | E57: =IF(COUNT(D41:AM41)=0,"Not within 36 mo",MIN(D41:AM41)) -> Not within 36 mo | F57: =IF(COUNT(D48:AM48)=0,"Not within 36 mo",MIN(D48:AM48)) -> Not within 36 mo
A58: Total R&D spend, 36 months | B58: =SUM(D18:AM18) -> 107100 | C58: =SUM(D25:AM25) -> 190800 | D58: =SUM(D32:AM32) -> 141715 | E58: =SUM(D39:AM39) -> 225415 | F58: =SUM(D46:AM46) -> 107100
A59: Cumulative net income, 36 months | B59: =SUM(D15:AM15) -> -297461.65 | C59: =SUM(D22:AM22) -> -387652.27 | D59: =SUM(D29:AM29) -> -332076.65 | E59: =SUM(D36:AM36) -> -422267.27 | F59: =SUM(D43:AM43) -> -297461.65

Sheet R&D
A1: R&D - one-time and program engineering cost by month (36 months)
A2: Gross program cost, independent of the include switches. Core launch engineering flows into Forecast (switch Scenarios!B46); Agent and Kiosk programs flow only through Compare and the Dashboard. Change rate and days on Inputs sections 15-15c.
A4: Line | B4: Unit | C4: Person-days / total | D4: M1 | E4: M2 | F4: M3 | G4: M4 | H4: M5 | I4: M6 | J4: M7 | K4: M8 | L4: M9 | M4: M10 | N4: M11 | O4: M12 | P4: M13 | Q4: M14 | R4: M15 | S4: M16 | T4: M17 | U4: M18 | V4: M19 | W4: M20 | X4: M21 | Y4: M22 | Z4: M23 | AA4: M24 | AB4: M25 | AC4: M26 | AD4: M27 | AE4: M28 | AF4: M29 | AG4: M30 | AH4: M31 | AI4: M32 | AJ4: M33 | AK4: M34 | AL4: M35 | AM4: M36 | AN4: 36-mo total | AO4: Year 1 | AP4: Year 2 | AQ4: Year 3
A5: Month # | B5: # | D5: =Forecast!D6 -> 1 | E5: =Forecast!E6 -> 2 | F5: =Forecast!F6 -> 3 | G5: =Forecast!G6 -> 4 | H5: =Forecast!H6 -> 5 | I5: =Forecast!I6 -> 6 | J5: =Forecast!J6 -> 7 | K5: =Forecast!K6 -> 8 | ... AM5: =Forecast!AM6 -> 36
A6: (a) CORE LAUNCH ENGINEERING (remaining app work; days from the backlogs' own ticket sizes)
A7: =Inputs!A163 -> SEC MUST before launch (SEC-01 to 25) | B7: $ | C7: =Inputs!I163*(1+Inputs!$B$155) -> 47.4 | D7: =IF(AND(D$5>=Inputs!$J$163,D$5<Inputs!$J$163+Inputs!$K$163),Inputs!$I$163*(1+Inputs!$B$155)/Inputs!$K$163*Inputs!$B$152*Inputs!$B$154,0) -> 14220 | E7: =IF(AND(E$5>=Inputs!$J$163,E$5<Inputs!$J$163+Inputs!$K$163),Inputs!$I$163*(1+Inputs!$B$155)/Inputs!$K$163*Inputs!$B$152*Inputs!$B$154,0) -> 14220 | F7: =IF(AND(F$5>=Inputs!$J$163,F$5<Inputs!$J$163+Inputs!$K$163),Inputs!$I$163*(1+Inputs!$B$155)/Inputs!$K$163*Inputs!$B$152*Inputs!$B$154,0) -> 0 | G7: =IF(AND(G$5>=Inputs!$J$163,G$5<Inputs!$J$163+Inputs!$K$163),Inputs!$I$163*(1+Inputs!$B$155)/Inputs!$K$163*Inputs!$B$152*Inputs!$B$154,0) -> 0 | H7: =IF(AND(H$5>=Inputs!$J$163,H$5<Inputs!$J$163+Inputs!$K$163),Inputs!$I$163*(1+Inputs!$B$155)/Inputs!$K$163*Inputs!$B$152*Inputs!$B$154,0) -> 0 | I7: =IF(AND(I$5>=Inputs!$J$163,I$5<Inputs!$J$163+Inputs!$K$163),Inputs!$I$163*(1+Inputs!$B$155)/Inputs!$K$163*Inputs!$B$152*Inputs!$B$154,0) -> 0 | J7: =IF(AND(J$5>=Inputs!$J$163,J$5<Inputs!$J$163+Inputs!$K$163),Inputs!$I$163*(1+Inputs!$B$155)/Inputs!$K$163*Inputs!$B$152*Inputs!$B$154,0) -> 0 | K7: =IF(AND(K$5>=Inputs!$J$163,K$5<Inputs!$J$163+Inputs!$K$163),Inputs!$I$163*(1+Inputs!$B$155)/Inputs!$K$163*Inputs!$B$152*Inputs!$B$154,0) -> 0 | ... AM7: =IF(AND(AM$5>=Inputs!$J$163,AM$5<Inputs!$J$163+Inputs!$K$163),Inputs!$I$163*(1+Inputs!$B$155)/Inputs!$K$163*Inputs!$B$152*Inputs!$B$154,0) -> 0 | AN7: =SUM(D7:AM7) -> 28440 | AO7: =SUM(D7:O7) -> 28440 | AP7: =SUM(P7:AA7) -> 0 | AQ7: =SUM(AB7:AM7) -> 0
A8: =Inputs!A164 -> SEC AFTER launch (SEC-30 to 40) | B8: $ | C8: =Inputs!I164*(1+Inputs!$B$155) -> 17.4 | D8: =IF(AND(D$5>=Inputs!$J$164,D$5<Inputs!$J$164+Inputs!$K$164),Inputs!$I$164*(1+Inputs!$B$155)/Inputs!$K$164*Inputs!$B$152*Inputs!$B$154,0) -> 0 | E8: =IF(AND(E$5>=Inputs!$J$164,E$5<Inputs!$J$164+Inputs!$K$164),Inputs!$I$164*(1+Inputs!$B$155)/Inputs!$K$164*Inputs!$B$152*Inputs!$B$154,0) -> 3480 | F8: =IF(AND(F$5>=Inputs!$J$164,F$5<Inputs!$J$164+Inputs!$K$164),Inputs!$I$164*(1+Inputs!$B$155)/Inputs!$K$164*Inputs!$B$152*Inputs!$B$154,0) -> 3480 | G8: =IF(AND(G$5>=Inputs!$J$164,G$5<Inputs!$J$164+Inputs!$K$164),Inputs!$I$164*(1+Inputs!$B$155)/Inputs!$K$164*Inputs!$B$152*Inputs!$B$154,0) -> 3480 | H8: =IF(AND(H$5>=Inputs!$J$164,H$5<Inputs!$J$164+Inputs!$K$164),Inputs!$I$164*(1+Inputs!$B$155)/Inputs!$K$164*Inputs!$B$152*Inputs!$B$154,0) -> 0 | I8: =IF(AND(I$5>=Inputs!$J$164,I$5<Inputs!$J$164+Inputs!$K$164),Inputs!$I$164*(1+Inputs!$B$155)/Inputs!$K$164*Inputs!$B$152*Inputs!$B$154,0) -> 0 | J8: =IF(AND(J$5>=Inputs!$J$164,J$5<Inputs!$J$164+Inputs!$K$164),Inputs!$I$164*(1+Inputs!$B$155)/Inputs!$K$164*Inputs!$B$152*Inputs!$B$154,0) -> 0 | K8: =IF(AND(K$5>=Inputs!$J$164,K$5<Inputs!$J$164+Inputs!$K$164),Inputs!$I$164*(1+Inputs!$B$155)/Inputs!$K$164*Inputs!$B$152*Inputs!$B$154,0) -> 0 | ... AM8: =IF(AND(AM$5>=Inputs!$J$164,AM$5<Inputs!$J$164+Inputs!$K$164),Inputs!$I$164*(1+Inputs!$B$155)/Inputs!$K$164*Inputs!$B$152*Inputs!$B$154,0) -> 0 | AN8: =SUM(D8:AM8) -> 10440 | AO8: =SUM(D8:O8) -> 10440 | AP8: =SUM(P8:AA8) -> 0 | AQ8: =SUM(AB8:AM8) -> 0
A9: =Inputs!A165 -> Data backlog, must-have before launch (DATA-001 to 020) | B9: $ | C9: =Inputs!I165*(1+Inputs!$B$155) -> 64.8 | D9: =IF(AND(D$5>=Inputs!$J$165,D$5<Inputs!$J$165+Inputs!$K$165),Inputs!$I$165*(1+Inputs!$B$155)/Inputs!$K$165*Inputs!$B$152*Inputs!$B$154,0) -> 12960 | E9: =IF(AND(E$5>=Inputs!$J$165,E$5<Inputs!$J$165+Inputs!$K$165),Inputs!$I$165*(1+Inputs!$B$155)/Inputs!$K$165*Inputs!$B$152*Inputs!$B$154,0) -> 12960 | F9: =IF(AND(F$5>=Inputs!$J$165,F$5<Inputs!$J$165+Inputs!$K$165),Inputs!$I$165*(1+Inputs!$B$155)/Inputs!$K$165*Inputs!$B$152*Inputs!$B$154,0) -> 12960 | G9: =IF(AND(G$5>=Inputs!$J$165,G$5<Inputs!$J$165+Inputs!$K$165),Inputs!$I$165*(1+Inputs!$B$155)/Inputs!$K$165*Inputs!$B$152*Inputs!$B$154,0) -> 0 | H9: =IF(AND(H$5>=Inputs!$J$165,H$5<Inputs!$J$165+Inputs!$K$165),Inputs!$I$165*(1+Inputs!$B$155)/Inputs!$K$165*Inputs!$B$152*Inputs!$B$154,0) -> 0 | I9: =IF(AND(I$5>=Inputs!$J$165,I$5<Inputs!$J$165+Inputs!$K$165),Inputs!$I$165*(1+Inputs!$B$155)/Inputs!$K$165*Inputs!$B$152*Inputs!$B$154,0) -> 0 | J9: =IF(AND(J$5>=Inputs!$J$165,J$5<Inputs!$J$165+Inputs!$K$165),Inputs!$I$165*(1+Inputs!$B$155)/Inputs!$K$165*Inputs!$B$152*Inputs!$B$154,0) -> 0 | K9: =IF(AND(K$5>=Inputs!$J$165,K$5<Inputs!$J$165+Inputs!$K$165),Inputs!$I$165*(1+Inputs!$B$155)/Inputs!$K$165*Inputs!$B$152*Inputs!$B$154,0) -> 0 | ... AM9: =IF(AND(AM$5>=Inputs!$J$165,AM$5<Inputs!$J$165+Inputs!$K$165),Inputs!$I$165*(1+Inputs!$B$155)/Inputs!$K$165*Inputs!$B$152*Inputs!$B$154,0) -> 0 | AN9: =SUM(D9:AM9) -> 38880 | AO9: =SUM(D9:O9) -> 38880 | AP9: =SUM(P9:AA9) -> 0 | AQ9: =SUM(AB9:AM9) -> 0
A10: =Inputs!A166 -> CX must-fix before launch (CX-01 to 36) | B10: $ | C10: =Inputs!I166*(1+Inputs!$B$155) -> 36.9 | D10: =IF(AND(D$5>=Inputs!$J$166,D$5<Inputs!$J$166+Inputs!$K$166),Inputs!$I$166*(1+Inputs!$B$155)/Inputs!$K$166*Inputs!$B$152*Inputs!$B$154,0) -> 11070 | E10: =IF(AND(E$5>=Inputs!$J$166,E$5<Inputs!$J$166+Inputs!$K$166),Inputs!$I$166*(1+Inputs!$B$155)/Inputs!$K$166*Inputs!$B$152*Inputs!$B$154,0) -> 11070 | F10: =IF(AND(F$5>=Inputs!$J$166,F$5<Inputs!$J$166+Inputs!$K$166),Inputs!$I$166*(1+Inputs!$B$155)/Inputs!$K$166*Inputs!$B$152*Inputs!$B$154,0) -> 0 | G10: =IF(AND(G$5>=Inputs!$J$166,G$5<Inputs!$J$166+Inputs!$K$166),Inputs!$I$166*(1+Inputs!$B$155)/Inputs!$K$166*Inputs!$B$152*Inputs!$B$154,0) -> 0 | H10: =IF(AND(H$5>=Inputs!$J$166,H$5<Inputs!$J$166+Inputs!$K$166),Inputs!$I$166*(1+Inputs!$B$155)/Inputs!$K$166*Inputs!$B$152*Inputs!$B$154,0) -> 0 | I10: =IF(AND(I$5>=Inputs!$J$166,I$5<Inputs!$J$166+Inputs!$K$166),Inputs!$I$166*(1+Inputs!$B$155)/Inputs!$K$166*Inputs!$B$152*Inputs!$B$154,0) -> 0 | J10: =IF(AND(J$5>=Inputs!$J$166,J$5<Inputs!$J$166+Inputs!$K$166),Inputs!$I$166*(1+Inputs!$B$155)/Inputs!$K$166*Inputs!$B$152*Inputs!$B$154,0) -> 0 | K10: =IF(AND(K$5>=Inputs!$J$166,K$5<Inputs!$J$166+Inputs!$K$166),Inputs!$I$166*(1+Inputs!$B$155)/Inputs!$K$166*Inputs!$B$152*Inputs!$B$154,0) -> 0 | ... AM10: =IF(AND(AM$5>=Inputs!$J$166,AM$5<Inputs!$J$166+Inputs!$K$166),Inputs!$I$166*(1+Inputs!$B$155)/Inputs!$K$166*Inputs!$B$152*Inputs!$B$154,0) -> 0 | AN10: =SUM(D10:AM10) -> 22140 | AO10: =SUM(D10:O10) -> 22140 | AP10: =SUM(P10:AA10) -> 0 | AQ10: =SUM(AB10:AM10) -> 0
A11: =Inputs!A167 -> CTO integration, wiring, review and release (placeholder) | B11: $ | C11: =Inputs!I167*(1+Inputs!$B$155) -> 12 | D11: =IF(AND(D$5>=Inputs!$J$167,D$5<Inputs!$J$167+Inputs!$K$167),Inputs!$I$167*(1+Inputs!$B$155)/Inputs!$K$167*Inputs!$B$152*Inputs!$B$154,0) -> 2400 | E11: =IF(AND(E$5>=Inputs!$J$167,E$5<Inputs!$J$167+Inputs!$K$167),Inputs!$I$167*(1+Inputs!$B$155)/Inputs!$K$167*Inputs!$B$152*Inputs!$B$154,0) -> 2400 | F11: =IF(AND(F$5>=Inputs!$J$167,F$5<Inputs!$J$167+Inputs!$K$167),Inputs!$I$167*(1+Inputs!$B$155)/Inputs!$K$167*Inputs!$B$152*Inputs!$B$154,0) -> 2400 | G11: =IF(AND(G$5>=Inputs!$J$167,G$5<Inputs!$J$167+Inputs!$K$167),Inputs!$I$167*(1+Inputs!$B$155)/Inputs!$K$167*Inputs!$B$152*Inputs!$B$154,0) -> 0 | H11: =IF(AND(H$5>=Inputs!$J$167,H$5<Inputs!$J$167+Inputs!$K$167),Inputs!$I$167*(1+Inputs!$B$155)/Inputs!$K$167*Inputs!$B$152*Inputs!$B$154,0) -> 0 | I11: =IF(AND(I$5>=Inputs!$J$167,I$5<Inputs!$J$167+Inputs!$K$167),Inputs!$I$167*(1+Inputs!$B$155)/Inputs!$K$167*Inputs!$B$152*Inputs!$B$154,0) -> 0 | J11: =IF(AND(J$5>=Inputs!$J$167,J$5<Inputs!$J$167+Inputs!$K$167),Inputs!$I$167*(1+Inputs!$B$155)/Inputs!$K$167*Inputs!$B$152*Inputs!$B$154,0) -> 0 | K11: =IF(AND(K$5>=Inputs!$J$167,K$5<Inputs!$J$167+Inputs!$K$167),Inputs!$I$167*(1+Inputs!$B$155)/Inputs!$K$167*Inputs!$B$152*Inputs!$B$154,0) -> 0 | ... AM11: =IF(AND(AM$5>=Inputs!$J$167,AM$5<Inputs!$J$167+Inputs!$K$167),Inputs!$I$167*(1+Inputs!$B$155)/Inputs!$K$167*Inputs!$B$152*Inputs!$B$154,0) -> 0 | AN11: =SUM(D11:AM11) -> 7200 | AO11: =SUM(D11:O11) -> 7200 | AP11: =SUM(P11:AA11) -> 0 | AQ11: =SUM(AB11:AM11) -> 0
A12: Core launch engineering, gross | B12: $ | C12: =SUM(C7:C11) -> 178.5 | D12: =SUM(D7:D11) -> 40650 | E12: =SUM(E7:E11) -> 44130 | F12: =SUM(F7:F11) -> 18840 | G12: =SUM(G7:G11) -> 3480 | H12: =SUM(H7:H11) -> 0 | I12: =SUM(I7:I11) -> 0 | J12: =SUM(J7:J11) -> 0 | ... AM12: =SUM(AM7:AM11) -> 0 | AN12: =SUM(D12:AM12) -> 107100 | AO12: =SUM(D12:O12) -> 107100 | AP12: =SUM(P12:AA12) -> 0 | AQ12: =SUM(AB12:AM12) -> 0
A13: Core launch engineering in the forecast (after switch Scenarios!B46) | B13: $ | D13: =D12*Scenarios!$B$46 -> 40650 | E13: =E12*Scenarios!$B$46 -> 44130 | F13: =F12*Scenarios!$B$46 -> 18840 | G13: =G12*Scenarios!$B$46 -> 3480 | H13: =H12*Scenarios!$B$46 -> 0 | I13: =I12*Scenarios!$B$46 -> 0 | J13: =J12*Scenarios!$B$46 -> 0 | K13: =K12*Scenarios!$B$46 -> 0 | ... AM13: =AM12*Scenarios!$B$46 -> 0 | AN13: =SUM(D13:AM13) -> 107100 | AO13: =SUM(D13:O13) -> 107100 | AP13: =SUM(P13:AA13) -> 0 | AQ13: =SUM(AB13:AM13) -> 0
A15: (b) AGENT / AI-PLATFORM INTEGRATIONS (phases P0-P4 from the integrations plan; gates cascade)
A17: Effective gate to run P0 (1 = spent) | C17: =1 -> 1
A18: Effective gate to run P1 (1 = spent) | C18: =Inputs!$E$172 -> 1
A19: Effective gate to run P2 (1 = spent) | C19: =Inputs!$E$172*Inputs!$E$173 -> 1
A20: Effective gate to run P3 (1 = spent) | C20: =Inputs!$E$172*Inputs!$E$173*Inputs!$E$174 -> 1
A21: Effective gate to run P4 (1 = spent) | C21: =Inputs!$E$172*Inputs!$E$173*Inputs!$E$174*Inputs!$E$175 -> 1
A23: =Inputs!A171&" + attorney (agent addenda)" -> P0 new agent work (AGT-001 to 007) + attorney (agent addenda) | B23: $ | C23: =Inputs!B171 -> 20 | D23: =IF(AND(D$5>=Inputs!$C$171,D$5<Inputs!$C$171+Inputs!$D$171),(Inputs!$B$171*Inputs!$B$153*Inputs!$B$154+Inputs!$B$176)/Inputs!$D$171,0)*$C$17 -> 18000 | E23: =IF(AND(E$5>=Inputs!$C$171,E$5<Inputs!$C$171+Inputs!$D$171),(Inputs!$B$171*Inputs!$B$153*Inputs!$B$154+Inputs!$B$176)/Inputs!$D$171,0)*$C$17 -> 0 | F23: =IF(AND(F$5>=Inputs!$C$171,F$5<Inputs!$C$171+Inputs!$D$171),(Inputs!$B$171*Inputs!$B$153*Inputs!$B$154+Inputs!$B$176)/Inputs!$D$171,0)*$C$17 -> 0 | G23: =IF(AND(G$5>=Inputs!$C$171,G$5<Inputs!$C$171+Inputs!$D$171),(Inputs!$B$171*Inputs!$B$153*Inputs!$B$154+Inputs!$B$176)/Inputs!$D$171,0)*$C$17 -> 0 | H23: =IF(AND(H$5>=Inputs!$C$171,H$5<Inputs!$C$171+Inputs!$D$171),(Inputs!$B$171*Inputs!$B$153*Inputs!$B$154+Inputs!$B$176)/Inputs!$D$171,0)*$C$17 -> 0 | I23: =IF(AND(I$5>=Inputs!$C$171,I$5<Inputs!$C$171+Inputs!$D$171),(Inputs!$B$171*Inputs!$B$153*Inputs!$B$154+Inputs!$B$176)/Inputs!$D$171,0)*$C$17 -> 0 | J23: =IF(AND(J$5>=Inputs!$C$171,J$5<Inputs!$C$171+Inputs!$D$171),(Inputs!$B$171*Inputs!$B$153*Inputs!$B$154+Inputs!$B$176)/Inputs!$D$171,0)*$C$17 -> 0 | K23: =IF(AND(K$5>=Inputs!$C$171,K$5<Inputs!$C$171+Inputs!$D$171),(Inputs!$B$171*Inputs!$B$153*Inputs!$B$154+Inputs!$B$176)/Inputs!$D$171,0)*$C$17 -> 0 | ... AM23: =IF(AND(AM$5>=Inputs!$C$171,AM$5<Inputs!$C$171+Inputs!$D$171),(Inputs!$B$171*Inputs!$B$153*Inputs!$B$154+Inputs!$B$176)/Inputs!$D$171,0)*$C$17 -> 0 | AN23: =SUM(D23:AM23) -> 18000 | AO23: =SUM(D23:O23) -> 18000 | AP23: =SUM(P23:AA23) -> 0 | AQ23: =SUM(AB23:AM23) -> 0
A24: =Inputs!A172 -> P1 read and draft (AGT-010 to 019) | B24: $ | C24: =Inputs!B172 -> 37.5 | D24: =IF(AND(D$5>=Inputs!$C$172,D$5<Inputs!$C$172+Inputs!$D$172),(Inputs!$B$172*Inputs!$B$153*Inputs!$B$154)/Inputs!$D$172,0)*$C$18 -> 0 | E24: =IF(AND(E$5>=Inputs!$C$172,E$5<Inputs!$C$172+Inputs!$D$172),(Inputs!$B$172*Inputs!$B$153*Inputs!$B$154)/Inputs!$D$172,0)*$C$18 -> 11250 | F24: =IF(AND(F$5>=Inputs!$C$172,F$5<Inputs!$C$172+Inputs!$D$172),(Inputs!$B$172*Inputs!$B$153*Inputs!$B$154)/Inputs!$D$172,0)*$C$18 -> 11250 | G24: =IF(AND(G$5>=Inputs!$C$172,G$5<Inputs!$C$172+Inputs!$D$172),(Inputs!$B$172*Inputs!$B$153*Inputs!$B$154)/Inputs!$D$172,0)*$C$18 -> 0 | H24: =IF(AND(H$5>=Inputs!$C$172,H$5<Inputs!$C$172+Inputs!$D$172),(Inputs!$B$172*Inputs!$B$153*Inputs!$B$154)/Inputs!$D$172,0)*$C$18 -> 0 | I24: =IF(AND(I$5>=Inputs!$C$172,I$5<Inputs!$C$172+Inputs!$D$172),(Inputs!$B$172*Inputs!$B$153*Inputs!$B$154)/Inputs!$D$172,0)*$C$18 -> 0 | J24: =IF(AND(J$5>=Inputs!$C$172,J$5<Inputs!$C$172+Inputs!$D$172),(Inputs!$B$172*Inputs!$B$153*Inputs!$B$154)/Inputs!$D$172,0)*$C$18 -> 0 | K24: =IF(AND(K$5>=Inputs!$C$172,K$5<Inputs!$C$172+Inputs!$D$172),(Inputs!$B$172*Inputs!$B$153*Inputs!$B$154)/Inputs!$D$172,0)*$C$18 -> 0 | ... AM24: =IF(AND(AM$5>=Inputs!$C$172,AM$5<Inputs!$C$172+Inputs!$D$172),(Inputs!$B$172*Inputs!$B$153*Inputs!$B$154)/Inputs!$D$172,0)*$C$18 -> 0 | AN24: =SUM(D24:AM24) -> 22500 | AO24: =SUM(D24:O24) -> 22500 | AP24: =SUM(P24:AA24) -> 0 | AQ24: =SUM(AB24:AM24) -> 0
A25: =Inputs!A173 -> P2 approve and pay (AGT-020 to 027) | B25: $ | C25: =Inputs!B173 -> 29 | D25: =IF(AND(D$5>=Inputs!$C$173,D$5<Inputs!$C$173+Inputs!$D$173),(Inputs!$B$173*Inputs!$B$153*Inputs!$B$154)/Inputs!$D$173,0)*$C$19 -> 0 | E25: =IF(AND(E$5>=Inputs!$C$173,E$5<Inputs!$C$173+Inputs!$D$173),(Inputs!$B$173*Inputs!$B$153*Inputs!$B$154)/Inputs!$D$173,0)*$C$19 -> 0 | F25: =IF(AND(F$5>=Inputs!$C$173,F$5<Inputs!$C$173+Inputs!$D$173),(Inputs!$B$173*Inputs!$B$153*Inputs!$B$154)/Inputs!$D$173,0)*$C$19 -> 0 | G25: =IF(AND(G$5>=Inputs!$C$173,G$5<Inputs!$C$173+Inputs!$D$173),(Inputs!$B$173*Inputs!$B$153*Inputs!$B$154)/Inputs!$D$173,0)*$C$19 -> 8700 | H25: =IF(AND(H$5>=Inputs!$C$173,H$5<Inputs!$C$173+Inputs!$D$173),(Inputs!$B$173*Inputs!$B$153*Inputs!$B$154)/Inputs!$D$173,0)*$C$19 -> 8700 | I25: =IF(AND(I$5>=Inputs!$C$173,I$5<Inputs!$C$173+Inputs!$D$173),(Inputs!$B$173*Inputs!$B$153*Inputs!$B$154)/Inputs!$D$173,0)*$C$19 -> 0 | J25: =IF(AND(J$5>=Inputs!$C$173,J$5<Inputs!$C$173+Inputs!$D$173),(Inputs!$B$173*Inputs!$B$153*Inputs!$B$154)/Inputs!$D$173,0)*$C$19 -> 0 | K25: =IF(AND(K$5>=Inputs!$C$173,K$5<Inputs!$C$173+Inputs!$D$173),(Inputs!$B$173*Inputs!$B$153*Inputs!$B$154)/Inputs!$D$173,0)*$C$19 -> 0 | ... AM25: =IF(AND(AM$5>=Inputs!$C$173,AM$5<Inputs!$C$173+Inputs!$D$173),(Inputs!$B$173*Inputs!$B$153*Inputs!$B$154)/Inputs!$D$173,0)*$C$19 -> 0 | AN25: =SUM(D25:AM25) -> 17400 | AO25: =SUM(D25:O25) -> 17400 | AP25: =SUM(P25:AA25) -> 0 | AQ25: =SUM(AB25:AM25) -> 0
A26: =Inputs!A174&" (+ wallet if on)" -> P3 rules, keys, autonomy (AGT-030 to 034) (+ wallet if on) | B26: $ | C26: =Inputs!B174 -> 19 | D26: =IF(AND(D$5>=Inputs!$C$174,D$5<Inputs!$C$174+Inputs!$D$174),(Inputs!$B$174*Inputs!$B$153*Inputs!$B$154+Inputs!$B$178*Inputs!$B$177*Inputs!$B$153*Inputs!$B$154)/Inputs!$D$174,0)*$C$20 -> 0 | E26: =IF(AND(E$5>=Inputs!$C$174,E$5<Inputs!$C$174+Inputs!$D$174),(Inputs!$B$174*Inputs!$B$153*Inputs!$B$154+Inputs!$B$178*Inputs!$B$177*Inputs!$B$153*Inputs!$B$154)/Inputs!$D$174,0)*$C$20 -> 0 | F26: =IF(AND(F$5>=Inputs!$C$174,F$5<Inputs!$C$174+Inputs!$D$174),(Inputs!$B$174*Inputs!$B$153*Inputs!$B$154+Inputs!$B$178*Inputs!$B$177*Inputs!$B$153*Inputs!$B$154)/Inputs!$D$174,0)*$C$20 -> 0 | G26: =IF(AND(G$5>=Inputs!$C$174,G$5<Inputs!$C$174+Inputs!$D$174),(Inputs!$B$174*Inputs!$B$153*Inputs!$B$154+Inputs!$B$178*Inputs!$B$177*Inputs!$B$153*Inputs!$B$154)/Inputs!$D$174,0)*$C$20 -> 0 | H26: =IF(AND(H$5>=Inputs!$C$174,H$5<Inputs!$C$174+Inputs!$D$174),(Inputs!$B$174*Inputs!$B$153*Inputs!$B$154+Inputs!$B$178*Inputs!$B$177*Inputs!$B$153*Inputs!$B$154)/Inputs!$D$174,0)*$C$20 -> 0 | I26: =IF(AND(I$5>=Inputs!$C$174,I$5<Inputs!$C$174+Inputs!$D$174),(Inputs!$B$174*Inputs!$B$153*Inputs!$B$154+Inputs!$B$178*Inputs!$B$177*Inputs!$B$153*Inputs!$B$154)/Inputs!$D$174,0)*$C$20 -> 0 | J26: =IF(AND(J$5>=Inputs!$C$174,J$5<Inputs!$C$174+Inputs!$D$174),(Inputs!$B$174*Inputs!$B$153*Inputs!$B$154+Inputs!$B$178*Inputs!$B$177*Inputs!$B$153*Inputs!$B$154)/Inputs!$D$174,0)*$C$20 -> 0 | K26: =IF(AND(K$5>=Inputs!$C$174,K$5<Inputs!$C$174+Inputs!$D$174),(Inputs!$B$174*Inputs!$B$153*Inputs!$B$154+Inputs!$B$178*Inputs!$B$177*Inputs!$B$153*Inputs!$B$154)/Inputs!$D$174,0)*$C$20 -> 0 | ... AM26: =IF(AND(AM$5>=Inputs!$C$174,AM$5<Inputs!$C$174+Inputs!$D$174),(Inputs!$B$174*Inputs!$B$153*Inputs!$B$154+Inputs!$B$178*Inputs!$B$177*Inputs!$B$153*Inputs!$B$154)/Inputs!$D$174,0)*$C$20 -> 0 | AN26: =SUM(D26:AM26) -> 11400 | AO26: =SUM(D26:O26) -> 11400 | AP26: =SUM(P26:AA26) -> 0 | AQ26: =SUM(AB26:AM26) -> 0
A27: =Inputs!A175 -> P4 distribution / directory listings (AGT-040 to 045) | B27: $ | C27: =Inputs!B175 -> 24 | D27: =IF(AND(D$5>=Inputs!$C$175,D$5<Inputs!$C$175+Inputs!$D$175),(Inputs!$B$175*Inputs!$B$153*Inputs!$B$154)/Inputs!$D$175,0)*$C$21 -> 0 | E27: =IF(AND(E$5>=Inputs!$C$175,E$5<Inputs!$C$175+Inputs!$D$175),(Inputs!$B$175*Inputs!$B$153*Inputs!$B$154)/Inputs!$D$175,0)*$C$21 -> 0 | F27: =IF(AND(F$5>=Inputs!$C$175,F$5<Inputs!$C$175+Inputs!$D$175),(Inputs!$B$175*Inputs!$B$153*Inputs!$B$154)/Inputs!$D$175,0)*$C$21 -> 0 | G27: =IF(AND(G$5>=Inputs!$C$175,G$5<Inputs!$C$175+Inputs!$D$175),(Inputs!$B$175*Inputs!$B$153*Inputs!$B$154)/Inputs!$D$175,0)*$C$21 -> 0 | H27: =IF(AND(H$5>=Inputs!$C$175,H$5<Inputs!$C$175+Inputs!$D$175),(Inputs!$B$175*Inputs!$B$153*Inputs!$B$154)/Inputs!$D$175,0)*$C$21 -> 0 | I27: =IF(AND(I$5>=Inputs!$C$175,I$5<Inputs!$C$175+Inputs!$D$175),(Inputs!$B$175*Inputs!$B$153*Inputs!$B$154)/Inputs!$D$175,0)*$C$21 -> 0 | J27: =IF(AND(J$5>=Inputs!$C$175,J$5<Inputs!$C$175+Inputs!$D$175),(Inputs!$B$175*Inputs!$B$153*Inputs!$B$154)/Inputs!$D$175,0)*$C$21 -> 0 | K27: =IF(AND(K$5>=Inputs!$C$175,K$5<Inputs!$C$175+Inputs!$D$175),(Inputs!$B$175*Inputs!$B$153*Inputs!$B$154)/Inputs!$D$175,0)*$C$21 -> 0 | ... AM27: =IF(AND(AM$5>=Inputs!$C$175,AM$5<Inputs!$C$175+Inputs!$D$175),(Inputs!$B$175*Inputs!$B$153*Inputs!$B$154)/Inputs!$D$175,0)*$C$21 -> 0 | AN27: =SUM(D27:AM27) -> 14400 | AO27: =SUM(D27:O27) -> 4800 | AP27: =SUM(P27:AA27) -> 9600 | AQ27: =SUM(AB27:AM27) -> 0
A28: Agent / AI-platform program R&D, gross | B28: $ | D28: =SUM(D23:D27) -> 18000 | E28: =SUM(E23:E27) -> 11250 | F28: =SUM(F23:F27) -> 11250 | G28: =SUM(G23:G27) -> 8700 | H28: =SUM(H23:H27) -> 8700 | I28: =SUM(I23:I27) -> 0 | J28: =SUM(J23:J27) -> 0 | K28: =SUM(K23:K27) -> 0 | ... AM28: =SUM(AM23:AM27) -> 0 | AN28: =SUM(D28:AM28) -> 83700 | AO28: =SUM(D28:O28) -> 74100 | AP28: =SUM(P28:AA28) -> 9600 | AQ28: =SUM(AB28:AM28) -> 0
A30: (c) KIOSK PROGRAM, PHASES P0-P4 (low / base / high follows the scenario selector; gates G0-G3 cascade)
A31: Phase summary (selected scenario) | B31: Gate eff. | C31: Labor $ | D31: Non-labor $ | E31: Contingency $ | F31: Phase total $ | G31: Spent $ (after gates)
A32: =Inputs!A182 -> P0 Concept validation | B32: =1 -> 1 | C32: =(Inputs!$B$182*Inputs!$H$189+Inputs!$C$182*Inputs!$H$190)*Inputs!$H$188 -> 26000 | D32: =INDEX(Inputs!$G$182:$I$182,Scenarios!$B$4) -> 4100 | E32: =(C32+D32)*INDEX(Inputs!$J$182:$L$182,Scenarios!$B$4) -> 4515 | F32: =C32+D32+E32 -> 34615 | G32: =F32*B32 -> 34615
A33: =Inputs!A183 -> P1 Pilot prototype | B33: =Inputs!$F$183 -> 0 | C33: =(Inputs!$B$183*Inputs!$H$189+Inputs!$C$183*Inputs!$H$190)*Inputs!$H$188 -> 187000 | D33: =INDEX(Inputs!$G$183:$I$183,Scenarios!$B$4) -> 38300 | E33: =(C33+D33)*INDEX(Inputs!$J$183:$L$183,Scenarios!$B$4) -> 45060 | F33: =C33+D33+E33 -> 270360 | G33: =F33*B33 -> 0
A34: =Inputs!A184 -> P2 Field pilot (1-3 sites) | B34: =Inputs!$F$183*Inputs!$F$184 -> 0 | C34: =(Inputs!$B$184*Inputs!$H$189+Inputs!$C$184*Inputs!$H$190)*Inputs!$H$188 -> 98600 | D34: =INDEX(Inputs!$G$184:$I$184,Scenarios!$B$4) -> 45900 | E34: =(C34+D34)*INDEX(Inputs!$J$184:$L$184,Scenarios!$B$4) -> 28900 | F34: =C34+D34+E34 -> 173400 | G34: =F34*B34 -> 0
A35: =Inputs!A185 -> P3 Productized small batch | B35: =Inputs!$F$183*Inputs!$F$184*Inputs!$F$185 -> 0 | C35: =(Inputs!$B$185*Inputs!$H$189+Inputs!$C$185*Inputs!$H$190)*Inputs!$H$188 -> 200000 | D35: =INDEX(Inputs!$G$185:$I$185,Scenarios!$B$4) -> 106000 | E35: =(C35+D35)*INDEX(Inputs!$J$185:$L$185,Scenarios!$B$4) -> 61200 | F35: =C35+D35+E35 -> 367200 | G35: =F35*B35 -> 0
A36: =Inputs!A186 -> P4 Scale (sustaining) | B36: =Inputs!$F$183*Inputs!$F$184*Inputs!$F$185*Inputs!$F$186 -> 0 | C36: =(Inputs!$B$186*Inputs!$H$189+Inputs!$C$186*Inputs!$H$190)*Inputs!$H$188 -> 160000 | D36: =INDEX(Inputs!$G$186:$I$186,Scenarios!$B$4) -> 53000 | E36: =(C36+D36)*INDEX(Inputs!$J$186:$L$186,Scenarios!$B$4) -> 42600 | F36: =C36+D36+E36 -> 255600 | G36: =F36*B36 -> 0
A37: Total (ties to kiosk/08: $561k low, $1,101k base, $2,248k high when all gates pass) | F37: =SUM(F32:F36) -> 1101175 | G37: =SUM(G32:G36) -> 34615
A40: =Inputs!A182 -> P0 Concept validation | B40: $ | C40: =(Inputs!B182+Inputs!C182)*Inputs!$H$188 -> 26 | D40: =IF(AND(D$5>=Inputs!$D$182,D$5<Inputs!$D$182+Inputs!$E$182),$G$32/Inputs!$E$182,0) -> 0 | E40: =IF(AND(E$5>=Inputs!$D$182,E$5<Inputs!$D$182+Inputs!$E$182),$G$32/Inputs!$E$182,0) -> 0 | F40: =IF(AND(F$5>=Inputs!$D$182,F$5<Inputs!$D$182+Inputs!$E$182),$G$32/Inputs!$E$182,0) -> 0 | G40: =IF(AND(G$5>=Inputs!$D$182,G$5<Inputs!$D$182+Inputs!$E$182),$G$32/Inputs!$E$182,0) -> 0 | H40: =IF(AND(H$5>=Inputs!$D$182,H$5<Inputs!$D$182+Inputs!$E$182),$G$32/Inputs!$E$182,0) -> 0 | I40: =IF(AND(I$5>=Inputs!$D$182,I$5<Inputs!$D$182+Inputs!$E$182),$G$32/Inputs!$E$182,0) -> 0 | J40: =IF(AND(J$5>=Inputs!$D$182,J$5<Inputs!$D$182+Inputs!$E$182),$G$32/Inputs!$E$182,0) -> 11538.333 | K40: =IF(AND(K$5>=Inputs!$D$182,K$5<Inputs!$D$182+Inputs!$E$182),$G$32/Inputs!$E$182,0) -> 11538.333 | ... AM40: =IF(AND(AM$5>=Inputs!$D$182,AM$5<Inputs!$D$182+Inputs!$E$182),$G$32/Inputs!$E$182,0) -> 0 | AN40: =SUM(D40:AM40) -> 34615 | AO40: =SUM(D40:O40) -> 34615 | AP40: =SUM(P40:AA40) -> 0 | AQ40: =SUM(AB40:AM40) -> 0
A41: =Inputs!A183 -> P1 Pilot prototype | B41: $ | C41: =(Inputs!B183+Inputs!C183)*Inputs!$H$188 -> 187 | D41: =IF(AND(D$5>=Inputs!$D$183,D$5<Inputs!$D$183+Inputs!$E$183),$G$33/Inputs!$E$183,0) -> 0 | E41: =IF(AND(E$5>=Inputs!$D$183,E$5<Inputs!$D$183+Inputs!$E$183),$G$33/Inputs!$E$183,0) -> 0 | F41: =IF(AND(F$5>=Inputs!$D$183,F$5<Inputs!$D$183+Inputs!$E$183),$G$33/Inputs!$E$183,0) -> 0 | G41: =IF(AND(G$5>=Inputs!$D$183,G$5<Inputs!$D$183+Inputs!$E$183),$G$33/Inputs!$E$183,0) -> 0 | H41: =IF(AND(H$5>=Inputs!$D$183,H$5<Inputs!$D$183+Inputs!$E$183),$G$33/Inputs!$E$183,0) -> 0 | I41: =IF(AND(I$5>=Inputs!$D$183,I$5<Inputs!$D$183+Inputs!$E$183),$G$33/Inputs!$E$183,0) -> 0 | J41: =IF(AND(J$5>=Inputs!$D$183,J$5<Inputs!$D$183+Inputs!$E$183),$G$33/Inputs!$E$183,0) -> 0 | K41: =IF(AND(K$5>=Inputs!$D$183,K$5<Inputs!$D$183+Inputs!$E$183),$G$33/Inputs!$E$183,0) -> 0 | ... AM41: =IF(AND(AM$5>=Inputs!$D$183,AM$5<Inputs!$D$183+Inputs!$E$183),$G$33/Inputs!$E$183,0) -> 0 | AN41: =SUM(D41:AM41) -> 0 | AO41: =SUM(D41:O41) -> 0 | AP41: =SUM(P41:AA41) -> 0 | AQ41: =SUM(AB41:AM41) -> 0
A42: =Inputs!A184 -> P2 Field pilot (1-3 sites) | B42: $ | C42: =(Inputs!B184+Inputs!C184)*Inputs!$H$188 -> 113 | D42: =IF(AND(D$5>=Inputs!$D$184,D$5<Inputs!$D$184+Inputs!$E$184),$G$34/Inputs!$E$184,0) -> 0 | E42: =IF(AND(E$5>=Inputs!$D$184,E$5<Inputs!$D$184+Inputs!$E$184),$G$34/Inputs!$E$184,0) -> 0 | F42: =IF(AND(F$5>=Inputs!$D$184,F$5<Inputs!$D$184+Inputs!$E$184),$G$34/Inputs!$E$184,0) -> 0 | G42: =IF(AND(G$5>=Inputs!$D$184,G$5<Inputs!$D$184+Inputs!$E$184),$G$34/Inputs!$E$184,0) -> 0 | H42: =IF(AND(H$5>=Inputs!$D$184,H$5<Inputs!$D$184+Inputs!$E$184),$G$34/Inputs!$E$184,0) -> 0 | I42: =IF(AND(I$5>=Inputs!$D$184,I$5<Inputs!$D$184+Inputs!$E$184),$G$34/Inputs!$E$184,0) -> 0 | J42: =IF(AND(J$5>=Inputs!$D$184,J$5<Inputs!$D$184+Inputs!$E$184),$G$34/Inputs!$E$184,0) -> 0 | K42: =IF(AND(K$5>=Inputs!$D$184,K$5<Inputs!$D$184+Inputs!$E$184),$G$34/Inputs!$E$184,0) -> 0 | ... AM42: =IF(AND(AM$5>=Inputs!$D$184,AM$5<Inputs!$D$184+Inputs!$E$184),$G$34/Inputs!$E$184,0) -> 0 | AN42: =SUM(D42:AM42) -> 0 | AO42: =SUM(D42:O42) -> 0 | AP42: =SUM(P42:AA42) -> 0 | AQ42: =SUM(AB42:AM42) -> 0
A43: =Inputs!A185 -> P3 Productized small batch | B43: $ | C43: =(Inputs!B185+Inputs!C185)*Inputs!$H$188 -> 200 | D43: =IF(AND(D$5>=Inputs!$D$185,D$5<Inputs!$D$185+Inputs!$E$185),$G$35/Inputs!$E$185,0) -> 0 | E43: =IF(AND(E$5>=Inputs!$D$185,E$5<Inputs!$D$185+Inputs!$E$185),$G$35/Inputs!$E$185,0) -> 0 | F43: =IF(AND(F$5>=Inputs!$D$185,F$5<Inputs!$D$185+Inputs!$E$185),$G$35/Inputs!$E$185,0) -> 0 | G43: =IF(AND(G$5>=Inputs!$D$185,G$5<Inputs!$D$185+Inputs!$E$185),$G$35/Inputs!$E$185,0) -> 0 | H43: =IF(AND(H$5>=Inputs!$D$185,H$5<Inputs!$D$185+Inputs!$E$185),$G$35/Inputs!$E$185,0) -> 0 | I43: =IF(AND(I$5>=Inputs!$D$185,I$5<Inputs!$D$185+Inputs!$E$185),$G$35/Inputs!$E$185,0) -> 0 | J43: =IF(AND(J$5>=Inputs!$D$185,J$5<Inputs!$D$185+Inputs!$E$185),$G$35/Inputs!$E$185,0) -> 0 | K43: =IF(AND(K$5>=Inputs!$D$185,K$5<Inputs!$D$185+Inputs!$E$185),$G$35/Inputs!$E$185,0) -> 0 | ... AM43: =IF(AND(AM$5>=Inputs!$D$185,AM$5<Inputs!$D$185+Inputs!$E$185),$G$35/Inputs!$E$185,0) -> 0 | AN43: =SUM(D43:AM43) -> 0 | AO43: =SUM(D43:O43) -> 0 | AP43: =SUM(P43:AA43) -> 0 | AQ43: =SUM(AB43:AM43) -> 0
A44: =Inputs!A186 -> P4 Scale (sustaining) | B44: $ | C44: =(Inputs!B186+Inputs!C186)*Inputs!$H$188 -> 160 | D44: =IF(AND(D$5>=Inputs!$D$186,D$5<Inputs!$D$186+Inputs!$E$186),$G$36/Inputs!$E$186,0) -> 0 | E44: =IF(AND(E$5>=Inputs!$D$186,E$5<Inputs!$D$186+Inputs!$E$186),$G$36/Inputs!$E$186,0) -> 0 | F44: =IF(AND(F$5>=Inputs!$D$186,F$5<Inputs!$D$186+Inputs!$E$186),$G$36/Inputs!$E$186,0) -> 0 | G44: =IF(AND(G$5>=Inputs!$D$186,G$5<Inputs!$D$186+Inputs!$E$186),$G$36/Inputs!$E$186,0) -> 0 | H44: =IF(AND(H$5>=Inputs!$D$186,H$5<Inputs!$D$186+Inputs!$E$186),$G$36/Inputs!$E$186,0) -> 0 | I44: =IF(AND(I$5>=Inputs!$D$186,I$5<Inputs!$D$186+Inputs!$E$186),$G$36/Inputs!$E$186,0) -> 0 | J44: =IF(AND(J$5>=Inputs!$D$186,J$5<Inputs!$D$186+Inputs!$E$186),$G$36/Inputs!$E$186,0) -> 0 | K44: =IF(AND(K$5>=Inputs!$D$186,K$5<Inputs!$D$186+Inputs!$E$186),$G$36/Inputs!$E$186,0) -> 0 | ... AM44: =IF(AND(AM$5>=Inputs!$D$186,AM$5<Inputs!$D$186+Inputs!$E$186),$G$36/Inputs!$E$186,0) -> 0 | AN44: =SUM(D44:AM44) -> 0 | AO44: =SUM(D44:O44) -> 0 | AP44: =SUM(P44:AA44) -> 0 | AQ44: =SUM(AB44:AM44) -> 0
A45: Kiosk program R&D (expensed), gross | B45: $ | D45: =SUM(D40:D44) -> 0 | E45: =SUM(E40:E44) -> 0 | F45: =SUM(F40:F44) -> 0 | G45: =SUM(G40:G44) -> 0 | H45: =SUM(H40:H44) -> 0 | I45: =SUM(I40:I44) -> 0 | J45: =SUM(J40:J44) -> 11538.333 | K45: =SUM(K40:K44) -> 11538.333 | ... AM45: =SUM(AM40:AM44) -> 0 | AN45: =SUM(D45:AM45) -> 34615 | AO45: =SUM(D45:O45) -> 34615 | AP45: =SUM(P45:AA45) -> 0 | AQ45: =SUM(AB45:AM45) -> 0
A47: All program R&D, gross (core + agent + kiosk) | B47: $ | D47: =D12+D28+D45 -> 58650 | E47: =E12+E28+E45 -> 55380 | F47: =F12+F28+F45 -> 30090 | G47: =G12+G28+G45 -> 12180 | H47: =H12+H28+H45 -> 8700 | I47: =I12+I28+I45 -> 0 | J47: =J12+J28+J45 -> 11538.333 | K47: =K12+K28+K45 -> 11538.333 | ... AM47: =AM12+AM28+AM45 -> 0 | AN47: =SUM(D47:AM47) -> 225415 | AO47: =SUM(D47:O47) -> 215815 | AP47: =SUM(P47:AA47) -> 9600 | AQ47: =SUM(AB47:AM47) -> 0
A49: Timing note: costs within a phase are spread evenly. The kiosk doc front-loads prototype hardware and back-loads tooling inside a phase; phase totals and cumulative cash by phase end are unchanged.

Sheet Kiosk
A1: Kiosk - fleet build, unit economics and cash (Tier B freestanding)
A2: Gross standalone program view (independent of Scenarios!B42). Case follows the scenario selector. Phase gates and fleet plan are on Inputs sections 15c-16. All kiosk numbers are guesses until P2 field data (kiosk/08).
A4: Line | B4: Unit | C4: Total / opening | D4: M1 | E4: M2 | F4: M3 | G4: M4 | H4: M5 | I4: M6 | J4: M7 | K4: M8 | L4: M9 | M4: M10 | N4: M11 | O4: M12 | P4: M13 | Q4: M14 | R4: M15 | S4: M16 | T4: M17 | U4: M18 | V4: M19 | W4: M20 | X4: M21 | Y4: M22 | Z4: M23 | AA4: M24 | AB4: M25 | AC4: M26 | AD4: M27 | AE4: M28 | AF4: M29 | AG4: M30 | AH4: M31 | AI4: M32 | AJ4: M33 | AK4: M34 | AL4: M35 | AM4: M36 | AN4: 36-mo total | AO4: Year 1 | AP4: Year 2 | AQ4: Year 3
A5: Month # | B5: # | D5: =Forecast!D6 -> 1 | E5: =Forecast!E6 -> 2 | F5: =Forecast!F6 -> 3 | G5: =Forecast!G6 -> 4 | H5: =Forecast!H6 -> 5 | I5: =Forecast!I6 -> 6 | J5: =Forecast!J6 -> 7 | K5: =Forecast!K6 -> 8 | ... AM5: =Forecast!AM6 -> 36
A6: UNIT ECONOMICS PER CARD AND PER KIOSK (selected scenario)
A7: Price per card (ex tax) | B7: =Inputs!$H$194 -> 6.99
A8: Host revenue share per card | B8: =B7*Inputs!$H$196 -> 1.7475
A9: Payment fee per card | B9: =B7*Inputs!$H$197+Inputs!$H$198 -> 0.23873
A10: Consumables per card | B10: =Inputs!$H$199 -> 0.3996
A11: Model cost, Totally custom session (live from Model Costs printed-card token cost + intake) | B11: ='Model Costs'!$J$36*Scenarios!$B$10*(1+Inputs!$B$42)+Inputs!$H$202 -> 0.3615345
A12: Model cost per card sold (session mix x cost, x (1 + abandoned sessions)) | B12: =(Inputs!$B$203*Inputs!$H$200+Inputs!$B$204*Inputs!$H$201+Inputs!$B$205*B11)*(1+Inputs!$B$206) -> 0.20381431
A13: Contribution per card (mature) | B13: =B7-B8-B9-B10-B12 -> 4.4003557
A14: Fixed operating cost per kiosk per month (6 lines, incl. service visits) | B14: =Inputs!$H$210+Inputs!$H$211+Inputs!$H$212+Inputs!$H$213+Inputs!$H$214+Inputs!$H$215 -> 262
A15: Cards per kiosk per month (mature) | B15: =Inputs!$H$195*Inputs!$B$209 -> 152
A16: Operating cash per kiosk per month (mature) | B16: =B15*B13-B14 -> 406.85406
A17: Hardware cost per kiosk at the 10-unit quantity (x scenario multiplier) | B17: =Inputs!$B$219*Inputs!$H$217 -> 11970
A18: Depreciation per kiosk per month | B18: =B17/Inputs!$H$216 -> 332.5
A19: Net after depreciation per kiosk per month (mature) | B19: =B16-B18 -> 74.354064
A20: Kiosk payback, months (hardware / operating cash; mature rate) | B20: =IF(B16>0,B17/B16,"Never at this rate") -> 29.420869
A21: Break-even cards per kiosk per day, cash | B21: =IF(B13>0,B14/(Inputs!$B$209*B13),"n/a") -> 1.9585737
A22: Break-even cards per kiosk per day, after depreciation | B22: =IF(B13>0,(B14+B18)/(Inputs!$B$209*B13),"n/a") -> 4.4441683
A24: FLEET BUILD (units deployed by month, driven by the gates)
A25: Target units live (fleet plan, Inputs) | B25: units | D25: =INDEX(Inputs!$B$226:$B$261,D$5) -> 0 | E25: =INDEX(Inputs!$B$226:$B$261,E$5) -> 0 | F25: =INDEX(Inputs!$B$226:$B$261,F$5) -> 0 | G25: =INDEX(Inputs!$B$226:$B$261,G$5) -> 0 | H25: =INDEX(Inputs!$B$226:$B$261,H$5) -> 0 | I25: =INDEX(Inputs!$B$226:$B$261,I$5) -> 0 | J25: =INDEX(Inputs!$B$226:$B$261,J$5) -> 0 | K25: =INDEX(Inputs!$B$226:$B$261,K$5) -> 0 | ... AM25: =INDEX(Inputs!$B$226:$B$261,AM$5) -> 50
A26: Units live (after gates: pilot needs G1, scale-out needs G3) | B26: units | C26: 0 | D26: =IF(AND(D$5>=Inputs!$B$224,'R&D'!$B$36=1),D25,MIN(D25,Inputs!$B$222)*'R&D'!$B$34) -> 0 | E26: =IF(AND(E$5>=Inputs!$B$224,'R&D'!$B$36=1),E25,MIN(E25,Inputs!$B$222)*'R&D'!$B$34) -> 0 | F26: =IF(AND(F$5>=Inputs!$B$224,'R&D'!$B$36=1),F25,MIN(F25,Inputs!$B$222)*'R&D'!$B$34) -> 0 | G26: =IF(AND(G$5>=Inputs!$B$224,'R&D'!$B$36=1),G25,MIN(G25,Inputs!$B$222)*'R&D'!$B$34) -> 0 | H26: =IF(AND(H$5>=Inputs!$B$224,'R&D'!$B$36=1),H25,MIN(H25,Inputs!$B$222)*'R&D'!$B$34) -> 0 | I26: =IF(AND(I$5>=Inputs!$B$224,'R&D'!$B$36=1),I25,MIN(I25,Inputs!$B$222)*'R&D'!$B$34) -> 0 | J26: =IF(AND(J$5>=Inputs!$B$224,'R&D'!$B$36=1),J25,MIN(J25,Inputs!$B$222)*'R&D'!$B$34) -> 0 | K26: =IF(AND(K$5>=Inputs!$B$224,'R&D'!$B$36=1),K25,MIN(K25,Inputs!$B$222)*'R&D'!$B$34) -> 0 | ... AM26: =IF(AND(AM$5>=Inputs!$B$224,'R&D'!$B$36=1),AM25,MIN(AM25,Inputs!$B$222)*'R&D'!$B$34) -> 0
A27: New units deployed | B27: units | D27: =MAX(0,D26-C26) -> 0 | E27: =MAX(0,E26-D26) -> 0 | F27: =MAX(0,F26-E26) -> 0 | G27: =MAX(0,G26-F26) -> 0 | H27: =MAX(0,H26-G26) -> 0 | I27: =MAX(0,I26-H26) -> 0 | J27: =MAX(0,J26-I26) -> 0 | K27: =MAX(0,K26-J26) -> 0 | ... AM27: =MAX(0,AM26-AL26) -> 0 | AN27: =SUM(D27:AM27) -> 0 | AO27: =SUM(D27:O27) -> 0 | AP27: =SUM(P27:AA27) -> 0 | AQ27: =SUM(AB27:AM27) -> 0
A28: of which scale units bought at the 10-unit price | B28: units | D28: =IF(D$5>=Inputs!$B$224,MAX(0,MIN(D26,Inputs!$B$221)-C26),0) -> 0 | E28: =IF(E$5>=Inputs!$B$224,MAX(0,MIN(E26,Inputs!$B$221)-D26),0) -> 0 | F28: =IF(F$5>=Inputs!$B$224,MAX(0,MIN(F26,Inputs!$B$221)-E26),0) -> 0 | G28: =IF(G$5>=Inputs!$B$224,MAX(0,MIN(G26,Inputs!$B$221)-F26),0) -> 0 | H28: =IF(H$5>=Inputs!$B$224,MAX(0,MIN(H26,Inputs!$B$221)-G26),0) -> 0 | I28: =IF(I$5>=Inputs!$B$224,MAX(0,MIN(I26,Inputs!$B$221)-H26),0) -> 0 | J28: =IF(J$5>=Inputs!$B$224,MAX(0,MIN(J26,Inputs!$B$221)-I26),0) -> 0 | K28: =IF(K$5>=Inputs!$B$224,MAX(0,MIN(K26,Inputs!$B$221)-J26),0) -> 0 | ... AM28: =IF(AM$5>=Inputs!$B$224,MAX(0,MIN(AM26,Inputs!$B$221)-AL26),0) -> 0 | AN28: =SUM(D28:AM28) -> 0 | AO28: =SUM(D28:O28) -> 0 | AP28: =SUM(P28:AA28) -> 0 | AQ28: =SUM(AB28:AM28) -> 0
A29: of which scale units bought at the 100-unit price | B29: units | D29: =IF(D$5>=Inputs!$B$224,D27-D28,0) -> 0 | E29: =IF(E$5>=Inputs!$B$224,E27-E28,0) -> 0 | F29: =IF(F$5>=Inputs!$B$224,F27-F28,0) -> 0 | G29: =IF(G$5>=Inputs!$B$224,G27-G28,0) -> 0 | H29: =IF(H$5>=Inputs!$B$224,H27-H28,0) -> 0 | I29: =IF(I$5>=Inputs!$B$224,I27-I28,0) -> 0 | J29: =IF(J$5>=Inputs!$B$224,J27-J28,0) -> 0 | K29: =IF(K$5>=Inputs!$B$224,K27-K28,0) -> 0 | ... AM29: =IF(AM$5>=Inputs!$B$224,AM27-AM28,0) -> 0 | AN29: =SUM(D29:AM29) -> 0 | AO29: =SUM(D29:O29) -> 0 | AP29: =SUM(P29:AA29) -> 0 | AQ29: =SUM(AB29:AM29) -> 0
A30: Hardware capex (scale units; pilot units sit in P2 R&D) | B30: $ | D30: =(D28*Inputs!$B$219+D29*Inputs!$B$220)*Inputs!$H$217 -> 0 | E30: =(E28*Inputs!$B$219+E29*Inputs!$B$220)*Inputs!$H$217 -> 0 | F30: =(F28*Inputs!$B$219+F29*Inputs!$B$220)*Inputs!$H$217 -> 0 | G30: =(G28*Inputs!$B$219+G29*Inputs!$B$220)*Inputs!$H$217 -> 0 | H30: =(H28*Inputs!$B$219+H29*Inputs!$B$220)*Inputs!$H$217 -> 0 | I30: =(I28*Inputs!$B$219+I29*Inputs!$B$220)*Inputs!$H$217 -> 0 | J30: =(J28*Inputs!$B$219+J29*Inputs!$B$220)*Inputs!$H$217 -> 0 | K30: =(K28*Inputs!$B$219+K29*Inputs!$B$220)*Inputs!$H$217 -> 0 | ... AM30: =(AM28*Inputs!$B$219+AM29*Inputs!$B$220)*Inputs!$H$217 -> 0 | AN30: =SUM(D30:AM30) -> 0 | AO30: =SUM(D30:O30) -> 0 | AP30: =SUM(P30:AA30) -> 0 | AQ30: =SUM(AB30:AM30) -> 0
A31: SALES AND CONTRIBUTION
A32: Sales ramp factor (pilot first months) | B32: x | D32: =IF(AND(D$5>=Inputs!$B$223,D$5<Inputs!$B$223+Inputs!$B$208),Inputs!$B$207,1) -> 1 | E32: =IF(AND(E$5>=Inputs!$B$223,E$5<Inputs!$B$223+Inputs!$B$208),Inputs!$B$207,1) -> 1 | F32: =IF(AND(F$5>=Inputs!$B$223,F$5<Inputs!$B$223+Inputs!$B$208),Inputs!$B$207,1) -> 1 | G32: =IF(AND(G$5>=Inputs!$B$223,G$5<Inputs!$B$223+Inputs!$B$208),Inputs!$B$207,1) -> 1 | H32: =IF(AND(H$5>=Inputs!$B$223,H$5<Inputs!$B$223+Inputs!$B$208),Inputs!$B$207,1) -> 1 | I32: =IF(AND(I$5>=Inputs!$B$223,I$5<Inputs!$B$223+Inputs!$B$208),Inputs!$B$207,1) -> 1 | J32: =IF(AND(J$5>=Inputs!$B$223,J$5<Inputs!$B$223+Inputs!$B$208),Inputs!$B$207,1) -> 1 | K32: =IF(AND(K$5>=Inputs!$B$223,K$5<Inputs!$B$223+Inputs!$B$208),Inputs!$B$207,1) -> 1 | ... AM32: =IF(AND(AM$5>=Inputs!$B$223,AM$5<Inputs!$B$223+Inputs!$B$208),Inputs!$B$207,1) -> 1
A33: Cards sold | B33: cards | D33: =D26*Inputs!$H$195*Inputs!$B$209*D32 -> 0 | E33: =E26*Inputs!$H$195*Inputs!$B$209*E32 -> 0 | F33: =F26*Inputs!$H$195*Inputs!$B$209*F32 -> 0 | G33: =G26*Inputs!$H$195*Inputs!$B$209*G32 -> 0 | H33: =H26*Inputs!$H$195*Inputs!$B$209*H32 -> 0 | I33: =I26*Inputs!$H$195*Inputs!$B$209*I32 -> 0 | J33: =J26*Inputs!$H$195*Inputs!$B$209*J32 -> 0 | K33: =K26*Inputs!$H$195*Inputs!$B$209*K32 -> 0 | ... AM33: =AM26*Inputs!$H$195*Inputs!$B$209*AM32 -> 0 | AN33: =SUM(D33:AM33) -> 0 | AO33: =SUM(D33:O33) -> 0 | AP33: =SUM(P33:AA33) -> 0 | AQ33: =SUM(AB33:AM33) -> 0
A34: Kiosk revenue (ex tax) | B34: $ | D34: =D33*$B$7 -> 0 | E34: =E33*$B$7 -> 0 | F34: =F33*$B$7 -> 0 | G34: =G33*$B$7 -> 0 | H34: =H33*$B$7 -> 0 | I34: =I33*$B$7 -> 0 | J34: =J33*$B$7 -> 0 | K34: =K33*$B$7 -> 0 | ... AM34: =AM33*$B$7 -> 0 | AN34: =SUM(D34:AM34) -> 0 | AO34: =SUM(D34:O34) -> 0 | AP34: =SUM(P34:AA34) -> 0 | AQ34: =SUM(AB34:AM34) -> 0
A35: Location revenue share | B35: $ | D35: =-D34*Inputs!$H$196 -> 0 | E35: =-E34*Inputs!$H$196 -> 0 | F35: =-F34*Inputs!$H$196 -> 0 | G35: =-G34*Inputs!$H$196 -> 0 | H35: =-H34*Inputs!$H$196 -> 0 | I35: =-I34*Inputs!$H$196 -> 0 | J35: =-J34*Inputs!$H$196 -> 0 | K35: =-K34*Inputs!$H$196 -> 0 | ... AM35: =-AM34*Inputs!$H$196 -> 0 | AN35: =SUM(D35:AM35) -> 0 | AO35: =SUM(D35:O35) -> 0 | AP35: =SUM(P35:AA35) -> 0 | AQ35: =SUM(AB35:AM35) -> 0
A36: Payment fees | B36: $ | D36: =-(D34*Inputs!$H$197+D33*Inputs!$H$198) -> 0 | E36: =-(E34*Inputs!$H$197+E33*Inputs!$H$198) -> 0 | F36: =-(F34*Inputs!$H$197+F33*Inputs!$H$198) -> 0 | G36: =-(G34*Inputs!$H$197+G33*Inputs!$H$198) -> 0 | H36: =-(H34*Inputs!$H$197+H33*Inputs!$H$198) -> 0 | I36: =-(I34*Inputs!$H$197+I33*Inputs!$H$198) -> 0 | J36: =-(J34*Inputs!$H$197+J33*Inputs!$H$198) -> 0 | K36: =-(K34*Inputs!$H$197+K33*Inputs!$H$198) -> 0 | ... AM36: =-(AM34*Inputs!$H$197+AM33*Inputs!$H$198) -> 0 | AN36: =SUM(D36:AM36) -> 0 | AO36: =SUM(D36:O36) -> 0 | AP36: =SUM(P36:AA36) -> 0 | AQ36: =SUM(AB36:AM36) -> 0
A37: Consumables | B37: $ | D37: =-D33*$B$10 -> 0 | E37: =-E33*$B$10 -> 0 | F37: =-F33*$B$10 -> 0 | G37: =-G33*$B$10 -> 0 | H37: =-H33*$B$10 -> 0 | I37: =-I33*$B$10 -> 0 | J37: =-J33*$B$10 -> 0 | K37: =-K33*$B$10 -> 0 | ... AM37: =-AM33*$B$10 -> 0 | AN37: =SUM(D37:AM37) -> 0 | AO37: =SUM(D37:O37) -> 0 | AP37: =SUM(P37:AA37) -> 0 | AQ37: =SUM(AB37:AM37) -> 0
A38: Model cost (from Model Costs sheet) | B38: $ | D38: =-D33*$B$12 -> 0 | E38: =-E33*$B$12 -> 0 | F38: =-F33*$B$12 -> 0 | G38: =-G33*$B$12 -> 0 | H38: =-H33*$B$12 -> 0 | I38: =-I33*$B$12 -> 0 | J38: =-J33*$B$12 -> 0 | K38: =-K33*$B$12 -> 0 | ... AM38: =-AM33*$B$12 -> 0 | AN38: =SUM(D38:AM38) -> 0 | AO38: =SUM(D38:O38) -> 0 | AP38: =SUM(P38:AA38) -> 0 | AQ38: =SUM(AB38:AM38) -> 0
A39: Service visits | B39: $ | D39: =-D26*Inputs!$H$213 -> 0 | E39: =-E26*Inputs!$H$213 -> 0 | F39: =-F26*Inputs!$H$213 -> 0 | G39: =-G26*Inputs!$H$213 -> 0 | H39: =-H26*Inputs!$H$213 -> 0 | I39: =-I26*Inputs!$H$213 -> 0 | J39: =-J26*Inputs!$H$213 -> 0 | K39: =-K26*Inputs!$H$213 -> 0 | ... AM39: =-AM26*Inputs!$H$213 -> 0 | AN39: =SUM(D39:AM39) -> 0 | AO39: =SUM(D39:O39) -> 0 | AP39: =SUM(P39:AA39) -> 0 | AQ39: =SUM(AB39:AM39) -> 0
A40: Other fixed (connectivity, device mgmt, insurance, parts, hosting) | B40: $ | D40: =-D26*(Inputs!$H$210+Inputs!$H$211+Inputs!$H$212+Inputs!$H$214+Inputs!$H$215) -> 0 | E40: =-E26*(Inputs!$H$210+Inputs!$H$211+Inputs!$H$212+Inputs!$H$214+Inputs!$H$215) -> 0 | F40: =-F26*(Inputs!$H$210+Inputs!$H$211+Inputs!$H$212+Inputs!$H$214+Inputs!$H$215) -> 0 | G40: =-G26*(Inputs!$H$210+Inputs!$H$211+Inputs!$H$212+Inputs!$H$214+Inputs!$H$215) -> 0 | H40: =-H26*(Inputs!$H$210+Inputs!$H$211+Inputs!$H$212+Inputs!$H$214+Inputs!$H$215) -> 0 | I40: =-I26*(Inputs!$H$210+Inputs!$H$211+Inputs!$H$212+Inputs!$H$214+Inputs!$H$215) -> 0 | J40: =-J26*(Inputs!$H$210+Inputs!$H$211+Inputs!$H$212+Inputs!$H$214+Inputs!$H$215) -> 0 | K40: =-K26*(Inputs!$H$210+Inputs!$H$211+Inputs!$H$212+Inputs!$H$214+Inputs!$H$215) -> 0 | ... AM40: =-AM26*(Inputs!$H$210+Inputs!$H$211+Inputs!$H$212+Inputs!$H$214+Inputs!$H$215) -> 0 | AN40: =SUM(D40:AM40) -> 0 | AO40: =SUM(D40:O40) -> 0 | AP40: =SUM(P40:AA40) -> 0 | AQ40: =SUM(AB40:AM40) -> 0
A41: Operating contribution | B41: $ | D41: =SUM(D34:D40) -> 0 | E41: =SUM(E34:E40) -> 0 | F41: =SUM(F34:F40) -> 0 | G41: =SUM(G34:G40) -> 0 | H41: =SUM(H34:H40) -> 0 | I41: =SUM(I34:I40) -> 0 | J41: =SUM(J34:J40) -> 0 | K41: =SUM(K34:K40) -> 0 | ... AM41: =SUM(AM34:AM40) -> 0 | AN41: =SUM(D41:AM41) -> 0 | AO41: =SUM(D41:O41) -> 0 | AP41: =SUM(P41:AA41) -> 0 | AQ41: =SUM(AB41:AM41) -> 0
A42: Depreciation (straight line from the month after deployment) | B42: $ | D42: =0 -> 0 | E42: =-SUM($D30:D30)/Inputs!$H$216 -> 0 | F42: =-SUM($D30:E30)/Inputs!$H$216 -> 0 | G42: =-SUM($D30:F30)/Inputs!$H$216 -> 0 | H42: =-SUM($D30:G30)/Inputs!$H$216 -> 0 | I42: =-SUM($D30:H30)/Inputs!$H$216 -> 0 | J42: =-SUM($D30:I30)/Inputs!$H$216 -> 0 | K42: =-SUM($D30:J30)/Inputs!$H$216 -> 0 | L42: =-SUM($D30:K30)/Inputs!$H$216 -> 0 | ... AM42: =-SUM($D30:AL30)/Inputs!$H$216 -> 0 | AN42: =SUM(D42:AM42) -> 0 | AO42: =SUM(D42:O42) -> 0 | AP42: =SUM(P42:AA42) -> 0 | AQ42: =SUM(AB42:AM42) -> 0
A43: Kiosk program R&D (expensed) | B43: $ | D43: =-'R&D'!D45 -> 0 | E43: =-'R&D'!E45 -> 0 | F43: =-'R&D'!F45 -> 0 | G43: =-'R&D'!G45 -> 0 | H43: =-'R&D'!H45 -> 0 | I43: =-'R&D'!I45 -> 0 | J43: =-'R&D'!J45 -> -11538.333 | K43: =-'R&D'!K45 -> -11538.333 | ... AM43: =-'R&D'!AM45 -> 0 | AN43: =SUM(D43:AM43) -> -34615 | AO43: =SUM(D43:O43) -> -34615 | AP43: =SUM(P43:AA43) -> 0 | AQ43: =SUM(AB43:AM43) -> 0
A44: Net income (contribution - depreciation - R&D) | B44: $ | D44: =D41+D42+D43 -> 0 | E44: =E41+E42+E43 -> 0 | F44: =F41+F42+F43 -> 0 | G44: =G41+G42+G43 -> 0 | H44: =H41+H42+H43 -> 0 | I44: =I41+I42+I43 -> 0 | J44: =J41+J42+J43 -> -11538.333 | K44: =K41+K42+K43 -> -11538.333 | ... AM44: =AM41+AM42+AM43 -> 0 | AN44: =SUM(D44:AM44) -> -34615 | AO44: =SUM(D44:O44) -> -34615 | AP44: =SUM(P44:AA44) -> 0 | AQ44: =SUM(AB44:AM44) -> 0
A45: Net cash flow (contribution - capex - R&D) | B45: $ | D45: =D41-D30+D43 -> 0 | E45: =E41-E30+E43 -> 0 | F45: =F41-F30+F43 -> 0 | G45: =G41-G30+G43 -> 0 | H45: =H41-H30+H43 -> 0 | I45: =I41-I30+I43 -> 0 | J45: =J41-J30+J43 -> -11538.333 | K45: =K41-K30+K43 -> -11538.333 | ... AM45: =AM41-AM30+AM43 -> 0 | AN45: =SUM(D45:AM45) -> -34615 | AO45: =SUM(D45:O45) -> -34615 | AP45: =SUM(P45:AA45) -> 0 | AQ45: =SUM(AB45:AM45) -> 0
A46: Cumulative kiosk cash (standalone, from $0) | B46: $ | D46: =D45 -> 0 | E46: =D46+E45 -> 0 | F46: =E46+F45 -> 0 | G46: =F46+G45 -> 0 | H46: =G46+H45 -> 0 | I46: =H46+I45 -> 0 | J46: =I46+J45 -> -11538.333 | K46: =J46+K45 -> -23076.667 | L46: =K46+L45 -> -34615 | ... AM46: =AL46+AM45 -> -34615
A47: Flag: cumulative kiosk cash back to >= 0 after spending starts | B47: month | D47: =IF(AND(D46>=0,MIN($D46:D46)<0),D$5,"") | E47: =IF(AND(E46>=0,MIN($D46:E46)<0),E$5,"") | F47: =IF(AND(F46>=0,MIN($D46:F46)<0),F$5,"") | G47: =IF(AND(G46>=0,MIN($D46:G46)<0),G$5,"") | H47: =IF(AND(H46>=0,MIN($D46:H46)<0),H$5,"") | I47: =IF(AND(I46>=0,MIN($D46:I46)<0),I$5,"") | J47: =IF(AND(J46>=0,MIN($D46:J46)<0),J$5,"") | K47: =IF(AND(K46>=0,MIN($D46:K46)<0),K$5,"") | ... AM47: =IF(AND(AM46>=0,MIN($D46:AM46)<0),AM$5,"")
A49: FLEET METRICS
A50: Units live, month 36 | B50: =AM26 -> 0
A51: Total hardware capex, 36 months | B51: =AN30 -> 0
A52: Total kiosk R&D, 36 months | B52: =-AN43 -> 34615
A53: Operating contribution, month 36 (run rate) | B53: =AM41 -> 0
A54: Cumulative kiosk cash, month 36 | B54: =AM46 -> -34615
A55: Lowest cumulative kiosk cash | B55: =MIN(D46:AM46) -> -34615
A56: Cash payback month for the whole program (cumulative >= 0) | B56: =IF(COUNT(D47:AM47)=0,"Not within 36 mo",MIN(D47:AM47)) -> Not within 36 mo
A57: Cumulative net income, 36 months | B57: =AN44 -> -34615

Sheet Agent Channel
A1: Agent Channel - AI-assistant mailed-card channel (MCP / agent API)
A2: Gross standalone program view (independent of Scenarios!B43). No adoption data exists: every volume is a guess (integrations/08). Platform-policy risk is a probability-weighted haircut.
A4: Line | B4: Unit | C4: Total / opening | D4: M1 | E4: M2 | F4: M3 | G4: M4 | H4: M5 | I4: M6 | J4: M7 | K4: M8 | L4: M9 | M4: M10 | N4: M11 | O4: M12 | P4: M13 | Q4: M14 | R4: M15 | S4: M16 | T4: M17 | U4: M18 | V4: M19 | W4: M20 | X4: M21 | Y4: M22 | Z4: M23 | AA4: M24 | AB4: M25 | AC4: M26 | AD4: M27 | AE4: M28 | AF4: M29 | AG4: M30 | AH4: M31 | AI4: M32 | AJ4: M33 | AK4: M34 | AL4: M35 | AM4: M36 | AN4: 36-mo total | AO4: Year 1 | AP4: Year 2 | AQ4: Year 3
A5: Month # | B5: # | D5: =Forecast!D6 -> 1 | E5: =Forecast!E6 -> 2 | F5: =Forecast!F6 -> 3 | G5: =Forecast!G6 -> 4 | H5: =Forecast!H6 -> 5 | I5: =Forecast!I6 -> 6 | J5: =Forecast!J6 -> 7 | K5: =Forecast!K6 -> 8 | ... AM5: =Forecast!AM6 -> 36
A6: CHANNEL PARAMETERS (selected scenario)
A7: Mailed card gross price, all-in (Unit Economics, follows Market-adjusted) | B7: ='Unit Economics'!$D$6 -> 10.681
A8: Gross price change vs launch list ($7.99 + postage x share) | B8: =Inputs!$E$48+Inputs!$F$48*Inputs!$D$48*Inputs!$B$43-B7 -> 0
A9: Mailed-card contribution per approved card used (plan value less price change after refund and Stripe %) | B9: =Inputs!$H$269-B8*(1-Inputs!$B$36-Inputs!$B$40) -> 3.3
A10: Cross-check: live card-printed contribution (Unit Economics) less agent adjustment of $0.30 | B10: ='Unit Economics'!$N$6-0.3 -> 4.1452865
A11: CAC used for CAC avoided | B11: =IF(Inputs!$B$286=1,Scenarios!$B$31,Scenarios!$B$32) -> 39.57446
A12: Platform-policy haircut (probability x loss share) | B12: =Inputs!$B$284*Inputs!$B$285 -> 0.25
A13: Monthly churn of paying users | B13: =1-Inputs!$H$267^(1/12) -> 0.041675471
A14: Recurring channel cost per month once live (6 lines) | B14: =Inputs!$H$270+Inputs!$H$271+Inputs!$H$272+Inputs!$H$273+Inputs!$H$274+Inputs!$H$275 -> 300
A16: USERS AND CARDS
A17: Channel live (P2 shipped, gate passed, month >= go-live) | B17: flag | D17: =IF(D$5>=Inputs!$B$276,1,0)*'R&D'!$C$19 -> 0 | E17: =IF(E$5>=Inputs!$B$276,1,0)*'R&D'!$C$19 -> 0 | F17: =IF(F$5>=Inputs!$B$276,1,0)*'R&D'!$C$19 -> 0 | G17: =IF(G$5>=Inputs!$B$276,1,0)*'R&D'!$C$19 -> 0 | H17: =IF(H$5>=Inputs!$B$276,1,0)*'R&D'!$C$19 -> 0 | I17: =IF(I$5>=Inputs!$B$276,1,0)*'R&D'!$C$19 -> 0 | J17: =IF(J$5>=Inputs!$B$276,1,0)*'R&D'!$C$19 -> 0 | K17: =IF(K$5>=Inputs!$B$276,1,0)*'R&D'!$C$19 -> 1 | ... AM17: =IF(AM$5>=Inputs!$B$276,1,0)*'R&D'!$C$19 -> 1
A18: New paying users | B18: users | D18: =D17*Inputs!$H$265/12*IF(D$5<Inputs!$B$276+12,1,Inputs!$B$277) -> 0 | E18: =E17*Inputs!$H$265/12*IF(E$5<Inputs!$B$276+12,1,Inputs!$B$277) -> 0 | F18: =F17*Inputs!$H$265/12*IF(F$5<Inputs!$B$276+12,1,Inputs!$B$277) -> 0 | G18: =G17*Inputs!$H$265/12*IF(G$5<Inputs!$B$276+12,1,Inputs!$B$277) -> 0 | H18: =H17*Inputs!$H$265/12*IF(H$5<Inputs!$B$276+12,1,Inputs!$B$277) -> 0 | I18: =I17*Inputs!$H$265/12*IF(I$5<Inputs!$B$276+12,1,Inputs!$B$277) -> 0 | J18: =J17*Inputs!$H$265/12*IF(J$5<Inputs!$B$276+12,1,Inputs!$B$277) -> 0 | K18: =K17*Inputs!$H$265/12*IF(K$5<Inputs!$B$276+12,1,Inputs!$B$277) -> 12.5 | ... AM18: =AM17*Inputs!$H$265/12*IF(AM$5<Inputs!$B$276+12,1,Inputs!$B$277) -> 12.5 | AN18: =SUM(D18:AM18) -> 362.5 | AO18: =SUM(D18:O18) -> 62.5 | AP18: =SUM(P18:AA18) -> 150 | AQ18: =SUM(AB18:AM18) -> 150
A19: Active paying users | B19: users | C19: 0 | D19: =D18 -> 0 | E19: =D19*(1-$B$13)+E18 -> 0 | F19: =E19*(1-$B$13)+F18 -> 0 | G19: =F19*(1-$B$13)+G18 -> 0 | H19: =G19*(1-$B$13)+H18 -> 0 | I19: =H19*(1-$B$13)+I18 -> 0 | J19: =I19*(1-$B$13)+J18 -> 0 | K19: =J19*(1-$B$13)+K18 -> 12.5 | L19: =K19*(1-$B$13)+L18 -> 24.479057 | ... AM19: =AL19*(1-$B$13)+AM18 -> 212.66058
A20: Connected users (signed in via an assistant) | B20: users | D20: =D19/Inputs!$B$278 -> 0 | E20: =E19/Inputs!$B$278 -> 0 | F20: =F19/Inputs!$B$278 -> 0 | G20: =G19/Inputs!$B$278 -> 0 | H20: =H19/Inputs!$B$278 -> 0 | I20: =I19/Inputs!$B$278 -> 0 | J20: =J19/Inputs!$B$278 -> 0 | K20: =K19/Inputs!$B$278 -> 31.25 | ... AM20: =AM19/Inputs!$B$278 -> 531.65146
A21: Active agents (connected users active this month) | B21: agents | D21: =D20*Inputs!$B$279 -> 0 | E21: =E20*Inputs!$B$279 -> 0 | F21: =F20*Inputs!$B$279 -> 0 | G21: =G20*Inputs!$B$279 -> 0 | H21: =H20*Inputs!$B$279 -> 0 | I21: =I20*Inputs!$B$279 -> 0 | J21: =J20*Inputs!$B$279 -> 0 | K21: =K20*Inputs!$B$279 -> 15.625 | ... AM21: =AM20*Inputs!$B$279 -> 265.82573
A22: Cards per paying user per month (with repeat uplift past year 1) | B22: cards | D22: =Inputs!$H$266/12*IF(AND(D17=1,D$5>=Inputs!$B$276+12),1+Inputs!$B$283,1) -> 0.41666667 | E22: =Inputs!$H$266/12*IF(AND(E17=1,E$5>=Inputs!$B$276+12),1+Inputs!$B$283,1) -> 0.41666667 | F22: =Inputs!$H$266/12*IF(AND(F17=1,F$5>=Inputs!$B$276+12),1+Inputs!$B$283,1) -> 0.41666667 | G22: =Inputs!$H$266/12*IF(AND(G17=1,G$5>=Inputs!$B$276+12),1+Inputs!$B$283,1) -> 0.41666667 | H22: =Inputs!$H$266/12*IF(AND(H17=1,H$5>=Inputs!$B$276+12),1+Inputs!$B$283,1) -> 0.41666667 | I22: =Inputs!$H$266/12*IF(AND(I17=1,I$5>=Inputs!$B$276+12),1+Inputs!$B$283,1) -> 0.41666667 | J22: =Inputs!$H$266/12*IF(AND(J17=1,J$5>=Inputs!$B$276+12),1+Inputs!$B$283,1) -> 0.41666667 | K22: =Inputs!$H$266/12*IF(AND(K17=1,K$5>=Inputs!$B$276+12),1+Inputs!$B$283,1) -> 0.41666667 | ... AM22: =Inputs!$H$266/12*IF(AND(AM17=1,AM$5>=Inputs!$B$276+12),1+Inputs!$B$283,1) -> 0.5
A23: Approved mailed cards | B23: cards | D23: =D19*D22 -> 0 | E23: =E19*E22 -> 0 | F23: =F19*F22 -> 0 | G23: =G19*G22 -> 0 | H23: =H19*H22 -> 0 | I23: =I19*I22 -> 0 | J23: =J19*J22 -> 0 | K23: =K19*K22 -> 5.2083333 | ... AM23: =AM19*AM22 -> 106.33029 | AN23: =SUM(D23:AM23) -> 1833.9875 | AO23: =SUM(D23:O23) -> 73.91725 | AP23: =SUM(P23:AA23) -> 629.41931 | AQ23: =SUM(AB23:AM23) -> 1130.6509
A24: REVENUE AND CONTRIBUTION
A25: Gross channel revenue (cards x all-in price) | B25: $ | D25: =D23*$B$7 -> 0 | E25: =E23*$B$7 -> 0 | F25: =F23*$B$7 -> 0 | G25: =G23*$B$7 -> 0 | H25: =H23*$B$7 -> 0 | I25: =I23*$B$7 -> 0 | J25: =J23*$B$7 -> 0 | K25: =K23*$B$7 -> 55.630208 | ... AM25: =AM23*$B$7 -> 1135.7138 | AN25: =SUM(D25:AM25) -> 19588.821 | AO25: =SUM(D25:O25) -> 789.51015 | AP25: =SUM(P25:AA25) -> 6722.8277 | AQ25: =SUM(AB25:AM25) -> 12076.483
A26: Gross channel contribution (cards x margin) | B26: $ | D26: =D23*$B$9 -> 0 | E26: =E23*$B$9 -> 0 | F26: =F23*$B$9 -> 0 | G26: =G23*$B$9 -> 0 | H26: =H23*$B$9 -> 0 | I26: =I23*$B$9 -> 0 | J26: =J23*$B$9 -> 0 | K26: =K23*$B$9 -> 17.1875 | ... AM26: =AM23*$B$9 -> 350.88996 | AN26: =SUM(D26:AM26) -> 6052.1588 | AO26: =SUM(D26:O26) -> 243.92692 | AP26: =SUM(P26:AA26) -> 2077.0837 | AQ26: =SUM(AB26:AM26) -> 3731.1481
A27: Incremental revenue (x incremental share) | B27: $ | D27: =D25*Inputs!$H$268 -> 0 | E27: =E25*Inputs!$H$268 -> 0 | F27: =F25*Inputs!$H$268 -> 0 | G27: =G25*Inputs!$H$268 -> 0 | H27: =H25*Inputs!$H$268 -> 0 | I27: =I25*Inputs!$H$268 -> 0 | J27: =J25*Inputs!$H$268 -> 0 | K27: =K25*Inputs!$H$268 -> 33.378125 | ... AM27: =AM25*Inputs!$H$268 -> 681.42831 | AN27: =SUM(D27:AM27) -> 11753.292 | AO27: =SUM(D27:O27) -> 473.70609 | AP27: =SUM(P27:AA27) -> 4033.6966 | AQ27: =SUM(AB27:AM27) -> 7245.8897
A28: Incremental contribution (x incremental share) | B28: $ | D28: =D26*Inputs!$H$268 -> 0 | E28: =E26*Inputs!$H$268 -> 0 | F28: =F26*Inputs!$H$268 -> 0 | G28: =G26*Inputs!$H$268 -> 0 | H28: =H26*Inputs!$H$268 -> 0 | I28: =I26*Inputs!$H$268 -> 0 | J28: =J26*Inputs!$H$268 -> 0 | K28: =K26*Inputs!$H$268 -> 10.3125 | ... AM28: =AM26*Inputs!$H$268 -> 210.53398 | AN28: =SUM(D28:AM28) -> 3631.2953 | AO28: =SUM(D28:O28) -> 146.35615 | AP28: =SUM(P28:AA28) -> 1246.2502 | AQ28: =SUM(AB28:AM28) -> 2238.6889
A29: Incremental revenue after policy-risk haircut | B29: $ | D29: =D27*(1-$B$12) -> 0 | E29: =E27*(1-$B$12) -> 0 | F29: =F27*(1-$B$12) -> 0 | G29: =G27*(1-$B$12) -> 0 | H29: =H27*(1-$B$12) -> 0 | I29: =I27*(1-$B$12) -> 0 | J29: =J27*(1-$B$12) -> 0 | K29: =K27*(1-$B$12) -> 25.033594 | ... AM29: =AM27*(1-$B$12) -> 511.07123 | AN29: =SUM(D29:AM29) -> 8814.9693 | AO29: =SUM(D29:O29) -> 355.27957 | AP29: =SUM(P29:AA29) -> 3025.2725 | AQ29: =SUM(AB29:AM29) -> 5434.4173
A30: Incremental contribution after policy-risk haircut | B30: $ | D30: =D28*(1-$B$12) -> 0 | E30: =E28*(1-$B$12) -> 0 | F30: =F28*(1-$B$12) -> 0 | G30: =G28*(1-$B$12) -> 0 | H30: =H28*(1-$B$12) -> 0 | I30: =I28*(1-$B$12) -> 0 | J30: =J28*(1-$B$12) -> 0 | K30: =K28*(1-$B$12) -> 7.734375 | ... AM30: =AM28*(1-$B$12) -> 157.90048 | AN30: =SUM(D30:AM30) -> 2723.4715 | AO30: =SUM(D30:O30) -> 109.76712 | AP30: =SUM(P30:AA30) -> 934.68768 | AQ30: =SUM(AB30:AM30) -> 1679.0167
A31: CAC avoided, memo (new users x incremental share x CAC x real-saving share, after haircut) | B31: $ | D31: =D18*Inputs!$H$268*$B$11*Inputs!$B$287*(1-$B$12) -> 0 | E31: =E18*Inputs!$H$268*$B$11*Inputs!$B$287*(1-$B$12) -> 0 | F31: =F18*Inputs!$H$268*$B$11*Inputs!$B$287*(1-$B$12) -> 0 | G31: =G18*Inputs!$H$268*$B$11*Inputs!$B$287*(1-$B$12) -> 0 | H31: =H18*Inputs!$H$268*$B$11*Inputs!$B$287*(1-$B$12) -> 0 | I31: =I18*Inputs!$H$268*$B$11*Inputs!$B$287*(1-$B$12) -> 0 | J31: =J18*Inputs!$H$268*$B$11*Inputs!$B$287*(1-$B$12) -> 0 | K31: =K18*Inputs!$H$268*$B$11*Inputs!$B$287*(1-$B$12) -> 111.30317 | ... AM31: =AM18*Inputs!$H$268*$B$11*Inputs!$B$287*(1-$B$12) -> 111.30317 | AN31: =SUM(D31:AM31) -> 3227.7919 | AO31: =SUM(D31:O31) -> 556.51584 | AP31: =SUM(P31:AA31) -> 1335.638 | AQ31: =SUM(AB31:AM31) -> 1335.638
A32: COSTS AND CASH
A33: Recurring channel costs (hosting, monitoring, support, review) | B33: $ | D33: =-D17*$B$14 -> 0 | E33: =-E17*$B$14 -> 0 | F33: =-F17*$B$14 -> 0 | G33: =-G17*$B$14 -> 0 | H33: =-H17*$B$14 -> 0 | I33: =-I17*$B$14 -> 0 | J33: =-J17*$B$14 -> 0 | K33: =-K17*$B$14 -> -300 | ... AM33: =-AM17*$B$14 -> -300 | AN33: =SUM(D33:AM33) -> -8700 | AO33: =SUM(D33:O33) -> -1500 | AP33: =SUM(P33:AA33) -> -3600 | AQ33: =SUM(AB33:AM33) -> -3600
A34: Free-draft exposure (non-paying active agents x drafts x cost, capped by pool) | B34: $ | D34: =-D17*MIN(Inputs!$B$282*Inputs!$B$209,MAX(0,D21-D19)*Inputs!$B$280*Inputs!$B$281) -> 0 | E34: =-E17*MIN(Inputs!$B$282*Inputs!$B$209,MAX(0,E21-E19)*Inputs!$B$280*Inputs!$B$281) -> 0 | F34: =-F17*MIN(Inputs!$B$282*Inputs!$B$209,MAX(0,F21-F19)*Inputs!$B$280*Inputs!$B$281) -> 0 | G34: =-G17*MIN(Inputs!$B$282*Inputs!$B$209,MAX(0,G21-G19)*Inputs!$B$280*Inputs!$B$281) -> 0 | H34: =-H17*MIN(Inputs!$B$282*Inputs!$B$209,MAX(0,H21-H19)*Inputs!$B$280*Inputs!$B$281) -> 0 | I34: =-I17*MIN(Inputs!$B$282*Inputs!$B$209,MAX(0,I21-I19)*Inputs!$B$280*Inputs!$B$281) -> 0 | J34: =-J17*MIN(Inputs!$B$282*Inputs!$B$209,MAX(0,J21-J19)*Inputs!$B$280*Inputs!$B$281) -> 0 | K34: =-K17*MIN(Inputs!$B$282*Inputs!$B$209,MAX(0,K21-K19)*Inputs!$B$280*Inputs!$B$281) -> -1.6875 | ... AM34: =-AM17*MIN(Inputs!$B$282*Inputs!$B$209,MAX(0,AM21-AM19)*Inputs!$B$280*Inputs!$B$281) -> -28.709179 | AN34: =SUM(D34:AM34) -> -514.08632 | AO34: =SUM(D34:O34) -> -23.949189 | AP34: =SUM(P34:AA34) -> -184.86138 | AQ34: =SUM(AB34:AM34) -> -305.27576
A35: CAC avoided counted as benefit (only if Scenarios!B47 = 1) | B35: $ | D35: =Scenarios!$B$47*D31 -> 0 | E35: =Scenarios!$B$47*E31 -> 0 | F35: =Scenarios!$B$47*F31 -> 0 | G35: =Scenarios!$B$47*G31 -> 0 | H35: =Scenarios!$B$47*H31 -> 0 | I35: =Scenarios!$B$47*I31 -> 0 | J35: =Scenarios!$B$47*J31 -> 0 | K35: =Scenarios!$B$47*K31 -> 0 | ... AM35: =Scenarios!$B$47*AM31 -> 0 | AN35: =SUM(D35:AM35) -> 0 | AO35: =SUM(D35:O35) -> 0 | AP35: =SUM(P35:AA35) -> 0 | AQ35: =SUM(AB35:AM35) -> 0
A36: Channel operating result before R&D | B36: $ | D36: =D30+D33+D34+D35 -> 0 | E36: =E30+E33+E34+E35 -> 0 | F36: =F30+F33+F34+F35 -> 0 | G36: =G30+G33+G34+G35 -> 0 | H36: =H30+H33+H34+H35 -> 0 | I36: =I30+I33+I34+I35 -> 0 | J36: =J30+J33+J34+J35 -> 0 | K36: =K30+K33+K34+K35 -> -293.95312 | ... AM36: =AM30+AM33+AM34+AM35 -> -170.8087 | AN36: =SUM(D36:AM36) -> -6490.6149 | AO36: =SUM(D36:O36) -> -1414.1821 | AP36: =SUM(P36:AA36) -> -2850.1737 | AQ36: =SUM(AB36:AM36) -> -2226.2591
A37: Agent / AI-platform R&D | B37: $ | D37: =-'R&D'!D28 -> -18000 | E37: =-'R&D'!E28 -> -11250 | F37: =-'R&D'!F28 -> -11250 | G37: =-'R&D'!G28 -> -8700 | H37: =-'R&D'!H28 -> -8700 | I37: =-'R&D'!I28 -> 0 | J37: =-'R&D'!J28 -> 0 | K37: =-'R&D'!K28 -> 0 | ... AM37: =-'R&D'!AM28 -> 0 | AN37: =SUM(D37:AM37) -> -83700 | AO37: =SUM(D37:O37) -> -74100 | AP37: =SUM(P37:AA37) -> -9600 | AQ37: =SUM(AB37:AM37) -> 0
A38: Net income = net cash flow | B38: $ | D38: =D36+D37 -> -18000 | E38: =E36+E37 -> -11250 | F38: =F36+F37 -> -11250 | G38: =G36+G37 -> -8700 | H38: =H36+H37 -> -8700 | I38: =I36+I37 -> 0 | J38: =J36+J37 -> 0 | K38: =K36+K37 -> -293.95312 | ... AM38: =AM36+AM37 -> -170.8087 | AN38: =SUM(D38:AM38) -> -90190.615 | AO38: =SUM(D38:O38) -> -75514.182 | AP38: =SUM(P38:AA38) -> -12450.174 | AQ38: =SUM(AB38:AM38) -> -2226.2591
A39: Cumulative channel cash (standalone, from $0) | B39: $ | D39: =D38 -> -18000 | E39: =D39+E38 -> -29250 | F39: =E39+F38 -> -40500 | G39: =F39+G38 -> -49200 | H39: =G39+H38 -> -57900 | I39: =H39+I38 -> -57900 | J39: =I39+J38 -> -57900 | K39: =J39+K38 -> -58193.953 | L39: =K39+L38 -> -64182.111 | ... AM39: =AL39+AM38 -> -90190.615
A40: Flag: cumulative channel cash >= 0 | B40: month | D40: =IF(D39>=0,D$5,"") | E40: =IF(E39>=0,E$5,"") | F40: =IF(F39>=0,F$5,"") | G40: =IF(G39>=0,G$5,"") | H40: =IF(H39>=0,H$5,"") | I40: =IF(I39>=0,I$5,"") | J40: =IF(J39>=0,J$5,"") | K40: =IF(K39>=0,K$5,"") | ... AM40: =IF(AM39>=0,AM$5,"")
A42: CHANNEL METRICS
A43: Cards, 36 months | B43: =AN23 -> 1833.9875
A44: Incremental contribution after haircut, 36 months | B44: =AN30 -> 2723.4715
A45: Recurring + exposure costs, 36 months | B45: =AN33+AN34 -> -9214.0863
A46: Agent R&D, 36 months | B46: =-AN37 -> 83700
A47: CAC avoided (memo), 36 months | B47: =AN31 -> 3227.7919
A48: Cumulative net cash, 36 months (CAC avoided excluded unless switch on) | B48: =AM39 -> -90190.615
A49: Cumulative net cash if CAC avoided were fully counted | B49: =AM39+AN31-AN35 -> -86962.823
A50: Lowest cumulative channel cash | B50: =MIN(D39:AM39) -> -90190.615
A51: Cash payback month for the channel (cumulative >= 0) | B51: =IF(COUNT(D40:AM40)=0,"Not within 36 mo",MIN(D40:AM40)) -> Not within 36 mo
A52: Approved cards needed to repay agent R&D at the incremental, risk-adjusted margin | B52: =IFERROR(-AN37/($B$9*Inputs!$H$268*(1-$B$12)),0) -> 56363.636

Sheet Unit Economics
A1: Unit Economics - contribution margin per item by SKU (selected scenario)
A2: Per item, single-item order basis. Print/shipping are ESTIMATES. Token cost includes scenario multiplier and OpenRouter fee. Stripe fixed fee spread over items per order.
A4: SKU | B4: List price | C4: Postage revenue | D4: Gross revenue | E4: Refund allowance | F4: Net revenue | G4: Token cost | H4: Print cost | I4: Shipping cost | J4: Reprint allowance | K4: Stripe fee | L4: Dispute allowance | M4: Total variable cost | N4: Contribution margin $ | O4: Contribution margin %
A5: =Inputs!A47 -> Card - Digital e-card/PDF | B5: =IF(Scenarios!$B$44=1,Inputs!B115,Inputs!E47) -> 3.99 | C5: =IF(Scenarios!$B$44=1,Inputs!C115,Inputs!F47)*Inputs!D47*Inputs!$B$43 -> 0 | D5: =B5+C5 -> 3.99 | E5: =D5*Inputs!$B$36*Scenarios!$B$11 -> 0.1197 | F5: =D5-E5 -> 3.8703 | G5: ='Model Costs'!J35*Scenarios!$B$10*(1+Inputs!$B$42) -> 0.2615345 | H5: =Inputs!H47*Inputs!D47*Scenarios!$B$13 -> 0 | I5: =Inputs!I47*Inputs!D47*Scenarios!$B$13 -> 0 | J5: =(H5+I5)*Inputs!$B$37*Scenarios!$B$11 -> 0 | K5: =D5*Inputs!$B$40+Inputs!$B$41/Inputs!$B$9 -> 0.37657957 | L5: =Inputs!$B$38*Inputs!$B$39/Inputs!$B$9 -> 0.039130435 | M5: =SUM(G5:L5) -> 0.6772445 | N5: =F5-M5 -> 3.1930555 | O5: =IFERROR(N5/F5,0) -> 0.82501499
A6: =Inputs!A48 -> Card - Printed 5x7 folded | B6: =IF(Scenarios!$B$44=1,Inputs!B116,Inputs!E48) -> 7.99 | C6: =IF(Scenarios!$B$44=1,Inputs!C116,Inputs!F48)*Inputs!D48*Inputs!$B$43 -> 2.691 | D6: =B6+C6 -> 10.681 | E6: =D6*Inputs!$B$36*Scenarios!$B$11 -> 0.32043 | F6: =D6-E6 -> 10.36057 | G6: ='Model Costs'!J36*Scenarios!$B$10*(1+Inputs!$B$42) -> 0.2615345 | H6: =Inputs!H48*Inputs!D48*Scenarios!$B$13 -> 3.25 | I6: =Inputs!I48*Inputs!D48*Scenarios!$B$13 -> 1.6 | J6: =(H6+I6)*Inputs!$B$37*Scenarios!$B$11 -> 0.194 | K6: =D6*Inputs!$B$40+Inputs!$B$41/Inputs!$B$9 -> 0.57061857 | L6: =Inputs!$B$38*Inputs!$B$39/Inputs!$B$9 -> 0.039130435 | M6: =SUM(G6:L6) -> 5.9152835 | N6: =F6-M6 -> 4.4452865 | O6: =IFERROR(N6/F6,0) -> 0.4290581
A7: =Inputs!A49 -> Book - Digital flipbook/PDF | B7: =IF(Scenarios!$B$44=1,Inputs!B117,Inputs!E49) -> 19.99 | C7: =IF(Scenarios!$B$44=1,Inputs!C117,Inputs!F49)*Inputs!D49*Inputs!$B$43 -> 0 | D7: =B7+C7 -> 19.99 | E7: =D7*Inputs!$B$36*Scenarios!$B$11 -> 0.5997 | F7: =D7-E7 -> 19.3903 | G7: ='Model Costs'!J37*Scenarios!$B$10*(1+Inputs!$B$42) -> 1.3336255 | H7: =Inputs!H49*Inputs!D49*Scenarios!$B$13 -> 0 | I7: =Inputs!I49*Inputs!D49*Scenarios!$B$13 -> 0 | J7: =(H7+I7)*Inputs!$B$37*Scenarios!$B$11 -> 0 | K7: =D7*Inputs!$B$40+Inputs!$B$41/Inputs!$B$9 -> 0.84057957 | L7: =Inputs!$B$38*Inputs!$B$39/Inputs!$B$9 -> 0.039130435 | M7: =SUM(G7:L7) -> 2.2133355 | N7: =F7-M7 -> 17.176965 | O7: =IFERROR(N7/F7,0) -> 0.88585347
A8: =Inputs!A50 -> Book - Hardcover 8.5x8.5, 24pp | B8: =IF(Scenarios!$B$44=1,Inputs!B118,Inputs!E50) -> 39 | C8: =IF(Scenarios!$B$44=1,Inputs!C118,Inputs!F50)*Inputs!D50*Inputs!$B$43 -> 5.391 | D8: =B8+C8 -> 44.391 | E8: =D8*Inputs!$B$36*Scenarios!$B$11 -> 1.33173 | F8: =D8-E8 -> 43.05927 | G8: ='Model Costs'!J38*Scenarios!$B$10*(1+Inputs!$B$42) -> 1.3336255 | H8: =Inputs!H50*Inputs!D50*Scenarios!$B$13 -> 12.5 | I8: =Inputs!I50*Inputs!D50*Scenarios!$B$13 -> 5.5 | J8: =(H8+I8)*Inputs!$B$37*Scenarios!$B$11 -> 0.72 | K8: =D8*Inputs!$B$40+Inputs!$B$41/Inputs!$B$9 -> 1.5482086 | L8: =Inputs!$B$38*Inputs!$B$39/Inputs!$B$9 -> 0.039130435 | M8: =SUM(G8:L8) -> 21.640964 | N8: =F8-M8 -> 21.418305 | O8: =IFERROR(N8/F8,0) -> 0.49741451
A9: =Inputs!A51 -> Book - Hardcover 8.5x8.5, 32pp | B9: =IF(Scenarios!$B$44=1,Inputs!B119,Inputs!E51) -> 49 | C9: =IF(Scenarios!$B$44=1,Inputs!C119,Inputs!F51)*Inputs!D51*Inputs!$B$43 -> 5.391 | D9: =B9+C9 -> 54.391 | E9: =D9*Inputs!$B$36*Scenarios!$B$11 -> 1.63173 | F9: =D9-E9 -> 52.75927 | G9: ='Model Costs'!J39*Scenarios!$B$10*(1+Inputs!$B$42) -> 1.7256635 | H9: =Inputs!H51*Inputs!D51*Scenarios!$B$13 -> 14.5 | I9: =Inputs!I51*Inputs!D51*Scenarios!$B$13 -> 6 | J9: =(H9+I9)*Inputs!$B$37*Scenarios!$B$11 -> 0.82 | K9: =D9*Inputs!$B$40+Inputs!$B$41/Inputs!$B$9 -> 1.8382086 | L9: =Inputs!$B$38*Inputs!$B$39/Inputs!$B$9 -> 0.039130435 | M9: =SUM(G9:L9) -> 24.923002 | N9: =F9-M9 -> 27.836268 | O9: =IFERROR(N9/F9,0) -> 0.52760903
A10: Blended (mix-weighted) per item | B10: =SUMPRODUCT(Inputs!$G$47:$G$51,B5:B9) -> 22.4738 | C10: =SUMPRODUCT(Inputs!$G$47:$G$51,C5:C9) -> 3.12498 | D10: =SUMPRODUCT(Inputs!$G$47:$G$51,D5:D9) -> 25.59878 | E10: =SUMPRODUCT(Inputs!$G$47:$G$51,E5:E9) -> 0.7679634 | F10: =SUMPRODUCT(Inputs!$G$47:$G$51,F5:F9) -> 24.830817 | G10: =SUMPRODUCT(Inputs!$G$47:$G$51,G5:G9) -> 0.8448651 | H10: =SUMPRODUCT(Inputs!$G$47:$G$51,H5:H9) -> 6.51 | I10: =SUMPRODUCT(Inputs!$G$47:$G$51,I5:I9) -> 2.845 | ... N10: =SUMPRODUCT(Inputs!$G$47:$G$51,N5:N9) -> 13.214387 | O10: =IFERROR(N10/F10,0) -> 0.5321769
A13: Paid channels in the selected scenario (CPC: Low scenario = CMO high CPC, High scenario = CMO low CPC)
A14: Channel | B14: Budget share | C14: Active CPC ($) | D14: CTR | E14: Visitor -> sign-up | F14: Sign-up -> purchase | G14: CAC ($ per customer) | H14: Visitor -> customer | I14: Orders to repay CAC
A15: =Inputs!A57 -> meta_instagram_ads | B15: =Inputs!J57 -> 0.30769231 | C15: =INDEX(Inputs!$C$57:$E$57,4-Scenarios!$B$4) -> 0.85 | D15: =Inputs!F57 -> 0.011 | E15: =Inputs!G57 -> 0.07 | F15: =Inputs!H57*Scenarios!$B$8 -> 0.14 | G15: =IFERROR(C15/(E15*F15),0) -> 86.734694 | H15: =E15*F15 -> 0.0098 | I15: =IFERROR(G15/$N$10/Inputs!$B$9,0) -> 5.7075272
A16: =Inputs!A58 -> pinterest_ads | B16: =Inputs!J58 -> 0.12307692 | C16: =INDEX(Inputs!$C$58:$E$58,4-Scenarios!$B$4) -> 0.55 | D16: =Inputs!F58 -> 0.006 | E16: =Inputs!G58 -> 0.06 | F16: =Inputs!H58*Scenarios!$B$8 -> 0.15 | G16: =IFERROR(C16/(E16*F16),0) -> 61.111111 | H16: =E16*F16 -> 0.009 | I16: =IFERROR(G16/$N$10/Inputs!$B$9,0) -> 4.0213819
A17: =Inputs!A59 -> google_search | B17: =Inputs!J59 -> 0.12307692 | C17: =IF(Scenarios!$B$44=1,Inputs!$H$121,INDEX(Inputs!$C$59:$E$59,4-Scenarios!$B$4)) -> 4.14 | D17: =Inputs!F59 -> 0.045 | E17: =Inputs!G59 -> 0.09 | F17: =Inputs!H59*Scenarios!$B$8 -> 0.2 | G17: =IFERROR(C17/(E17*F17),0) -> 230 | H17: =E17*F17 -> 0.018 | I17: =IFERROR(G17/$N$10/Inputs!$B$9,0) -> 15.135019
A18: =Inputs!A60 -> tiktok_ads | B18: =Inputs!J60 -> 0.046153846 | C18: =INDEX(Inputs!$C$60:$E$60,4-Scenarios!$B$4) -> 0.6 | D18: =Inputs!F60 -> 0.008 | E18: =Inputs!G60 -> 0.04 | F18: =Inputs!H60*Scenarios!$B$8 -> 0.09 | G18: =IFERROR(C18/(E18*F18),0) -> 166.66667 | H18: =E18*F18 -> 0.0036 | I18: =IFERROR(G18/$N$10/Inputs!$B$9,0) -> 10.967405
A19: =Inputs!A61 -> creators_affiliate | B19: =Inputs!J61 -> 0.21538462 | C19: =INDEX(Inputs!$C$61:$E$61,4-Scenarios!$B$4) -> 1.2 | D19: =Inputs!F61 -> 0.02 | E19: =Inputs!G61 -> 0.08 | F19: =Inputs!H61*Scenarios!$B$8 -> 0.16 | G19: =IFERROR(C19/(E19*F19),0) -> 93.75 | H19: =E19*F19 -> 0.0128 | I19: =IFERROR(G19/$N$10/Inputs!$B$9,0) -> 6.1691655
A20: =Inputs!A62 -> occasion_seo_content | B20: =Inputs!J62 -> 0.18461538 | C20: =INDEX(Inputs!$C$62:$E$62,4-Scenarios!$B$4) -> 0.35 | D20: =Inputs!F62 -> 0.03 | E20: =Inputs!G62 -> 0.07 | F20: =Inputs!H62*Scenarios!$B$8 -> 0.15 | G20: =IFERROR(C20/(E20*F20),0) -> 33.333333 | H20: =E20*F20 -> 0.0105 | I20: =IFERROR(G20/$N$10/Inputs!$B$9,0) -> 2.1934811
A22: Customer acquisition vs lifetime value
A23: Blended contribution margin per order ($) | B23: =N10*Inputs!$B$9 -> 15.196545 | C23: Before marketing and opex
A24: Expected orders per customer over lifetime | B24: =1+Inputs!$B$32*Inputs!$B$33*Scenarios!$B$9 -> 1.7 | C24: 1 + repeat/yr x lifetime yrs x scenario
A25: Lifetime value per customer (contribution, $) | B25: =$B$23*$B$24 -> 25.834126 | C25: Undiscounted
A26: Paid visits per $ of budget | B26: =SUMPRODUCT(B15:B20/C15:C20) -> 1.3993787 | C26: Budget / CPC, share-weighted
A27: New paid customers per $ of budget | B27: =SUMPRODUCT(B15:B20/C15:C20*H15:H20) -> 0.014209435
A28: Paid CAC, steady state ($ per new customer) | B28: =IFERROR(1/$B$27,0) -> 70.375775 | C28: Paid channels only; organic customers cost $0
A29: Orders needed to repay paid CAC | B29: =IFERROR($B$28/$B$23,0) -> 4.6310379
A31: Creator channel, all-in (v3: fixed gifts and fees are the channel budget; discount and commission are per order)
A32: Creator discount + commission per attributed order ($) | B32: =Inputs!$B$9*$B$10*Inputs!$B$293*(Inputs!$B$291+(1-Inputs!$B$291)*Inputs!$B$292) -> 4.9105253 | C32: Merchandise only; postage excluded
A33: Contribution per creator first order after discount and commission ($) | B33: =$B$23-$B$32 -> 10.28602 | C33: Compare B23
A34: Creator CAC, all-in ($ per new customer) | B34: =$G$19+$B$32 -> 98.660525 | C34: Fixed spend per customer (G19) + per-order cost

Sheet Model Costs
A1: Model Costs - token and render cost per product
A2: MEASURED = CTO pipeline ledger (finance/measured_costs.json, OpenRouter usage.cost, 4 runs, $1.53 test spend). EXTRAPOLATED = CTO scaled measured per-call costs linearly to full 24/32-page books (no full-book run yet). ESTIMATE = my assumption, not measured. Yellow = pasted CTO data (blank = fall back to estimate).
A3: Exception to 'inputs only on Inputs': the CTO swap-in slots and cost tables live here by owner request. Image size selector below chooses 2K (CTO default, measured totals apply) or 4K (totals recomputed from the 4K per-call price).
A5: Print image size (2K or 4K) | B5: 2K | C5: 2K = about 280 DPI at card size and 234 DPI at book size (CTO). Below the 300 DPI print norm but CTO judges 4K (2x cost) gives little visible gain. Verify with a physical Lulu proof and the Lulu file validator before launch.
A7: Unit price | B7: Estimate (superseded) | C7: Measured (CTO paste) | D7: Active | E7: Unit | F7: Status / source
A8: Image render 2K (nano-banana-2.1 via OpenRouter) | B8: 0.11 | C8: 0.0609 | D8: =IF(ISNUMBER(C8),C8,B8) -> 0.0609 | E8: $ / render | F8: MEASURED, n=14. Old estimate $0.11 was a 4K-class figure from the Eye Story.
A9: Image render 4K | B9: 0.12 | C9: 0.1233 | D9: =IF(ISNUMBER(C9),C9,B9) -> 0.1233 | E9: $ / render | F9: MEASURED, n=1 (single probe call).
A10: Image render 1K (guest preview) | B10: 0.04 | C10: 0.041 | D10: =IF(ISNUMBER(C10),C10,B10) -> 0.041 | E10: $ / render | F10: MEASURED, n=5.
A11: Vision QA check per render | B11: 0.003 | C11: 0.0025 | D11: =IF(ISNUMBER(C11),C11,B11) -> 0.0025 | E11: $ / call | F11: MEASURED.
A12: Claude Sonnet input (for unmeasured intake chat) | B12: 3 | D12: =IF(ISNUMBER(C12),C12,B12) -> 3 | E12: $ / M tokens | F12: ESTIMATE: list price - verify.
A13: Claude Sonnet output (for unmeasured intake chat) | B13: 15 | D13: =IF(ISNUMBER(C13),C13,B13) -> 15 | E13: $ / M tokens | F13: ESTIMATE: list price - verify.
A14: Render price used (follows size selector) | D14: =IF($B$5="4K",$D$9,$D$8) -> 0.0609 | E14: $ / render
A16: Text calls: estimate from tokens, then CTO measured cost per unit
A17: Call type | B17: Intake chat (card) | C17: Intake chat (book) | D17: Story writer (per spread) | E17: Identity sheet (vision) | F17: Art-director prompts (per page) | G17: Card copy + prompts (per card) | H17: Guest intake (mini)
A18: Input tokens / unit (ESTIMATE) | B18: 14000 | C18: 22000 | D18: 450 | E18: 6000 | F18: 900 | G18: 4500 | H18: 6000
A19: Output tokens / unit (ESTIMATE) | B19: 1800 | C19: 2500 | D19: 250 | E19: 900 | F19: 450 | G19: 1300 | H19: 800
A20: Estimated cost per unit ($) | B20: =B18/1000000*$D$12+B19/1000000*$D$13 -> 0.069 | C20: =C18/1000000*$D$12+C19/1000000*$D$13 -> 0.1035 | D20: =D18/1000000*$D$12+D19/1000000*$D$13 -> 0.0051 | E20: =E18/1000000*$D$12+E19/1000000*$D$13 -> 0.0315 | F20: =F18/1000000*$D$12+F19/1000000*$D$13 -> 0.00945 | G20: =G18/1000000*$D$12+G19/1000000*$D$13 -> 0.033 | H20: =H18/1000000*$D$12+H19/1000000*$D$13 -> 0.03
A21: MEASURED cost per unit (CTO paste) | D21: 0.0074 | E21: 0.0106 | F21: 0.0094 | G21: 0.0471
A22: Cost per unit used ($) | B22: =IF(ISNUMBER(B21),B21,B20) -> 0.069 | C22: =IF(ISNUMBER(C21),C21,C20) -> 0.1035 | D22: =IF(ISNUMBER(D21),D21,D20) -> 0.0074 | E22: =IF(ISNUMBER(E21),E21,E20) -> 0.0106 | F22: =IF(ISNUMBER(F21),F21,F20) -> 0.0094 | G22: =IF(ISNUMBER(G21),G21,G20) -> 0.0471 | H22: =IF(ISNUMBER(H21),H21,H20) -> 0.03
A23: Measured: identity 0.0106, story 0.0074 per spread, prompts 0.0094 per page, card copy 0.0054 + card prompts 0.0417. Intake chat and guest intake are NOT measured (Greet Guide not built).
A25: Units per SKU (ESTIMATE; spreads/pages per CTO: 24pp = 11 spreads, 14 renders; 32pp = 15 spreads, 18 renders)
A26: SKU | B26: Intake chat (card) | C26: Intake chat (book) | D26: Story writer (per spread) | E26: Identity sheet (vision) | F26: Art-director prompts (per page) | G26: Card copy + prompts (per card) | H26: Guest intake (mini)
A27: =Inputs!A47 -> Card - Digital e-card/PDF | B27: 1 | C27: 0 | D27: 0 | E27: 0 | F27: 0 | G27: 1 | H27: 0
A28: =Inputs!A48 -> Card - Printed 5x7 folded | B28: 1 | C28: 0 | D28: 0 | E28: 0 | F28: 0 | G28: 1 | H28: 0
A29: =Inputs!A49 -> Book - Digital flipbook/PDF | B29: 0 | C29: 1 | D29: 11 | E29: 1 | F29: 14 | G29: 0 | H29: 0
A30: =Inputs!A50 -> Book - Hardcover 8.5x8.5, 24pp | B30: 0 | C30: 1 | D30: 11 | E30: 1 | F30: 14 | G30: 0 | H30: 0
A31: =Inputs!A51 -> Book - Hardcover 8.5x8.5, 32pp | B31: 0 | C31: 1 | D31: 15 | E31: 1 | F31: 18 | G31: 0 | H31: 0
A33: Token cost per SKU (before scenario multiplier and OpenRouter fee)
A34: SKU | B34: Base renders (CTO) | C34: Re-roll rate | D34: Effective renders | E34: Render $ | F34: QA $ | G34: Text $ | H34: Computed total $ | I34: Measured total $ with re-rolls (CTO paste, 2K) | J34: Token cost used $ | K34: Basis of measured figure
A35: =Inputs!A47 -> Card - Digital e-card/PDF | B35: 3 | C35: =IF(Inputs!B47="Card",Inputs!$B$34,Inputs!$B$35) -> 0.2 | D35: =B35*(1+C35) -> 3.6 | E35: =D35*$D$14 -> 0.21924 | F35: =D35*$D$11 -> 0.009 | G35: =SUMPRODUCT(B27:H27,$B$22:$H$22) -> 0.1161 | H35: =E35+F35+G35 -> 0.34434 | I35: 0.2479 | J35: =IF(AND($B$5="2K",ISNUMBER(I35)),I35+(C35-Inputs!$B$294)*MAX(0,B35-1)*($D$14+$D$11),H35) -> 0.2479 | K35: EXTRAPOLATED from per-call costs; clean 3-render run measured $0.239
A36: =Inputs!A48 -> Card - Printed 5x7 folded | B36: 3 | C36: =IF(Inputs!B48="Card",Inputs!$B$34,Inputs!$B$35) -> 0.2 | D36: =B36*(1+C36) -> 3.6 | E36: =D36*$D$14 -> 0.21924 | F36: =D36*$D$11 -> 0.009 | G36: =SUMPRODUCT(B28:H28,$B$22:$H$22) -> 0.1161 | H36: =E36+F36+G36 -> 0.34434 | I36: 0.2479 | J36: =IF(AND($B$5="2K",ISNUMBER(I36)),I36+(C36-Inputs!$B$294)*MAX(0,B36-1)*($D$14+$D$11),H36) -> 0.2479 | K36: EXTRAPOLATED (same as digital card)
A37: =Inputs!A49 -> Book - Digital flipbook/PDF | B37: 14 | C37: =IF(Inputs!B49="Card",Inputs!$B$34,Inputs!$B$35) -> 0.2 | D37: =B37*(1+C37) -> 16.8 | E37: =D37*$D$14 -> 1.02312 | F37: =D37*$D$11 -> 0.042 | G37: =SUMPRODUCT(B29:H29,$B$22:$H$22) -> 0.3271 | H37: =E37+F37+G37 -> 1.39222 | I37: 1.2641 | J37: =IF(AND($B$5="2K",ISNUMBER(I37)),I37+(C37-Inputs!$B$294)*MAX(0,B37-1)*($D$14+$D$11),H37) -> 1.2641 | K37: EXTRAPOLATED, 24pp book (4-art-page run measured $0.469, not a full book)
A38: =Inputs!A50 -> Book - Hardcover 8.5x8.5, 24pp | B38: 14 | C38: =IF(Inputs!B50="Card",Inputs!$B$34,Inputs!$B$35) -> 0.2 | D38: =B38*(1+C38) -> 16.8 | E38: =D38*$D$14 -> 1.02312 | F38: =D38*$D$11 -> 0.042 | G38: =SUMPRODUCT(B30:H30,$B$22:$H$22) -> 0.3271 | H38: =E38+F38+G38 -> 1.39222 | I38: 1.2641 | J38: =IF(AND($B$5="2K",ISNUMBER(I38)),I38+(C38-Inputs!$B$294)*MAX(0,B38-1)*($D$14+$D$11),H38) -> 1.2641 | K38: EXTRAPOLATED, no full 24pp run yet
A39: =Inputs!A51 -> Book - Hardcover 8.5x8.5, 32pp | B39: 18 | C39: =IF(Inputs!B51="Card",Inputs!$B$34,Inputs!$B$35) -> 0.2 | D39: =B39*(1+C39) -> 21.6 | E39: =D39*$D$14 -> 1.31544 | F39: =D39*$D$11 -> 0.054 | G39: =SUMPRODUCT(B31:H31,$B$22:$H$22) -> 0.3943 | H39: =E39+F39+G39 -> 1.76374 | I39: 1.6357 | J39: =IF(AND($B$5="2K",ISNUMBER(I39)),I39+(C39-Inputs!$B$294)*MAX(0,B39-1)*($D$14+$D$11),H39) -> 1.6357 | K39: EXTRAPOLATED, no full 32pp run yet
A40: At 2K the CTO measured/extrapolated total is used. At 4K the totals are recomputed from the 4K render price (pasted totals are 2K only). CTO reference for 24pp at 4K: $2.31 with re-rolls.
A42: Guest free preview (cost with no revenue)
A43: Renders per guest preview (1K) | B43: 1
A44: Guest preview cost, computed $ | B44: =B43*$D$10+H22 -> 0.071
A45: Guest preview cost, CTO estimate $ (not run end to end) | B45: 0.0689
A46: Guest preview cost used $ | B46: =IF(ISNUMBER(B45),B45,B44) -> 0.0689
A48: Scenario token multiplier and the OpenRouter fee are applied on Unit Economics.

Sheet Opex
A1: Opex - monthly operating costs (fixed + variable, rates from Inputs section 10)
A2: Driver codes: 1 visits, 2 sign-ups, 3 orders, 4 gross revenue ($). One-time launch costs hit month 1.
A4: Line | B4: Driver | C4: Opening | D4: M1 | E4: M2 | F4: M3 | G4: M4 | H4: M5 | I4: M6 | J4: M7 | K4: M8 | L4: M9 | M4: M10 | N4: M11 | O4: M12 | P4: M13 | Q4: M14 | R4: M15 | S4: M16 | T4: M17 | U4: M18 | V4: M19 | W4: M20 | X4: M21 | Y4: M22 | Z4: M23 | AA4: M24 | AB4: M25 | AC4: M26 | AD4: M27 | AE4: M28 | AF4: M29 | AG4: M30 | AH4: M31 | AI4: M32 | AJ4: M33 | AK4: M34 | AL4: M35 | AM4: M36
A5: Month # | D5: =Forecast!D6 -> 1 | E5: =Forecast!E6 -> 2 | F5: =Forecast!F6 -> 3 | G5: =Forecast!G6 -> 4 | H5: =Forecast!H6 -> 5 | I5: =Forecast!I6 -> 6 | J5: =Forecast!J6 -> 7 | K5: =Forecast!K6 -> 8 | ... AM5: =Forecast!AM6 -> 36
A7: =Inputs!A94 -> Vercel (Pro) | B7: =Inputs!D94 -> 1 | D7: =Inputs!$B$94+Inputs!$C$94/1000*CHOOSE(Inputs!$D$94,Forecast!D30,Forecast!D35,Forecast!D43,Forecast!D58) -> 26.530178 | E7: =Inputs!$B$94+Inputs!$C$94/1000*CHOOSE(Inputs!$D$94,Forecast!E30,Forecast!E35,Forecast!E43,Forecast!E58) -> 28.733098 | F7: =Inputs!$B$94+Inputs!$C$94/1000*CHOOSE(Inputs!$D$94,Forecast!F30,Forecast!F35,Forecast!F43,Forecast!F58) -> 24.770862 | G7: =Inputs!$B$94+Inputs!$C$94/1000*CHOOSE(Inputs!$D$94,Forecast!G30,Forecast!G35,Forecast!G43,Forecast!G58) -> 26.994952 | H7: =Inputs!$B$94+Inputs!$C$94/1000*CHOOSE(Inputs!$D$94,Forecast!H30,Forecast!H35,Forecast!H43,Forecast!H58) -> 25.484794 | I7: =Inputs!$B$94+Inputs!$C$94/1000*CHOOSE(Inputs!$D$94,Forecast!I30,Forecast!I35,Forecast!I43,Forecast!I58) -> 25.771036 | J7: =Inputs!$B$94+Inputs!$C$94/1000*CHOOSE(Inputs!$D$94,Forecast!J30,Forecast!J35,Forecast!J43,Forecast!J58) -> 27.87708 | K7: =Inputs!$B$94+Inputs!$C$94/1000*CHOOSE(Inputs!$D$94,Forecast!K30,Forecast!K35,Forecast!K43,Forecast!K58) -> 26.628606 | ... AM7: =Inputs!$B$94+Inputs!$C$94/1000*CHOOSE(Inputs!$D$94,Forecast!AM30,Forecast!AM35,Forecast!AM43,Forecast!AM58) -> 28.763081
A8: =Inputs!A95 -> Supabase (Pro + compute) | B8: =Inputs!D95 -> 2 | D8: =Inputs!$B$95+Inputs!$C$95/1000*CHOOSE(Inputs!$D$95,Forecast!D30,Forecast!D35,Forecast!D43,Forecast!D58) -> 52.962175 | E8: =Inputs!$B$95+Inputs!$C$95/1000*CHOOSE(Inputs!$D$95,Forecast!E30,Forecast!E35,Forecast!E43,Forecast!E58) -> 59.046267 | F8: =Inputs!$B$95+Inputs!$C$95/1000*CHOOSE(Inputs!$D$95,Forecast!F30,Forecast!F35,Forecast!F43,Forecast!F58) -> 48.120173 | G8: =Inputs!$B$95+Inputs!$C$95/1000*CHOOSE(Inputs!$D$95,Forecast!G30,Forecast!G35,Forecast!G43,Forecast!G58) -> 54.263541 | H8: =Inputs!$B$95+Inputs!$C$95/1000*CHOOSE(Inputs!$D$95,Forecast!H30,Forecast!H35,Forecast!H43,Forecast!H58) -> 50.098163 | I8: =Inputs!$B$95+Inputs!$C$95/1000*CHOOSE(Inputs!$D$95,Forecast!I30,Forecast!I35,Forecast!I43,Forecast!I58) -> 50.892634 | J8: =Inputs!$B$95+Inputs!$C$95/1000*CHOOSE(Inputs!$D$95,Forecast!J30,Forecast!J35,Forecast!J43,Forecast!J58) -> 56.719486 | K8: =Inputs!$B$95+Inputs!$C$95/1000*CHOOSE(Inputs!$D$95,Forecast!K30,Forecast!K35,Forecast!K43,Forecast!K58) -> 53.272808 | ... AM8: =Inputs!$B$95+Inputs!$C$95/1000*CHOOSE(Inputs!$D$95,Forecast!AM30,Forecast!AM35,Forecast!AM43,Forecast!AM58) -> 59.256346
A9: =Inputs!A96 -> Resend (email) | B9: =Inputs!D96 -> 3 | D9: =Inputs!$B$96+Inputs!$C$96/1000*CHOOSE(Inputs!$D$96,Forecast!D30,Forecast!D35,Forecast!D43,Forecast!D58) -> 20.076771 | E9: =Inputs!$B$96+Inputs!$C$96/1000*CHOOSE(Inputs!$D$96,Forecast!E30,Forecast!E35,Forecast!E43,Forecast!E58) -> 20.133908 | F9: =Inputs!$B$96+Inputs!$C$96/1000*CHOOSE(Inputs!$D$96,Forecast!F30,Forecast!F35,Forecast!F43,Forecast!F58) -> 20.045658 | G9: =Inputs!$B$96+Inputs!$C$96/1000*CHOOSE(Inputs!$D$96,Forecast!G30,Forecast!G35,Forecast!G43,Forecast!G58) -> 20.091782 | H9: =Inputs!$B$96+Inputs!$C$96/1000*CHOOSE(Inputs!$D$96,Forecast!H30,Forecast!H35,Forecast!H43,Forecast!H58) -> 20.060113 | I9: =Inputs!$B$96+Inputs!$C$96/1000*CHOOSE(Inputs!$D$96,Forecast!I30,Forecast!I35,Forecast!I43,Forecast!I58) -> 20.066178 | J9: =Inputs!$B$96+Inputs!$C$96/1000*CHOOSE(Inputs!$D$96,Forecast!J30,Forecast!J35,Forecast!J43,Forecast!J58) -> 20.114884 | K9: =Inputs!$B$96+Inputs!$C$96/1000*CHOOSE(Inputs!$D$96,Forecast!K30,Forecast!K35,Forecast!K43,Forecast!K58) -> 20.086081 | ... AM9: =Inputs!$B$96+Inputs!$C$96/1000*CHOOSE(Inputs!$D$96,Forecast!AM30,Forecast!AM35,Forecast!AM43,Forecast!AM58) -> 20.179072
A10: =Inputs!A97 -> Domain | B10: =Inputs!D97 -> 1 | D10: =Inputs!$B$97+Inputs!$C$97/1000*CHOOSE(Inputs!$D$97,Forecast!D30,Forecast!D35,Forecast!D43,Forecast!D58) -> 1.67 | E10: =Inputs!$B$97+Inputs!$C$97/1000*CHOOSE(Inputs!$D$97,Forecast!E30,Forecast!E35,Forecast!E43,Forecast!E58) -> 1.67 | F10: =Inputs!$B$97+Inputs!$C$97/1000*CHOOSE(Inputs!$D$97,Forecast!F30,Forecast!F35,Forecast!F43,Forecast!F58) -> 1.67 | G10: =Inputs!$B$97+Inputs!$C$97/1000*CHOOSE(Inputs!$D$97,Forecast!G30,Forecast!G35,Forecast!G43,Forecast!G58) -> 1.67 | H10: =Inputs!$B$97+Inputs!$C$97/1000*CHOOSE(Inputs!$D$97,Forecast!H30,Forecast!H35,Forecast!H43,Forecast!H58) -> 1.67 | I10: =Inputs!$B$97+Inputs!$C$97/1000*CHOOSE(Inputs!$D$97,Forecast!I30,Forecast!I35,Forecast!I43,Forecast!I58) -> 1.67 | J10: =Inputs!$B$97+Inputs!$C$97/1000*CHOOSE(Inputs!$D$97,Forecast!J30,Forecast!J35,Forecast!J43,Forecast!J58) -> 1.67 | K10: =Inputs!$B$97+Inputs!$C$97/1000*CHOOSE(Inputs!$D$97,Forecast!K30,Forecast!K35,Forecast!K43,Forecast!K58) -> 1.67 | ... AM10: =Inputs!$B$97+Inputs!$C$97/1000*CHOOSE(Inputs!$D$97,Forecast!AM30,Forecast!AM35,Forecast!AM43,Forecast!AM58) -> 1.67
A11: =Inputs!A98 -> Stripe Tax | B11: =Inputs!D98 -> 4 | D11: =Inputs!$B$98+Inputs!$C$98/1000*CHOOSE(Inputs!$D$98,Forecast!D30,Forecast!D35,Forecast!D43,Forecast!D58) -> 13.560259 | E11: =Inputs!$B$98+Inputs!$C$98/1000*CHOOSE(Inputs!$D$98,Forecast!E30,Forecast!E35,Forecast!E43,Forecast!E58) -> 23.652439 | F11: =Inputs!$B$98+Inputs!$C$98/1000*CHOOSE(Inputs!$D$98,Forecast!F30,Forecast!F35,Forecast!F43,Forecast!F58) -> 8.0646212 | G11: =Inputs!$B$98+Inputs!$C$98/1000*CHOOSE(Inputs!$D$98,Forecast!G30,Forecast!G35,Forecast!G43,Forecast!G58) -> 16.211587 | H11: =Inputs!$B$98+Inputs!$C$98/1000*CHOOSE(Inputs!$D$98,Forecast!H30,Forecast!H35,Forecast!H43,Forecast!H58) -> 10.617775 | I11: =Inputs!$B$98+Inputs!$C$98/1000*CHOOSE(Inputs!$D$98,Forecast!I30,Forecast!I35,Forecast!I43,Forecast!I58) -> 11.689211 | J11: =Inputs!$B$98+Inputs!$C$98/1000*CHOOSE(Inputs!$D$98,Forecast!J30,Forecast!J35,Forecast!J43,Forecast!J58) -> 20.292161 | K11: =Inputs!$B$98+Inputs!$C$98/1000*CHOOSE(Inputs!$D$98,Forecast!K30,Forecast!K35,Forecast!K43,Forecast!K58) -> 15.204703 | ... AM11: =Inputs!$B$98+Inputs!$C$98/1000*CHOOSE(Inputs!$D$98,Forecast!AM30,Forecast!AM35,Forecast!AM43,Forecast!AM58) -> 31.629771
A12: =Inputs!A99 -> Monitoring (Sentry + uptime) | B12: =Inputs!D99 -> 1 | D12: =Inputs!$B$99+Inputs!$C$99/1000*CHOOSE(Inputs!$D$99,Forecast!D30,Forecast!D35,Forecast!D43,Forecast!D58) -> 26 | E12: =Inputs!$B$99+Inputs!$C$99/1000*CHOOSE(Inputs!$D$99,Forecast!E30,Forecast!E35,Forecast!E43,Forecast!E58) -> 26 | F12: =Inputs!$B$99+Inputs!$C$99/1000*CHOOSE(Inputs!$D$99,Forecast!F30,Forecast!F35,Forecast!F43,Forecast!F58) -> 26 | G12: =Inputs!$B$99+Inputs!$C$99/1000*CHOOSE(Inputs!$D$99,Forecast!G30,Forecast!G35,Forecast!G43,Forecast!G58) -> 26 | H12: =Inputs!$B$99+Inputs!$C$99/1000*CHOOSE(Inputs!$D$99,Forecast!H30,Forecast!H35,Forecast!H43,Forecast!H58) -> 26 | I12: =Inputs!$B$99+Inputs!$C$99/1000*CHOOSE(Inputs!$D$99,Forecast!I30,Forecast!I35,Forecast!I43,Forecast!I58) -> 26 | J12: =Inputs!$B$99+Inputs!$C$99/1000*CHOOSE(Inputs!$D$99,Forecast!J30,Forecast!J35,Forecast!J43,Forecast!J58) -> 26 | K12: =Inputs!$B$99+Inputs!$C$99/1000*CHOOSE(Inputs!$D$99,Forecast!K30,Forecast!K35,Forecast!K43,Forecast!K58) -> 26 | ... AM12: =Inputs!$B$99+Inputs!$C$99/1000*CHOOSE(Inputs!$D$99,Forecast!AM30,Forecast!AM35,Forecast!AM43,Forecast!AM58) -> 26
A13: =Inputs!A100 -> OpenRouter base (dev/QA/pipeline testing) | B13: =Inputs!D100 -> 1 | D13: =Inputs!$B$100+Inputs!$C$100/1000*CHOOSE(Inputs!$D$100,Forecast!D30,Forecast!D35,Forecast!D43,Forecast!D58) -> 75 | E13: =Inputs!$B$100+Inputs!$C$100/1000*CHOOSE(Inputs!$D$100,Forecast!E30,Forecast!E35,Forecast!E43,Forecast!E58) -> 75 | F13: =Inputs!$B$100+Inputs!$C$100/1000*CHOOSE(Inputs!$D$100,Forecast!F30,Forecast!F35,Forecast!F43,Forecast!F58) -> 75 | G13: =Inputs!$B$100+Inputs!$C$100/1000*CHOOSE(Inputs!$D$100,Forecast!G30,Forecast!G35,Forecast!G43,Forecast!G58) -> 75 | H13: =Inputs!$B$100+Inputs!$C$100/1000*CHOOSE(Inputs!$D$100,Forecast!H30,Forecast!H35,Forecast!H43,Forecast!H58) -> 75 | I13: =Inputs!$B$100+Inputs!$C$100/1000*CHOOSE(Inputs!$D$100,Forecast!I30,Forecast!I35,Forecast!I43,Forecast!I58) -> 75 | J13: =Inputs!$B$100+Inputs!$C$100/1000*CHOOSE(Inputs!$D$100,Forecast!J30,Forecast!J35,Forecast!J43,Forecast!J58) -> 75 | K13: =Inputs!$B$100+Inputs!$C$100/1000*CHOOSE(Inputs!$D$100,Forecast!K30,Forecast!K35,Forecast!K43,Forecast!K58) -> 75 | ... AM13: =Inputs!$B$100+Inputs!$C$100/1000*CHOOSE(Inputs!$D$100,Forecast!AM30,Forecast!AM35,Forecast!AM43,Forecast!AM58) -> 75
A14: =Inputs!A101 -> Design and dev tools | B14: =Inputs!D101 -> 1 | D14: =Inputs!$B$101+Inputs!$C$101/1000*CHOOSE(Inputs!$D$101,Forecast!D30,Forecast!D35,Forecast!D43,Forecast!D58) -> 40 | E14: =Inputs!$B$101+Inputs!$C$101/1000*CHOOSE(Inputs!$D$101,Forecast!E30,Forecast!E35,Forecast!E43,Forecast!E58) -> 40 | F14: =Inputs!$B$101+Inputs!$C$101/1000*CHOOSE(Inputs!$D$101,Forecast!F30,Forecast!F35,Forecast!F43,Forecast!F58) -> 40 | G14: =Inputs!$B$101+Inputs!$C$101/1000*CHOOSE(Inputs!$D$101,Forecast!G30,Forecast!G35,Forecast!G43,Forecast!G58) -> 40 | H14: =Inputs!$B$101+Inputs!$C$101/1000*CHOOSE(Inputs!$D$101,Forecast!H30,Forecast!H35,Forecast!H43,Forecast!H58) -> 40 | I14: =Inputs!$B$101+Inputs!$C$101/1000*CHOOSE(Inputs!$D$101,Forecast!I30,Forecast!I35,Forecast!I43,Forecast!I58) -> 40 | J14: =Inputs!$B$101+Inputs!$C$101/1000*CHOOSE(Inputs!$D$101,Forecast!J30,Forecast!J35,Forecast!J43,Forecast!J58) -> 40 | K14: =Inputs!$B$101+Inputs!$C$101/1000*CHOOSE(Inputs!$D$101,Forecast!K30,Forecast!K35,Forecast!K43,Forecast!K58) -> 40 | ... AM14: =Inputs!$B$101+Inputs!$C$101/1000*CHOOSE(Inputs!$D$101,Forecast!AM30,Forecast!AM35,Forecast!AM43,Forecast!AM58) -> 40
A15: =Inputs!A102 -> Legal / LLC upkeep and accounting | B15: =Inputs!D102 -> 1 | D15: =Inputs!$B$102+Inputs!$C$102/1000*CHOOSE(Inputs!$D$102,Forecast!D30,Forecast!D35,Forecast!D43,Forecast!D58) -> 150 | E15: =Inputs!$B$102+Inputs!$C$102/1000*CHOOSE(Inputs!$D$102,Forecast!E30,Forecast!E35,Forecast!E43,Forecast!E58) -> 150 | F15: =Inputs!$B$102+Inputs!$C$102/1000*CHOOSE(Inputs!$D$102,Forecast!F30,Forecast!F35,Forecast!F43,Forecast!F58) -> 150 | G15: =Inputs!$B$102+Inputs!$C$102/1000*CHOOSE(Inputs!$D$102,Forecast!G30,Forecast!G35,Forecast!G43,Forecast!G58) -> 150 | H15: =Inputs!$B$102+Inputs!$C$102/1000*CHOOSE(Inputs!$D$102,Forecast!H30,Forecast!H35,Forecast!H43,Forecast!H58) -> 150 | I15: =Inputs!$B$102+Inputs!$C$102/1000*CHOOSE(Inputs!$D$102,Forecast!I30,Forecast!I35,Forecast!I43,Forecast!I58) -> 150 | J15: =Inputs!$B$102+Inputs!$C$102/1000*CHOOSE(Inputs!$D$102,Forecast!J30,Forecast!J35,Forecast!J43,Forecast!J58) -> 150 | K15: =Inputs!$B$102+Inputs!$C$102/1000*CHOOSE(Inputs!$D$102,Forecast!K30,Forecast!K35,Forecast!K43,Forecast!K58) -> 150 | ... AM15: =Inputs!$B$102+Inputs!$C$102/1000*CHOOSE(Inputs!$D$102,Forecast!AM30,Forecast!AM35,Forecast!AM43,Forecast!AM58) -> 150
A16: =Inputs!A103 -> Insurance (GL + cyber) | B16: =Inputs!D103 -> 1 | D16: =Inputs!$B$103+Inputs!$C$103/1000*CHOOSE(Inputs!$D$103,Forecast!D30,Forecast!D35,Forecast!D43,Forecast!D58) -> 95 | E16: =Inputs!$B$103+Inputs!$C$103/1000*CHOOSE(Inputs!$D$103,Forecast!E30,Forecast!E35,Forecast!E43,Forecast!E58) -> 95 | F16: =Inputs!$B$103+Inputs!$C$103/1000*CHOOSE(Inputs!$D$103,Forecast!F30,Forecast!F35,Forecast!F43,Forecast!F58) -> 95 | G16: =Inputs!$B$103+Inputs!$C$103/1000*CHOOSE(Inputs!$D$103,Forecast!G30,Forecast!G35,Forecast!G43,Forecast!G58) -> 95 | H16: =Inputs!$B$103+Inputs!$C$103/1000*CHOOSE(Inputs!$D$103,Forecast!H30,Forecast!H35,Forecast!H43,Forecast!H58) -> 95 | I16: =Inputs!$B$103+Inputs!$C$103/1000*CHOOSE(Inputs!$D$103,Forecast!I30,Forecast!I35,Forecast!I43,Forecast!I58) -> 95 | J16: =Inputs!$B$103+Inputs!$C$103/1000*CHOOSE(Inputs!$D$103,Forecast!J30,Forecast!J35,Forecast!J43,Forecast!J58) -> 95 | K16: =Inputs!$B$103+Inputs!$C$103/1000*CHOOSE(Inputs!$D$103,Forecast!K30,Forecast!K35,Forecast!K43,Forecast!K58) -> 95 | ... AM16: =Inputs!$B$103+Inputs!$C$103/1000*CHOOSE(Inputs!$D$103,Forecast!AM30,Forecast!AM35,Forecast!AM43,Forecast!AM58) -> 95
A17: =Inputs!A104 -> Support (helpdesk + hourly help) | B17: =Inputs!D104 -> 3 | D17: =Inputs!$B$104+Inputs!$C$104/1000*CHOOSE(Inputs!$D$104,Forecast!D30,Forecast!D35,Forecast!D43,Forecast!D58) -> 163.18857 | E17: =Inputs!$B$104+Inputs!$C$104/1000*CHOOSE(Inputs!$D$104,Forecast!E30,Forecast!E35,Forecast!E43,Forecast!E58) -> 266.03498 | F17: =Inputs!$B$104+Inputs!$C$104/1000*CHOOSE(Inputs!$D$104,Forecast!F30,Forecast!F35,Forecast!F43,Forecast!F58) -> 107.18416 | G17: =Inputs!$B$104+Inputs!$C$104/1000*CHOOSE(Inputs!$D$104,Forecast!G30,Forecast!G35,Forecast!G43,Forecast!G58) -> 190.20747 | H17: =Inputs!$B$104+Inputs!$C$104/1000*CHOOSE(Inputs!$D$104,Forecast!H30,Forecast!H35,Forecast!H43,Forecast!H58) -> 133.2026 | I17: =Inputs!$B$104+Inputs!$C$104/1000*CHOOSE(Inputs!$D$104,Forecast!I30,Forecast!I35,Forecast!I43,Forecast!I58) -> 144.12128 | J17: =Inputs!$B$104+Inputs!$C$104/1000*CHOOSE(Inputs!$D$104,Forecast!J30,Forecast!J35,Forecast!J43,Forecast!J58) -> 231.79139 | K17: =Inputs!$B$104+Inputs!$C$104/1000*CHOOSE(Inputs!$D$104,Forecast!K30,Forecast!K35,Forecast!K43,Forecast!K58) -> 179.94661 | ... AM17: =Inputs!$B$104+Inputs!$C$104/1000*CHOOSE(Inputs!$D$104,Forecast!AM30,Forecast!AM35,Forecast!AM43,Forecast!AM58) -> 347.32961
A18: =Inputs!A105 -> Founder / contractor pay (optional) | B18: =Inputs!D105 -> 1 | D18: =Inputs!$B$105+Inputs!$C$105/1000*CHOOSE(Inputs!$D$105,Forecast!D30,Forecast!D35,Forecast!D43,Forecast!D58) -> 0 | E18: =Inputs!$B$105+Inputs!$C$105/1000*CHOOSE(Inputs!$D$105,Forecast!E30,Forecast!E35,Forecast!E43,Forecast!E58) -> 0 | F18: =Inputs!$B$105+Inputs!$C$105/1000*CHOOSE(Inputs!$D$105,Forecast!F30,Forecast!F35,Forecast!F43,Forecast!F58) -> 0 | G18: =Inputs!$B$105+Inputs!$C$105/1000*CHOOSE(Inputs!$D$105,Forecast!G30,Forecast!G35,Forecast!G43,Forecast!G58) -> 0 | H18: =Inputs!$B$105+Inputs!$C$105/1000*CHOOSE(Inputs!$D$105,Forecast!H30,Forecast!H35,Forecast!H43,Forecast!H58) -> 0 | I18: =Inputs!$B$105+Inputs!$C$105/1000*CHOOSE(Inputs!$D$105,Forecast!I30,Forecast!I35,Forecast!I43,Forecast!I58) -> 0 | J18: =Inputs!$B$105+Inputs!$C$105/1000*CHOOSE(Inputs!$D$105,Forecast!J30,Forecast!J35,Forecast!J43,Forecast!J58) -> 0 | K18: =Inputs!$B$105+Inputs!$C$105/1000*CHOOSE(Inputs!$D$105,Forecast!K30,Forecast!K35,Forecast!K43,Forecast!K58) -> 0 | ... AM18: =Inputs!$B$105+Inputs!$C$105/1000*CHOOSE(Inputs!$D$105,Forecast!AM30,Forecast!AM35,Forecast!AM43,Forecast!AM58) -> 0
A19: Total operating costs | D19: =SUM(D7:D18) -> 663.98795 | E19: =SUM(E7:E18) -> 785.27069 | F19: =SUM(F7:F18) -> 595.85547 | G19: =SUM(G7:G18) -> 695.43933 | H19: =SUM(H7:H18) -> 627.13344 | I19: =SUM(I7:I18) -> 640.21034 | J19: =SUM(J7:J18) -> 744.465 | K19: =SUM(K7:K18) -> 682.80881 | ... AM19: =SUM(AM7:AM18) -> 874.82788
A21: One-time launch costs | D21: =IF(D5=1,SUM(Inputs!$B$109:$B$111),0) -> 6000 | E21: =IF(E5=1,SUM(Inputs!$B$109:$B$111),0) -> 0 | F21: =IF(F5=1,SUM(Inputs!$B$109:$B$111),0) -> 0 | G21: =IF(G5=1,SUM(Inputs!$B$109:$B$111),0) -> 0 | H21: =IF(H5=1,SUM(Inputs!$B$109:$B$111),0) -> 0 | I21: =IF(I5=1,SUM(Inputs!$B$109:$B$111),0) -> 0 | J21: =IF(J5=1,SUM(Inputs!$B$109:$B$111),0) -> 0 | K21: =IF(K5=1,SUM(Inputs!$B$109:$B$111),0) -> 0 | ... AM21: =IF(AM5=1,SUM(Inputs!$B$109:$B$111),0) -> 0
A23: v2 ADDED COST LINES (Inputs section 13; switch Scenarios!B45)
A24: =Inputs!A125 -> Cloudflare Turnstile (bot challenge, SEC-13) | B24: =Inputs!D125 -> 1 | D24: =Scenarios!$B$45*IF(AND(D$5>=Inputs!$G$125,D$5<=Inputs!$H$125,OR(Inputs!$I$125=0,MONTH(Forecast!D$7)=Inputs!$I$125)),Inputs!$B$125+Inputs!$C$125/1000*CHOOSE(Inputs!$D$125,Forecast!D$30,Forecast!D$35,Forecast!D$43,Forecast!D$58),0) -> 0 | E24: =Scenarios!$B$45*IF(AND(E$5>=Inputs!$G$125,E$5<=Inputs!$H$125,OR(Inputs!$I$125=0,MONTH(Forecast!E$7)=Inputs!$I$125)),Inputs!$B$125+Inputs!$C$125/1000*CHOOSE(Inputs!$D$125,Forecast!E$30,Forecast!E$35,Forecast!E$43,Forecast!E$58),0) -> 0 | F24: =Scenarios!$B$45*IF(AND(F$5>=Inputs!$G$125,F$5<=Inputs!$H$125,OR(Inputs!$I$125=0,MONTH(Forecast!F$7)=Inputs!$I$125)),Inputs!$B$125+Inputs!$C$125/1000*CHOOSE(Inputs!$D$125,Forecast!F$30,Forecast!F$35,Forecast!F$43,Forecast!F$58),0) -> 0 | G24: =Scenarios!$B$45*IF(AND(G$5>=Inputs!$G$125,G$5<=Inputs!$H$125,OR(Inputs!$I$125=0,MONTH(Forecast!G$7)=Inputs!$I$125)),Inputs!$B$125+Inputs!$C$125/1000*CHOOSE(Inputs!$D$125,Forecast!G$30,Forecast!G$35,Forecast!G$43,Forecast!G$58),0) -> 0 | H24: =Scenarios!$B$45*IF(AND(H$5>=Inputs!$G$125,H$5<=Inputs!$H$125,OR(Inputs!$I$125=0,MONTH(Forecast!H$7)=Inputs!$I$125)),Inputs!$B$125+Inputs!$C$125/1000*CHOOSE(Inputs!$D$125,Forecast!H$30,Forecast!H$35,Forecast!H$43,Forecast!H$58),0) -> 0 | I24: =Scenarios!$B$45*IF(AND(I$5>=Inputs!$G$125,I$5<=Inputs!$H$125,OR(Inputs!$I$125=0,MONTH(Forecast!I$7)=Inputs!$I$125)),Inputs!$B$125+Inputs!$C$125/1000*CHOOSE(Inputs!$D$125,Forecast!I$30,Forecast!I$35,Forecast!I$43,Forecast!I$58),0) -> 0 | J24: =Scenarios!$B$45*IF(AND(J$5>=Inputs!$G$125,J$5<=Inputs!$H$125,OR(Inputs!$I$125=0,MONTH(Forecast!J$7)=Inputs!$I$125)),Inputs!$B$125+Inputs!$C$125/1000*CHOOSE(Inputs!$D$125,Forecast!J$30,Forecast!J$35,Forecast!J$43,Forecast!J$58),0) -> 0 | K24: =Scenarios!$B$45*IF(AND(K$5>=Inputs!$G$125,K$5<=Inputs!$H$125,OR(Inputs!$I$125=0,MONTH(Forecast!K$7)=Inputs!$I$125)),Inputs!$B$125+Inputs!$C$125/1000*CHOOSE(Inputs!$D$125,Forecast!K$30,Forecast!K$35,Forecast!K$43,Forecast!K$58),0) -> 0 | ... AM24: =Scenarios!$B$45*IF(AND(AM$5>=Inputs!$G$125,AM$5<=Inputs!$H$125,OR(Inputs!$I$125=0,MONTH(Forecast!AM$7)=Inputs!$I$125)),Inputs!$B$125+Inputs!$C$125/1000*CHOOSE(Inputs!$D$125,Forecast!AM$30,Forecast!AM$35,Forecast!AM$43,Forecast!AM$58),0) -> 0
A25: =Inputs!A126 -> Bot-protection reserve (Vercel BotID or Cloudflare Pro, only if attacked) | B25: =Inputs!D126 -> 1 | D25: =Scenarios!$B$45*IF(AND(D$5>=Inputs!$G$126,D$5<=Inputs!$H$126,OR(Inputs!$I$126=0,MONTH(Forecast!D$7)=Inputs!$I$126)),Inputs!$B$126+Inputs!$C$126/1000*CHOOSE(Inputs!$D$126,Forecast!D$30,Forecast!D$35,Forecast!D$43,Forecast!D$58),0) -> 0 | E25: =Scenarios!$B$45*IF(AND(E$5>=Inputs!$G$126,E$5<=Inputs!$H$126,OR(Inputs!$I$126=0,MONTH(Forecast!E$7)=Inputs!$I$126)),Inputs!$B$126+Inputs!$C$126/1000*CHOOSE(Inputs!$D$126,Forecast!E$30,Forecast!E$35,Forecast!E$43,Forecast!E$58),0) -> 0 | F25: =Scenarios!$B$45*IF(AND(F$5>=Inputs!$G$126,F$5<=Inputs!$H$126,OR(Inputs!$I$126=0,MONTH(Forecast!F$7)=Inputs!$I$126)),Inputs!$B$126+Inputs!$C$126/1000*CHOOSE(Inputs!$D$126,Forecast!F$30,Forecast!F$35,Forecast!F$43,Forecast!F$58),0) -> 0 | G25: =Scenarios!$B$45*IF(AND(G$5>=Inputs!$G$126,G$5<=Inputs!$H$126,OR(Inputs!$I$126=0,MONTH(Forecast!G$7)=Inputs!$I$126)),Inputs!$B$126+Inputs!$C$126/1000*CHOOSE(Inputs!$D$126,Forecast!G$30,Forecast!G$35,Forecast!G$43,Forecast!G$58),0) -> 0 | H25: =Scenarios!$B$45*IF(AND(H$5>=Inputs!$G$126,H$5<=Inputs!$H$126,OR(Inputs!$I$126=0,MONTH(Forecast!H$7)=Inputs!$I$126)),Inputs!$B$126+Inputs!$C$126/1000*CHOOSE(Inputs!$D$126,Forecast!H$30,Forecast!H$35,Forecast!H$43,Forecast!H$58),0) -> 0 | I25: =Scenarios!$B$45*IF(AND(I$5>=Inputs!$G$126,I$5<=Inputs!$H$126,OR(Inputs!$I$126=0,MONTH(Forecast!I$7)=Inputs!$I$126)),Inputs!$B$126+Inputs!$C$126/1000*CHOOSE(Inputs!$D$126,Forecast!I$30,Forecast!I$35,Forecast!I$43,Forecast!I$58),0) -> 0 | J25: =Scenarios!$B$45*IF(AND(J$5>=Inputs!$G$126,J$5<=Inputs!$H$126,OR(Inputs!$I$126=0,MONTH(Forecast!J$7)=Inputs!$I$126)),Inputs!$B$126+Inputs!$C$126/1000*CHOOSE(Inputs!$D$126,Forecast!J$30,Forecast!J$35,Forecast!J$43,Forecast!J$58),0) -> 25 | K25: =Scenarios!$B$45*IF(AND(K$5>=Inputs!$G$126,K$5<=Inputs!$H$126,OR(Inputs!$I$126=0,MONTH(Forecast!K$7)=Inputs!$I$126)),Inputs!$B$126+Inputs!$C$126/1000*CHOOSE(Inputs!$D$126,Forecast!K$30,Forecast!K$35,Forecast!K$43,Forecast!K$58),0) -> 25 | ... AM25: =Scenarios!$B$45*IF(AND(AM$5>=Inputs!$G$126,AM$5<=Inputs!$H$126,OR(Inputs!$I$126=0,MONTH(Forecast!AM$7)=Inputs!$I$126)),Inputs!$B$126+Inputs!$C$126/1000*CHOOSE(Inputs!$D$126,Forecast!AM$30,Forecast!AM$35,Forecast!AM$43,Forecast!AM$58),0) -> 25
A26: =Inputs!A127 -> Rate-limit store (Upstash Redis or extra Postgres) | B26: =Inputs!D127 -> 1 | D26: =Scenarios!$B$45*IF(AND(D$5>=Inputs!$G$127,D$5<=Inputs!$H$127,OR(Inputs!$I$127=0,MONTH(Forecast!D$7)=Inputs!$I$127)),Inputs!$B$127+Inputs!$C$127/1000*CHOOSE(Inputs!$D$127,Forecast!D$30,Forecast!D$35,Forecast!D$43,Forecast!D$58),0) -> 5 | E26: =Scenarios!$B$45*IF(AND(E$5>=Inputs!$G$127,E$5<=Inputs!$H$127,OR(Inputs!$I$127=0,MONTH(Forecast!E$7)=Inputs!$I$127)),Inputs!$B$127+Inputs!$C$127/1000*CHOOSE(Inputs!$D$127,Forecast!E$30,Forecast!E$35,Forecast!E$43,Forecast!E$58),0) -> 5 | F26: =Scenarios!$B$45*IF(AND(F$5>=Inputs!$G$127,F$5<=Inputs!$H$127,OR(Inputs!$I$127=0,MONTH(Forecast!F$7)=Inputs!$I$127)),Inputs!$B$127+Inputs!$C$127/1000*CHOOSE(Inputs!$D$127,Forecast!F$30,Forecast!F$35,Forecast!F$43,Forecast!F$58),0) -> 5 | G26: =Scenarios!$B$45*IF(AND(G$5>=Inputs!$G$127,G$5<=Inputs!$H$127,OR(Inputs!$I$127=0,MONTH(Forecast!G$7)=Inputs!$I$127)),Inputs!$B$127+Inputs!$C$127/1000*CHOOSE(Inputs!$D$127,Forecast!G$30,Forecast!G$35,Forecast!G$43,Forecast!G$58),0) -> 5 | H26: =Scenarios!$B$45*IF(AND(H$5>=Inputs!$G$127,H$5<=Inputs!$H$127,OR(Inputs!$I$127=0,MONTH(Forecast!H$7)=Inputs!$I$127)),Inputs!$B$127+Inputs!$C$127/1000*CHOOSE(Inputs!$D$127,Forecast!H$30,Forecast!H$35,Forecast!H$43,Forecast!H$58),0) -> 5 | I26: =Scenarios!$B$45*IF(AND(I$5>=Inputs!$G$127,I$5<=Inputs!$H$127,OR(Inputs!$I$127=0,MONTH(Forecast!I$7)=Inputs!$I$127)),Inputs!$B$127+Inputs!$C$127/1000*CHOOSE(Inputs!$D$127,Forecast!I$30,Forecast!I$35,Forecast!I$43,Forecast!I$58),0) -> 5 | J26: =Scenarios!$B$45*IF(AND(J$5>=Inputs!$G$127,J$5<=Inputs!$H$127,OR(Inputs!$I$127=0,MONTH(Forecast!J$7)=Inputs!$I$127)),Inputs!$B$127+Inputs!$C$127/1000*CHOOSE(Inputs!$D$127,Forecast!J$30,Forecast!J$35,Forecast!J$43,Forecast!J$58),0) -> 5 | K26: =Scenarios!$B$45*IF(AND(K$5>=Inputs!$G$127,K$5<=Inputs!$H$127,OR(Inputs!$I$127=0,MONTH(Forecast!K$7)=Inputs!$I$127)),Inputs!$B$127+Inputs!$C$127/1000*CHOOSE(Inputs!$D$127,Forecast!K$30,Forecast!K$35,Forecast!K$43,Forecast!K$58),0) -> 5 | ... AM26: =Scenarios!$B$45*IF(AND(AM$5>=Inputs!$G$127,AM$5<=Inputs!$H$127,OR(Inputs!$I$127=0,MONTH(Forecast!AM$7)=Inputs!$I$127)),Inputs!$B$127+Inputs!$C$127/1000*CHOOSE(Inputs!$D$127,Forecast!AM$30,Forecast!AM$35,Forecast!AM$43,Forecast!AM$58),0) -> 5
A27: =Inputs!A128 -> Error and spend alerting add-on (SEC-09; Sentry Team already in Monitoring line) | B27: =Inputs!D128 -> 1 | D27: =Scenarios!$B$45*IF(AND(D$5>=Inputs!$G$128,D$5<=Inputs!$H$128,OR(Inputs!$I$128=0,MONTH(Forecast!D$7)=Inputs!$I$128)),Inputs!$B$128+Inputs!$C$128/1000*CHOOSE(Inputs!$D$128,Forecast!D$30,Forecast!D$35,Forecast!D$43,Forecast!D$58),0) -> 10 | E27: =Scenarios!$B$45*IF(AND(E$5>=Inputs!$G$128,E$5<=Inputs!$H$128,OR(Inputs!$I$128=0,MONTH(Forecast!E$7)=Inputs!$I$128)),Inputs!$B$128+Inputs!$C$128/1000*CHOOSE(Inputs!$D$128,Forecast!E$30,Forecast!E$35,Forecast!E$43,Forecast!E$58),0) -> 10 | F27: =Scenarios!$B$45*IF(AND(F$5>=Inputs!$G$128,F$5<=Inputs!$H$128,OR(Inputs!$I$128=0,MONTH(Forecast!F$7)=Inputs!$I$128)),Inputs!$B$128+Inputs!$C$128/1000*CHOOSE(Inputs!$D$128,Forecast!F$30,Forecast!F$35,Forecast!F$43,Forecast!F$58),0) -> 10 | G27: =Scenarios!$B$45*IF(AND(G$5>=Inputs!$G$128,G$5<=Inputs!$H$128,OR(Inputs!$I$128=0,MONTH(Forecast!G$7)=Inputs!$I$128)),Inputs!$B$128+Inputs!$C$128/1000*CHOOSE(Inputs!$D$128,Forecast!G$30,Forecast!G$35,Forecast!G$43,Forecast!G$58),0) -> 10 | H27: =Scenarios!$B$45*IF(AND(H$5>=Inputs!$G$128,H$5<=Inputs!$H$128,OR(Inputs!$I$128=0,MONTH(Forecast!H$7)=Inputs!$I$128)),Inputs!$B$128+Inputs!$C$128/1000*CHOOSE(Inputs!$D$128,Forecast!H$30,Forecast!H$35,Forecast!H$43,Forecast!H$58),0) -> 10 | I27: =Scenarios!$B$45*IF(AND(I$5>=Inputs!$G$128,I$5<=Inputs!$H$128,OR(Inputs!$I$128=0,MONTH(Forecast!I$7)=Inputs!$I$128)),Inputs!$B$128+Inputs!$C$128/1000*CHOOSE(Inputs!$D$128,Forecast!I$30,Forecast!I$35,Forecast!I$43,Forecast!I$58),0) -> 10 | J27: =Scenarios!$B$45*IF(AND(J$5>=Inputs!$G$128,J$5<=Inputs!$H$128,OR(Inputs!$I$128=0,MONTH(Forecast!J$7)=Inputs!$I$128)),Inputs!$B$128+Inputs!$C$128/1000*CHOOSE(Inputs!$D$128,Forecast!J$30,Forecast!J$35,Forecast!J$43,Forecast!J$58),0) -> 10 | K27: =Scenarios!$B$45*IF(AND(K$5>=Inputs!$G$128,K$5<=Inputs!$H$128,OR(Inputs!$I$128=0,MONTH(Forecast!K$7)=Inputs!$I$128)),Inputs!$B$128+Inputs!$C$128/1000*CHOOSE(Inputs!$D$128,Forecast!K$30,Forecast!K$35,Forecast!K$43,Forecast!K$58),0) -> 10 | ... AM27: =Scenarios!$B$45*IF(AND(AM$5>=Inputs!$G$128,AM$5<=Inputs!$H$128,OR(Inputs!$I$128=0,MONTH(Forecast!AM$7)=Inputs!$I$128)),Inputs!$B$128+Inputs!$C$128/1000*CHOOSE(Inputs!$D$128,Forecast!AM$30,Forecast!AM$35,Forecast!AM$43,Forecast!AM$58),0) -> 10
A28: =Inputs!A129 -> Data / BI: Metabase OSS host | B28: =Inputs!D129 -> 1 | D28: =Scenarios!$B$45*IF(AND(D$5>=Inputs!$G$129,D$5<=Inputs!$H$129,OR(Inputs!$I$129=0,MONTH(Forecast!D$7)=Inputs!$I$129)),Inputs!$B$129+Inputs!$C$129/1000*CHOOSE(Inputs!$D$129,Forecast!D$30,Forecast!D$35,Forecast!D$43,Forecast!D$58),0) -> 7.5 | E28: =Scenarios!$B$45*IF(AND(E$5>=Inputs!$G$129,E$5<=Inputs!$H$129,OR(Inputs!$I$129=0,MONTH(Forecast!E$7)=Inputs!$I$129)),Inputs!$B$129+Inputs!$C$129/1000*CHOOSE(Inputs!$D$129,Forecast!E$30,Forecast!E$35,Forecast!E$43,Forecast!E$58),0) -> 7.5 | F28: =Scenarios!$B$45*IF(AND(F$5>=Inputs!$G$129,F$5<=Inputs!$H$129,OR(Inputs!$I$129=0,MONTH(Forecast!F$7)=Inputs!$I$129)),Inputs!$B$129+Inputs!$C$129/1000*CHOOSE(Inputs!$D$129,Forecast!F$30,Forecast!F$35,Forecast!F$43,Forecast!F$58),0) -> 7.5 | G28: =Scenarios!$B$45*IF(AND(G$5>=Inputs!$G$129,G$5<=Inputs!$H$129,OR(Inputs!$I$129=0,MONTH(Forecast!G$7)=Inputs!$I$129)),Inputs!$B$129+Inputs!$C$129/1000*CHOOSE(Inputs!$D$129,Forecast!G$30,Forecast!G$35,Forecast!G$43,Forecast!G$58),0) -> 7.5 | H28: =Scenarios!$B$45*IF(AND(H$5>=Inputs!$G$129,H$5<=Inputs!$H$129,OR(Inputs!$I$129=0,MONTH(Forecast!H$7)=Inputs!$I$129)),Inputs!$B$129+Inputs!$C$129/1000*CHOOSE(Inputs!$D$129,Forecast!H$30,Forecast!H$35,Forecast!H$43,Forecast!H$58),0) -> 7.5 | I28: =Scenarios!$B$45*IF(AND(I$5>=Inputs!$G$129,I$5<=Inputs!$H$129,OR(Inputs!$I$129=0,MONTH(Forecast!I$7)=Inputs!$I$129)),Inputs!$B$129+Inputs!$C$129/1000*CHOOSE(Inputs!$D$129,Forecast!I$30,Forecast!I$35,Forecast!I$43,Forecast!I$58),0) -> 7.5 | J28: =Scenarios!$B$45*IF(AND(J$5>=Inputs!$G$129,J$5<=Inputs!$H$129,OR(Inputs!$I$129=0,MONTH(Forecast!J$7)=Inputs!$I$129)),Inputs!$B$129+Inputs!$C$129/1000*CHOOSE(Inputs!$D$129,Forecast!J$30,Forecast!J$35,Forecast!J$43,Forecast!J$58),0) -> 7.5 | K28: =Scenarios!$B$45*IF(AND(K$5>=Inputs!$G$129,K$5<=Inputs!$H$129,OR(Inputs!$I$129=0,MONTH(Forecast!K$7)=Inputs!$I$129)),Inputs!$B$129+Inputs!$C$129/1000*CHOOSE(Inputs!$D$129,Forecast!K$30,Forecast!K$35,Forecast!K$43,Forecast!K$58),0) -> 7.5 | ... AM28: =Scenarios!$B$45*IF(AND(AM$5>=Inputs!$G$129,AM$5<=Inputs!$H$129,OR(Inputs!$I$129=0,MONTH(Forecast!AM$7)=Inputs!$I$129)),Inputs!$B$129+Inputs!$C$129/1000*CHOOSE(Inputs!$D$129,Forecast!AM$30,Forecast!AM$35,Forecast!AM$43,Forecast!AM$58),0) -> 7.5
A29: =Inputs!A130 -> Data / BI: evaluation runs (OpenRouter golden-set) | B29: =Inputs!D130 -> 1 | D29: =Scenarios!$B$45*IF(AND(D$5>=Inputs!$G$130,D$5<=Inputs!$H$130,OR(Inputs!$I$130=0,MONTH(Forecast!D$7)=Inputs!$I$130)),Inputs!$B$130+Inputs!$C$130/1000*CHOOSE(Inputs!$D$130,Forecast!D$30,Forecast!D$35,Forecast!D$43,Forecast!D$58),0) -> 0 | E29: =Scenarios!$B$45*IF(AND(E$5>=Inputs!$G$130,E$5<=Inputs!$H$130,OR(Inputs!$I$130=0,MONTH(Forecast!E$7)=Inputs!$I$130)),Inputs!$B$130+Inputs!$C$130/1000*CHOOSE(Inputs!$D$130,Forecast!E$30,Forecast!E$35,Forecast!E$43,Forecast!E$58),0) -> 40 | F29: =Scenarios!$B$45*IF(AND(F$5>=Inputs!$G$130,F$5<=Inputs!$H$130,OR(Inputs!$I$130=0,MONTH(Forecast!F$7)=Inputs!$I$130)),Inputs!$B$130+Inputs!$C$130/1000*CHOOSE(Inputs!$D$130,Forecast!F$30,Forecast!F$35,Forecast!F$43,Forecast!F$58),0) -> 40 | G29: =Scenarios!$B$45*IF(AND(G$5>=Inputs!$G$130,G$5<=Inputs!$H$130,OR(Inputs!$I$130=0,MONTH(Forecast!G$7)=Inputs!$I$130)),Inputs!$B$130+Inputs!$C$130/1000*CHOOSE(Inputs!$D$130,Forecast!G$30,Forecast!G$35,Forecast!G$43,Forecast!G$58),0) -> 40 | H29: =Scenarios!$B$45*IF(AND(H$5>=Inputs!$G$130,H$5<=Inputs!$H$130,OR(Inputs!$I$130=0,MONTH(Forecast!H$7)=Inputs!$I$130)),Inputs!$B$130+Inputs!$C$130/1000*CHOOSE(Inputs!$D$130,Forecast!H$30,Forecast!H$35,Forecast!H$43,Forecast!H$58),0) -> 40 | I29: =Scenarios!$B$45*IF(AND(I$5>=Inputs!$G$130,I$5<=Inputs!$H$130,OR(Inputs!$I$130=0,MONTH(Forecast!I$7)=Inputs!$I$130)),Inputs!$B$130+Inputs!$C$130/1000*CHOOSE(Inputs!$D$130,Forecast!I$30,Forecast!I$35,Forecast!I$43,Forecast!I$58),0) -> 40 | J29: =Scenarios!$B$45*IF(AND(J$5>=Inputs!$G$130,J$5<=Inputs!$H$130,OR(Inputs!$I$130=0,MONTH(Forecast!J$7)=Inputs!$I$130)),Inputs!$B$130+Inputs!$C$130/1000*CHOOSE(Inputs!$D$130,Forecast!J$30,Forecast!J$35,Forecast!J$43,Forecast!J$58),0) -> 40 | K29: =Scenarios!$B$45*IF(AND(K$5>=Inputs!$G$130,K$5<=Inputs!$H$130,OR(Inputs!$I$130=0,MONTH(Forecast!K$7)=Inputs!$I$130)),Inputs!$B$130+Inputs!$C$130/1000*CHOOSE(Inputs!$D$130,Forecast!K$30,Forecast!K$35,Forecast!K$43,Forecast!K$58),0) -> 40 | ... AM29: =Scenarios!$B$45*IF(AND(AM$5>=Inputs!$G$130,AM$5<=Inputs!$H$130,OR(Inputs!$I$130=0,MONTH(Forecast!AM$7)=Inputs!$I$130)),Inputs!$B$130+Inputs!$C$130/1000*CHOOSE(Inputs!$D$130,Forecast!AM$30,Forecast!AM$35,Forecast!AM$43,Forecast!AM$58),0) -> 40
A30: =Inputs!A131 -> Support tooling stage 1: shared inbox (about $7) - inside existing $25 Support line | B30: =Inputs!D131 -> 1 | D30: =Scenarios!$B$45*IF(AND(D$5>=Inputs!$G$131,D$5<=Inputs!$H$131,OR(Inputs!$I$131=0,MONTH(Forecast!D$7)=Inputs!$I$131)),Inputs!$B$131+Inputs!$C$131/1000*CHOOSE(Inputs!$D$131,Forecast!D$30,Forecast!D$35,Forecast!D$43,Forecast!D$58),0) -> 0 | E30: =Scenarios!$B$45*IF(AND(E$5>=Inputs!$G$131,E$5<=Inputs!$H$131,OR(Inputs!$I$131=0,MONTH(Forecast!E$7)=Inputs!$I$131)),Inputs!$B$131+Inputs!$C$131/1000*CHOOSE(Inputs!$D$131,Forecast!E$30,Forecast!E$35,Forecast!E$43,Forecast!E$58),0) -> 0 | F30: =Scenarios!$B$45*IF(AND(F$5>=Inputs!$G$131,F$5<=Inputs!$H$131,OR(Inputs!$I$131=0,MONTH(Forecast!F$7)=Inputs!$I$131)),Inputs!$B$131+Inputs!$C$131/1000*CHOOSE(Inputs!$D$131,Forecast!F$30,Forecast!F$35,Forecast!F$43,Forecast!F$58),0) -> 0 | G30: =Scenarios!$B$45*IF(AND(G$5>=Inputs!$G$131,G$5<=Inputs!$H$131,OR(Inputs!$I$131=0,MONTH(Forecast!G$7)=Inputs!$I$131)),Inputs!$B$131+Inputs!$C$131/1000*CHOOSE(Inputs!$D$131,Forecast!G$30,Forecast!G$35,Forecast!G$43,Forecast!G$58),0) -> 0 | H30: =Scenarios!$B$45*IF(AND(H$5>=Inputs!$G$131,H$5<=Inputs!$H$131,OR(Inputs!$I$131=0,MONTH(Forecast!H$7)=Inputs!$I$131)),Inputs!$B$131+Inputs!$C$131/1000*CHOOSE(Inputs!$D$131,Forecast!H$30,Forecast!H$35,Forecast!H$43,Forecast!H$58),0) -> 0 | I30: =Scenarios!$B$45*IF(AND(I$5>=Inputs!$G$131,I$5<=Inputs!$H$131,OR(Inputs!$I$131=0,MONTH(Forecast!I$7)=Inputs!$I$131)),Inputs!$B$131+Inputs!$C$131/1000*CHOOSE(Inputs!$D$131,Forecast!I$30,Forecast!I$35,Forecast!I$43,Forecast!I$58),0) -> 0 | J30: =Scenarios!$B$45*IF(AND(J$5>=Inputs!$G$131,J$5<=Inputs!$H$131,OR(Inputs!$I$131=0,MONTH(Forecast!J$7)=Inputs!$I$131)),Inputs!$B$131+Inputs!$C$131/1000*CHOOSE(Inputs!$D$131,Forecast!J$30,Forecast!J$35,Forecast!J$43,Forecast!J$58),0) -> 0 | K30: =Scenarios!$B$45*IF(AND(K$5>=Inputs!$G$131,K$5<=Inputs!$H$131,OR(Inputs!$I$131=0,MONTH(Forecast!K$7)=Inputs!$I$131)),Inputs!$B$131+Inputs!$C$131/1000*CHOOSE(Inputs!$D$131,Forecast!K$30,Forecast!K$35,Forecast!K$43,Forecast!K$58),0) -> 0 | ... AM30: =Scenarios!$B$45*IF(AND(AM$5>=Inputs!$G$131,AM$5<=Inputs!$H$131,OR(Inputs!$I$131=0,MONTH(Forecast!AM$7)=Inputs!$I$131)),Inputs!$B$131+Inputs!$C$131/1000*CHOOSE(Inputs!$D$131,Forecast!AM$30,Forecast!AM$35,Forecast!AM$43,Forecast!AM$58),0) -> 0
A31: =Inputs!A132 -> Support tooling stage 2: Help Scout Standard (about $22) - inside existing $25 Support line | B31: =Inputs!D132 -> 1 | D31: =Scenarios!$B$45*IF(AND(D$5>=Inputs!$G$132,D$5<=Inputs!$H$132,OR(Inputs!$I$132=0,MONTH(Forecast!D$7)=Inputs!$I$132)),Inputs!$B$132+Inputs!$C$132/1000*CHOOSE(Inputs!$D$132,Forecast!D$30,Forecast!D$35,Forecast!D$43,Forecast!D$58),0) -> 0 | E31: =Scenarios!$B$45*IF(AND(E$5>=Inputs!$G$132,E$5<=Inputs!$H$132,OR(Inputs!$I$132=0,MONTH(Forecast!E$7)=Inputs!$I$132)),Inputs!$B$132+Inputs!$C$132/1000*CHOOSE(Inputs!$D$132,Forecast!E$30,Forecast!E$35,Forecast!E$43,Forecast!E$58),0) -> 0 | F31: =Scenarios!$B$45*IF(AND(F$5>=Inputs!$G$132,F$5<=Inputs!$H$132,OR(Inputs!$I$132=0,MONTH(Forecast!F$7)=Inputs!$I$132)),Inputs!$B$132+Inputs!$C$132/1000*CHOOSE(Inputs!$D$132,Forecast!F$30,Forecast!F$35,Forecast!F$43,Forecast!F$58),0) -> 0 | G31: =Scenarios!$B$45*IF(AND(G$5>=Inputs!$G$132,G$5<=Inputs!$H$132,OR(Inputs!$I$132=0,MONTH(Forecast!G$7)=Inputs!$I$132)),Inputs!$B$132+Inputs!$C$132/1000*CHOOSE(Inputs!$D$132,Forecast!G$30,Forecast!G$35,Forecast!G$43,Forecast!G$58),0) -> 0 | H31: =Scenarios!$B$45*IF(AND(H$5>=Inputs!$G$132,H$5<=Inputs!$H$132,OR(Inputs!$I$132=0,MONTH(Forecast!H$7)=Inputs!$I$132)),Inputs!$B$132+Inputs!$C$132/1000*CHOOSE(Inputs!$D$132,Forecast!H$30,Forecast!H$35,Forecast!H$43,Forecast!H$58),0) -> 0 | I31: =Scenarios!$B$45*IF(AND(I$5>=Inputs!$G$132,I$5<=Inputs!$H$132,OR(Inputs!$I$132=0,MONTH(Forecast!I$7)=Inputs!$I$132)),Inputs!$B$132+Inputs!$C$132/1000*CHOOSE(Inputs!$D$132,Forecast!I$30,Forecast!I$35,Forecast!I$43,Forecast!I$58),0) -> 0 | J31: =Scenarios!$B$45*IF(AND(J$5>=Inputs!$G$132,J$5<=Inputs!$H$132,OR(Inputs!$I$132=0,MONTH(Forecast!J$7)=Inputs!$I$132)),Inputs!$B$132+Inputs!$C$132/1000*CHOOSE(Inputs!$D$132,Forecast!J$30,Forecast!J$35,Forecast!J$43,Forecast!J$58),0) -> 0 | K31: =Scenarios!$B$45*IF(AND(K$5>=Inputs!$G$132,K$5<=Inputs!$H$132,OR(Inputs!$I$132=0,MONTH(Forecast!K$7)=Inputs!$I$132)),Inputs!$B$132+Inputs!$C$132/1000*CHOOSE(Inputs!$D$132,Forecast!K$30,Forecast!K$35,Forecast!K$43,Forecast!K$58),0) -> 0 | ... AM31: =Scenarios!$B$45*IF(AND(AM$5>=Inputs!$G$132,AM$5<=Inputs!$H$132,OR(Inputs!$I$132=0,MONTH(Forecast!AM$7)=Inputs!$I$132)),Inputs!$B$132+Inputs!$C$132/1000*CHOOSE(Inputs!$D$132,Forecast!AM$30,Forecast!AM$35,Forecast!AM$43,Forecast!AM$58),0) -> 0
A32: =Inputs!A133 -> Support tooling stage 3: chat + knowledge base (Crisp Pro about $25) | B32: =Inputs!D133 -> 1 | D32: =Scenarios!$B$45*IF(AND(D$5>=Inputs!$G$133,D$5<=Inputs!$H$133,OR(Inputs!$I$133=0,MONTH(Forecast!D$7)=Inputs!$I$133)),Inputs!$B$133+Inputs!$C$133/1000*CHOOSE(Inputs!$D$133,Forecast!D$30,Forecast!D$35,Forecast!D$43,Forecast!D$58),0) -> 0 | E32: =Scenarios!$B$45*IF(AND(E$5>=Inputs!$G$133,E$5<=Inputs!$H$133,OR(Inputs!$I$133=0,MONTH(Forecast!E$7)=Inputs!$I$133)),Inputs!$B$133+Inputs!$C$133/1000*CHOOSE(Inputs!$D$133,Forecast!E$30,Forecast!E$35,Forecast!E$43,Forecast!E$58),0) -> 0 | F32: =Scenarios!$B$45*IF(AND(F$5>=Inputs!$G$133,F$5<=Inputs!$H$133,OR(Inputs!$I$133=0,MONTH(Forecast!F$7)=Inputs!$I$133)),Inputs!$B$133+Inputs!$C$133/1000*CHOOSE(Inputs!$D$133,Forecast!F$30,Forecast!F$35,Forecast!F$43,Forecast!F$58),0) -> 0 | G32: =Scenarios!$B$45*IF(AND(G$5>=Inputs!$G$133,G$5<=Inputs!$H$133,OR(Inputs!$I$133=0,MONTH(Forecast!G$7)=Inputs!$I$133)),Inputs!$B$133+Inputs!$C$133/1000*CHOOSE(Inputs!$D$133,Forecast!G$30,Forecast!G$35,Forecast!G$43,Forecast!G$58),0) -> 0 | H32: =Scenarios!$B$45*IF(AND(H$5>=Inputs!$G$133,H$5<=Inputs!$H$133,OR(Inputs!$I$133=0,MONTH(Forecast!H$7)=Inputs!$I$133)),Inputs!$B$133+Inputs!$C$133/1000*CHOOSE(Inputs!$D$133,Forecast!H$30,Forecast!H$35,Forecast!H$43,Forecast!H$58),0) -> 0 | I32: =Scenarios!$B$45*IF(AND(I$5>=Inputs!$G$133,I$5<=Inputs!$H$133,OR(Inputs!$I$133=0,MONTH(Forecast!I$7)=Inputs!$I$133)),Inputs!$B$133+Inputs!$C$133/1000*CHOOSE(Inputs!$D$133,Forecast!I$30,Forecast!I$35,Forecast!I$43,Forecast!I$58),0) -> 0 | J32: =Scenarios!$B$45*IF(AND(J$5>=Inputs!$G$133,J$5<=Inputs!$H$133,OR(Inputs!$I$133=0,MONTH(Forecast!J$7)=Inputs!$I$133)),Inputs!$B$133+Inputs!$C$133/1000*CHOOSE(Inputs!$D$133,Forecast!J$30,Forecast!J$35,Forecast!J$43,Forecast!J$58),0) -> 0 | K32: =Scenarios!$B$45*IF(AND(K$5>=Inputs!$G$133,K$5<=Inputs!$H$133,OR(Inputs!$I$133=0,MONTH(Forecast!K$7)=Inputs!$I$133)),Inputs!$B$133+Inputs!$C$133/1000*CHOOSE(Inputs!$D$133,Forecast!K$30,Forecast!K$35,Forecast!K$43,Forecast!K$58),0) -> 0 | ... AM32: =Scenarios!$B$45*IF(AND(AM$5>=Inputs!$G$133,AM$5<=Inputs!$H$133,OR(Inputs!$I$133=0,MONTH(Forecast!AM$7)=Inputs!$I$133)),Inputs!$B$133+Inputs!$C$133/1000*CHOOSE(Inputs!$D$133,Forecast!AM$30,Forecast!AM$35,Forecast!AM$43,Forecast!AM$58),0) -> 25
A33: =Inputs!A134 -> Peak-season support contractor (10 h/week x 4.33 x $22.50, December) | B33: =Inputs!D134 -> 1 | D33: =Scenarios!$B$45*IF(AND(D$5>=Inputs!$G$134,D$5<=Inputs!$H$134,OR(Inputs!$I$134=0,MONTH(Forecast!D$7)=Inputs!$I$134)),Inputs!$B$134+Inputs!$C$134/1000*CHOOSE(Inputs!$D$134,Forecast!D$30,Forecast!D$35,Forecast!D$43,Forecast!D$58),0) -> 0 | E33: =Scenarios!$B$45*IF(AND(E$5>=Inputs!$G$134,E$5<=Inputs!$H$134,OR(Inputs!$I$134=0,MONTH(Forecast!E$7)=Inputs!$I$134)),Inputs!$B$134+Inputs!$C$134/1000*CHOOSE(Inputs!$D$134,Forecast!E$30,Forecast!E$35,Forecast!E$43,Forecast!E$58),0) -> 975 | F33: =Scenarios!$B$45*IF(AND(F$5>=Inputs!$G$134,F$5<=Inputs!$H$134,OR(Inputs!$I$134=0,MONTH(Forecast!F$7)=Inputs!$I$134)),Inputs!$B$134+Inputs!$C$134/1000*CHOOSE(Inputs!$D$134,Forecast!F$30,Forecast!F$35,Forecast!F$43,Forecast!F$58),0) -> 0 | G33: =Scenarios!$B$45*IF(AND(G$5>=Inputs!$G$134,G$5<=Inputs!$H$134,OR(Inputs!$I$134=0,MONTH(Forecast!G$7)=Inputs!$I$134)),Inputs!$B$134+Inputs!$C$134/1000*CHOOSE(Inputs!$D$134,Forecast!G$30,Forecast!G$35,Forecast!G$43,Forecast!G$58),0) -> 0 | H33: =Scenarios!$B$45*IF(AND(H$5>=Inputs!$G$134,H$5<=Inputs!$H$134,OR(Inputs!$I$134=0,MONTH(Forecast!H$7)=Inputs!$I$134)),Inputs!$B$134+Inputs!$C$134/1000*CHOOSE(Inputs!$D$134,Forecast!H$30,Forecast!H$35,Forecast!H$43,Forecast!H$58),0) -> 0 | I33: =Scenarios!$B$45*IF(AND(I$5>=Inputs!$G$134,I$5<=Inputs!$H$134,OR(Inputs!$I$134=0,MONTH(Forecast!I$7)=Inputs!$I$134)),Inputs!$B$134+Inputs!$C$134/1000*CHOOSE(Inputs!$D$134,Forecast!I$30,Forecast!I$35,Forecast!I$43,Forecast!I$58),0) -> 0 | J33: =Scenarios!$B$45*IF(AND(J$5>=Inputs!$G$134,J$5<=Inputs!$H$134,OR(Inputs!$I$134=0,MONTH(Forecast!J$7)=Inputs!$I$134)),Inputs!$B$134+Inputs!$C$134/1000*CHOOSE(Inputs!$D$134,Forecast!J$30,Forecast!J$35,Forecast!J$43,Forecast!J$58),0) -> 0 | K33: =Scenarios!$B$45*IF(AND(K$5>=Inputs!$G$134,K$5<=Inputs!$H$134,OR(Inputs!$I$134=0,MONTH(Forecast!K$7)=Inputs!$I$134)),Inputs!$B$134+Inputs!$C$134/1000*CHOOSE(Inputs!$D$134,Forecast!K$30,Forecast!K$35,Forecast!K$43,Forecast!K$58),0) -> 0 | ... AM33: =Scenarios!$B$45*IF(AND(AM$5>=Inputs!$G$134,AM$5<=Inputs!$H$134,OR(Inputs!$I$134=0,MONTH(Forecast!AM$7)=Inputs!$I$134)),Inputs!$B$134+Inputs!$C$134/1000*CHOOSE(Inputs!$D$134,Forecast!AM$30,Forecast!AM$35,Forecast!AM$43,Forecast!AM$58),0) -> 0
A34: =Inputs!A135 -> Postal address / virtual mailbox for footer and CAN-SPAM | B34: =Inputs!D135 -> 1 | D34: =Scenarios!$B$45*IF(AND(D$5>=Inputs!$G$135,D$5<=Inputs!$H$135,OR(Inputs!$I$135=0,MONTH(Forecast!D$7)=Inputs!$I$135)),Inputs!$B$135+Inputs!$C$135/1000*CHOOSE(Inputs!$D$135,Forecast!D$30,Forecast!D$35,Forecast!D$43,Forecast!D$58),0) -> 10 | E34: =Scenarios!$B$45*IF(AND(E$5>=Inputs!$G$135,E$5<=Inputs!$H$135,OR(Inputs!$I$135=0,MONTH(Forecast!E$7)=Inputs!$I$135)),Inputs!$B$135+Inputs!$C$135/1000*CHOOSE(Inputs!$D$135,Forecast!E$30,Forecast!E$35,Forecast!E$43,Forecast!E$58),0) -> 10 | F34: =Scenarios!$B$45*IF(AND(F$5>=Inputs!$G$135,F$5<=Inputs!$H$135,OR(Inputs!$I$135=0,MONTH(Forecast!F$7)=Inputs!$I$135)),Inputs!$B$135+Inputs!$C$135/1000*CHOOSE(Inputs!$D$135,Forecast!F$30,Forecast!F$35,Forecast!F$43,Forecast!F$58),0) -> 10 | G34: =Scenarios!$B$45*IF(AND(G$5>=Inputs!$G$135,G$5<=Inputs!$H$135,OR(Inputs!$I$135=0,MONTH(Forecast!G$7)=Inputs!$I$135)),Inputs!$B$135+Inputs!$C$135/1000*CHOOSE(Inputs!$D$135,Forecast!G$30,Forecast!G$35,Forecast!G$43,Forecast!G$58),0) -> 10 | H34: =Scenarios!$B$45*IF(AND(H$5>=Inputs!$G$135,H$5<=Inputs!$H$135,OR(Inputs!$I$135=0,MONTH(Forecast!H$7)=Inputs!$I$135)),Inputs!$B$135+Inputs!$C$135/1000*CHOOSE(Inputs!$D$135,Forecast!H$30,Forecast!H$35,Forecast!H$43,Forecast!H$58),0) -> 10 | I34: =Scenarios!$B$45*IF(AND(I$5>=Inputs!$G$135,I$5<=Inputs!$H$135,OR(Inputs!$I$135=0,MONTH(Forecast!I$7)=Inputs!$I$135)),Inputs!$B$135+Inputs!$C$135/1000*CHOOSE(Inputs!$D$135,Forecast!I$30,Forecast!I$35,Forecast!I$43,Forecast!I$58),0) -> 10 | J34: =Scenarios!$B$45*IF(AND(J$5>=Inputs!$G$135,J$5<=Inputs!$H$135,OR(Inputs!$I$135=0,MONTH(Forecast!J$7)=Inputs!$I$135)),Inputs!$B$135+Inputs!$C$135/1000*CHOOSE(Inputs!$D$135,Forecast!J$30,Forecast!J$35,Forecast!J$43,Forecast!J$58),0) -> 10 | K34: =Scenarios!$B$45*IF(AND(K$5>=Inputs!$G$135,K$5<=Inputs!$H$135,OR(Inputs!$I$135=0,MONTH(Forecast!K$7)=Inputs!$I$135)),Inputs!$B$135+Inputs!$C$135/1000*CHOOSE(Inputs!$D$135,Forecast!K$30,Forecast!K$35,Forecast!K$43,Forecast!K$58),0) -> 10 | ... AM34: =Scenarios!$B$45*IF(AND(AM$5>=Inputs!$G$135,AM$5<=Inputs!$H$135,OR(Inputs!$I$135=0,MONTH(Forecast!AM$7)=Inputs!$I$135)),Inputs!$B$135+Inputs!$C$135/1000*CHOOSE(Inputs!$D$135,Forecast!AM$30,Forecast!AM$35,Forecast!AM$43,Forecast!AM$58),0) -> 10
A35: =Inputs!A136 -> Accountant / sales-tax filing service (incremental to the $150 LLC and accounting line) | B35: =Inputs!D136 -> 1 | D35: =Scenarios!$B$45*IF(AND(D$5>=Inputs!$G$136,D$5<=Inputs!$H$136,OR(Inputs!$I$136=0,MONTH(Forecast!D$7)=Inputs!$I$136)),Inputs!$B$136+Inputs!$C$136/1000*CHOOSE(Inputs!$D$136,Forecast!D$30,Forecast!D$35,Forecast!D$43,Forecast!D$58),0) -> 100 | E35: =Scenarios!$B$45*IF(AND(E$5>=Inputs!$G$136,E$5<=Inputs!$H$136,OR(Inputs!$I$136=0,MONTH(Forecast!E$7)=Inputs!$I$136)),Inputs!$B$136+Inputs!$C$136/1000*CHOOSE(Inputs!$D$136,Forecast!E$30,Forecast!E$35,Forecast!E$43,Forecast!E$58),0) -> 100 | F35: =Scenarios!$B$45*IF(AND(F$5>=Inputs!$G$136,F$5<=Inputs!$H$136,OR(Inputs!$I$136=0,MONTH(Forecast!F$7)=Inputs!$I$136)),Inputs!$B$136+Inputs!$C$136/1000*CHOOSE(Inputs!$D$136,Forecast!F$30,Forecast!F$35,Forecast!F$43,Forecast!F$58),0) -> 100 | G35: =Scenarios!$B$45*IF(AND(G$5>=Inputs!$G$136,G$5<=Inputs!$H$136,OR(Inputs!$I$136=0,MONTH(Forecast!G$7)=Inputs!$I$136)),Inputs!$B$136+Inputs!$C$136/1000*CHOOSE(Inputs!$D$136,Forecast!G$30,Forecast!G$35,Forecast!G$43,Forecast!G$58),0) -> 100 | H35: =Scenarios!$B$45*IF(AND(H$5>=Inputs!$G$136,H$5<=Inputs!$H$136,OR(Inputs!$I$136=0,MONTH(Forecast!H$7)=Inputs!$I$136)),Inputs!$B$136+Inputs!$C$136/1000*CHOOSE(Inputs!$D$136,Forecast!H$30,Forecast!H$35,Forecast!H$43,Forecast!H$58),0) -> 100 | I35: =Scenarios!$B$45*IF(AND(I$5>=Inputs!$G$136,I$5<=Inputs!$H$136,OR(Inputs!$I$136=0,MONTH(Forecast!I$7)=Inputs!$I$136)),Inputs!$B$136+Inputs!$C$136/1000*CHOOSE(Inputs!$D$136,Forecast!I$30,Forecast!I$35,Forecast!I$43,Forecast!I$58),0) -> 100 | J35: =Scenarios!$B$45*IF(AND(J$5>=Inputs!$G$136,J$5<=Inputs!$H$136,OR(Inputs!$I$136=0,MONTH(Forecast!J$7)=Inputs!$I$136)),Inputs!$B$136+Inputs!$C$136/1000*CHOOSE(Inputs!$D$136,Forecast!J$30,Forecast!J$35,Forecast!J$43,Forecast!J$58),0) -> 100 | K35: =Scenarios!$B$45*IF(AND(K$5>=Inputs!$G$136,K$5<=Inputs!$H$136,OR(Inputs!$I$136=0,MONTH(Forecast!K$7)=Inputs!$I$136)),Inputs!$B$136+Inputs!$C$136/1000*CHOOSE(Inputs!$D$136,Forecast!K$30,Forecast!K$35,Forecast!K$43,Forecast!K$58),0) -> 100 | ... AM35: =Scenarios!$B$45*IF(AND(AM$5>=Inputs!$G$136,AM$5<=Inputs!$H$136,OR(Inputs!$I$136=0,MONTH(Forecast!AM$7)=Inputs!$I$136)),Inputs!$B$136+Inputs!$C$136/1000*CHOOSE(Inputs!$D$136,Forecast!AM$30,Forecast!AM$35,Forecast!AM$43,Forecast!AM$58),0) -> 100
A36: =Inputs!A137 -> Insurance stack top-up (cyber + media/IP + GL about $4,600/yr vs $95/mo carried) | B36: =Inputs!D137 -> 1 | D36: =Scenarios!$B$45*IF(AND(D$5>=Inputs!$G$137,D$5<=Inputs!$H$137,OR(Inputs!$I$137=0,MONTH(Forecast!D$7)=Inputs!$I$137)),Inputs!$B$137+Inputs!$C$137/1000*CHOOSE(Inputs!$D$137,Forecast!D$30,Forecast!D$35,Forecast!D$43,Forecast!D$58),0) -> 288 | E36: =Scenarios!$B$45*IF(AND(E$5>=Inputs!$G$137,E$5<=Inputs!$H$137,OR(Inputs!$I$137=0,MONTH(Forecast!E$7)=Inputs!$I$137)),Inputs!$B$137+Inputs!$C$137/1000*CHOOSE(Inputs!$D$137,Forecast!E$30,Forecast!E$35,Forecast!E$43,Forecast!E$58),0) -> 288 | F36: =Scenarios!$B$45*IF(AND(F$5>=Inputs!$G$137,F$5<=Inputs!$H$137,OR(Inputs!$I$137=0,MONTH(Forecast!F$7)=Inputs!$I$137)),Inputs!$B$137+Inputs!$C$137/1000*CHOOSE(Inputs!$D$137,Forecast!F$30,Forecast!F$35,Forecast!F$43,Forecast!F$58),0) -> 288 | G36: =Scenarios!$B$45*IF(AND(G$5>=Inputs!$G$137,G$5<=Inputs!$H$137,OR(Inputs!$I$137=0,MONTH(Forecast!G$7)=Inputs!$I$137)),Inputs!$B$137+Inputs!$C$137/1000*CHOOSE(Inputs!$D$137,Forecast!G$30,Forecast!G$35,Forecast!G$43,Forecast!G$58),0) -> 288 | H36: =Scenarios!$B$45*IF(AND(H$5>=Inputs!$G$137,H$5<=Inputs!$H$137,OR(Inputs!$I$137=0,MONTH(Forecast!H$7)=Inputs!$I$137)),Inputs!$B$137+Inputs!$C$137/1000*CHOOSE(Inputs!$D$137,Forecast!H$30,Forecast!H$35,Forecast!H$43,Forecast!H$58),0) -> 288 | I36: =Scenarios!$B$45*IF(AND(I$5>=Inputs!$G$137,I$5<=Inputs!$H$137,OR(Inputs!$I$137=0,MONTH(Forecast!I$7)=Inputs!$I$137)),Inputs!$B$137+Inputs!$C$137/1000*CHOOSE(Inputs!$D$137,Forecast!I$30,Forecast!I$35,Forecast!I$43,Forecast!I$58),0) -> 288 | J36: =Scenarios!$B$45*IF(AND(J$5>=Inputs!$G$137,J$5<=Inputs!$H$137,OR(Inputs!$I$137=0,MONTH(Forecast!J$7)=Inputs!$I$137)),Inputs!$B$137+Inputs!$C$137/1000*CHOOSE(Inputs!$D$137,Forecast!J$30,Forecast!J$35,Forecast!J$43,Forecast!J$58),0) -> 288 | K36: =Scenarios!$B$45*IF(AND(K$5>=Inputs!$G$137,K$5<=Inputs!$H$137,OR(Inputs!$I$137=0,MONTH(Forecast!K$7)=Inputs!$I$137)),Inputs!$B$137+Inputs!$C$137/1000*CHOOSE(Inputs!$D$137,Forecast!K$30,Forecast!K$35,Forecast!K$43,Forecast!K$58),0) -> 288 | ... AM36: =Scenarios!$B$45*IF(AND(AM$5>=Inputs!$G$137,AM$5<=Inputs!$H$137,OR(Inputs!$I$137=0,MONTH(Forecast!AM$7)=Inputs!$I$137)),Inputs!$B$137+Inputs!$C$137/1000*CHOOSE(Inputs!$D$137,Forecast!AM$30,Forecast!AM$35,Forecast!AM$43,Forecast!AM$58),0) -> 288
A37: =Inputs!A138 -> Trademark monitoring service ($400/yr) | B37: =Inputs!D138 -> 1 | D37: =Scenarios!$B$45*IF(AND(D$5>=Inputs!$G$138,D$5<=Inputs!$H$138,OR(Inputs!$I$138=0,MONTH(Forecast!D$7)=Inputs!$I$138)),Inputs!$B$138+Inputs!$C$138/1000*CHOOSE(Inputs!$D$138,Forecast!D$30,Forecast!D$35,Forecast!D$43,Forecast!D$58),0) -> 0 | E37: =Scenarios!$B$45*IF(AND(E$5>=Inputs!$G$138,E$5<=Inputs!$H$138,OR(Inputs!$I$138=0,MONTH(Forecast!E$7)=Inputs!$I$138)),Inputs!$B$138+Inputs!$C$138/1000*CHOOSE(Inputs!$D$138,Forecast!E$30,Forecast!E$35,Forecast!E$43,Forecast!E$58),0) -> 0 | F37: =Scenarios!$B$45*IF(AND(F$5>=Inputs!$G$138,F$5<=Inputs!$H$138,OR(Inputs!$I$138=0,MONTH(Forecast!F$7)=Inputs!$I$138)),Inputs!$B$138+Inputs!$C$138/1000*CHOOSE(Inputs!$D$138,Forecast!F$30,Forecast!F$35,Forecast!F$43,Forecast!F$58),0) -> 0 | G37: =Scenarios!$B$45*IF(AND(G$5>=Inputs!$G$138,G$5<=Inputs!$H$138,OR(Inputs!$I$138=0,MONTH(Forecast!G$7)=Inputs!$I$138)),Inputs!$B$138+Inputs!$C$138/1000*CHOOSE(Inputs!$D$138,Forecast!G$30,Forecast!G$35,Forecast!G$43,Forecast!G$58),0) -> 0 | H37: =Scenarios!$B$45*IF(AND(H$5>=Inputs!$G$138,H$5<=Inputs!$H$138,OR(Inputs!$I$138=0,MONTH(Forecast!H$7)=Inputs!$I$138)),Inputs!$B$138+Inputs!$C$138/1000*CHOOSE(Inputs!$D$138,Forecast!H$30,Forecast!H$35,Forecast!H$43,Forecast!H$58),0) -> 0 | I37: =Scenarios!$B$45*IF(AND(I$5>=Inputs!$G$138,I$5<=Inputs!$H$138,OR(Inputs!$I$138=0,MONTH(Forecast!I$7)=Inputs!$I$138)),Inputs!$B$138+Inputs!$C$138/1000*CHOOSE(Inputs!$D$138,Forecast!I$30,Forecast!I$35,Forecast!I$43,Forecast!I$58),0) -> 0 | J37: =Scenarios!$B$45*IF(AND(J$5>=Inputs!$G$138,J$5<=Inputs!$H$138,OR(Inputs!$I$138=0,MONTH(Forecast!J$7)=Inputs!$I$138)),Inputs!$B$138+Inputs!$C$138/1000*CHOOSE(Inputs!$D$138,Forecast!J$30,Forecast!J$35,Forecast!J$43,Forecast!J$58),0) -> 33.33 | K37: =Scenarios!$B$45*IF(AND(K$5>=Inputs!$G$138,K$5<=Inputs!$H$138,OR(Inputs!$I$138=0,MONTH(Forecast!K$7)=Inputs!$I$138)),Inputs!$B$138+Inputs!$C$138/1000*CHOOSE(Inputs!$D$138,Forecast!K$30,Forecast!K$35,Forecast!K$43,Forecast!K$58),0) -> 33.33 | ... AM37: =Scenarios!$B$45*IF(AND(AM$5>=Inputs!$G$138,AM$5<=Inputs!$H$138,OR(Inputs!$I$138=0,MONTH(Forecast!AM$7)=Inputs!$I$138)),Inputs!$B$138+Inputs!$C$138/1000*CHOOSE(Inputs!$D$138,Forecast!AM$30,Forecast!AM$35,Forecast!AM$43,Forecast!AM$58),0) -> 33.33
A38: =Inputs!A139 -> Annual attorney policy and compliance refresh ($2,500/yr) | B38: =Inputs!D139 -> 1 | D38: =Scenarios!$B$45*IF(AND(D$5>=Inputs!$G$139,D$5<=Inputs!$H$139,OR(Inputs!$I$139=0,MONTH(Forecast!D$7)=Inputs!$I$139)),Inputs!$B$139+Inputs!$C$139/1000*CHOOSE(Inputs!$D$139,Forecast!D$30,Forecast!D$35,Forecast!D$43,Forecast!D$58),0) -> 0 | E38: =Scenarios!$B$45*IF(AND(E$5>=Inputs!$G$139,E$5<=Inputs!$H$139,OR(Inputs!$I$139=0,MONTH(Forecast!E$7)=Inputs!$I$139)),Inputs!$B$139+Inputs!$C$139/1000*CHOOSE(Inputs!$D$139,Forecast!E$30,Forecast!E$35,Forecast!E$43,Forecast!E$58),0) -> 0 | F38: =Scenarios!$B$45*IF(AND(F$5>=Inputs!$G$139,F$5<=Inputs!$H$139,OR(Inputs!$I$139=0,MONTH(Forecast!F$7)=Inputs!$I$139)),Inputs!$B$139+Inputs!$C$139/1000*CHOOSE(Inputs!$D$139,Forecast!F$30,Forecast!F$35,Forecast!F$43,Forecast!F$58),0) -> 0 | G38: =Scenarios!$B$45*IF(AND(G$5>=Inputs!$G$139,G$5<=Inputs!$H$139,OR(Inputs!$I$139=0,MONTH(Forecast!G$7)=Inputs!$I$139)),Inputs!$B$139+Inputs!$C$139/1000*CHOOSE(Inputs!$D$139,Forecast!G$30,Forecast!G$35,Forecast!G$43,Forecast!G$58),0) -> 0 | H38: =Scenarios!$B$45*IF(AND(H$5>=Inputs!$G$139,H$5<=Inputs!$H$139,OR(Inputs!$I$139=0,MONTH(Forecast!H$7)=Inputs!$I$139)),Inputs!$B$139+Inputs!$C$139/1000*CHOOSE(Inputs!$D$139,Forecast!H$30,Forecast!H$35,Forecast!H$43,Forecast!H$58),0) -> 0 | I38: =Scenarios!$B$45*IF(AND(I$5>=Inputs!$G$139,I$5<=Inputs!$H$139,OR(Inputs!$I$139=0,MONTH(Forecast!I$7)=Inputs!$I$139)),Inputs!$B$139+Inputs!$C$139/1000*CHOOSE(Inputs!$D$139,Forecast!I$30,Forecast!I$35,Forecast!I$43,Forecast!I$58),0) -> 0 | J38: =Scenarios!$B$45*IF(AND(J$5>=Inputs!$G$139,J$5<=Inputs!$H$139,OR(Inputs!$I$139=0,MONTH(Forecast!J$7)=Inputs!$I$139)),Inputs!$B$139+Inputs!$C$139/1000*CHOOSE(Inputs!$D$139,Forecast!J$30,Forecast!J$35,Forecast!J$43,Forecast!J$58),0) -> 0 | K38: =Scenarios!$B$45*IF(AND(K$5>=Inputs!$G$139,K$5<=Inputs!$H$139,OR(Inputs!$I$139=0,MONTH(Forecast!K$7)=Inputs!$I$139)),Inputs!$B$139+Inputs!$C$139/1000*CHOOSE(Inputs!$D$139,Forecast!K$30,Forecast!K$35,Forecast!K$43,Forecast!K$58),0) -> 0 | ... AM38: =Scenarios!$B$45*IF(AND(AM$5>=Inputs!$G$139,AM$5<=Inputs!$H$139,OR(Inputs!$I$139=0,MONTH(Forecast!AM$7)=Inputs!$I$139)),Inputs!$B$139+Inputs!$C$139/1000*CHOOSE(Inputs!$D$139,Forecast!AM$30,Forecast!AM$35,Forecast!AM$43,Forecast!AM$58),0) -> 208.33
A39: =Inputs!A140 -> Defensive domains (.co, .net, greet-hub; $65/yr) | B39: =Inputs!D140 -> 1 | D39: =Scenarios!$B$45*IF(AND(D$5>=Inputs!$G$140,D$5<=Inputs!$H$140,OR(Inputs!$I$140=0,MONTH(Forecast!D$7)=Inputs!$I$140)),Inputs!$B$140+Inputs!$C$140/1000*CHOOSE(Inputs!$D$140,Forecast!D$30,Forecast!D$35,Forecast!D$43,Forecast!D$58),0) -> 5.42 | E39: =Scenarios!$B$45*IF(AND(E$5>=Inputs!$G$140,E$5<=Inputs!$H$140,OR(Inputs!$I$140=0,MONTH(Forecast!E$7)=Inputs!$I$140)),Inputs!$B$140+Inputs!$C$140/1000*CHOOSE(Inputs!$D$140,Forecast!E$30,Forecast!E$35,Forecast!E$43,Forecast!E$58),0) -> 5.42 | F39: =Scenarios!$B$45*IF(AND(F$5>=Inputs!$G$140,F$5<=Inputs!$H$140,OR(Inputs!$I$140=0,MONTH(Forecast!F$7)=Inputs!$I$140)),Inputs!$B$140+Inputs!$C$140/1000*CHOOSE(Inputs!$D$140,Forecast!F$30,Forecast!F$35,Forecast!F$43,Forecast!F$58),0) -> 5.42 | G39: =Scenarios!$B$45*IF(AND(G$5>=Inputs!$G$140,G$5<=Inputs!$H$140,OR(Inputs!$I$140=0,MONTH(Forecast!G$7)=Inputs!$I$140)),Inputs!$B$140+Inputs!$C$140/1000*CHOOSE(Inputs!$D$140,Forecast!G$30,Forecast!G$35,Forecast!G$43,Forecast!G$58),0) -> 5.42 | H39: =Scenarios!$B$45*IF(AND(H$5>=Inputs!$G$140,H$5<=Inputs!$H$140,OR(Inputs!$I$140=0,MONTH(Forecast!H$7)=Inputs!$I$140)),Inputs!$B$140+Inputs!$C$140/1000*CHOOSE(Inputs!$D$140,Forecast!H$30,Forecast!H$35,Forecast!H$43,Forecast!H$58),0) -> 5.42 | I39: =Scenarios!$B$45*IF(AND(I$5>=Inputs!$G$140,I$5<=Inputs!$H$140,OR(Inputs!$I$140=0,MONTH(Forecast!I$7)=Inputs!$I$140)),Inputs!$B$140+Inputs!$C$140/1000*CHOOSE(Inputs!$D$140,Forecast!I$30,Forecast!I$35,Forecast!I$43,Forecast!I$58),0) -> 5.42 | J39: =Scenarios!$B$45*IF(AND(J$5>=Inputs!$G$140,J$5<=Inputs!$H$140,OR(Inputs!$I$140=0,MONTH(Forecast!J$7)=Inputs!$I$140)),Inputs!$B$140+Inputs!$C$140/1000*CHOOSE(Inputs!$D$140,Forecast!J$30,Forecast!J$35,Forecast!J$43,Forecast!J$58),0) -> 5.42 | K39: =Scenarios!$B$45*IF(AND(K$5>=Inputs!$G$140,K$5<=Inputs!$H$140,OR(Inputs!$I$140=0,MONTH(Forecast!K$7)=Inputs!$I$140)),Inputs!$B$140+Inputs!$C$140/1000*CHOOSE(Inputs!$D$140,Forecast!K$30,Forecast!K$35,Forecast!K$43,Forecast!K$58),0) -> 5.42 | ... AM39: =Scenarios!$B$45*IF(AND(AM$5>=Inputs!$G$140,AM$5<=Inputs!$H$140,OR(Inputs!$I$140=0,MONTH(Forecast!AM$7)=Inputs!$I$140)),Inputs!$B$140+Inputs!$C$140/1000*CHOOSE(Inputs!$D$140,Forecast!AM$30,Forecast!AM$35,Forecast!AM$43,Forecast!AM$58),0) -> 5.42
A40: Total v2 operating costs | D40: =SUM(D24:D39) -> 425.92 | E40: =SUM(E24:E39) -> 1440.92 | F40: =SUM(F24:F39) -> 465.92 | G40: =SUM(G24:G39) -> 465.92 | H40: =SUM(H24:H39) -> 465.92 | I40: =SUM(I24:I39) -> 465.92 | J40: =SUM(J24:J39) -> 524.25 | K40: =SUM(K24:K39) -> 524.25 | ... AM40: =SUM(AM24:AM39) -> 757.58
A41: v2 one-time costs (Inputs section 14, charged in their month) | D41: =Scenarios!$B$45*SUMPRODUCT((Inputs!$C$144:$C$148=D$5)*Inputs!$B$144:$B$148) -> 9506 | E41: =Scenarios!$B$45*SUMPRODUCT((Inputs!$C$144:$C$148=E$5)*Inputs!$B$144:$B$148) -> 2000 | F41: =Scenarios!$B$45*SUMPRODUCT((Inputs!$C$144:$C$148=F$5)*Inputs!$B$144:$B$148) -> 0 | G41: =Scenarios!$B$45*SUMPRODUCT((Inputs!$C$144:$C$148=G$5)*Inputs!$B$144:$B$148) -> 3000 | H41: =Scenarios!$B$45*SUMPRODUCT((Inputs!$C$144:$C$148=H$5)*Inputs!$B$144:$B$148) -> 0 | I41: =Scenarios!$B$45*SUMPRODUCT((Inputs!$C$144:$C$148=I$5)*Inputs!$B$144:$B$148) -> 0 | J41: =Scenarios!$B$45*SUMPRODUCT((Inputs!$C$144:$C$148=J$5)*Inputs!$B$144:$B$148) -> 0 | K41: =Scenarios!$B$45*SUMPRODUCT((Inputs!$C$144:$C$148=K$5)*Inputs!$B$144:$B$148) -> 0 | ... AM41: =Scenarios!$B$45*SUMPRODUCT((Inputs!$C$144:$C$148=AM$5)*Inputs!$B$144:$B$148) -> 0

Sheet Forecast
A1: Forecast - 36 months (selected scenario)
A3: ="Scenario: "&Scenarios!B3 -> Scenario: Base
A4: Line | B4: Unit | C4: Opening | D4: M1 | E4: M2 | F4: M3 | G4: M4 | H4: M5 | I4: M6 | J4: M7 | K4: M8 | L4: M9 | M4: M10 | N4: M11 | O4: M12 | P4: M13 | Q4: M14 | R4: M15 | S4: M16 | T4: M17 | U4: M18 | V4: M19 | W4: M20 | X4: M21 | Y4: M22 | Z4: M23 | AA4: M24 | AB4: M25 | AC4: M26 | AD4: M27 | AE4: M28 | AF4: M29 | AG4: M30 | AH4: M31 | AI4: M32 | AJ4: M33 | AK4: M34 | AL4: M35 | AM4: M36 | AO4: Year 1 | AP4: Year 2 | AQ4: Year 3
A5: TIMELINE
A6: Month # | B6: # | C6: 0 | D6: =C6+1 -> 1 | E6: =D6+1 -> 2 | F6: =E6+1 -> 3 | G6: =F6+1 -> 4 | H6: =G6+1 -> 5 | I6: =H6+1 -> 6 | J6: =I6+1 -> 7 | K6: =J6+1 -> 8 | ... AM6: =AL6+1 -> 36
A7: Month | B7: date | D7: =EDATE(Inputs!$B$7,D6-1) -> 46327 | E7: =EDATE(Inputs!$B$7,E6-1) -> 46357 | F7: =EDATE(Inputs!$B$7,F6-1) -> 46388 | G7: =EDATE(Inputs!$B$7,G6-1) -> 46419 | H7: =EDATE(Inputs!$B$7,H6-1) -> 46447 | I7: =EDATE(Inputs!$B$7,I6-1) -> 46478 | J7: =EDATE(Inputs!$B$7,J6-1) -> 46508 | K7: =EDATE(Inputs!$B$7,K6-1) -> 46539 | ... AM7: =EDATE(Inputs!$B$7,AM6-1) -> 47392
A8: Calendar month | B8: 1-12 | D8: =MONTH(D7) -> 11 | E8: =MONTH(E7) -> 12 | F8: =MONTH(F7) -> 1 | G8: =MONTH(G7) -> 2 | H8: =MONTH(H7) -> 3 | I8: =MONTH(I7) -> 4 | J8: =MONTH(J7) -> 5 | K8: =MONTH(K7) -> 6 | ... AM8: =MONTH(AM7) -> 10
A9: Seasonality index | B9: x | D9: =INDEX(Inputs!$B$68:$B$79,D8) -> 1.3 | E9: =INDEX(Inputs!$B$68:$B$79,E8) -> 1.9 | F9: =INDEX(Inputs!$B$68:$B$79,F8) -> 0.7 | G9: =INDEX(Inputs!$B$68:$B$79,G8) -> 1.3 | H9: =INDEX(Inputs!$B$68:$B$79,H8) -> 0.85 | I9: =INDEX(Inputs!$B$68:$B$79,I8) -> 0.9 | J9: =INDEX(Inputs!$B$68:$B$79,J8) -> 1.4 | K9: =INDEX(Inputs!$B$68:$B$79,K8) -> 1.05 | ... AM9: =INDEX(Inputs!$B$68:$B$79,AM8) -> 1 | AO9: =AVERAGE(D9:O9) -> 1.0916667 | AP9: =AVERAGE(P9:AA9) -> 1.0916667 | AQ9: =AVERAGE(AB9:AM9) -> 1.0916667
A10: Conversion seasonality | B10: x | D10: =1+(D9-1)*Inputs!$B$16 -> 1.15 | E10: =1+(E9-1)*Inputs!$B$16 -> 1.45 | F10: =1+(F9-1)*Inputs!$B$16 -> 0.85 | G10: =1+(G9-1)*Inputs!$B$16 -> 1.15 | H10: =1+(H9-1)*Inputs!$B$16 -> 0.925 | I10: =1+(I9-1)*Inputs!$B$16 -> 0.95 | J10: =1+(J9-1)*Inputs!$B$16 -> 1.2 | K10: =1+(K9-1)*Inputs!$B$16 -> 1.025 | ... AM10: =1+(AM9-1)*Inputs!$B$16 -> 1 | AO10: =AVERAGE(D10:O10) -> 1.0458333 | AP10: =AVERAGE(P10:AA10) -> 1.0458333 | AQ10: =AVERAGE(AB10:AM10) -> 1.0458333
A11: MARKETING BUDGET (drives paid traffic)
A12: Total marketing budget | B12: $ | D12: =MIN(Inputs!$B$28,Inputs!$B$26*(1+Inputs!$B$27)^(D6-1))*Scenarios!$B$12*(1+Inputs!$B$29*(D9-1)) -> 7475 | E12: =MIN(Inputs!$B$28,Inputs!$B$26*(1+Inputs!$B$27)^(E6-1))*Scenarios!$B$12*(1+Inputs!$B$29*(E9-1)) -> 9425 | F12: =MIN(Inputs!$B$28,Inputs!$B$26*(1+Inputs!$B$27)^(F6-1))*Scenarios!$B$12*(1+Inputs!$B$29*(F9-1)) -> 5525 | G12: =MIN(Inputs!$B$28,Inputs!$B$26*(1+Inputs!$B$27)^(G6-1))*Scenarios!$B$12*(1+Inputs!$B$29*(G9-1)) -> 7475 | H12: =MIN(Inputs!$B$28,Inputs!$B$26*(1+Inputs!$B$27)^(H6-1))*Scenarios!$B$12*(1+Inputs!$B$29*(H9-1)) -> 6012.5 | I12: =MIN(Inputs!$B$28,Inputs!$B$26*(1+Inputs!$B$27)^(I6-1))*Scenarios!$B$12*(1+Inputs!$B$29*(I9-1)) -> 6175 | J12: =MIN(Inputs!$B$28,Inputs!$B$26*(1+Inputs!$B$27)^(J6-1))*Scenarios!$B$12*(1+Inputs!$B$29*(J9-1)) -> 7800 | K12: =MIN(Inputs!$B$28,Inputs!$B$26*(1+Inputs!$B$27)^(K6-1))*Scenarios!$B$12*(1+Inputs!$B$29*(K9-1)) -> 6662.5 | ... AM12: =MIN(Inputs!$B$28,Inputs!$B$26*(1+Inputs!$B$27)^(AM6-1))*Scenarios!$B$12*(1+Inputs!$B$29*(AM9-1)) -> 6500 | AO12: =SUM(D12:O12) -> 81575 | AP12: =SUM(P12:AA12) -> 81575 | AQ12: =SUM(AB12:AM12) -> 81575
A13: =" Budget - "&Inputs!A57 -> Budget - meta_instagram_ads | B13: $ | D13: =D12*'Unit Economics'!$B$15 -> 2300 | E13: =E12*'Unit Economics'!$B$15 -> 2900 | F13: =F12*'Unit Economics'!$B$15 -> 1700 | G13: =G12*'Unit Economics'!$B$15 -> 2300 | H13: =H12*'Unit Economics'!$B$15 -> 1850 | I13: =I12*'Unit Economics'!$B$15 -> 1900 | J13: =J12*'Unit Economics'!$B$15 -> 2400 | K13: =K12*'Unit Economics'!$B$15 -> 2050 | ... AM13: =AM12*'Unit Economics'!$B$15 -> 2000 | AO13: =SUM(D13:O13) -> 25100 | AP13: =SUM(P13:AA13) -> 25100 | AQ13: =SUM(AB13:AM13) -> 25100
A14: =" Budget - "&Inputs!A58 -> Budget - pinterest_ads | B14: $ | D14: =D12*'Unit Economics'!$B$16 -> 920 | E14: =E12*'Unit Economics'!$B$16 -> 1160 | F14: =F12*'Unit Economics'!$B$16 -> 680 | G14: =G12*'Unit Economics'!$B$16 -> 920 | H14: =H12*'Unit Economics'!$B$16 -> 740 | I14: =I12*'Unit Economics'!$B$16 -> 760 | J14: =J12*'Unit Economics'!$B$16 -> 960 | K14: =K12*'Unit Economics'!$B$16 -> 820 | ... AM14: =AM12*'Unit Economics'!$B$16 -> 800 | AO14: =SUM(D14:O14) -> 10040 | AP14: =SUM(P14:AA14) -> 10040 | AQ14: =SUM(AB14:AM14) -> 10040
A15: =" Budget - "&Inputs!A59 -> Budget - google_search | B15: $ | D15: =D12*'Unit Economics'!$B$17 -> 920 | E15: =E12*'Unit Economics'!$B$17 -> 1160 | F15: =F12*'Unit Economics'!$B$17 -> 680 | G15: =G12*'Unit Economics'!$B$17 -> 920 | H15: =H12*'Unit Economics'!$B$17 -> 740 | I15: =I12*'Unit Economics'!$B$17 -> 760 | J15: =J12*'Unit Economics'!$B$17 -> 960 | K15: =K12*'Unit Economics'!$B$17 -> 820 | ... AM15: =AM12*'Unit Economics'!$B$17 -> 800 | AO15: =SUM(D15:O15) -> 10040 | AP15: =SUM(P15:AA15) -> 10040 | AQ15: =SUM(AB15:AM15) -> 10040
A16: =" Budget - "&Inputs!A60 -> Budget - tiktok_ads | B16: $ | D16: =D12*'Unit Economics'!$B$18 -> 345 | E16: =E12*'Unit Economics'!$B$18 -> 435 | F16: =F12*'Unit Economics'!$B$18 -> 255 | G16: =G12*'Unit Economics'!$B$18 -> 345 | H16: =H12*'Unit Economics'!$B$18 -> 277.5 | I16: =I12*'Unit Economics'!$B$18 -> 285 | J16: =J12*'Unit Economics'!$B$18 -> 360 | K16: =K12*'Unit Economics'!$B$18 -> 307.5 | ... AM16: =AM12*'Unit Economics'!$B$18 -> 300 | AO16: =SUM(D16:O16) -> 3765 | AP16: =SUM(P16:AA16) -> 3765 | AQ16: =SUM(AB16:AM16) -> 3765
A17: =" Budget - "&Inputs!A61 -> Budget - creators_affiliate | B17: $ | D17: =D12*'Unit Economics'!$B$19 -> 1610 | E17: =E12*'Unit Economics'!$B$19 -> 2030 | F17: =F12*'Unit Economics'!$B$19 -> 1190 | G17: =G12*'Unit Economics'!$B$19 -> 1610 | H17: =H12*'Unit Economics'!$B$19 -> 1295 | I17: =I12*'Unit Economics'!$B$19 -> 1330 | J17: =J12*'Unit Economics'!$B$19 -> 1680 | K17: =K12*'Unit Economics'!$B$19 -> 1435 | ... AM17: =AM12*'Unit Economics'!$B$19 -> 1400 | AO17: =SUM(D17:O17) -> 17570 | AP17: =SUM(P17:AA17) -> 17570 | AQ17: =SUM(AB17:AM17) -> 17570
A18: =" Budget - "&Inputs!A62 -> Budget - occasion_seo_content | B18: $ | D18: =D12*'Unit Economics'!$B$20 -> 1380 | E18: =E12*'Unit Economics'!$B$20 -> 1740 | F18: =F12*'Unit Economics'!$B$20 -> 1020 | G18: =G12*'Unit Economics'!$B$20 -> 1380 | H18: =H12*'Unit Economics'!$B$20 -> 1110 | I18: =I12*'Unit Economics'!$B$20 -> 1140 | J18: =J12*'Unit Economics'!$B$20 -> 1440 | K18: =K12*'Unit Economics'!$B$20 -> 1230 | ... AM18: =AM12*'Unit Economics'!$B$20 -> 1200 | AO18: =SUM(D18:O18) -> 15060 | AP18: =SUM(P18:AA18) -> 15060 | AQ18: =SUM(AB18:AM18) -> 15060
A19: TRAFFIC (visits)
A20: =" Paid visits - "&Inputs!A57 -> Paid visits - meta_instagram_ads | B20: visits | D20: =IFERROR(D13/'Unit Economics'!$C$15,0) -> 2705.8824 | E20: =IFERROR(E13/'Unit Economics'!$C$15,0) -> 3411.7647 | F20: =IFERROR(F13/'Unit Economics'!$C$15,0) -> 2000 | G20: =IFERROR(G13/'Unit Economics'!$C$15,0) -> 2705.8824 | H20: =IFERROR(H13/'Unit Economics'!$C$15,0) -> 2176.4706 | I20: =IFERROR(I13/'Unit Economics'!$C$15,0) -> 2235.2941 | J20: =IFERROR(J13/'Unit Economics'!$C$15,0) -> 2823.5294 | K20: =IFERROR(K13/'Unit Economics'!$C$15,0) -> 2411.7647 | ... AM20: =IFERROR(AM13/'Unit Economics'!$C$15,0) -> 2352.9412 | AO20: =SUM(D20:O20) -> 29529.412 | AP20: =SUM(P20:AA20) -> 29529.412 | AQ20: =SUM(AB20:AM20) -> 29529.412
A21: =" Paid visits - "&Inputs!A58 -> Paid visits - pinterest_ads | B21: visits | D21: =IFERROR(D14/'Unit Economics'!$C$16,0) -> 1672.7273 | E21: =IFERROR(E14/'Unit Economics'!$C$16,0) -> 2109.0909 | F21: =IFERROR(F14/'Unit Economics'!$C$16,0) -> 1236.3636 | G21: =IFERROR(G14/'Unit Economics'!$C$16,0) -> 1672.7273 | H21: =IFERROR(H14/'Unit Economics'!$C$16,0) -> 1345.4545 | I21: =IFERROR(I14/'Unit Economics'!$C$16,0) -> 1381.8182 | J21: =IFERROR(J14/'Unit Economics'!$C$16,0) -> 1745.4545 | K21: =IFERROR(K14/'Unit Economics'!$C$16,0) -> 1490.9091 | ... AM21: =IFERROR(AM14/'Unit Economics'!$C$16,0) -> 1454.5455 | AO21: =SUM(D21:O21) -> 18254.545 | AP21: =SUM(P21:AA21) -> 18254.545 | AQ21: =SUM(AB21:AM21) -> 18254.545
A22: =" Paid visits - "&Inputs!A59 -> Paid visits - google_search | B22: visits | D22: =IFERROR(D15/'Unit Economics'!$C$17,0) -> 222.22222 | E22: =IFERROR(E15/'Unit Economics'!$C$17,0) -> 280.19324 | F22: =IFERROR(F15/'Unit Economics'!$C$17,0) -> 164.25121 | G22: =IFERROR(G15/'Unit Economics'!$C$17,0) -> 222.22222 | H22: =IFERROR(H15/'Unit Economics'!$C$17,0) -> 178.74396 | I22: =IFERROR(I15/'Unit Economics'!$C$17,0) -> 183.57488 | J22: =IFERROR(J15/'Unit Economics'!$C$17,0) -> 231.88406 | K22: =IFERROR(K15/'Unit Economics'!$C$17,0) -> 198.06763 | ... AM22: =IFERROR(AM15/'Unit Economics'!$C$17,0) -> 193.23671 | AO22: =SUM(D22:O22) -> 2425.1208 | AP22: =SUM(P22:AA22) -> 2425.1208 | AQ22: =SUM(AB22:AM22) -> 2425.1208
A23: =" Paid visits - "&Inputs!A60 -> Paid visits - tiktok_ads | B23: visits | D23: =IFERROR(D16/'Unit Economics'!$C$18,0) -> 575 | E23: =IFERROR(E16/'Unit Economics'!$C$18,0) -> 725 | F23: =IFERROR(F16/'Unit Economics'!$C$18,0) -> 425 | G23: =IFERROR(G16/'Unit Economics'!$C$18,0) -> 575 | H23: =IFERROR(H16/'Unit Economics'!$C$18,0) -> 462.5 | I23: =IFERROR(I16/'Unit Economics'!$C$18,0) -> 475 | J23: =IFERROR(J16/'Unit Economics'!$C$18,0) -> 600 | K23: =IFERROR(K16/'Unit Economics'!$C$18,0) -> 512.5 | ... AM23: =IFERROR(AM16/'Unit Economics'!$C$18,0) -> 500 | AO23: =SUM(D23:O23) -> 6275 | AP23: =SUM(P23:AA23) -> 6275 | AQ23: =SUM(AB23:AM23) -> 6275
A24: =" Paid visits - "&Inputs!A61 -> Paid visits - creators_affiliate | B24: visits | D24: =IFERROR(D17/'Unit Economics'!$C$19,0) -> 1341.6667 | E24: =IFERROR(E17/'Unit Economics'!$C$19,0) -> 1691.6667 | F24: =IFERROR(F17/'Unit Economics'!$C$19,0) -> 991.66667 | G24: =IFERROR(G17/'Unit Economics'!$C$19,0) -> 1341.6667 | H24: =IFERROR(H17/'Unit Economics'!$C$19,0) -> 1079.1667 | I24: =IFERROR(I17/'Unit Economics'!$C$19,0) -> 1108.3333 | J24: =IFERROR(J17/'Unit Economics'!$C$19,0) -> 1400 | K24: =IFERROR(K17/'Unit Economics'!$C$19,0) -> 1195.8333 | ... AM24: =IFERROR(AM17/'Unit Economics'!$C$19,0) -> 1166.6667 | AO24: =SUM(D24:O24) -> 14641.667 | AP24: =SUM(P24:AA24) -> 14641.667 | AQ24: =SUM(AB24:AM24) -> 14641.667
A25: =" Paid visits - "&Inputs!A62 -> Paid visits - occasion_seo_content | B25: visits | D25: =IFERROR(D18/'Unit Economics'!$C$20,0) -> 3942.8571 | E25: =IFERROR(E18/'Unit Economics'!$C$20,0) -> 4971.4286 | F25: =IFERROR(F18/'Unit Economics'!$C$20,0) -> 2914.2857 | G25: =IFERROR(G18/'Unit Economics'!$C$20,0) -> 3942.8571 | H25: =IFERROR(H18/'Unit Economics'!$C$20,0) -> 3171.4286 | I25: =IFERROR(I18/'Unit Economics'!$C$20,0) -> 3257.1429 | J25: =IFERROR(J18/'Unit Economics'!$C$20,0) -> 4114.2857 | K25: =IFERROR(K18/'Unit Economics'!$C$20,0) -> 3514.2857 | ... AM25: =IFERROR(AM18/'Unit Economics'!$C$20,0) -> 3428.5714 | AO25: =SUM(D25:O25) -> 43028.571 | AP25: =SUM(P25:AA25) -> 43028.571 | AQ25: =SUM(AB25:AM25) -> 43028.571
A26: Paid visits (budget / CPC) | B26: visits | D26: =SUM(D20:D25) -> 10460.356 | E26: =SUM(E20:E25) -> 13189.144 | F26: =SUM(F20:F25) -> 7731.5672 | G26: =SUM(G20:G25) -> 10460.356 | H26: =SUM(H20:H25) -> 8413.7643 | I26: =SUM(I20:I25) -> 8641.1634 | J26: =SUM(J20:J25) -> 10915.154 | K26: =SUM(K20:K25) -> 9323.3605 | ... AM26: =SUM(AM20:AM25) -> 9095.9614 | AO26: =SUM(D26:O26) -> 114154.32 | AP26: =SUM(P26:AA26) -> 114154.32 | AQ26: =SUM(AB26:AM26) -> 114154.32
A27: Organic trend (pre-season) | B27: visits | D27: =IF(D6=1,Inputs!$B$20,C27*(1+Inputs!$B$21*Inputs!$B$22^(D6-1))) -> 2000 | E27: =IF(E6=1,Inputs!$B$20,D27*(1+Inputs!$B$21*Inputs!$B$22^(E6-1))) -> 2223.2 | F27: =IF(F6=1,Inputs!$B$20,E27*(1+Inputs!$B$21*Inputs!$B$22^(F6-1))) -> 2453.9415 | G27: =IF(G6=1,Inputs!$B$20,F27*(1+Inputs!$B$21*Inputs!$B$22^(G6-1))) -> 2690.8029 | H27: =IF(H6=1,Inputs!$B$20,G27*(1+Inputs!$B$21*Inputs!$B$22^(H6-1))) -> 2932.3461 | I27: =IF(I6=1,Inputs!$B$20,H27*(1+Inputs!$B$21*Inputs!$B$22^(I6-1))) -> 3177.146 | J27: =IF(J6=1,Inputs!$B$20,I27*(1+Inputs!$B$21*Inputs!$B$22^(J6-1))) -> 3423.8159 | K27: =IF(K6=1,Inputs!$B$20,J27*(1+Inputs!$B$21*Inputs!$B$22^(K6-1))) -> 3671.0295 | ... AM27: =IF(AM6=1,Inputs!$B$20,AL27*(1+Inputs!$B$21*Inputs!$B$22^(AM6-1))) -> 8315.411
A28: Organic visits | B28: visits | D28: =D27*D9*Scenarios!$B$7 -> 2600 | E28: =E27*E9*Scenarios!$B$7 -> 4224.08 | F28: =F27*F9*Scenarios!$B$7 -> 1717.759 | G28: =G27*G9*Scenarios!$B$7 -> 3498.0437 | H28: =H27*H9*Scenarios!$B$7 -> 2492.4942 | I28: =I27*I9*Scenarios!$B$7 -> 2859.4314 | J28: =J27*J9*Scenarios!$B$7 -> 4793.3423 | K28: =K27*K9*Scenarios!$B$7 -> 3854.5809 | ... AM28: =AM27*AM9*Scenarios!$B$7 -> 8315.411 | AO28: =SUM(D28:O28) -> 41941.111 | AP28: =SUM(P28:AA28) -> 77467.834 | AQ28: =SUM(AB28:AM28) -> 101322.88
A29: Referral visits (recipients of prior month's items) | B29: visits | D29: =C44*Inputs!$B$23*Scenarios!$B$7 -> 0 | E29: =D44*Inputs!$B$23*Scenarios!$B$7 -> 52.972285 | F29: =E44*Inputs!$B$23*Scenarios!$B$7 -> 92.396742 | G29: =F44*Inputs!$B$23*Scenarios!$B$7 -> 31.503928 | H29: =G44*Inputs!$B$23*Scenarios!$B$7 -> 63.329529 | I29: =H44*Inputs!$B$23*Scenarios!$B$7 -> 41.477662 | J29: =I44*Inputs!$B$23*Scenarios!$B$7 -> 45.663156 | K29: =J44*Inputs!$B$23*Scenarios!$B$7 -> 79.270032 | ... AM29: =AL44*Inputs!$B$23*Scenarios!$B$7 -> 114.78993 | AO29: =SUM(D29:O29) -> 627.82293 | AP29: =SUM(P29:AA29) -> 1058.9261 | AQ29: =SUM(AB29:AM29) -> 1457.328
A30: Total visits | B30: visits | D30: =D26+D28+D29 -> 13060.356 | E30: =E26+E28+E29 -> 17466.196 | F30: =F26+F28+F29 -> 9541.723 | G30: =G26+G28+G29 -> 13989.903 | H30: =H26+H28+H29 -> 10969.588 | I30: =I26+I28+I29 -> 11542.072 | J30: =J26+J28+J29 -> 15754.159 | K30: =K26+K28+K29 -> 13257.211 | ... AM30: =AM26+AM28+AM29 -> 17526.162 | AO30: =SUM(D30:O30) -> 156723.25 | AP30: =SUM(P30:AA30) -> 192681.08 | AQ30: =SUM(AB30:AM30) -> 216934.53
A31: FUNNEL
A32: Guest free previews (cost, no revenue) | B32: # | D32: =D30*Inputs!$B$15 -> 1959.0533 | E32: =E30*Inputs!$B$15 -> 2619.9295 | F32: =F30*Inputs!$B$15 -> 1431.2585 | G32: =G30*Inputs!$B$15 -> 2098.4855 | H32: =H30*Inputs!$B$15 -> 1645.4382 | I32: =I30*Inputs!$B$15 -> 1731.3109 | J32: =J30*Inputs!$B$15 -> 2363.1239 | K32: =K30*Inputs!$B$15 -> 1988.5817 | ... AM32: =AM30*Inputs!$B$15 -> 2628.9244 | AO32: =SUM(D32:O32) -> 23508.488 | AP32: =SUM(P32:AA32) -> 28902.161 | AQ32: =SUM(AB32:AM32) -> 32540.179
A33: Sign-ups from paid | B33: # | D33: =SUMPRODUCT(D20:D25,'Unit Economics'!$E$15:$E$20) -> 716.10873 | E33: =SUMPRODUCT(E20:E25,'Unit Economics'!$E$15:$E$20) -> 902.91971 | F33: =SUMPRODUCT(F20:F25,'Unit Economics'!$E$15:$E$20) -> 529.29776 | G33: =SUMPRODUCT(G20:G25,'Unit Economics'!$E$15:$E$20) -> 716.10873 | H33: =SUMPRODUCT(H20:H25,'Unit Economics'!$E$15:$E$20) -> 576.0005 | I33: =SUMPRODUCT(I20:I25,'Unit Economics'!$E$15:$E$20) -> 591.56808 | J33: =SUMPRODUCT(J20:J25,'Unit Economics'!$E$15:$E$20) -> 747.2439 | K33: =SUMPRODUCT(K20:K25,'Unit Economics'!$E$15:$E$20) -> 638.27083 | ... AM33: =SUMPRODUCT(AM20:AM25,'Unit Economics'!$E$15:$E$20) -> 622.70325 | AO33: =SUM(D33:O33) -> 7814.9258 | AP33: =SUM(P33:AA33) -> 7814.9258 | AQ33: =SUM(AB33:AM33) -> 7814.9258
A34: Sign-ups from organic + referral | B34: # | D34: =Inputs!$B$12*(D28+D29) -> 182 | E34: =Inputs!$B$12*(E28+E29) -> 299.39366 | F34: =Inputs!$B$12*(F28+F29) -> 126.7109 | G34: =Inputs!$B$12*(G28+G29) -> 247.06834 | H34: =Inputs!$B$12*(H28+H29) -> 178.90766 | I34: =Inputs!$B$12*(I28+I29) -> 203.06364 | J34: =Inputs!$B$12*(J28+J29) -> 338.73038 | K34: =Inputs!$B$12*(K28+K29) -> 275.36957 | ... AM34: =Inputs!$B$12*(AM28+AM29) -> 590.11407 | AO34: =SUM(D34:O34) -> 2979.8254 | AP34: =SUM(P34:AA34) -> 5496.8732 | AQ34: =SUM(AB34:AM34) -> 7194.6148
A35: Sign-ups | B35: # | D35: =D33+D34 -> 898.10873 | E35: =E33+E34 -> 1202.3134 | F35: =F33+F34 -> 656.00866 | G35: =G33+G34 -> 963.17707 | H35: =H33+H34 -> 754.90817 | I35: =I33+I34 -> 794.63172 | J35: =J33+J34 -> 1085.9743 | K35: =K33+K34 -> 913.6404 | ... AM35: =AM33+AM34 -> 1212.8173 | AO35: =SUM(D35:O35) -> 10794.751 | AP35: =SUM(P35:AA35) -> 13311.799 | AQ35: =SUM(AB35:AM35) -> 15009.541
A36: Creator starts | B36: # | D36: =D35*Inputs!$B$13 -> 538.86524 | E36: =E35*Inputs!$B$13 -> 721.38802 | F36: =F35*Inputs!$B$13 -> 393.6052 | G36: =G35*Inputs!$B$13 -> 577.90624 | H36: =H35*Inputs!$B$13 -> 452.9449 | I36: =I35*Inputs!$B$13 -> 476.77903 | J36: =J35*Inputs!$B$13 -> 651.58457 | K36: =K35*Inputs!$B$13 -> 548.18424 | ... AM36: =AM35*Inputs!$B$13 -> 727.69039 | AO36: =SUM(D36:O36) -> 6476.8507 | AP36: =SUM(P36:AA36) -> 7987.0794 | AQ36: =SUM(AB36:AM36) -> 9005.7243
A37: Conversion factor (scenario x season) | B37: x | D37: =Scenarios!$B$8*D10 -> 1.15 | E37: =Scenarios!$B$8*E10 -> 1.45 | F37: =Scenarios!$B$8*F10 -> 0.85 | G37: =Scenarios!$B$8*G10 -> 1.15 | H37: =Scenarios!$B$8*H10 -> 0.925 | I37: =Scenarios!$B$8*I10 -> 0.95 | J37: =Scenarios!$B$8*J10 -> 1.2 | K37: =Scenarios!$B$8*K10 -> 1.025 | ... AM37: =Scenarios!$B$8*AM10 -> 1 | AO37: =AVERAGE(D37:O37) -> 1.0458333 | AP37: =AVERAGE(P37:AA37) -> 1.0458333 | AQ37: =AVERAGE(AB37:AM37) -> 1.0458333
A38: New-customer orders from paid | B38: # | D38: =SUMPRODUCT(D20:D25,'Unit Economics'!$E$15:$E$20,Inputs!$H$57:$H$62)*D37 -> 122.14785 | E38: =SUMPRODUCT(E20:E25,'Unit Economics'!$E$15:$E$20,Inputs!$H$57:$H$62)*E37 -> 194.18969 | F38: =SUMPRODUCT(F20:F25,'Unit Economics'!$E$15:$E$20,Inputs!$H$57:$H$62)*F37 -> 66.731059 | G38: =SUMPRODUCT(G20:G25,'Unit Economics'!$E$15:$E$20,Inputs!$H$57:$H$62)*G37 -> 122.14785 | H38: =SUMPRODUCT(H20:H25,'Unit Economics'!$E$15:$E$20,Inputs!$H$57:$H$62)*H37 -> 79.02666 | I38: =SUMPRODUCT(I20:I25,'Unit Economics'!$E$15:$E$20,Inputs!$H$57:$H$62)*I37 -> 83.356097 | J38: =SUMPRODUCT(J20:J25,'Unit Economics'!$E$15:$E$20,Inputs!$H$57:$H$62)*J37 -> 133.00031 | K38: =SUMPRODUCT(K20:K25,'Unit Economics'!$E$15:$E$20,Inputs!$H$57:$H$62)*K37 -> 97.037119 | ... AM38: =SUMPRODUCT(AM20:AM25,'Unit Economics'!$E$15:$E$20,Inputs!$H$57:$H$62)*AM37 -> 92.361327 | AO38: =SUM(D38:O38) -> 1240.1817 | AP38: =SUM(P38:AA38) -> 1240.1817 | AQ38: =SUM(AB38:AM38) -> 1240.1817
A39: New-customer orders from organic + referral | B39: # | D39: =D34*Inputs!$B$13*Inputs!$B$14*D37 -> 31.395 | E39: =E34*Inputs!$B$13*Inputs!$B$14*E37 -> 65.118121 | F39: =F34*Inputs!$B$13*Inputs!$B$14*F37 -> 16.15564 | G39: =G34*Inputs!$B$13*Inputs!$B$14*G37 -> 42.619288 | H39: =H34*Inputs!$B$13*Inputs!$B$14*H37 -> 24.823438 | I39: =I34*Inputs!$B$13*Inputs!$B$14*I37 -> 28.936568 | J39: =J34*Inputs!$B$13*Inputs!$B$14*J37 -> 60.971468 | K39: =K34*Inputs!$B$13*Inputs!$B$14*K37 -> 42.338071 | ... AM39: =AM34*Inputs!$B$13*Inputs!$B$14*AM37 -> 88.51711 | AO39: =SUM(D39:O39) -> 475.87102 | AP39: =SUM(P39:AA39) -> 890.02788 | AQ39: =SUM(AB39:AM39) -> 1172.1111
A40: New-customer orders | B40: # | D40: =D38+D39 -> 153.54285 | E40: =E38+E39 -> 259.30781 | F40: =F38+F39 -> 82.886699 | G40: =G38+G39 -> 164.76714 | H40: =H38+H39 -> 103.8501 | I40: =I38+I39 -> 112.29267 | J40: =J38+J39 -> 193.97178 | K40: =K38+K39 -> 139.37519 | ... AM40: =AM38+AM39 -> 180.87844 | AO40: =SUM(D40:O40) -> 1716.0527 | AP40: =SUM(P40:AA40) -> 2130.2096 | AQ40: =SUM(AB40:AM40) -> 2412.2928
A41: Cumulative customers | B41: # | C41: 0 | D41: =C41+D40 -> 153.54285 | E41: =D41+E40 -> 412.85067 | F41: =E41+F40 -> 495.73736 | G41: =F41+G40 -> 660.50451 | H41: =G41+H40 -> 764.35461 | I41: =H41+I40 -> 876.64727 | J41: =I41+J40 -> 1070.6191 | K41: =J41+K40 -> 1209.9942 | ... AM41: =AL41+AM40 -> 6258.5551 | AO41: =O41 -> 1716.0527 | AP41: =AA41 -> 3846.2623 | AQ41: =AM41 -> 6258.5551
A42: Repeat orders | B42: # | D42: =C41*Inputs!$B$32/12*Scenarios!$B$9*D9 -> 0 | E42: =D41*Inputs!$B$32/12*Scenarios!$B$9*E9 -> 8.5088332 | F42: =E41*Inputs!$B$32/12*Scenarios!$B$9*F9 -> 8.4290344 | G42: =F41*Inputs!$B$32/12*Scenarios!$B$9*G9 -> 18.796708 | H42: =G41*Inputs!$B$32/12*Scenarios!$B$9*H9 -> 16.375008 | I42: =H41*Inputs!$B$32/12*Scenarios!$B$9*I9 -> 20.064308 | J42: =I41*Inputs!$B$32/12*Scenarios!$B$9*J9 -> 35.79643 | K42: =J41*Inputs!$B$32/12*Scenarios!$B$9*K9 -> 32.787708 | ... AM42: =AL41*Inputs!$B$32/12*Scenarios!$B$9*AM9 -> 177.26557 | AO42: =SUM(D42:O42) -> 291.36204 | AP42: =SUM(P42:AA42) -> 1025.5196 | AQ42: =SUM(AB42:AM42) -> 1895.974
A43: Total orders | B43: # | D43: =D40+D42 -> 153.54285 | E43: =E40+E42 -> 267.81664 | F43: =F40+F42 -> 91.315733 | G43: =G40+G42 -> 183.56385 | H43: =H40+H42 -> 120.22511 | I43: =I40+I42 -> 132.35697 | J43: =J40+J42 -> 229.76821 | K43: =K40+K42 -> 172.1629 | ... AM43: =AM40+AM42 -> 358.14401 | AO43: =SUM(D43:O43) -> 2007.4148 | AP43: =SUM(P43:AA43) -> 3155.7292 | AQ43: =SUM(AB43:AM43) -> 4308.2667
A44: Items sold | B44: # | C44: 0 | D44: =D43*Inputs!$B$9 -> 176.57428 | E44: =E43*Inputs!$B$9 -> 307.98914 | F44: =F43*Inputs!$B$9 -> 105.01309 | G44: =G43*Inputs!$B$9 -> 211.09843 | H44: =H43*Inputs!$B$9 -> 138.25887 | I44: =I43*Inputs!$B$9 -> 152.21052 | J44: =J43*Inputs!$B$9 -> 264.23344 | K44: =K43*Inputs!$B$9 -> 197.98733 | ... AM44: =AM43*Inputs!$B$9 -> 411.86561 | AO44: =SUM(D44:O44) -> 2308.527 | AP44: =SUM(P44:AA44) -> 3629.0886 | AQ44: =SUM(AB44:AM44) -> 4954.5068
A45: Visit -> new order conversion | B45: % | D45: =IFERROR(D40/D30,0) -> 0.011756407 | E45: =IFERROR(E40/E30,0) -> 0.014846267 | F45: =IFERROR(F40/F30,0) -> 0.0086867643 | G45: =IFERROR(G40/G30,0) -> 0.011777576 | H45: =IFERROR(H40/H30,0) -> 0.0094670919 | I45: =IFERROR(I40/I30,0) -> 0.0097289864 | J45: =IFERROR(J40/J30,0) -> 0.012312417 | K45: =IFERROR(K40/K30,0) -> 0.01051316 | ... AM45: =IFERROR(AM40/AM30,0) -> 0.010320482 | AO45: =IFERROR(AO40/AO30,0) -> 0.010949573 | AP45: =IFERROR(AP40/AP30,0) -> 0.011055624 | AQ45: =IFERROR(AQ40/AQ30,0) -> 0.011119912
A46: ITEMS BY SKU (product mix)
A47: =" Items - "&Inputs!A47 -> Items - Card - Digital e-card/PDF | B47: # | D47: =D44*Inputs!$G$47 -> 24.7204 | E47: =E44*Inputs!$G$47 -> 43.11848 | F47: =F44*Inputs!$G$47 -> 14.701833 | G47: =G44*Inputs!$G$47 -> 29.55378 | H47: =H44*Inputs!$G$47 -> 19.356242 | I47: =I44*Inputs!$G$47 -> 21.309473 | J47: =J44*Inputs!$G$47 -> 36.992682 | K47: =K44*Inputs!$G$47 -> 27.718227 | ... AM47: =AM44*Inputs!$G$47 -> 57.661185 | AO47: =SUM(D47:O47) -> 323.19378 | AP47: =SUM(P47:AA47) -> 508.0724 | AQ47: =SUM(AB47:AM47) -> 693.63095
A48: =" Items - "&Inputs!A48 -> Items - Card - Printed 5x7 folded | B48: # | D48: =D44*Inputs!$G$48 -> 70.629713 | E48: =E44*Inputs!$G$48 -> 123.19566 | F48: =F44*Inputs!$G$48 -> 42.005237 | G48: =G44*Inputs!$G$48 -> 84.439372 | H48: =H44*Inputs!$G$48 -> 55.303549 | I48: =I44*Inputs!$G$48 -> 60.884208 | J48: =J44*Inputs!$G$48 -> 105.69338 | K48: =K44*Inputs!$G$48 -> 79.194933 | ... AM48: =AM44*Inputs!$G$48 -> 164.74624 | AO48: =SUM(D48:O48) -> 923.41079 | AP48: =SUM(P48:AA48) -> 1451.6354 | AQ48: =SUM(AB48:AM48) -> 1981.8027
A49: =" Items - "&Inputs!A49 -> Items - Book - Digital flipbook/PDF | B49: # | D49: =D44*Inputs!$G$49 -> 14.125943 | E49: =E44*Inputs!$G$49 -> 24.639131 | F49: =F44*Inputs!$G$49 -> 8.4010475 | G49: =G44*Inputs!$G$49 -> 16.887874 | H49: =H44*Inputs!$G$49 -> 11.06071 | I49: =I44*Inputs!$G$49 -> 12.176842 | J49: =J44*Inputs!$G$49 -> 21.138675 | K49: =K44*Inputs!$G$49 -> 15.838987 | ... AM49: =AM44*Inputs!$G$49 -> 32.949249 | AO49: =SUM(D49:O49) -> 184.68216 | AP49: =SUM(P49:AA49) -> 290.32709 | AQ49: =SUM(AB49:AM49) -> 396.36054
A50: =" Items - "&Inputs!A50 -> Items - Book - Hardcover 8.5x8.5, 24pp | B50: # | D50: =D44*Inputs!$G$50 -> 26.486142 | E50: =E44*Inputs!$G$50 -> 46.198371 | F50: =F44*Inputs!$G$50 -> 15.751964 | G50: =G44*Inputs!$G$50 -> 31.664764 | H50: =H44*Inputs!$G$50 -> 20.738831 | I50: =I44*Inputs!$G$50 -> 22.831578 | J50: =J44*Inputs!$G$50 -> 39.635016 | K50: =K44*Inputs!$G$50 -> 29.6981 | ... AM50: =AM44*Inputs!$G$50 -> 61.779841 | AO50: =SUM(D50:O50) -> 346.27905 | AP50: =SUM(P50:AA50) -> 544.36328 | AQ50: =SUM(AB50:AM50) -> 743.17601
A51: =" Items - "&Inputs!A51 -> Items - Book - Hardcover 8.5x8.5, 32pp | B51: # | D51: =D44*Inputs!$G$51 -> 40.612085 | E51: =E44*Inputs!$G$51 -> 70.837502 | F51: =F44*Inputs!$G$51 -> 24.153011 | G51: =G44*Inputs!$G$51 -> 48.552639 | H51: =H44*Inputs!$G$51 -> 31.799541 | I51: =I44*Inputs!$G$51 -> 35.00842 | J51: =J44*Inputs!$G$51 -> 60.773691 | K51: =K44*Inputs!$G$51 -> 45.537087 | ... AM51: =AM44*Inputs!$G$51 -> 94.72909 | AO51: =SUM(D51:O51) -> 530.96121 | AP51: =SUM(P51:AA51) -> 834.69037 | AQ51: =SUM(AB51:AM51) -> 1139.5366
A52: REVENUE BY SKU (gross incl. postage)
A53: =" Revenue - "&Inputs!A47 -> Revenue - Card - Digital e-card/PDF | B53: $ | D53: =D47*'Unit Economics'!$D$5 -> 98.634394 | E53: =E47*'Unit Economics'!$D$5 -> 172.04273 | F53: =F47*'Unit Economics'!$D$5 -> 58.660314 | G53: =G47*'Unit Economics'!$D$5 -> 117.91958 | H53: =H47*'Unit Economics'!$D$5 -> 77.231406 | I53: =I47*'Unit Economics'!$D$5 -> 85.024797 | J53: =J47*'Unit Economics'!$D$5 -> 147.6008 | K53: =K47*'Unit Economics'!$D$5 -> 110.59572 | ... AM53: =AM47*'Unit Economics'!$D$5 -> 230.06813 | AO53: =SUM(D53:O53) -> 1289.5432 | AP53: =SUM(P53:AA53) -> 2027.2089 | AQ53: =SUM(AB53:AM53) -> 2767.5875
A54: =" Revenue - "&Inputs!A48 -> Revenue - Card - Printed 5x7 folded | B54: $ | D54: =D48*'Unit Economics'!$D$6 -> 754.39597 | E54: =E48*'Unit Economics'!$D$6 -> 1315.8528 | F54: =F48*'Unit Economics'!$D$6 -> 448.65794 | G54: =G48*'Unit Economics'!$D$6 -> 901.89693 | H54: =H48*'Unit Economics'!$D$6 -> 590.6972 | I54: =I48*'Unit Economics'!$D$6 -> 650.30423 | J54: =J48*'Unit Economics'!$D$6 -> 1128.911 | K54: =K48*'Unit Economics'!$D$6 -> 845.88108 | ... AM54: =AM48*'Unit Economics'!$D$6 -> 1759.6546 | AO54: =SUM(D54:O54) -> 9862.9507 | AP54: =SUM(P54:AA54) -> 15504.918 | AQ54: =SUM(AB54:AM54) -> 21167.635
A55: =" Revenue - "&Inputs!A49 -> Revenue - Book - Digital flipbook/PDF | B55: $ | D55: =D49*'Unit Economics'!$D$7 -> 282.37759 | E55: =E49*'Unit Economics'!$D$7 -> 492.53623 | F55: =F49*'Unit Economics'!$D$7 -> 167.93694 | G55: =G49*'Unit Economics'!$D$7 -> 337.58861 | H55: =H49*'Unit Economics'!$D$7 -> 221.10359 | I55: =I49*'Unit Economics'!$D$7 -> 243.41506 | J55: =J49*'Unit Economics'!$D$7 -> 422.56212 | K55: =K49*'Unit Economics'!$D$7 -> 316.62134 | ... AM55: =AM49*'Unit Economics'!$D$7 -> 658.65548 | AO55: =SUM(D55:O55) -> 3691.7964 | AP55: =SUM(P55:AA55) -> 5803.6384 | AQ55: =SUM(AB55:AM55) -> 7923.2472
A56: =" Revenue - "&Inputs!A50 -> Revenue - Book - Hardcover 8.5x8.5, 24pp | B56: $ | D56: =D50*'Unit Economics'!$D$8 -> 1175.7463 | E56: =E50*'Unit Economics'!$D$8 -> 2050.7919 | F56: =F50*'Unit Economics'!$D$8 -> 699.24543 | G56: =G50*'Unit Economics'!$D$8 -> 1405.6306 | H56: =H50*'Unit Economics'!$D$8 -> 920.61744 | I56: =I50*'Unit Economics'!$D$8 -> 1013.5166 | J56: =J50*'Unit Economics'!$D$8 -> 1759.438 | K56: =K50*'Unit Economics'!$D$8 -> 1318.3284 | ... AM56: =AM50*'Unit Economics'!$D$8 -> 2742.4689 | AO56: =SUM(D56:O56) -> 15371.673 | AP56: =SUM(P56:AA56) -> 24164.831 | AQ56: =SUM(AB56:AM56) -> 32990.326
A57: =" Revenue - "&Inputs!A51 -> Revenue - Book - Hardcover 8.5x8.5, 32pp | B57: $ | D57: =D51*'Unit Economics'!$D$9 -> 2208.9319 | E57: =E51*'Unit Economics'!$D$9 -> 3852.9226 | F57: =F51*'Unit Economics'!$D$9 -> 1313.7064 | G57: =G51*'Unit Economics'!$D$9 -> 2640.8266 | H57: =H51*'Unit Economics'!$D$9 -> 1729.6088 | I57: =I51*'Unit Economics'!$D$9 -> 1904.143 | J57: =J51*'Unit Economics'!$D$9 -> 3305.5418 | K57: =K51*'Unit Economics'!$D$9 -> 2476.8077 | ... AM57: =AM51*'Unit Economics'!$D$9 -> 5152.4099 | AO57: =SUM(D57:O57) -> 28879.511 | AP57: =SUM(P57:AA57) -> 45399.644 | AQ57: =SUM(AB57:AM57) -> 61980.533
