Workbook

Sheet Inputs
A1: GreetHub - Inputs (all business assumptions live here)
A2: Blue = input you can edit. Black = formula. Yellow fill = slot reserved for CMO/CTO data. Status: SOURCED / ESTIMATE / GUESS. Printer prices are ESTIMATES to verify against live Lulu / Prodigi / Gelato price sheets.
A3: Legend: | B3: Input | C3: Formula | D3: CMO / CTO data
A5: 1. General
A6: Assumption | B6: Value | C6: Unit | D6: Status | E6: Sensible range | F6: Notes / source
A7: Launch month (month 1) | B7: 46327 | C7: date | D7: SOURCED | E7: any | F7: CMO launch assumption: November 2026. Drives seasonality alignment.
A8: Opening cash (founder capital) | B8: 30000 | C8: $ | D8: GUESS | E8: $10k-100k | F8: Starting cash balance; also sets funding need.
A9: Items per paid order | B9: 1.15 | C9: items | D9: GUESS | E9: 1.0-1.5 | F9: Card+book bundles; Stripe $0.30 is per order, not per item.
A10: 2. Funnel (visitor -> sign-up -> creator start -> purchase)
A11: Assumption | B11: Value | C11: Unit | D11: Status | E11: Sensible range | F11: Notes / source
A12: Organic/referral visitor -> sign-up rate | B12: 0.07 | C12: % of visits | D12: GUESS | E12: 3%-12% | F12: Paid channels use per-channel CMO rates in section 7. Matches CMO range (4-9%).
A13: Sign-up -> creator start rate (all sources) | B13: 0.6 | C13: % of sign-ups | D13: GUESS | E13: 40%-80% | F13: Sign-ups who begin a brief; drives token cost of unpaid starts.
A14: Organic: creator start -> purchase rate | B14: 0.25 | C14: % of starts | D14: GUESS | E14: 12%-40% | F14: 0.60 x 0.25 = 15% sign-up -> purchase, in line with CMO channel rates (9-20%). Paid channels use CMO signup->purchase directly.
A15: Share of visitors who run a free guest preview | B15: 0.15 | C15: % of visits | D15: GUESS | E15: 5%-30% | F15: Guest previews cost tokens and earn no revenue (cost line in Forecast).
A16: Seasonality sensitivity of purchase conversion | B16: 0.5 | C16: 0-1 | D16: GUESS | E16: 0-1 | F16: 0 = season only changes traffic; 1 = conversion moves fully with season index.
A17: Token cost incurred before an unpaid creator start abandons | B17: 0.35 | C17: % of full cost | D17: ESTIMATE | E17: 20%-60% | F17: The model-sheet approval gate caps waste (PLAN.md).
A18: 3. Traffic
A19: Assumption | B19: Value | C19: Unit | D19: Status | E19: Sensible range | F19: Notes / source
A20: Organic visits, month 1 (before seasonality) | B20: 2000 | C20: visits | D20: GUESS | E20: 500-8,000 | F20: Brand/social/referral at launch.
A21: Organic monthly growth, month 2 | B21: 0.12 | C21: % / mo | D21: GUESS | E21: 5%-20% | F21: Compounds, then decays (next row).
A22: Organic growth decay factor per month | B22: 0.93 | C22: x | D22: GUESS | E22: 0.88-0.98 | F22: growth_t = g x decay^(t-1). 0.93 -> ~5x organic by month 36.
A23: Recipient referral visits per item sold (prior month) | B23: 0.3 | C23: visits/item | D23: GUESS | E23: 0.1-0.8 | F23: Card/book recipients open the 'made with GreetHub' link.
A24: 4. Marketing budget (paid visits = budget / CPC)
A25: Assumption | B25: Value | C25: Unit | D25: Status | E25: Sensible range | F25: Notes / source
A26: Monthly marketing budget, month 1 | B26: =SUM(B57:B62) | C26: $ / mo | D26: SOURCED | E26: $1k-15k | F26: Sum of CMO channel budgets (section 7), $6.5k/mo = $19.5k per 90 days. Overwrite with a number to test.
A27: Budget monthly growth | B27: 0 | C27: % / mo | D27: GUESS | E27: 0%-10% | F27: Compounds until cap. Growth only pays if contribution per order beats CAC.
A28: Budget cap | B28: 20000 | C28: $ / mo | D28: GUESS | E28: $5k-100k | F28: Ceiling on base monthly budget.
A29: Budget follows season index | B29: 0.5 | C29: 0-1 | D29: GUESS | E29: 0-1 | F29: 1 = budget scales fully with season index.
A30: 5. Repeat, refunds, re-rolls, payments
A31: Assumption | B31: Value | C31: Unit | D31: Status | E31: Sensible range | F31: Notes / source
A32: Repeat orders per existing customer per year | B32: 0.35 | C32: orders/yr | D32: GUESS | E32: 0.15-0.8 | F32: Occasion-driven; applied to cumulative customers.
A33: Customer lifetime used for LTV | B33: 2 | C33: years | D33: GUESS | E33: 1-3 | F33: LTV = contribution per order x (1 + repeat x lifetime).
A34: Re-roll rate, cards (extra renders over base) | B34: 0.35 | C34: % of renders | D34: ESTIMATE | E34: 15%-60% | F34: Includes auto-QA retries.
A35: Re-roll rate, books (extra renders over base) | B35: 0.12 | C35: % of renders | D35: ESTIMATE | E35: 5%-30% | F35: Eye Story: ~16 renders incl. reroll allowance for a 14-page book.
A36: Refund rate (share of revenue refunded) | B36: 0.03 | C36: % of revenue | D36: GUESS | E36: 1%-6% | F36: Token cost is sunk on refund.
A37: Reprint rate (printed items reshipped) | B37: 0.04 | C37: % of printed | D37: GUESS | E37: 2%-8% | F37: Print defects, transit damage. Costs print + shipping again.
A38: Chargeback rate | B38: 0.003 | C38: % of orders | D38: ESTIMATE | E38: 0.1%-1%
A39: Chargeback fee | B39: 15 | C39: $ / dispute | D39: SOURCED | E39: $15 | F39: Stripe dispute fee (US) - verify.
A40: Stripe fee, percentage | B40: 0.029 | C40: % of charge | D40: SOURCED | E40: 2.9% | F40: Owner brief / Stripe standard US card rate.
A41: Stripe fee, fixed | B41: 0.3 | C41: $ / order | D41: SOURCED | E41: $0.30 | F41: Owner brief / Stripe standard US card rate.
A42: OpenRouter credit-purchase fee on token spend | B42: 0.055 | C42: % of tokens | D42: ESTIMATE | E42: 0-8% | F42: OpenRouter charges a fee when buying credits - verify.
A43: Share of printed items where postage fee is charged | B43: 0.9 | C43: % of printed | D43: GUESS | E43: 50%-100% | F43: Rest = free-shipping promos.
A45: 6. SKU table: launch prices, mix, print and shipping costs (ESTIMATES - verify against live printer price sheets)
A46: SKU | B46: Product line | C46: Format | D46: Printed? (1/0) | E46: List price ($) | F46: Postage fee charged ($) | G46: Mix (% of items) | H46: Print cost est. ($) | I46: Shipping cost est. ($) | J46: Fulfilment partner | K46: Pricing reasoning
A47: Card - Digital e-card/PDF | B47: Card | C47: Digital | D47: 0 | E47: 3.99 | F47: 0 | G47: 0.14 | H47: 0 | I47: 0 | J47: None (instant delivery) | K47: Impulse price; near-pure margin, upsell path to print.
A48: Card - Printed 5x7 folded | B48: Card | C48: Printed | D48: 1 | E48: 7.99 | F48: 2.99 | G48: 0.4 | H48: 3.25 | I48: 1.6 | J48: Prodigi / Gelato | K48: Retail premium cards sell $5-8; personalised justifies the top. Postage option $2.99 covers ~2x shipping cost.
A49: Book - Digital flipbook/PDF | B49: Book | C49: Digital | D49: 0 | E49: 19.99 | F49: 0 | G49: 0.08 | H49: 0 | I49: 0 | J49: None (instant delivery) | K49: Anchors printed price at about half.
A50: Book - Hardcover 8.5x8.5, 24pp | B50: Book | C50: Printed | D50: 1 | E50: 39 | F50: 5.99 | G50: 0.15 | H50: 12.5 | I50: 5.5 | J50: Lulu | K50: Personalised hardcovers sell ~$35-45. Lulu 24pp casewrap est ~$12.50.
A51: Book - Hardcover 8.5x8.5, 32pp | B51: Book | C51: Printed | D51: 1 | E51: 49 | F51: 5.99 | G51: 0.23 | H51: 14.5 | I51: 6 | J51: Lulu | K51: +8 pages: +$2 print, +4 renders (~$0.5); +$10 price keeps margin %.
A52: Mix check (must equal 100%) | G52: =SUM(G47:G51) | H52: =IF(ABS(G52-1)<0.0001,"OK","MIX MUST SUM TO 100%")
A53: Print/shipping costs are ESTIMATES from memory of public Lulu / Prodigi / Gelato calculators for US delivery. Verify on live sheets before launch. CMO copy tokens: {card_digital}, {card_printed}, {book_digital}, {book_24}, {book_32} map to the list prices above.
A55: 7. Marketing channels - from docs/cmo/channel-assumptions.csv (CMO; every value is a labelled GUESS). Paste new rows over these.
A56: Channel | B56: Monthly budget base ($) | C56: CPC low | D56: CPC base | E56: CPC high | F56: CTR base | G56: Visitor -> sign-up | H56: Sign-up -> purchase | I56: CAC base (formula) | J56: Budget share (formula)
A57: meta_instagram_ads | B57: 2000 | C57: 0.55 | D57: 0.85 | E57: 1.4 | F57: 0.011 | G57: 0.07 | H57: 0.14 | I57: =IFERROR(D57/(G57*H57),0) | J57: =B57/SUM($B$57:$B$62)
A58: pinterest_ads | B58: 800 | C58: 0.3 | D58: 0.55 | E58: 0.95 | F58: 0.006 | G58: 0.06 | H58: 0.15 | I58: =IFERROR(D58/(G58*H58),0) | J58: =B58/SUM($B$57:$B$62)
A59: google_search | B59: 1500 | C59: 0.9 | D59: 1.6 | E59: 2.8 | F59: 0.045 | G59: 0.09 | H59: 0.2 | I59: =IFERROR(D59/(G59*H59),0) | J59: =B59/SUM($B$57:$B$62)
A60: tiktok_ads | B60: 600 | C60: 0.3 | D60: 0.6 | E60: 1.1 | F60: 0.008 | G60: 0.04 | H60: 0.09 | I60: =IFERROR(D60/(G60*H60),0) | J60: =B60/SUM($B$57:$B$62)
A61: creators_affiliate | B61: 1000 | C61: 0.7 | D61: 1.2 | E61: 2.2 | F61: 0.02 | G61: 0.08 | H61: 0.16 | I61: =IFERROR(D61/(G61*H61),0) | J61: =B61/SUM($B$57:$B$62)
A62: occasion_seo_content | B62: 600 | C62: 0.2 | D62: 0.35 | E62: 0.7 | F62: 0.03 | G62: 0.07 | H62: 0.15 | I62: =IFERROR(D62/(G62*H62),0) | J62: =B62/SUM($B$57:$B$62)
A63: Total / check | B63: =SUM(B57:B62) | J63: =SUM(J57:J62)
A64: Scenario: Low uses CPC high, Base uses CPC base, High uses CPC low. Channel conversion held constant across scenarios except the conversion lever. CMO notes: blended CAC ~$76 at base; SEO ~$33, TikTok ~$167. Sensible ranges: CPC $0.2-3.0; sign-up 3-10%; sign-up->purchase 8-20%.
A66: 8. Seasonality index by calendar month (1.00 = average; birthdays steady underneath)
A67: Calendar month | B67: Index | C67: Driver
A68: Jan | B68: 0.7 | C68: Post-holiday trough; birthdays only
A69: Feb | B69: 1.3 | C69: Valentine's Day
A70: Mar | B70: 0.85 | C70: Birthdays; Easter lead
A71: Apr | B71: 0.9 | C71: Easter / spring
A72: May | B72: 1.4 | C72: Mother's Day
A73: Jun | B73: 1.05 | C73: Father's Day, graduations, weddings
A74: Jul | B74: 0.85 | C74: Summer trough
A75: Aug | B75: 0.9 | C75: Back to school
A76: Sep | B76: 0.95 | C76: Grandparents Day, holiday SEO build
A77: Oct | B77: 1 | C77: Halloween, holiday lead
A78: Nov | B78: 1.3 | C78: Holiday shopping starts
A79: Dec | B79: 1.9 | C79: Christmas (print cutoffs ~Dec 15)
A80: Average index | B80: =AVERAGE(B68:B79)
A82: 9. Scenario levers (selector on the Scenarios sheet picks a column). CPC scenarios come from the CMO low/base/high CPC columns.
A83: Lever | B83: Applies to | C83: Low | D83: Base | E83: High | F83: Notes
A84: Organic traffic multiplier | B84: organic + referral visits | C84: 0.6 | D84: 1 | E84: 1.5 | F84: GUESS
A85: Purchase conversion multiplier | B85: sign-up/start -> purchase | C85: 0.7 | D85: 1 | E85: 1.3 | F85: GUESS
A86: Repeat purchase multiplier | B86: repeat orders | C86: 0.6 | D86: 1 | E86: 1.4 | F86: GUESS
A87: Token cost multiplier | B87: all model costs | C87: 1.4 | D87: 1 | E87: 0.85 | F87: GUESS
A88: Refund / reprint multiplier | B88: refund and reprint rates | C88: 1.5 | D88: 1 | E88: 0.7 | F88: GUESS
A89: Marketing budget multiplier | B89: monthly budget | C89: 1 | D89: 1 | E89: 1 | F89: GUESS
A90: Print + shipping cost multiplier | B90: printer and carrier costs | C90: 1.1 | D90: 1 | E90: 0.95 | F90: GUESS
A92: 10. Operating costs (monthly). Cost = fixed + variable per 1,000 units of driver
A93: Opex line | B93: Fixed ($/mo) | C93: Variable ($ per 1,000 units) | D93: Driver code (1 visits, 2 sign-ups, 3 orders, 4 revenue $) | E93: Status | F93: Basis
A94: Vercel (Pro) | B94: 20 | C94: 0.5 | D94: 1 | E94: ESTIMATE | F94: Pro $20/seat; bandwidth overage grows with visits - verify plan.
A95: Supabase (Pro + compute) | B95: 35 | C95: 20 | D95: 2 | E95: ESTIMATE | F95: Pro $25 + small compute add-on; storage grows with sign-ups.
A96: Resend (email) | B96: 20 | C96: 0.5 | D96: 3 | E96: ESTIMATE | F96: Pro plan $20 up to 50k emails.
A97: Domain | B97: 1.67 | C97: 0 | D97: 1 | E97: ESTIMATE | F97: ~$20/yr amortised.
A98: Stripe Tax | B98: 0 | C98: 3 | D98: 4 | E98: ESTIMATE | F98: 0.5% per transaction x ~60% of sales in registered states = $3 per $1,000. Tax collected is pass-through.
A99: Monitoring (Sentry + uptime) | B99: 26 | C99: 0 | D99: 1 | E99: ESTIMATE | F99: Sentry Team ~$26.
A100: OpenRouter base (dev/QA/pipeline testing) | B100: 75 | C100: 0 | D100: 1 | E100: GUESS | F100: Non-customer token spend: regression tests, prompt tuning.
A101: Design and dev tools | B101: 40 | C101: 0 | D101: 1 | E101: GUESS | F101: Figma, fonts, misc SaaS.
A102: Legal / LLC upkeep and accounting | B102: 150 | C102: 0 | D102: 1 | E102: GUESS | F102: Registered agent, bookkeeping, annual report amortised.
A103: Insurance (GL + cyber) | B103: 95 | C103: 0 | D103: 1 | E103: GUESS | F103: Small-business package; quote needed.
A104: Support (helpdesk + hourly help) | B104: 25 | C104: 900 | D104: 3 | E104: GUESS | F104: Helpdesk $25 + ~$0.90 of support labour per order.
A105: Founder / contractor pay (optional) | B105: 0 | C105: 0 | D105: 1 | E105: GUESS | F105: Zero by default; enter pay to see a sustainable-business break-even.
A107: 11. One-time launch costs (charged in month 1)
...

Sheet Unit Economics
A1: Unit Economics - contribution margin per item by SKU (selected scenario)
A2: Per item, single-item order basis. Print/shipping are ESTIMATES. Token cost includes scenario multiplier and OpenRouter fee. Stripe fixed fee spread over items per order.
A4: SKU | B4: List price | C4: Postage revenue | D4: Gross revenue | E4: Refund allowance | F4: Net revenue | G4: Token cost | H4: Print cost | I4: Shipping cost | J4: Reprint allowance | K4: Stripe fee | L4: Dispute allowance | M4: Total variable cost | N4: Contribution margin $ | O4: Contribution margin %
A5: =Inputs!A47 | B5: =Inputs!E47 | C5: =Inputs!F47*Inputs!D47*Inputs!$B$43 | D5: =B5+C5 | E5: =D5*Inputs!$B$36*Scenarios!$B$11 | F5: =D5-E5 | G5: ='Model Costs'!J27*Scenarios!$B$10*(1+Inputs!$B$42) | H5: =Inputs!H47*Inputs!D47*Scenarios!$B$13 | I5: =Inputs!I47*Inputs!D47*Scenarios!$B$13 | J5: =(H5+I5)*Inputs!$B$37*Scenarios!$B$11 | K5: =D5*Inputs!$B$40+Inputs!$B$41/Inputs!$B$9 | L5: =Inputs!$B$38*Inputs!$B$39/Inputs!$B$9 | M5: =SUM(G5:L5) | N5: =F5-M5 | O5: =IFERROR(N5/F5,0)
A6: =Inputs!A48 | B6: =Inputs!E48 | C6: =Inputs!F48*Inputs!D48*Inputs!$B$43 | D6: =B6+C6 | E6: =D6*Inputs!$B$36*Scenarios!$B$11 | F6: =D6-E6 | G6: ='Model Costs'!J28*Scenarios!$B$10*(1+Inputs!$B$42) | H6: =Inputs!H48*Inputs!D48*Scenarios!$B$13 | I6: =Inputs!I48*Inputs!D48*Scenarios!$B$13 | J6: =(H6+I6)*Inputs!$B$37*Scenarios!$B$11 | K6: =D6*Inputs!$B$40+Inputs!$B$41/Inputs!$B$9 | L6: =Inputs!$B$38*Inputs!$B$39/Inputs!$B$9 | M6: =SUM(G6:L6) | N6: =F6-M6 | O6: =IFERROR(N6/F6,0)
A7: =Inputs!A49 | B7: =Inputs!E49 | C7: =Inputs!F49*Inputs!D49*Inputs!$B$43 | D7: =B7+C7 | E7: =D7*Inputs!$B$36*Scenarios!$B$11 | F7: =D7-E7 | G7: ='Model Costs'!J29*Scenarios!$B$10*(1+Inputs!$B$42) | H7: =Inputs!H49*Inputs!D49*Scenarios!$B$13 | I7: =Inputs!I49*Inputs!D49*Scenarios!$B$13 | J7: =(H7+I7)*Inputs!$B$37*Scenarios!$B$11 | K7: =D7*Inputs!$B$40+Inputs!$B$41/Inputs!$B$9 | L7: =Inputs!$B$38*Inputs!$B$39/Inputs!$B$9 | M7: =SUM(G7:L7) | N7: =F7-M7 | O7: =IFERROR(N7/F7,0)
A8: =Inputs!A50 | B8: =Inputs!E50 | C8: =Inputs!F50*Inputs!D50*Inputs!$B$43 | D8: =B8+C8 | E8: =D8*Inputs!$B$36*Scenarios!$B$11 | F8: =D8-E8 | G8: ='Model Costs'!J30*Scenarios!$B$10*(1+Inputs!$B$42) | H8: =Inputs!H50*Inputs!D50*Scenarios!$B$13 | I8: =Inputs!I50*Inputs!D50*Scenarios!$B$13 | J8: =(H8+I8)*Inputs!$B$37*Scenarios!$B$11 | K8: =D8*Inputs!$B$40+Inputs!$B$41/Inputs!$B$9 | L8: =Inputs!$B$38*Inputs!$B$39/Inputs!$B$9 | M8: =SUM(G8:L8) | N8: =F8-M8 | O8: =IFERROR(N8/F8,0)
A9: =Inputs!A51 | B9: =Inputs!E51 | C9: =Inputs!F51*Inputs!D51*Inputs!$B$43 | D9: =B9+C9 | E9: =D9*Inputs!$B$36*Scenarios!$B$11 | F9: =D9-E9 | G9: ='Model Costs'!J31*Scenarios!$B$10*(1+Inputs!$B$42) | H9: =Inputs!H51*Inputs!D51*Scenarios!$B$13 | I9: =Inputs!I51*Inputs!D51*Scenarios!$B$13 | J9: =(H9+I9)*Inputs!$B$37*Scenarios!$B$11 | K9: =D9*Inputs!$B$40+Inputs!$B$41/Inputs!$B$9 | L9: =Inputs!$B$38*Inputs!$B$39/Inputs!$B$9 | M9: =SUM(G9:L9) | N9: =F9-M9 | O9: =IFERROR(N9/F9,0)
A10: Blended (mix-weighted) per item | B10: =SUMPRODUCT(Inputs!$G$47:$G$51,B5:B9) | C10: =SUMPRODUCT(Inputs!$G$47:$G$51,C5:C9) | D10: =SUMPRODUCT(Inputs!$G$47:$G$51,D5:D9) | E10: =SUMPRODUCT(Inputs!$G$47:$G$51,E5:E9) | F10: =SUMPRODUCT(Inputs!$G$47:$G$51,F5:F9) | G10: =SUMPRODUCT(Inputs!$G$47:$G$51,G5:G9) | H10: =SUMPRODUCT(Inputs!$G$47:$G$51,H5:H9) | I10: =SUMPRODUCT(Inputs!$G$47:$G$51,I5:I9) | ... N10: =SUMPRODUCT(Inputs!$G$47:$G$51,N5:N9) | O10: =IFERROR(N10/F10,0)
A13: Paid channels in the selected scenario (CPC: Low scenario = CMO high CPC, High scenario = CMO low CPC)
A14: Channel | B14: Budget share | C14: Active CPC ($) | D14: CTR | E14: Visitor -> sign-up | F14: Sign-up -> purchase | G14: CAC ($ per customer) | H14: Visitor -> customer | I14: Orders to repay CAC
A15: =Inputs!A57 | B15: =Inputs!J57 | C15: =INDEX(Inputs!$C$57:$E$57,4-Scenarios!$B$4) | D15: =Inputs!F57 | E15: =Inputs!G57 | F15: =Inputs!H57*Scenarios!$B$8 | G15: =IFERROR(C15/(E15*F15),0) | H15: =E15*F15 | I15: =IFERROR(G15/$N$10/Inputs!$B$9,0)
A16: =Inputs!A58 | B16: =Inputs!J58 | C16: =INDEX(Inputs!$C$58:$E$58,4-Scenarios!$B$4) | D16: =Inputs!F58 | E16: =Inputs!G58 | F16: =Inputs!H58*Scenarios!$B$8 | G16: =IFERROR(C16/(E16*F16),0) | H16: =E16*F16 | I16: =IFERROR(G16/$N$10/Inputs!$B$9,0)
A17: =Inputs!A59 | B17: =Inputs!J59 | C17: =INDEX(Inputs!$C$59:$E$59,4-Scenarios!$B$4) | D17: =Inputs!F59 | E17: =Inputs!G59 | F17: =Inputs!H59*Scenarios!$B$8 | G17: =IFERROR(C17/(E17*F17),0) | H17: =E17*F17 | I17: =IFERROR(G17/$N$10/Inputs!$B$9,0)
A18: =Inputs!A60 | B18: =Inputs!J60 | C18: =INDEX(Inputs!$C$60:$E$60,4-Scenarios!$B$4) | D18: =Inputs!F60 | E18: =Inputs!G60 | F18: =Inputs!H60*Scenarios!$B$8 | G18: =IFERROR(C18/(E18*F18),0) | H18: =E18*F18 | I18: =IFERROR(G18/$N$10/Inputs!$B$9,0)
A19: =Inputs!A61 | B19: =Inputs!J61 | C19: =INDEX(Inputs!$C$61:$E$61,4-Scenarios!$B$4) | D19: =Inputs!F61 | E19: =Inputs!G61 | F19: =Inputs!H61*Scenarios!$B$8 | G19: =IFERROR(C19/(E19*F19),0) | H19: =E19*F19 | I19: =IFERROR(G19/$N$10/Inputs!$B$9,0)
A20: =Inputs!A62 | B20: =Inputs!J62 | C20: =INDEX(Inputs!$C$62:$E$62,4-Scenarios!$B$4) | D20: =Inputs!F62 | E20: =Inputs!G62 | F20: =Inputs!H62*Scenarios!$B$8 | G20: =IFERROR(C20/(E20*F20),0) | H20: =E20*F20 | I20: =IFERROR(G20/$N$10/Inputs!$B$9,0)
A22: Customer acquisition vs lifetime value
A23: Blended contribution margin per order ($) | B23: =N10*Inputs!$B$9 | C23: Before marketing and opex
A24: Expected orders per customer over lifetime | B24: =1+Inputs!$B$32*Inputs!$B$33*Scenarios!$B$9 | C24: 1 + repeat/yr x lifetime yrs x scenario
A25: Lifetime value per customer (contribution, $) | B25: =$B$23*$B$24 | C25: Undiscounted
A26: Paid visits per $ of budget | B26: =SUMPRODUCT(B15:B20/C15:C20) | C26: Budget / CPC, share-weighted
A27: New paid customers per $ of budget | B27: =SUMPRODUCT(B15:B20/C15:C20*H15:H20)
A28: Paid CAC, steady state ($ per new customer) | B28: =IFERROR(1/$B$27,0) | C28: Paid channels only; organic customers cost $0
A29: Orders needed to repay paid CAC | B29: =IFERROR($B$28/$B$23,0)

Sheet Model Costs
A1: Model Costs - token and render cost per product
A2: Blue = ESTIMATE input. Yellow = paste CTO measured values from finance/measured_costs.json (blank = use estimate). Active = measured if present, else estimate. Exception to 'inputs only on Inputs': the CTO swap-in slots live here by owner request.
A4: Unit price | B4: Estimate | C4: Measured (CTO paste) | D4: Active | E4: Unit | F4: Source
A5: Image render, 4K print page (Gemini image via OpenRouter) | B5: 0.11 | D5: =IF(ISNUMBER(C5),C5,B5) | E5: $ / render | F5: Eye Story build: ~30 renders = $3.50 (~$0.117). Owner: ~$0.11.
A6: Image render, guest preview (low-res, watermarked) | B6: 0.04 | D6: =IF(ISNUMBER(C6),C6,B6) | E6: $ / render | F6: GUESS: 1K render cheaper than 4K.
A7: Vision QA check (cheap model) per render | B7: 0.003 | D7: =IF(ISNUMBER(C7),C7,B7) | E7: $ / call | F7: GUESS; PLAN.md stage 6.
A8: Claude Sonnet input | B8: 3 | D8: =IF(ISNUMBER(C8),C8,B8) | E8: $ / M tokens | F8: Anthropic list price - verify.
A9: Claude Sonnet output | B9: 15 | D9: =IF(ISNUMBER(C9),C9,B9) | E9: $ / M tokens | F9: Anthropic list price - verify.
A11: Text calls (Claude Sonnet): tokens per call, then cost per call
A12: Call type | B12: Intake chat (card) | C12: Intake chat (book) | D12: Story writer (book) | E12: Identity sheet (vision) | F12: Art-director page prompts (book) | G12: Card prompts + message | H12: Guest intake (mini)
A13: Input tokens / call (ESTIMATE) | B13: 14000 | C13: 22000 | D13: 4000 | E13: 6000 | F13: 12000 | G13: 4500 | H13: 6000
A14: Output tokens / call (ESTIMATE) | B14: 1800 | C14: 2500 | D14: 2500 | E14: 900 | F14: 6000 | G14: 1300 | H14: 800
A15: Cost per call ($) | B15: =B13/1000000*$D$8+B14/1000000*$D$9 | C15: =C13/1000000*$D$8+C14/1000000*$D$9 | D15: =D13/1000000*$D$8+D14/1000000*$D$9 | E15: =E13/1000000*$D$8+E14/1000000*$D$9 | F15: =F13/1000000*$D$8+F14/1000000*$D$9 | G15: =G13/1000000*$D$8+G14/1000000*$D$9 | H15: =H13/1000000*$D$8+H14/1000000*$D$9
A17: Calls per SKU (count of each call type; ESTIMATE)
A18: SKU | B18: Intake chat (card) | C18: Intake chat (book) | D18: Story writer (book) | E18: Identity sheet (vision) | F18: Art-director page prompts (book) | G18: Card prompts + message | H18: Guest intake (mini)
A19: =Inputs!A47 | B19: 1 | C19: 0 | D19: 0 | E19: 0 | F19: 0 | G19: 1 | H19: 0
A20: =Inputs!A48 | B20: 1 | C20: 0 | D20: 0 | E20: 0 | F20: 0 | G20: 1 | H20: 0
A21: =Inputs!A49 | B21: 0 | C21: 1 | D21: 1 | E21: 1 | F21: 1 | G21: 0 | H21: 0
A22: =Inputs!A50 | B22: 0 | C22: 1 | D22: 1 | E22: 1 | F22: 1 | G22: 0 | H22: 0
A23: =Inputs!A51 | B23: 0 | C23: 1 | D23: 1 | E23: 1 | F23: 1.3 | G23: 0 | H23: 0
A25: Token cost per SKU (before scenario multiplier and OpenRouter fee)
A26: SKU | B26: Base renders (ESTIMATE) | C26: Re-roll rate | D26: Effective renders | E26: Render $ | F26: QA $ | G26: Text (Sonnet) $ | H26: Computed total $ | I26: Measured total $ (CTO paste) | J26: Token cost used $
A27: =Inputs!A47 | B27: 3 | C27: =IF(Inputs!B47="Card",Inputs!$B$34,Inputs!$B$35) | D27: =B27*(1+C27) | E27: =D27*$D$5 | F27: =D27*$D$7 | G27: =SUMPRODUCT(B19:H19,$B$15:$H$15) | H27: =E27+F27+G27 | J27: =IF(ISNUMBER(I27),I27,H27)
A28: =Inputs!A48 | B28: 3 | C28: =IF(Inputs!B48="Card",Inputs!$B$34,Inputs!$B$35) | D28: =B28*(1+C28) | E28: =D28*$D$5 | F28: =D28*$D$7 | G28: =SUMPRODUCT(B20:H20,$B$15:$H$15) | H28: =E28+F28+G28 | J28: =IF(ISNUMBER(I28),I28,H28)
A29: =Inputs!A49 | B29: 11 | C29: =IF(Inputs!B49="Card",Inputs!$B$34,Inputs!$B$35) | D29: =B29*(1+C29) | E29: =D29*$D$5 | F29: =D29*$D$7 | G29: =SUMPRODUCT(B21:H21,$B$15:$H$15) | H29: =E29+F29+G29 | J29: =IF(ISNUMBER(I29),I29,H29)
A30: =Inputs!A50 | B30: 11 | C30: =IF(Inputs!B50="Card",Inputs!$B$34,Inputs!$B$35) | D30: =B30*(1+C30) | E30: =D30*$D$5 | F30: =D30*$D$7 | G30: =SUMPRODUCT(B22:H22,$B$15:$H$15) | H30: =E30+F30+G30 | J30: =IF(ISNUMBER(I30),I30,H30)
A31: =Inputs!A51 | B31: 15 | C31: =IF(Inputs!B51="Card",Inputs!$B$34,Inputs!$B$35) | D31: =B31*(1+C31) | E31: =D31*$D$5 | F31: =D31*$D$7 | G31: =SUMPRODUCT(B23:H23,$B$15:$H$15) | H31: =E31+F31+G31 | J31: =IF(ISNUMBER(I31),I31,H31)
A33: Guest free preview (cost with no revenue)
A34: Renders per guest preview | B34: 1
A35: Guest preview cost, computed $ | B35: =B34*$D$6+H15
A36: Guest preview cost, measured $ (CTO paste)
A37: Guest preview cost used $ | B37: =IF(ISNUMBER(B36),B36,B35)
A39: Reference: PLAN.md expects ~$2-4 per book and ~$0.30-0.60 per card. Scenario token multiplier and OpenRouter fee are applied on Unit Economics.

Sheet Opex
A1: Opex - monthly operating costs (fixed + variable, rates from Inputs section 10)
A2: Driver codes: 1 visits, 2 sign-ups, 3 orders, 4 gross revenue ($). One-time launch costs hit month 1.
A4: Line | B4: Driver | C4: Opening | D4: M1 | E4: M2 | F4: M3 | G4: M4 | H4: M5 | I4: M6 | J4: M7 | K4: M8 | L4: M9 | M4: M10 | N4: M11 | O4: M12 | P4: M13 | Q4: M14 | R4: M15 | S4: M16 | T4: M17 | U4: M18 | V4: M19 | W4: M20 | X4: M21 | Y4: M22 | Z4: M23 | AA4: M24 | AB4: M25 | AC4: M26 | AD4: M27 | AE4: M28 | AF4: M29 | AG4: M30 | AH4: M31 | AI4: M32 | AJ4: M33 | AK4: M34 | AL4: M35 | AM4: M36
A5: Month # | D5: =Forecast!D6 | E5: =Forecast!E6 | F5: =Forecast!F6 | G5: =Forecast!G6 | H5: =Forecast!H6 | I5: =Forecast!I6 | J5: =Forecast!J6 | K5: =Forecast!K6 | ... AM5: =Forecast!AM6
A7: =Inputs!A94 | B7: =Inputs!D94 | D7: =Inputs!$B$94+Inputs!$C$94/1000*CHOOSE(Inputs!$D$94,Forecast!D30,Forecast!D35,Forecast!D43,Forecast!D58) | E7: =Inputs!$B$94+Inputs!$C$94/1000*CHOOSE(Inputs!$D$94,Forecast!E30,Forecast!E35,Forecast!E43,Forecast!E58) | F7: =Inputs!$B$94+Inputs!$C$94/1000*CHOOSE(Inputs!$D$94,Forecast!F30,Forecast!F35,Forecast!F43,Forecast!F58) | G7: =Inputs!$B$94+Inputs!$C$94/1000*CHOOSE(Inputs!$D$94,Forecast!G30,Forecast!G35,Forecast!G43,Forecast!G58) | H7: =Inputs!$B$94+Inputs!$C$94/1000*CHOOSE(Inputs!$D$94,Forecast!H30,Forecast!H35,Forecast!H43,Forecast!H58) | I7: =Inputs!$B$94+Inputs!$C$94/1000*CHOOSE(Inputs!$D$94,Forecast!I30,Forecast!I35,Forecast!I43,Forecast!I58) | J7: =Inputs!$B$94+Inputs!$C$94/1000*CHOOSE(Inputs!$D$94,Forecast!J30,Forecast!J35,Forecast!J43,Forecast!J58) | K7: =Inputs!$B$94+Inputs!$C$94/1000*CHOOSE(Inputs!$D$94,Forecast!K30,Forecast!K35,Forecast!K43,Forecast!K58) | ... AM7: =Inputs!$B$94+Inputs!$C$94/1000*CHOOSE(Inputs!$D$94,Forecast!AM30,Forecast!AM35,Forecast!AM43,Forecast!AM58)
A8: =Inputs!A95 | B8: =Inputs!D95 | D8: =Inputs!$B$95+Inputs!$C$95/1000*CHOOSE(Inputs!$D$95,Forecast!D30,Forecast!D35,Forecast!D43,Forecast!D58) | E8: =Inputs!$B$95+Inputs!$C$95/1000*CHOOSE(Inputs!$D$95,Forecast!E30,Forecast!E35,Forecast!E43,Forecast!E58) | F8: =Inputs!$B$95+Inputs!$C$95/1000*CHOOSE(Inputs!$D$95,Forecast!F30,Forecast!F35,Forecast!F43,Forecast!F58) | G8: =Inputs!$B$95+Inputs!$C$95/1000*CHOOSE(Inputs!$D$95,Forecast!G30,Forecast!G35,Forecast!G43,Forecast!G58) | H8: =Inputs!$B$95+Inputs!$C$95/1000*CHOOSE(Inputs!$D$95,Forecast!H30,Forecast!H35,Forecast!H43,Forecast!H58) | I8: =Inputs!$B$95+Inputs!$C$95/1000*CHOOSE(Inputs!$D$95,Forecast!I30,Forecast!I35,Forecast!I43,Forecast!I58) | J8: =Inputs!$B$95+Inputs!$C$95/1000*CHOOSE(Inputs!$D$95,Forecast!J30,Forecast!J35,Forecast!J43,Forecast!J58) | K8: =Inputs!$B$95+Inputs!$C$95/1000*CHOOSE(Inputs!$D$95,Forecast!K30,Forecast!K35,Forecast!K43,Forecast!K58) | ... AM8: =Inputs!$B$95+Inputs!$C$95/1000*CHOOSE(Inputs!$D$95,Forecast!AM30,Forecast!AM35,Forecast!AM43,Forecast!AM58)
A9: =Inputs!A96 | B9: =Inputs!D96 | D9: =Inputs!$B$96+Inputs!$C$96/1000*CHOOSE(Inputs!$D$96,Forecast!D30,Forecast!D35,Forecast!D43,Forecast!D58) | E9: =Inputs!$B$96+Inputs!$C$96/1000*CHOOSE(Inputs!$D$96,Forecast!E30,Forecast!E35,Forecast!E43,Forecast!E58) | F9: =Inputs!$B$96+Inputs!$C$96/1000*CHOOSE(Inputs!$D$96,Forecast!F30,Forecast!F35,Forecast!F43,Forecast!F58) | G9: =Inputs!$B$96+Inputs!$C$96/1000*CHOOSE(Inputs!$D$96,Forecast!G30,Forecast!G35,Forecast!G43,Forecast!G58) | H9: =Inputs!$B$96+Inputs!$C$96/1000*CHOOSE(Inputs!$D$96,Forecast!H30,Forecast!H35,Forecast!H43,Forecast!H58) | I9: =Inputs!$B$96+Inputs!$C$96/1000*CHOOSE(Inputs!$D$96,Forecast!I30,Forecast!I35,Forecast!I43,Forecast!I58) | J9: =Inputs!$B$96+Inputs!$C$96/1000*CHOOSE(Inputs!$D$96,Forecast!J30,Forecast!J35,Forecast!J43,Forecast!J58) | K9: =Inputs!$B$96+Inputs!$C$96/1000*CHOOSE(Inputs!$D$96,Forecast!K30,Forecast!K35,Forecast!K43,Forecast!K58) | ... AM9: =Inputs!$B$96+Inputs!$C$96/1000*CHOOSE(Inputs!$D$96,Forecast!AM30,Forecast!AM35,Forecast!AM43,Forecast!AM58)
A10: =Inputs!A97 | B10: =Inputs!D97 | D10: =Inputs!$B$97+Inputs!$C$97/1000*CHOOSE(Inputs!$D$97,Forecast!D30,Forecast!D35,Forecast!D43,Forecast!D58) | E10: =Inputs!$B$97+Inputs!$C$97/1000*CHOOSE(Inputs!$D$97,Forecast!E30,Forecast!E35,Forecast!E43,Forecast!E58) | F10: =Inputs!$B$97+Inputs!$C$97/1000*CHOOSE(Inputs!$D$97,Forecast!F30,Forecast!F35,Forecast!F43,Forecast!F58) | G10: =Inputs!$B$97+Inputs!$C$97/1000*CHOOSE(Inputs!$D$97,Forecast!G30,Forecast!G35,Forecast!G43,Forecast!G58) | H10: =Inputs!$B$97+Inputs!$C$97/1000*CHOOSE(Inputs!$D$97,Forecast!H30,Forecast!H35,Forecast!H43,Forecast!H58) | I10: =Inputs!$B$97+Inputs!$C$97/1000*CHOOSE(Inputs!$D$97,Forecast!I30,Forecast!I35,Forecast!I43,Forecast!I58) | J10: =Inputs!$B$97+Inputs!$C$97/1000*CHOOSE(Inputs!$D$97,Forecast!J30,Forecast!J35,Forecast!J43,Forecast!J58) | K10: =Inputs!$B$97+Inputs!$C$97/1000*CHOOSE(Inputs!$D$97,Forecast!K30,Forecast!K35,Forecast!K43,Forecast!K58) | ... AM10: =Inputs!$B$97+Inputs!$C$97/1000*CHOOSE(Inputs!$D$97,Forecast!AM30,Forecast!AM35,Forecast!AM43,Forecast!AM58)
A11: =Inputs!A98 | B11: =Inputs!D98 | D11: =Inputs!$B$98+Inputs!$C$98/1000*CHOOSE(Inputs!$D$98,Forecast!D30,Forecast!D35,Forecast!D43,Forecast!D58) | E11: =Inputs!$B$98+Inputs!$C$98/1000*CHOOSE(Inputs!$D$98,Forecast!E30,Forecast!E35,Forecast!E43,Forecast!E58) | F11: =Inputs!$B$98+Inputs!$C$98/1000*CHOOSE(Inputs!$D$98,Forecast!F30,Forecast!F35,Forecast!F43,Forecast!F58) | G11: =Inputs!$B$98+Inputs!$C$98/1000*CHOOSE(Inputs!$D$98,Forecast!G30,Forecast!G35,Forecast!G43,Forecast!G58) | H11: =Inputs!$B$98+Inputs!$C$98/1000*CHOOSE(Inputs!$D$98,Forecast!H30,Forecast!H35,Forecast!H43,Forecast!H58) | I11: =Inputs!$B$98+Inputs!$C$98/1000*CHOOSE(Inputs!$D$98,Forecast!I30,Forecast!I35,Forecast!I43,Forecast!I58) | J11: =Inputs!$B$98+Inputs!$C$98/1000*CHOOSE(Inputs!$D$98,Forecast!J30,Forecast!J35,Forecast!J43,Forecast!J58) | K11: =Inputs!$B$98+Inputs!$C$98/1000*CHOOSE(Inputs!$D$98,Forecast!K30,Forecast!K35,Forecast!K43,Forecast!K58) | ... AM11: =Inputs!$B$98+Inputs!$C$98/1000*CHOOSE(Inputs!$D$98,Forecast!AM30,Forecast!AM35,Forecast!AM43,Forecast!AM58)
A12: =Inputs!A99 | B12: =Inputs!D99 | D12: =Inputs!$B$99+Inputs!$C$99/1000*CHOOSE(Inputs!$D$99,Forecast!D30,Forecast!D35,Forecast!D43,Forecast!D58) | E12: =Inputs!$B$99+Inputs!$C$99/1000*CHOOSE(Inputs!$D$99,Forecast!E30,Forecast!E35,Forecast!E43,Forecast!E58) | F12: =Inputs!$B$99+Inputs!$C$99/1000*CHOOSE(Inputs!$D$99,Forecast!F30,Forecast!F35,Forecast!F43,Forecast!F58) | G12: =Inputs!$B$99+Inputs!$C$99/1000*CHOOSE(Inputs!$D$99,Forecast!G30,Forecast!G35,Forecast!G43,Forecast!G58) | H12: =Inputs!$B$99+Inputs!$C$99/1000*CHOOSE(Inputs!$D$99,Forecast!H30,Forecast!H35,Forecast!H43,Forecast!H58) | I12: =Inputs!$B$99+Inputs!$C$99/1000*CHOOSE(Inputs!$D$99,Forecast!I30,Forecast!I35,Forecast!I43,Forecast!I58) | J12: =Inputs!$B$99+Inputs!$C$99/1000*CHOOSE(Inputs!$D$99,Forecast!J30,Forecast!J35,Forecast!J43,Forecast!J58) | K12: =Inputs!$B$99+Inputs!$C$99/1000*CHOOSE(Inputs!$D$99,Forecast!K30,Forecast!K35,Forecast!K43,Forecast!K58) | ... AM12: =Inputs!$B$99+Inputs!$C$99/1000*CHOOSE(Inputs!$D$99,Forecast!AM30,Forecast!AM35,Forecast!AM43,Forecast!AM58)
A13: =Inputs!A100 | B13: =Inputs!D100 | D13: =Inputs!$B$100+Inputs!$C$100/1000*CHOOSE(Inputs!$D$100,Forecast!D30,Forecast!D35,Forecast!D43,Forecast!D58) | E13: =Inputs!$B$100+Inputs!$C$100/1000*CHOOSE(Inputs!$D$100,Forecast!E30,Forecast!E35,Forecast!E43,Forecast!E58) | F13: =Inputs!$B$100+Inputs!$C$100/1000*CHOOSE(Inputs!$D$100,Forecast!F30,Forecast!F35,Forecast!F43,Forecast!F58) | G13: =Inputs!$B$100+Inputs!$C$100/1000*CHOOSE(Inputs!$D$100,Forecast!G30,Forecast!G35,Forecast!G43,Forecast!G58) | H13: =Inputs!$B$100+Inputs!$C$100/1000*CHOOSE(Inputs!$D$100,Forecast!H30,Forecast!H35,Forecast!H43,Forecast!H58) | I13: =Inputs!$B$100+Inputs!$C$100/1000*CHOOSE(Inputs!$D$100,Forecast!I30,Forecast!I35,Forecast!I43,Forecast!I58) | J13: =Inputs!$B$100+Inputs!$C$100/1000*CHOOSE(Inputs!$D$100,Forecast!J30,Forecast!J35,Forecast!J43,Forecast!J58) | K13: =Inputs!$B$100+Inputs!$C$100/1000*CHOOSE(Inputs!$D$100,Forecast!K30,Forecast!K35,Forecast!K43,Forecast!K58) | ... AM13: =Inputs!$B$100+Inputs!$C$100/1000*CHOOSE(Inputs!$D$100,Forecast!AM30,Forecast!AM35,Forecast!AM43,Forecast!AM58)
A14: =Inputs!A101 | B14: =Inputs!D101 | D14: =Inputs!$B$101+Inputs!$C$101/1000*CHOOSE(Inputs!$D$101,Forecast!D30,Forecast!D35,Forecast!D43,Forecast!D58) | E14: =Inputs!$B$101+Inputs!$C$101/1000*CHOOSE(Inputs!$D$101,Forecast!E30,Forecast!E35,Forecast!E43,Forecast!E58) | F14: =Inputs!$B$101+Inputs!$C$101/1000*CHOOSE(Inputs!$D$101,Forecast!F30,Forecast!F35,Forecast!F43,Forecast!F58) | G14: =Inputs!$B$101+Inputs!$C$101/1000*CHOOSE(Inputs!$D$101,Forecast!G30,Forecast!G35,Forecast!G43,Forecast!G58) | H14: =Inputs!$B$101+Inputs!$C$101/1000*CHOOSE(Inputs!$D$101,Forecast!H30,Forecast!H35,Forecast!H43,Forecast!H58) | I14: =Inputs!$B$101+Inputs!$C$101/1000*CHOOSE(Inputs!$D$101,Forecast!I30,Forecast!I35,Forecast!I43,Forecast!I58) | J14: =Inputs!$B$101+Inputs!$C$101/1000*CHOOSE(Inputs!$D$101,Forecast!J30,Forecast!J35,Forecast!J43,Forecast!J58) | K14: =Inputs!$B$101+Inputs!$C$101/1000*CHOOSE(Inputs!$D$101,Forecast!K30,Forecast!K35,Forecast!K43,Forecast!K58) | ... AM14: =Inputs!$B$101+Inputs!$C$101/1000*CHOOSE(Inputs!$D$101,Forecast!AM30,Forecast!AM35,Forecast!AM43,Forecast!AM58)
A15: =Inputs!A102 | B15: =Inputs!D102 | D15: =Inputs!$B$102+Inputs!$C$102/1000*CHOOSE(Inputs!$D$102,Forecast!D30,Forecast!D35,Forecast!D43,Forecast!D58) | E15: =Inputs!$B$102+Inputs!$C$102/1000*CHOOSE(Inputs!$D$102,Forecast!E30,Forecast!E35,Forecast!E43,Forecast!E58) | F15: =Inputs!$B$102+Inputs!$C$102/1000*CHOOSE(Inputs!$D$102,Forecast!F30,Forecast!F35,Forecast!F43,Forecast!F58) | G15: =Inputs!$B$102+Inputs!$C$102/1000*CHOOSE(Inputs!$D$102,Forecast!G30,Forecast!G35,Forecast!G43,Forecast!G58) | H15: =Inputs!$B$102+Inputs!$C$102/1000*CHOOSE(Inputs!$D$102,Forecast!H30,Forecast!H35,Forecast!H43,Forecast!H58) | I15: =Inputs!$B$102+Inputs!$C$102/1000*CHOOSE(Inputs!$D$102,Forecast!I30,Forecast!I35,Forecast!I43,Forecast!I58) | J15: =Inputs!$B$102+Inputs!$C$102/1000*CHOOSE(Inputs!$D$102,Forecast!J30,Forecast!J35,Forecast!J43,Forecast!J58) | K15: =Inputs!$B$102+Inputs!$C$102/1000*CHOOSE(Inputs!$D$102,Forecast!K30,Forecast!K35,Forecast!K43,Forecast!K58) | ... AM15: =Inputs!$B$102+Inputs!$C$102/1000*CHOOSE(Inputs!$D$102,Forecast!AM30,Forecast!AM35,Forecast!AM43,Forecast!AM58)
A16: =Inputs!A103 | B16: =Inputs!D103 | D16: =Inputs!$B$103+Inputs!$C$103/1000*CHOOSE(Inputs!$D$103,Forecast!D30,Forecast!D35,Forecast!D43,Forecast!D58) | E16: =Inputs!$B$103+Inputs!$C$103/1000*CHOOSE(Inputs!$D$103,Forecast!E30,Forecast!E35,Forecast!E43,Forecast!E58) | F16: =Inputs!$B$103+Inputs!$C$103/1000*CHOOSE(Inputs!$D$103,Forecast!F30,Forecast!F35,Forecast!F43,Forecast!F58) | G16: =Inputs!$B$103+Inputs!$C$103/1000*CHOOSE(Inputs!$D$103,Forecast!G30,Forecast!G35,Forecast!G43,Forecast!G58) | H16: =Inputs!$B$103+Inputs!$C$103/1000*CHOOSE(Inputs!$D$103,Forecast!H30,Forecast!H35,Forecast!H43,Forecast!H58) | I16: =Inputs!$B$103+Inputs!$C$103/1000*CHOOSE(Inputs!$D$103,Forecast!I30,Forecast!I35,Forecast!I43,Forecast!I58) | J16: =Inputs!$B$103+Inputs!$C$103/1000*CHOOSE(Inputs!$D$103,Forecast!J30,Forecast!J35,Forecast!J43,Forecast!J58) | K16: =Inputs!$B$103+Inputs!$C$103/1000*CHOOSE(Inputs!$D$103,Forecast!K30,Forecast!K35,Forecast!K43,Forecast!K58) | ... AM16: =Inputs!$B$103+Inputs!$C$103/1000*CHOOSE(Inputs!$D$103,Forecast!AM30,Forecast!AM35,Forecast!AM43,Forecast!AM58)
A17: =Inputs!A104 | B17: =Inputs!D104 | D17: =Inputs!$B$104+Inputs!$C$104/1000*CHOOSE(Inputs!$D$104,Forecast!D30,Forecast!D35,Forecast!D43,Forecast!D58) | E17: =Inputs!$B$104+Inputs!$C$104/1000*CHOOSE(Inputs!$D$104,Forecast!E30,Forecast!E35,Forecast!E43,Forecast!E58) | F17: =Inputs!$B$104+Inputs!$C$104/1000*CHOOSE(Inputs!$D$104,Forecast!F30,Forecast!F35,Forecast!F43,Forecast!F58) | G17: =Inputs!$B$104+Inputs!$C$104/1000*CHOOSE(Inputs!$D$104,Forecast!G30,Forecast!G35,Forecast!G43,Forecast!G58) | H17: =Inputs!$B$104+Inputs!$C$104/1000*CHOOSE(Inputs!$D$104,Forecast!H30,Forecast!H35,Forecast!H43,Forecast!H58) | I17: =Inputs!$B$104+Inputs!$C$104/1000*CHOOSE(Inputs!$D$104,Forecast!I30,Forecast!I35,Forecast!I43,Forecast!I58) | J17: =Inputs!$B$104+Inputs!$C$104/1000*CHOOSE(Inputs!$D$104,Forecast!J30,Forecast!J35,Forecast!J43,Forecast!J58) | K17: =Inputs!$B$104+Inputs!$C$104/1000*CHOOSE(Inputs!$D$104,Forecast!K30,Forecast!K35,Forecast!K43,Forecast!K58) | ... AM17: =Inputs!$B$104+Inputs!$C$104/1000*CHOOSE(Inputs!$D$104,Forecast!AM30,Forecast!AM35,Forecast!AM43,Forecast!AM58)
A18: =Inputs!A105 | B18: =Inputs!D105 | D18: =Inputs!$B$105+Inputs!$C$105/1000*CHOOSE(Inputs!$D$105,Forecast!D30,Forecast!D35,Forecast!D43,Forecast!D58) | E18: =Inputs!$B$105+Inputs!$C$105/1000*CHOOSE(Inputs!$D$105,Forecast!E30,Forecast!E35,Forecast!E43,Forecast!E58) | F18: =Inputs!$B$105+Inputs!$C$105/1000*CHOOSE(Inputs!$D$105,Forecast!F30,Forecast!F35,Forecast!F43,Forecast!F58) | G18: =Inputs!$B$105+Inputs!$C$105/1000*CHOOSE(Inputs!$D$105,Forecast!G30,Forecast!G35,Forecast!G43,Forecast!G58) | H18: =Inputs!$B$105+Inputs!$C$105/1000*CHOOSE(Inputs!$D$105,Forecast!H30,Forecast!H35,Forecast!H43,Forecast!H58) | I18: =Inputs!$B$105+Inputs!$C$105/1000*CHOOSE(Inputs!$D$105,Forecast!I30,Forecast!I35,Forecast!I43,Forecast!I58) | J18: =Inputs!$B$105+Inputs!$C$105/1000*CHOOSE(Inputs!$D$105,Forecast!J30,Forecast!J35,Forecast!J43,Forecast!J58) | K18: =Inputs!$B$105+Inputs!$C$105/1000*CHOOSE(Inputs!$D$105,Forecast!K30,Forecast!K35,Forecast!K43,Forecast!K58) | ... AM18: =Inputs!$B$105+Inputs!$C$105/1000*CHOOSE(Inputs!$D$105,Forecast!AM30,Forecast!AM35,Forecast!AM43,Forecast!AM58)
A19: Total operating costs | D19: =SUM(D7:D18) | E19: =SUM(E7:E18) | F19: =SUM(F7:F18) | G19: =SUM(G7:G18) | H19: =SUM(H7:H18) | I19: =SUM(I7:I18) | J19: =SUM(J7:J18) | K19: =SUM(K7:K18) | ... AM19: =SUM(AM7:AM18)
A21: One-time launch costs | D21: =IF(D5=1,SUM(Inputs!$B$109:$B$111),0) | E21: =IF(E5=1,SUM(Inputs!$B$109:$B$111),0) | F21: =IF(F5=1,SUM(Inputs!$B$109:$B$111),0) | G21: =IF(G5=1,SUM(Inputs!$B$109:$B$111),0) | H21: =IF(H5=1,SUM(Inputs!$B$109:$B$111),0) | I21: =IF(I5=1,SUM(Inputs!$B$109:$B$111),0) | J21: =IF(J5=1,SUM(Inputs!$B$109:$B$111),0) | K21: =IF(K5=1,SUM(Inputs!$B$109:$B$111),0) | ... AM21: =IF(AM5=1,SUM(Inputs!$B$109:$B$111),0)

Sheet Forecast
A1: Forecast - 36 months (selected scenario)
A3: ="Scenario: "&Scenarios!B3
A4: Line | B4: Unit | C4: Opening | D4: M1 | E4: M2 | F4: M3 | G4: M4 | H4: M5 | I4: M6 | J4: M7 | K4: M8 | L4: M9 | M4: M10 | N4: M11 | O4: M12 | P4: M13 | Q4: M14 | R4: M15 | S4: M16 | T4: M17 | U4: M18 | V4: M19 | W4: M20 | X4: M21 | Y4: M22 | Z4: M23 | AA4: M24 | AB4: M25 | AC4: M26 | AD4: M27 | AE4: M28 | AF4: M29 | AG4: M30 | AH4: M31 | AI4: M32 | AJ4: M33 | AK4: M34 | AL4: M35 | AM4: M36 | AO4: Year 1 | AP4: Year 2 | AQ4: Year 3
A5: TIMELINE
A6: Month # | B6: # | C6: 0 | D6: =C6+1 | E6: =D6+1 | F6: =E6+1 | G6: =F6+1 | H6: =G6+1 | I6: =H6+1 | J6: =I6+1 | K6: =J6+1 | ... AM6: =AL6+1
A7: Month | B7: date | D7: =EDATE(Inputs!$B$7,D6-1) | E7: =EDATE(Inputs!$B$7,E6-1) | F7: =EDATE(Inputs!$B$7,F6-1) | G7: =EDATE(Inputs!$B$7,G6-1) | H7: =EDATE(Inputs!$B$7,H6-1) | I7: =EDATE(Inputs!$B$7,I6-1) | J7: =EDATE(Inputs!$B$7,J6-1) | K7: =EDATE(Inputs!$B$7,K6-1) | ... AM7: =EDATE(Inputs!$B$7,AM6-1)
A8: Calendar month | B8: 1-12 | D8: =MONTH(D7) | E8: =MONTH(E7) | F8: =MONTH(F7) | G8: =MONTH(G7) | H8: =MONTH(H7) | I8: =MONTH(I7) | J8: =MONTH(J7) | K8: =MONTH(K7) | ... AM8: =MONTH(AM7)
A9: Seasonality index | B9: x | D9: =INDEX(Inputs!$B$68:$B$79,D8) | E9: =INDEX(Inputs!$B$68:$B$79,E8) | F9: =INDEX(Inputs!$B$68:$B$79,F8) | G9: =INDEX(Inputs!$B$68:$B$79,G8) | H9: =INDEX(Inputs!$B$68:$B$79,H8) | I9: =INDEX(Inputs!$B$68:$B$79,I8) | J9: =INDEX(Inputs!$B$68:$B$79,J8) | K9: =INDEX(Inputs!$B$68:$B$79,K8) | ... AM9: =INDEX(Inputs!$B$68:$B$79,AM8) | AO9: =AVERAGE(D9:O9) | AP9: =AVERAGE(P9:AA9) | AQ9: =AVERAGE(AB9:AM9)
A10: Conversion seasonality | B10: x | D10: =1+(D9-1)*Inputs!$B$16 | E10: =1+(E9-1)*Inputs!$B$16 | F10: =1+(F9-1)*Inputs!$B$16 | G10: =1+(G9-1)*Inputs!$B$16 | H10: =1+(H9-1)*Inputs!$B$16 | I10: =1+(I9-1)*Inputs!$B$16 | J10: =1+(J9-1)*Inputs!$B$16 | K10: =1+(K9-1)*Inputs!$B$16 | ... AM10: =1+(AM9-1)*Inputs!$B$16 | AO10: =AVERAGE(D10:O10) | AP10: =AVERAGE(P10:AA10) | AQ10: =AVERAGE(AB10:AM10)
A11: MARKETING BUDGET (drives paid traffic)
A12: Total marketing budget | B12: $ | D12: =MIN(Inputs!$B$28,Inputs!$B$26*(1+Inputs!$B$27)^(D6-1))*Scenarios!$B$12*(1+Inputs!$B$29*(D9-1)) | E12: =MIN(Inputs!$B$28,Inputs!$B$26*(1+Inputs!$B$27)^(E6-1))*Scenarios!$B$12*(1+Inputs!$B$29*(E9-1)) | F12: =MIN(Inputs!$B$28,Inputs!$B$26*(1+Inputs!$B$27)^(F6-1))*Scenarios!$B$12*(1+Inputs!$B$29*(F9-1)) | G12: =MIN(Inputs!$B$28,Inputs!$B$26*(1+Inputs!$B$27)^(G6-1))*Scenarios!$B$12*(1+Inputs!$B$29*(G9-1)) | H12: =MIN(Inputs!$B$28,Inputs!$B$26*(1+Inputs!$B$27)^(H6-1))*Scenarios!$B$12*(1+Inputs!$B$29*(H9-1)) | I12: =MIN(Inputs!$B$28,Inputs!$B$26*(1+Inputs!$B$27)^(I6-1))*Scenarios!$B$12*(1+Inputs!$B$29*(I9-1)) | J12: =MIN(Inputs!$B$28,Inputs!$B$26*(1+Inputs!$B$27)^(J6-1))*Scenarios!$B$12*(1+Inputs!$B$29*(J9-1)) | K12: =MIN(Inputs!$B$28,Inputs!$B$26*(1+Inputs!$B$27)^(K6-1))*Scenarios!$B$12*(1+Inputs!$B$29*(K9-1)) | ... AM12: =MIN(Inputs!$B$28,Inputs!$B$26*(1+Inputs!$B$27)^(AM6-1))*Scenarios!$B$12*(1+Inputs!$B$29*(AM9-1)) | AO12: =SUM(D12:O12) | AP12: =SUM(P12:AA12) | AQ12: =SUM(AB12:AM12)
A13: =" Budget - "&Inputs!A57 | B13: $ | D13: =D12*'Unit Economics'!$B$15 | E13: =E12*'Unit Economics'!$B$15 | F13: =F12*'Unit Economics'!$B$15 | G13: =G12*'Unit Economics'!$B$15 | H13: =H12*'Unit Economics'!$B$15 | I13: =I12*'Unit Economics'!$B$15 | J13: =J12*'Unit Economics'!$B$15 | K13: =K12*'Unit Economics'!$B$15 | ... AM13: =AM12*'Unit Economics'!$B$15 | AO13: =SUM(D13:O13) | AP13: =SUM(P13:AA13) | AQ13: =SUM(AB13:AM13)
A14: =" Budget - "&Inputs!A58 | B14: $ | D14: =D12*'Unit Economics'!$B$16 | E14: =E12*'Unit Economics'!$B$16 | F14: =F12*'Unit Economics'!$B$16 | G14: =G12*'Unit Economics'!$B$16 | H14: =H12*'Unit Economics'!$B$16 | I14: =I12*'Unit Economics'!$B$16 | J14: =J12*'Unit Economics'!$B$16 | K14: =K12*'Unit Economics'!$B$16 | ... AM14: =AM12*'Unit Economics'!$B$16 | AO14: =SUM(D14:O14) | AP14: =SUM(P14:AA14) | AQ14: =SUM(AB14:AM14)
A15: =" Budget - "&Inputs!A59 | B15: $ | D15: =D12*'Unit Economics'!$B$17 | E15: =E12*'Unit Economics'!$B$17 | F15: =F12*'Unit Economics'!$B$17 | G15: =G12*'Unit Economics'!$B$17 | H15: =H12*'Unit Economics'!$B$17 | I15: =I12*'Unit Economics'!$B$17 | J15: =J12*'Unit Economics'!$B$17 | K15: =K12*'Unit Economics'!$B$17 | ... AM15: =AM12*'Unit Economics'!$B$17 | AO15: =SUM(D15:O15) | AP15: =SUM(P15:AA15) | AQ15: =SUM(AB15:AM15)
A16: =" Budget - "&Inputs!A60 | B16: $ | D16: =D12*'Unit Economics'!$B$18 | E16: =E12*'Unit Economics'!$B$18 | F16: =F12*'Unit Economics'!$B$18 | G16: =G12*'Unit Economics'!$B$18 | H16: =H12*'Unit Economics'!$B$18 | I16: =I12*'Unit Economics'!$B$18 | J16: =J12*'Unit Economics'!$B$18 | K16: =K12*'Unit Economics'!$B$18 | ... AM16: =AM12*'Unit Economics'!$B$18 | AO16: =SUM(D16:O16) | AP16: =SUM(P16:AA16) | AQ16: =SUM(AB16:AM16)
A17: =" Budget - "&Inputs!A61 | B17: $ | D17: =D12*'Unit Economics'!$B$19 | E17: =E12*'Unit Economics'!$B$19 | F17: =F12*'Unit Economics'!$B$19 | G17: =G12*'Unit Economics'!$B$19 | H17: =H12*'Unit Economics'!$B$19 | I17: =I12*'Unit Economics'!$B$19 | J17: =J12*'Unit Economics'!$B$19 | K17: =K12*'Unit Economics'!$B$19 | ... AM17: =AM12*'Unit Economics'!$B$19 | AO17: =SUM(D17:O17) | AP17: =SUM(P17:AA17) | AQ17: =SUM(AB17:AM17)
A18: =" Budget - "&Inputs!A62 | B18: $ | D18: =D12*'Unit Economics'!$B$20 | E18: =E12*'Unit Economics'!$B$20 | F18: =F12*'Unit Economics'!$B$20 | G18: =G12*'Unit Economics'!$B$20 | H18: =H12*'Unit Economics'!$B$20 | I18: =I12*'Unit Economics'!$B$20 | J18: =J12*'Unit Economics'!$B$20 | K18: =K12*'Unit Economics'!$B$20 | ... AM18: =AM12*'Unit Economics'!$B$20 | AO18: =SUM(D18:O18) | AP18: =SUM(P18:AA18) | AQ18: =SUM(AB18:AM18)
A19: TRAFFIC (visits)
A20: =" Paid visits - "&Inputs!A57 | B20: visits | D20: =IFERROR(D13/'Unit Economics'!$C$15,0) | E20: =IFERROR(E13/'Unit Economics'!$C$15,0) | F20: =IFERROR(F13/'Unit Economics'!$C$15,0) | G20: =IFERROR(G13/'Unit Economics'!$C$15,0) | H20: =IFERROR(H13/'Unit Economics'!$C$15,0) | I20: =IFERROR(I13/'Unit Economics'!$C$15,0) | J20: =IFERROR(J13/'Unit Economics'!$C$15,0) | K20: =IFERROR(K13/'Unit Economics'!$C$15,0) | ... AM20: =IFERROR(AM13/'Unit Economics'!$C$15,0) | AO20: =SUM(D20:O20) | AP20: =SUM(P20:AA20) | AQ20: =SUM(AB20:AM20)
A21: =" Paid visits - "&Inputs!A58 | B21: visits | D21: =IFERROR(D14/'Unit Economics'!$C$16,0) | E21: =IFERROR(E14/'Unit Economics'!$C$16,0) | F21: =IFERROR(F14/'Unit Economics'!$C$16,0) | G21: =IFERROR(G14/'Unit Economics'!$C$16,0) | H21: =IFERROR(H14/'Unit Economics'!$C$16,0) | I21: =IFERROR(I14/'Unit Economics'!$C$16,0) | J21: =IFERROR(J14/'Unit Economics'!$C$16,0) | K21: =IFERROR(K14/'Unit Economics'!$C$16,0) | ... AM21: =IFERROR(AM14/'Unit Economics'!$C$16,0) | AO21: =SUM(D21:O21) | AP21: =SUM(P21:AA21) | AQ21: =SUM(AB21:AM21)
A22: =" Paid visits - "&Inputs!A59 | B22: visits | D22: =IFERROR(D15/'Unit Economics'!$C$17,0) | E22: =IFERROR(E15/'Unit Economics'!$C$17,0) | F22: =IFERROR(F15/'Unit Economics'!$C$17,0) | G22: =IFERROR(G15/'Unit Economics'!$C$17,0) | H22: =IFERROR(H15/'Unit Economics'!$C$17,0) | I22: =IFERROR(I15/'Unit Economics'!$C$17,0) | J22: =IFERROR(J15/'Unit Economics'!$C$17,0) | K22: =IFERROR(K15/'Unit Economics'!$C$17,0) | ... AM22: =IFERROR(AM15/'Unit Economics'!$C$17,0) | AO22: =SUM(D22:O22) | AP22: =SUM(P22:AA22) | AQ22: =SUM(AB22:AM22)
A23: =" Paid visits - "&Inputs!A60 | B23: visits | D23: =IFERROR(D16/'Unit Economics'!$C$18,0) | E23: =IFERROR(E16/'Unit Economics'!$C$18,0) | F23: =IFERROR(F16/'Unit Economics'!$C$18,0) | G23: =IFERROR(G16/'Unit Economics'!$C$18,0) | H23: =IFERROR(H16/'Unit Economics'!$C$18,0) | I23: =IFERROR(I16/'Unit Economics'!$C$18,0) | J23: =IFERROR(J16/'Unit Economics'!$C$18,0) | K23: =IFERROR(K16/'Unit Economics'!$C$18,0) | ... AM23: =IFERROR(AM16/'Unit Economics'!$C$18,0) | AO23: =SUM(D23:O23) | AP23: =SUM(P23:AA23) | AQ23: =SUM(AB23:AM23)
A24: =" Paid visits - "&Inputs!A61 | B24: visits | D24: =IFERROR(D17/'Unit Economics'!$C$19,0) | E24: =IFERROR(E17/'Unit Economics'!$C$19,0) | F24: =IFERROR(F17/'Unit Economics'!$C$19,0) | G24: =IFERROR(G17/'Unit Economics'!$C$19,0) | H24: =IFERROR(H17/'Unit Economics'!$C$19,0) | I24: =IFERROR(I17/'Unit Economics'!$C$19,0) | J24: =IFERROR(J17/'Unit Economics'!$C$19,0) | K24: =IFERROR(K17/'Unit Economics'!$C$19,0) | ... AM24: =IFERROR(AM17/'Unit Economics'!$C$19,0) | AO24: =SUM(D24:O24) | AP24: =SUM(P24:AA24) | AQ24: =SUM(AB24:AM24)
A25: =" Paid visits - "&Inputs!A62 | B25: visits | D25: =IFERROR(D18/'Unit Economics'!$C$20,0) | E25: =IFERROR(E18/'Unit Economics'!$C$20,0) | F25: =IFERROR(F18/'Unit Economics'!$C$20,0) | G25: =IFERROR(G18/'Unit Economics'!$C$20,0) | H25: =IFERROR(H18/'Unit Economics'!$C$20,0) | I25: =IFERROR(I18/'Unit Economics'!$C$20,0) | J25: =IFERROR(J18/'Unit Economics'!$C$20,0) | K25: =IFERROR(K18/'Unit Economics'!$C$20,0) | ... AM25: =IFERROR(AM18/'Unit Economics'!$C$20,0) | AO25: =SUM(D25:O25) | AP25: =SUM(P25:AA25) | AQ25: =SUM(AB25:AM25)
A26: Paid visits (budget / CPC) | B26: visits | D26: =SUM(D20:D25) | E26: =SUM(E20:E25) | F26: =SUM(F20:F25) | G26: =SUM(G20:G25) | H26: =SUM(H20:H25) | I26: =SUM(I20:I25) | J26: =SUM(J20:J25) | K26: =SUM(K20:K25) | ... AM26: =SUM(AM20:AM25) | AO26: =SUM(D26:O26) | AP26: =SUM(P26:AA26) | AQ26: =SUM(AB26:AM26)
A27: Organic trend (pre-season) | B27: visits | D27: =IF(D6=1,Inputs!$B$20,C27*(1+Inputs!$B$21*Inputs!$B$22^(D6-1))) | E27: =IF(E6=1,Inputs!$B$20,D27*(1+Inputs!$B$21*Inputs!$B$22^(E6-1))) | F27: =IF(F6=1,Inputs!$B$20,E27*(1+Inputs!$B$21*Inputs!$B$22^(F6-1))) | G27: =IF(G6=1,Inputs!$B$20,F27*(1+Inputs!$B$21*Inputs!$B$22^(G6-1))) | H27: =IF(H6=1,Inputs!$B$20,G27*(1+Inputs!$B$21*Inputs!$B$22^(H6-1))) | I27: =IF(I6=1,Inputs!$B$20,H27*(1+Inputs!$B$21*Inputs!$B$22^(I6-1))) | J27: =IF(J6=1,Inputs!$B$20,I27*(1+Inputs!$B$21*Inputs!$B$22^(J6-1))) | K27: =IF(K6=1,Inputs!$B$20,J27*(1+Inputs!$B$21*Inputs!$B$22^(K6-1))) | ... AM27: =IF(AM6=1,Inputs!$B$20,AL27*(1+Inputs!$B$21*Inputs!$B$22^(AM6-1)))
A28: Organic visits | B28: visits | D28: =D27*D9*Scenarios!$B$7 | E28: =E27*E9*Scenarios!$B$7 | F28: =F27*F9*Scenarios!$B$7 | G28: =G27*G9*Scenarios!$B$7 | H28: =H27*H9*Scenarios!$B$7 | I28: =I27*I9*Scenarios!$B$7 | J28: =J27*J9*Scenarios!$B$7 | K28: =K27*K9*Scenarios!$B$7 | ... AM28: =AM27*AM9*Scenarios!$B$7 | AO28: =SUM(D28:O28) | AP28: =SUM(P28:AA28) | AQ28: =SUM(AB28:AM28)
A29: Referral visits (recipients of prior month's items) | B29: visits | D29: =C44*Inputs!$B$23*Scenarios!$B$7 | E29: =D44*Inputs!$B$23*Scenarios!$B$7 | F29: =E44*Inputs!$B$23*Scenarios!$B$7 | G29: =F44*Inputs!$B$23*Scenarios!$B$7 | H29: =G44*Inputs!$B$23*Scenarios!$B$7 | I29: =H44*Inputs!$B$23*Scenarios!$B$7 | J29: =I44*Inputs!$B$23*Scenarios!$B$7 | K29: =J44*Inputs!$B$23*Scenarios!$B$7 | ... AM29: =AL44*Inputs!$B$23*Scenarios!$B$7 | AO29: =SUM(D29:O29) | AP29: =SUM(P29:AA29) | AQ29: =SUM(AB29:AM29)
A30: Total visits | B30: visits | D30: =D26+D28+D29 | E30: =E26+E28+E29 | F30: =F26+F28+F29 | G30: =G26+G28+G29 | H30: =H26+H28+H29 | I30: =I26+I28+I29 | J30: =J26+J28+J29 | K30: =K26+K28+K29 | ... AM30: =AM26+AM28+AM29 | AO30: =SUM(D30:O30) | AP30: =SUM(P30:AA30) | AQ30: =SUM(AB30:AM30)
A31: FUNNEL
A32: Guest free previews (cost, no revenue) | B32: # | D32: =D30*Inputs!$B$15 | E32: =E30*Inputs!$B$15 | F32: =F30*Inputs!$B$15 | G32: =G30*Inputs!$B$15 | H32: =H30*Inputs!$B$15 | I32: =I30*Inputs!$B$15 | J32: =J30*Inputs!$B$15 | K32: =K30*Inputs!$B$15 | ... AM32: =AM30*Inputs!$B$15 | AO32: =SUM(D32:O32) | AP32: =SUM(P32:AA32) | AQ32: =SUM(AB32:AM32)
A33: Sign-ups from paid | B33: # | D33: =SUMPRODUCT(D20:D25,'Unit Economics'!$E$15:$E$20) | E33: =SUMPRODUCT(E20:E25,'Unit Economics'!$E$15:$E$20) | F33: =SUMPRODUCT(F20:F25,'Unit Economics'!$E$15:$E$20) | G33: =SUMPRODUCT(G20:G25,'Unit Economics'!$E$15:$E$20) | H33: =SUMPRODUCT(H20:H25,'Unit Economics'!$E$15:$E$20) | I33: =SUMPRODUCT(I20:I25,'Unit Economics'!$E$15:$E$20) | J33: =SUMPRODUCT(J20:J25,'Unit Economics'!$E$15:$E$20) | K33: =SUMPRODUCT(K20:K25,'Unit Economics'!$E$15:$E$20) | ... AM33: =SUMPRODUCT(AM20:AM25,'Unit Economics'!$E$15:$E$20) | AO33: =SUM(D33:O33) | AP33: =SUM(P33:AA33) | AQ33: =SUM(AB33:AM33)
A34: Sign-ups from organic + referral | B34: # | D34: =Inputs!$B$12*(D28+D29) | E34: =Inputs!$B$12*(E28+E29) | F34: =Inputs!$B$12*(F28+F29) | G34: =Inputs!$B$12*(G28+G29) | H34: =Inputs!$B$12*(H28+H29) | I34: =Inputs!$B$12*(I28+I29) | J34: =Inputs!$B$12*(J28+J29) | K34: =Inputs!$B$12*(K28+K29) | ... AM34: =Inputs!$B$12*(AM28+AM29) | AO34: =SUM(D34:O34) | AP34: =SUM(P34:AA34) | AQ34: =SUM(AB34:AM34)
A35: Sign-ups | B35: # | D35: =D33+D34 | E35: =E33+E34 | F35: =F33+F34 | G35: =G33+G34 | H35: =H33+H34 | I35: =I33+I34 | J35: =J33+J34 | K35: =K33+K34 | ... AM35: =AM33+AM34 | AO35: =SUM(D35:O35) | AP35: =SUM(P35:AA35) | AQ35: =SUM(AB35:AM35)
A36: Creator starts | B36: # | D36: =D35*Inputs!$B$13 | E36: =E35*Inputs!$B$13 | F36: =F35*Inputs!$B$13 | G36: =G35*Inputs!$B$13 | H36: =H35*Inputs!$B$13 | I36: =I35*Inputs!$B$13 | J36: =J35*Inputs!$B$13 | K36: =K35*Inputs!$B$13 | ... AM36: =AM35*Inputs!$B$13 | AO36: =SUM(D36:O36) | AP36: =SUM(P36:AA36) | AQ36: =SUM(AB36:AM36)
A37: Conversion factor (scenario x season) | B37: x | D37: =Scenarios!$B$8*D10 | E37: =Scenarios!$B$8*E10 | F37: =Scenarios!$B$8*F10 | G37: =Scenarios!$B$8*G10 | H37: =Scenarios!$B$8*H10 | I37: =Scenarios!$B$8*I10 | J37: =Scenarios!$B$8*J10 | K37: =Scenarios!$B$8*K10 | ... AM37: =Scenarios!$B$8*AM10 | AO37: =AVERAGE(D37:O37) | AP37: =AVERAGE(P37:AA37) | AQ37: =AVERAGE(AB37:AM37)
A38: New-customer orders from paid | B38: # | D38: =SUMPRODUCT(D20:D25,'Unit Economics'!$E$15:$E$20,Inputs!$H$57:$H$62)*D37 | E38: =SUMPRODUCT(E20:E25,'Unit Economics'!$E$15:$E$20,Inputs!$H$57:$H$62)*E37 | F38: =SUMPRODUCT(F20:F25,'Unit Economics'!$E$15:$E$20,Inputs!$H$57:$H$62)*F37 | G38: =SUMPRODUCT(G20:G25,'Unit Economics'!$E$15:$E$20,Inputs!$H$57:$H$62)*G37 | H38: =SUMPRODUCT(H20:H25,'Unit Economics'!$E$15:$E$20,Inputs!$H$57:$H$62)*H37 | I38: =SUMPRODUCT(I20:I25,'Unit Economics'!$E$15:$E$20,Inputs!$H$57:$H$62)*I37 | J38: =SUMPRODUCT(J20:J25,'Unit Economics'!$E$15:$E$20,Inputs!$H$57:$H$62)*J37 | K38: =SUMPRODUCT(K20:K25,'Unit Economics'!$E$15:$E$20,Inputs!$H$57:$H$62)*K37 | ... AM38: =SUMPRODUCT(AM20:AM25,'Unit Economics'!$E$15:$E$20,Inputs!$H$57:$H$62)*AM37 | AO38: =SUM(D38:O38) | AP38: =SUM(P38:AA38) | AQ38: =SUM(AB38:AM38)
A39: New-customer orders from organic + referral | B39: # | D39: =D34*Inputs!$B$13*Inputs!$B$14*D37 | E39: =E34*Inputs!$B$13*Inputs!$B$14*E37 | F39: =F34*Inputs!$B$13*Inputs!$B$14*F37 | G39: =G34*Inputs!$B$13*Inputs!$B$14*G37 | H39: =H34*Inputs!$B$13*Inputs!$B$14*H37 | I39: =I34*Inputs!$B$13*Inputs!$B$14*I37 | J39: =J34*Inputs!$B$13*Inputs!$B$14*J37 | K39: =K34*Inputs!$B$13*Inputs!$B$14*K37 | ... AM39: =AM34*Inputs!$B$13*Inputs!$B$14*AM37 | AO39: =SUM(D39:O39) | AP39: =SUM(P39:AA39) | AQ39: =SUM(AB39:AM39)
A40: New-customer orders | B40: # | D40: =D38+D39 | E40: =E38+E39 | F40: =F38+F39 | G40: =G38+G39 | H40: =H38+H39 | I40: =I38+I39 | J40: =J38+J39 | K40: =K38+K39 | ... AM40: =AM38+AM39 | AO40: =SUM(D40:O40) | AP40: =SUM(P40:AA40) | AQ40: =SUM(AB40:AM40)
A41: Cumulative customers | B41: # | C41: 0 | D41: =C41+D40 | E41: =D41+E40 | F41: =E41+F40 | G41: =F41+G40 | H41: =G41+H40 | I41: =H41+I40 | J41: =I41+J40 | K41: =J41+K40 | ... AM41: =AL41+AM40 | AO41: =O41 | AP41: =AA41 | AQ41: =AM41
A42: Repeat orders | B42: # | D42: =C41*Inputs!$B$32/12*Scenarios!$B$9*D9 | E42: =D41*Inputs!$B$32/12*Scenarios!$B$9*E9 | F42: =E41*Inputs!$B$32/12*Scenarios!$B$9*F9 | G42: =F41*Inputs!$B$32/12*Scenarios!$B$9*G9 | H42: =G41*Inputs!$B$32/12*Scenarios!$B$9*H9 | I42: =H41*Inputs!$B$32/12*Scenarios!$B$9*I9 | J42: =I41*Inputs!$B$32/12*Scenarios!$B$9*J9 | K42: =J41*Inputs!$B$32/12*Scenarios!$B$9*K9 | ... AM42: =AL41*Inputs!$B$32/12*Scenarios!$B$9*AM9 | AO42: =SUM(D42:O42) | AP42: =SUM(P42:AA42) | AQ42: =SUM(AB42:AM42)
A43: Total orders | B43: # | D43: =D40+D42 | E43: =E40+E42 | F43: =F40+F42 | G43: =G40+G42 | H43: =H40+H42 | I43: =I40+I42 | J43: =J40+J42 | K43: =K40+K42 | ... AM43: =AM40+AM42 | AO43: =SUM(D43:O43) | AP43: =SUM(P43:AA43) | AQ43: =SUM(AB43:AM43)
A44: Items sold | B44: # | C44: 0 | D44: =D43*Inputs!$B$9 | E44: =E43*Inputs!$B$9 | F44: =F43*Inputs!$B$9 | G44: =G43*Inputs!$B$9 | H44: =H43*Inputs!$B$9 | I44: =I43*Inputs!$B$9 | J44: =J43*Inputs!$B$9 | K44: =K43*Inputs!$B$9 | ... AM44: =AM43*Inputs!$B$9 | AO44: =SUM(D44:O44) | AP44: =SUM(P44:AA44) | AQ44: =SUM(AB44:AM44)
A45: Visit -> new order conversion | B45: % | D45: =IFERROR(D40/D30,0) | E45: =IFERROR(E40/E30,0) | F45: =IFERROR(F40/F30,0) | G45: =IFERROR(G40/G30,0) | H45: =IFERROR(H40/H30,0) | I45: =IFERROR(I40/I30,0) | J45: =IFERROR(J40/J30,0) | K45: =IFERROR(K40/K30,0) | ... AM45: =IFERROR(AM40/AM30,0) | AO45: =IFERROR(AO40/AO30,0) | AP45: =IFERROR(AP40/AP30,0) | AQ45: =IFERROR(AQ40/AQ30,0)
A46: ITEMS BY SKU (product mix)
A47: =" Items - "&Inputs!A47 | B47: # | D47: =D44*Inputs!$G$47 | E47: =E44*Inputs!$G$47 | F47: =F44*Inputs!$G$47 | G47: =G44*Inputs!$G$47 | H47: =H44*Inputs!$G$47 | I47: =I44*Inputs!$G$47 | J47: =J44*Inputs!$G$47 | K47: =K44*Inputs!$G$47 | ... AM47: =AM44*Inputs!$G$47 | AO47: =SUM(D47:O47) | AP47: =SUM(P47:AA47) | AQ47: =SUM(AB47:AM47)
A48: =" Items - "&Inputs!A48 | B48: # | D48: =D44*Inputs!$G$48 | E48: =E44*Inputs!$G$48 | F48: =F44*Inputs!$G$48 | G48: =G44*Inputs!$G$48 | H48: =H44*Inputs!$G$48 | I48: =I44*Inputs!$G$48 | J48: =J44*Inputs!$G$48 | K48: =K44*Inputs!$G$48 | ... AM48: =AM44*Inputs!$G$48 | AO48: =SUM(D48:O48) | AP48: =SUM(P48:AA48) | AQ48: =SUM(AB48:AM48)
A49: =" Items - "&Inputs!A49 | B49: # | D49: =D44*Inputs!$G$49 | E49: =E44*Inputs!$G$49 | F49: =F44*Inputs!$G$49 | G49: =G44*Inputs!$G$49 | H49: =H44*Inputs!$G$49 | I49: =I44*Inputs!$G$49 | J49: =J44*Inputs!$G$49 | K49: =K44*Inputs!$G$49 | ... AM49: =AM44*Inputs!$G$49 | AO49: =SUM(D49:O49) | AP49: =SUM(P49:AA49) | AQ49: =SUM(AB49:AM49)
A50: =" Items - "&Inputs!A50 | B50: # | D50: =D44*Inputs!$G$50 | E50: =E44*Inputs!$G$50 | F50: =F44*Inputs!$G$50 | G50: =G44*Inputs!$G$50 | H50: =H44*Inputs!$G$50 | I50: =I44*Inputs!$G$50 | J50: =J44*Inputs!$G$50 | K50: =K44*Inputs!$G$50 | ... AM50: =AM44*Inputs!$G$50 | AO50: =SUM(D50:O50) | AP50: =SUM(P50:AA50) | AQ50: =SUM(AB50:AM50)
A51: =" Items - "&Inputs!A51 | B51: # | D51: =D44*Inputs!$G$51 | E51: =E44*Inputs!$G$51 | F51: =F44*Inputs!$G$51 | G51: =G44*Inputs!$G$51 | H51: =H44*Inputs!$G$51 | I51: =I44*Inputs!$G$51 | J51: =J44*Inputs!$G$51 | K51: =K44*Inputs!$G$51 | ... AM51: =AM44*Inputs!$G$51 | AO51: =SUM(D51:O51) | AP51: =SUM(P51:AA51) | AQ51: =SUM(AB51:AM51)
A52: REVENUE BY SKU (gross incl. postage)
A53: =" Revenue - "&Inputs!A47 | B53: $ | D53: =D47*'Unit Economics'!$D$5 | E53: =E47*'Unit Economics'!$D$5 | F53: =F47*'Unit Economics'!$D$5 | G53: =G47*'Unit Economics'!$D$5 | H53: =H47*'Unit Economics'!$D$5 | I53: =I47*'Unit Economics'!$D$5 | J53: =J47*'Unit Economics'!$D$5 | K53: =K47*'Unit Economics'!$D$5 | ... AM53: =AM47*'Unit Economics'!$D$5 | AO53: =SUM(D53:O53) | AP53: =SUM(P53:AA53) | AQ53: =SUM(AB53:AM53)
A54: =" Revenue - "&Inputs!A48 | B54: $ | D54: =D48*'Unit Economics'!$D$6 | E54: =E48*'Unit Economics'!$D$6 | F54: =F48*'Unit Economics'!$D$6 | G54: =G48*'Unit Economics'!$D$6 | H54: =H48*'Unit Economics'!$D$6 | I54: =I48*'Unit Economics'!$D$6 | J54: =J48*'Unit Economics'!$D$6 | K54: =K48*'Unit Economics'!$D$6 | ... AM54: =AM48*'Unit Economics'!$D$6 | AO54: =SUM(D54:O54) | AP54: =SUM(P54:AA54) | AQ54: =SUM(AB54:AM54)
A55: =" Revenue - "&Inputs!A49 | B55: $ | D55: =D49*'Unit Economics'!$D$7 | E55: =E49*'Unit Economics'!$D$7 | F55: =F49*'Unit Economics'!$D$7 | G55: =G49*'Unit Economics'!$D$7 | H55: =H49*'Unit Economics'!$D$7 | I55: =I49*'Unit Economics'!$D$7 | J55: =J49*'Unit Economics'!$D$7 | K55: =K49*'Unit Economics'!$D$7 | ... AM55: =AM49*'Unit Economics'!$D$7 | AO55: =SUM(D55:O55) | AP55: =SUM(P55:AA55) | AQ55: =SUM(AB55:AM55)
A56: =" Revenue - "&Inputs!A50 | B56: $ | D56: =D50*'Unit Economics'!$D$8 | E56: =E50*'Unit Economics'!$D$8 | F56: =F50*'Unit Economics'!$D$8 | G56: =G50*'Unit Economics'!$D$8 | H56: =H50*'Unit Economics'!$D$8 | I56: =I50*'Unit Economics'!$D$8 | J56: =J50*'Unit Economics'!$D$8 | K56: =K50*'Unit Economics'!$D$8 | ... AM56: =AM50*'Unit Economics'!$D$8 | AO56: =SUM(D56:O56) | AP56: =SUM(P56:AA56) | AQ56: =SUM(AB56:AM56)
A57: =" Revenue - "&Inputs!A51 | B57: $ | D57: =D51*'Unit Economics'!$D$9 | E57: =E51*'Unit Economics'!$D$9 | F57: =F51*'Unit Economics'!$D$9 | G57: =G51*'Unit Economics'!$D$9 | H57: =H51*'Unit Economics'!$D$9 | I57: =I51*'Unit Economics'!$D$9 | J57: =J51*'Unit Economics'!$D$9 | K57: =K51*'Unit Economics'!$D$9 | ... AM57: =AM51*'Unit Economics'!$D$9 | AO57: =SUM(D57:O57) | AP57: =SUM(P57:AA57) | AQ57: =SUM(AB57:AM57)
A58: Gross revenue | B58: $ | D58: =SUM(D53:D57) | E58: =SUM(E53:E57) | F58: =SUM(F53:F57) | G58: =SUM(G53:G57) | H58: =SUM(H53:H57) | I58: =SUM(I53:I57) | J58: =SUM(J53:J57) | K58: =SUM(K53:K57) | ... AM58: =SUM(AM53:AM57) | AO58: =SUM(D58:O58) | AP58: =SUM(P58:AA58) | AQ58: =SUM(AB58:AM58)
A59: Less: refunds | B59: $ | D59: =-SUMPRODUCT(D47:D51,'Unit Economics'!$E$5:$E$9) | E59: =-SUMPRODUCT(E47:E51,'Unit Economics'!$E$5:$E$9) | F59: =-SUMPRODUCT(F47:F51,'Unit Economics'!$E$5:$E$9) | G59: =-SUMPRODUCT(G47:G51,'Unit Economics'!$E$5:$E$9) | H59: =-SUMPRODUCT(H47:H51,'Unit Economics'!$E$5:$E$9) | I59: =-SUMPRODUCT(I47:I51,'Unit Economics'!$E$5:$E$9) | J59: =-SUMPRODUCT(J47:J51,'Unit Economics'!$E$5:$E$9) | K59: =-SUMPRODUCT(K47:K51,'Unit Economics'!$E$5:$E$9) | ... AM59: =-SUMPRODUCT(AM47:AM51,'Unit Economics'!$E$5:$E$9) | AO59: =SUM(D59:O59) | AP59: =SUM(P59:AA59) | AQ59: =SUM(AB59:AM59)
A60: Net revenue | B60: $ | D60: =D58+D59 | E60: =E58+E59 | F60: =F58+F59 | G60: =G58+G59 | H60: =H58+H59 | I60: =I58+I59 | J60: =J58+J59 | K60: =K58+K59 | ... AM60: =AM58+AM59 | AO60: =SUM(D60:O60) | AP60: =SUM(P60:AA60) | AQ60: =SUM(AB60:AM60)
A61: COST OF GOODS SOLD
A62: Tokens - paid items (renders + text) | B62: $ | D62: =SUMPRODUCT(D47:D51,'Unit Economics'!$G$5:$G$9) | E62: =SUMPRODUCT(E47:E51,'Unit Economics'!$G$5:$G$9) | F62: =SUMPRODUCT(F47:F51,'Unit Economics'!$G$5:$G$9) | G62: =SUMPRODUCT(G47:G51,'Unit Economics'!$G$5:$G$9) | H62: =SUMPRODUCT(H47:H51,'Unit Economics'!$G$5:$G$9) | I62: =SUMPRODUCT(I47:I51,'Unit Economics'!$G$5:$G$9) | J62: =SUMPRODUCT(J47:J51,'Unit Economics'!$G$5:$G$9) | K62: =SUMPRODUCT(K47:K51,'Unit Economics'!$G$5:$G$9) | ... AM62: =SUMPRODUCT(AM47:AM51,'Unit Economics'!$G$5:$G$9) | AO62: =SUM(D62:O62) | AP62: =SUM(P62:AA62) | AQ62: =SUM(AB62:AM62)
A63: Tokens - guest free previews (no revenue) | B63: $ | D63: =D32*'Model Costs'!$B$37*Scenarios!$B$10*(1+Inputs!$B$42) | E63: =E32*'Model Costs'!$B$37*Scenarios!$B$10*(1+Inputs!$B$42) | F63: =F32*'Model Costs'!$B$37*Scenarios!$B$10*(1+Inputs!$B$42) | G63: =G32*'Model Costs'!$B$37*Scenarios!$B$10*(1+Inputs!$B$42) | H63: =H32*'Model Costs'!$B$37*Scenarios!$B$10*(1+Inputs!$B$42) | I63: =I32*'Model Costs'!$B$37*Scenarios!$B$10*(1+Inputs!$B$42) | J63: =J32*'Model Costs'!$B$37*Scenarios!$B$10*(1+Inputs!$B$42) | K63: =K32*'Model Costs'!$B$37*Scenarios!$B$10*(1+Inputs!$B$42) | ... AM63: =AM32*'Model Costs'!$B$37*Scenarios!$B$10*(1+Inputs!$B$42) | AO63: =SUM(D63:O63) | AP63: =SUM(P63:AA63) | AQ63: =SUM(AB63:AM63)
A64: Tokens - abandoned drafts (started, not bought) | B64: $ | D64: =MAX(0,D36-D40)*Inputs!$B$17*'Unit Economics'!$G$10 | E64: =MAX(0,E36-E40)*Inputs!$B$17*'Unit Economics'!$G$10 | F64: =MAX(0,F36-F40)*Inputs!$B$17*'Unit Economics'!$G$10 | G64: =MAX(0,G36-G40)*Inputs!$B$17*'Unit Economics'!$G$10 | H64: =MAX(0,H36-H40)*Inputs!$B$17*'Unit Economics'!$G$10 | I64: =MAX(0,I36-I40)*Inputs!$B$17*'Unit Economics'!$G$10 | J64: =MAX(0,J36-J40)*Inputs!$B$17*'Unit Economics'!$G$10 | K64: =MAX(0,K36-K40)*Inputs!$B$17*'Unit Economics'!$G$10 | ... AM64: =MAX(0,AM36-AM40)*Inputs!$B$17*'Unit Economics'!$G$10 | AO64: =SUM(D64:O64) | AP64: =SUM(P64:AA64) | AQ64: =SUM(AB64:AM64)
A65: Print cost | B65: $ | D65: =SUMPRODUCT(D47:D51,'Unit Economics'!$H$5:$H$9) | E65: =SUMPRODUCT(E47:E51,'Unit Economics'!$H$5:$H$9) | F65: =SUMPRODUCT(F47:F51,'Unit Economics'!$H$5:$H$9) | G65: =SUMPRODUCT(G47:G51,'Unit Economics'!$H$5:$H$9) | H65: =SUMPRODUCT(H47:H51,'Unit Economics'!$H$5:$H$9) | I65: =SUMPRODUCT(I47:I51,'Unit Economics'!$H$5:$H$9) | J65: =SUMPRODUCT(J47:J51,'Unit Economics'!$H$5:$H$9) | K65: =SUMPRODUCT(K47:K51,'Unit Economics'!$H$5:$H$9) | ... AM65: =SUMPRODUCT(AM47:AM51,'Unit Economics'!$H$5:$H$9) | AO65: =SUM(D65:O65) | AP65: =SUM(P65:AA65) | AQ65: =SUM(AB65:AM65)
A66: Shipping cost | B66: $ | D66: =SUMPRODUCT(D47:D51,'Unit Economics'!$I$5:$I$9) | E66: =SUMPRODUCT(E47:E51,'Unit Economics'!$I$5:$I$9) | F66: =SUMPRODUCT(F47:F51,'Unit Economics'!$I$5:$I$9) | G66: =SUMPRODUCT(G47:G51,'Unit Economics'!$I$5:$I$9) | H66: =SUMPRODUCT(H47:H51,'Unit Economics'!$I$5:$I$9) | I66: =SUMPRODUCT(I47:I51,'Unit Economics'!$I$5:$I$9) | J66: =SUMPRODUCT(J47:J51,'Unit Economics'!$I$5:$I$9) | K66: =SUMPRODUCT(K47:K51,'Unit Economics'!$I$5:$I$9) | ... AM66: =SUMPRODUCT(AM47:AM51,'Unit Economics'!$I$5:$I$9) | AO66: =SUM(D66:O66) | AP66: =SUM(P66:AA66) | AQ66: =SUM(AB66:AM66)
A67: Reprint allowance | B67: $ | D67: =SUMPRODUCT(D47:D51,'Unit Economics'!$J$5:$J$9) | E67: =SUMPRODUCT(E47:E51,'Unit Economics'!$J$5:$J$9) | F67: =SUMPRODUCT(F47:F51,'Unit Economics'!$J$5:$J$9) | G67: =SUMPRODUCT(G47:G51,'Unit Economics'!$J$5:$J$9) | H67: =SUMPRODUCT(H47:H51,'Unit Economics'!$J$5:$J$9) | I67: =SUMPRODUCT(I47:I51,'Unit Economics'!$J$5:$J$9) | J67: =SUMPRODUCT(J47:J51,'Unit Economics'!$J$5:$J$9) | K67: =SUMPRODUCT(K47:K51,'Unit Economics'!$J$5:$J$9) | ... AM67: =SUMPRODUCT(AM47:AM51,'Unit Economics'!$J$5:$J$9) | AO67: =SUM(D67:O67) | AP67: =SUM(P67:AA67) | AQ67: =SUM(AB67:AM67)
A68: Stripe fees (2.9% + $0.30) | B68: $ | D68: =SUMPRODUCT(D47:D51,'Unit Economics'!$K$5:$K$9) | E68: =SUMPRODUCT(E47:E51,'Unit Economics'!$K$5:$K$9) | F68: =SUMPRODUCT(F47:F51,'Unit Economics'!$K$5:$K$9) | G68: =SUMPRODUCT(G47:G51,'Unit Economics'!$K$5:$K$9) | H68: =SUMPRODUCT(H47:H51,'Unit Economics'!$K$5:$K$9) | I68: =SUMPRODUCT(I47:I51,'Unit Economics'!$K$5:$K$9) | J68: =SUMPRODUCT(J47:J51,'Unit Economics'!$K$5:$K$9) | K68: =SUMPRODUCT(K47:K51,'Unit Economics'!$K$5:$K$9) | ... AM68: =SUMPRODUCT(AM47:AM51,'Unit Economics'!$K$5:$K$9) | AO68: =SUM(D68:O68) | AP68: =SUM(P68:AA68) | AQ68: =SUM(AB68:AM68)
A69: Dispute allowance | B69: $ | D69: =SUMPRODUCT(D47:D51,'Unit Economics'!$L$5:$L$9) | E69: =SUMPRODUCT(E47:E51,'Unit Economics'!$L$5:$L$9) | F69: =SUMPRODUCT(F47:F51,'Unit Economics'!$L$5:$L$9) | G69: =SUMPRODUCT(G47:G51,'Unit Economics'!$L$5:$L$9) | H69: =SUMPRODUCT(H47:H51,'Unit Economics'!$L$5:$L$9) | I69: =SUMPRODUCT(I47:I51,'Unit Economics'!$L$5:$L$9) | J69: =SUMPRODUCT(J47:J51,'Unit Economics'!$L$5:$L$9) | K69: =SUMPRODUCT(K47:K51,'Unit Economics'!$L$5:$L$9) | ... AM69: =SUMPRODUCT(AM47:AM51,'Unit Economics'!$L$5:$L$9) | AO69: =SUM(D69:O69) | AP69: =SUM(P69:AA69) | AQ69: =SUM(AB69:AM69)
A70: Total COGS | B70: $ | D70: =SUM(D62:D69) | E70: =SUM(E62:E69) | F70: =SUM(F62:F69) | G70: =SUM(G62:G69) | H70: =SUM(H62:H69) | I70: =SUM(I62:I69) | J70: =SUM(J62:J69) | K70: =SUM(K62:K69) | ... AM70: =SUM(AM62:AM69) | AO70: =SUM(D70:O70) | AP70: =SUM(P70:AA70) | AQ70: =SUM(AB70:AM70)
A71: Gross profit | B71: $ | D71: =D60-D70 | E71: =E60-E70 | F71: =F60-F70 | G71: =G60-G70 | H71: =H60-H70 | I71: =I60-I70 | J71: =J60-J70 | K71: =K60-K70 | ... AM71: =AM60-AM70 | AO71: =SUM(D71:O71) | AP71: =SUM(P71:AA71) | AQ71: =SUM(AB71:AM71)
A72: Gross margin | B72: % | D72: =IFERROR(D71/D60,0) | E72: =IFERROR(E71/E60,0) | F72: =IFERROR(F71/F60,0) | G72: =IFERROR(G71/G60,0) | H72: =IFERROR(H71/H60,0) | I72: =IFERROR(I71/I60,0) | J72: =IFERROR(J71/J60,0) | K72: =IFERROR(K71/K60,0) | ... AM72: =IFERROR(AM71/AM60,0) | AO72: =IFERROR(AO71/AO60,0) | AP72: =IFERROR(AP71/AP60,0) | AQ72: =IFERROR(AQ71/AQ60,0)
A73: OPERATING RESULT
A74: Marketing | B74: $ | D74: =D12 | E74: =E12 | F74: =F12 | G74: =G12 | H74: =H12 | I74: =I12 | J74: =J12 | K74: =K12 | ... AM74: =AM12 | AO74: =SUM(D74:O74) | AP74: =SUM(P74:AA74) | AQ74: =SUM(AB74:AM74)
A75: Operating costs (Opex sheet) | B75: $ | D75: =Opex!D19 | E75: =Opex!E19 | F75: =Opex!F19 | G75: =Opex!G19 | H75: =Opex!H19 | I75: =Opex!I19 | J75: =Opex!J19 | K75: =Opex!K19 | ... AM75: =Opex!AM19 | AO75: =SUM(D75:O75) | AP75: =SUM(P75:AA75) | AQ75: =SUM(AB75:AM75)
A76: One-time launch costs | B76: $ | D76: =Opex!D21 | E76: =Opex!E21 | F76: =Opex!F21 | G76: =Opex!G21 | H76: =Opex!H21 | I76: =Opex!I21 | J76: =Opex!J21 | K76: =Opex!K21 | ... AM76: =Opex!AM21 | AO76: =SUM(D76:O76) | AP76: =SUM(P76:AA76) | AQ76: =SUM(AB76:AM76)
A77: Net income (pre-tax) | B77: $ | D77: =D71-D74-D75-D76 | E77: =E71-E74-E75-E76 | F77: =F71-F74-F75-F76 | G77: =G71-G74-G75-G76 | H77: =H71-H74-H75-H76 | I77: =I71-I74-I75-I76 | J77: =J71-J74-J75-J76 | K77: =K71-K74-K75-K76 | ... AM77: =AM71-AM74-AM75-AM76 | AO77: =SUM(D77:O77) | AP77: =SUM(P77:AA77) | AQ77: =SUM(AB77:AM77)
A78: Net margin | B78: % | D78: =IFERROR(D77/D60,0) | E78: =IFERROR(E77/E60,0) | F78: =IFERROR(F77/F60,0) | G78: =IFERROR(G77/G60,0) | H78: =IFERROR(H77/H60,0) | I78: =IFERROR(I77/I60,0) | J78: =IFERROR(J77/J60,0) | K78: =IFERROR(K77/K60,0) | ... AM78: =IFERROR(AM77/AM60,0) | AO78: =IFERROR(AO77/AO60,0) | AP78: =IFERROR(AP77/AP60,0) | AQ78: =IFERROR(AQ77/AQ60,0)
A79: Cumulative net income | B79: $ | C79: 0 | D79: =C79+D77 | E79: =D79+E77 | F79: =E79+F77 | G79: =F79+G77 | H79: =G79+H77 | I79: =H79+I77 | J79: =I79+J77 | K79: =J79+K77 | ... AM79: =AL79+AM77 | AO79: =O79 | AP79: =AA79 | AQ79: =AM79
A80: Cumulative cash balance | B80: $ | C80: =Inputs!$B$8 | D80: =C80+D77 | E80: =D80+E77 | F80: =E80+F77 | G80: =F80+G77 | H80: =G80+H77 | I80: =H80+I77 | J80: =I80+J77 | K80: =J80+K77 | ... AM80: =AL80+AM77 | AO80: =O80 | AP80: =AA80 | AQ80: =AM80
A81: KPIs AND BREAK-EVEN TESTS
A82: Blended CAC (marketing / new customers) | B82: $ | D82: =IFERROR(D74/D40,0) | E82: =IFERROR(E74/E40,0) | F82: =IFERROR(F74/F40,0) | G82: =IFERROR(G74/G40,0) | H82: =IFERROR(H74/H40,0) | I82: =IFERROR(I74/I40,0) | J82: =IFERROR(J74/J40,0) | K82: =IFERROR(K74/K40,0) | ... AM82: =IFERROR(AM74/AM40,0) | AO82: =IFERROR(AO74/AO40,0) | AP82: =IFERROR(AP74/AP40,0) | AQ82: =IFERROR(AQ74/AQ40,0)
A83: Trailing 3-month net income | B83: $ | D83: =SUM(D77:D77) | E83: =SUM(D77:E77) | F83: =SUM(D77:F77) | G83: =SUM(E77:G77) | H83: =SUM(F77:H77) | I83: =SUM(G77:I77) | J83: =SUM(H77:J77) | K83: =SUM(I77:K77) | L83: =SUM(J77:L77) | M83: =SUM(K77:M77) | ... AM83: =SUM(AK77:AM77)
A84: Flag: month net income >= 0 | B84: month | D84: =IF(D77>=0,D6,"") | E84: =IF(E77>=0,E6,"") | F84: =IF(F77>=0,F6,"") | G84: =IF(G77>=0,G6,"") | H84: =IF(H77>=0,H6,"") | I84: =IF(I77>=0,I6,"") | J84: =IF(J77>=0,J6,"") | K84: =IF(K77>=0,K6,"") | ... AM84: =IF(AM77>=0,AM6,"")
A85: Flag: sustained (all later T3M >= 0) | B85: month | D85: =IF(MIN(D83:$AM83)>=0,D6,"") | E85: =IF(MIN(E83:$AM83)>=0,E6,"") | F85: =IF(MIN(F83:$AM83)>=0,F6,"") | G85: =IF(MIN(G83:$AM83)>=0,G6,"") | H85: =IF(MIN(H83:$AM83)>=0,H6,"") | I85: =IF(MIN(I83:$AM83)>=0,I6,"") | J85: =IF(MIN(J83:$AM83)>=0,J6,"") | K85: =IF(MIN(K83:$AM83)>=0,K6,"") | ... AM85: =IF(MIN(AM83:$AM83)>=0,AM6,"")
A86: Flag: cumulative net income >= 0 | B86: month | D86: =IF(D79>=0,D6,"") | E86: =IF(E79>=0,E6,"") | F86: =IF(F79>=0,F6,"") | G86: =IF(G79>=0,G6,"") | H86: =IF(H79>=0,H6,"") | I86: =IF(I79>=0,I6,"") | J86: =IF(J79>=0,J6,"") | K86: =IF(K79>=0,K6,"") | ... AM86: =IF(AM79>=0,AM6,"")

Sheet Scenarios
A1: Scenarios - selector drives the whole model
A3: Select scenario | B3: Base | C3: <- choose Low / Base / High (only control cell outside Inputs)
A4: Scenario index (1=Low, 2=Base, 3=High) | B4: =MATCH(B3,Inputs!$C$83:$E$83,0)
A6: Active lever | B6: Active value
A7: Organic traffic multiplier | B7: =INDEX(Inputs!$C$84:$E$84,$B$4)
A8: Purchase conversion multiplier | B8: =INDEX(Inputs!$C$85:$E$85,$B$4)
A9: Repeat purchase multiplier | B9: =INDEX(Inputs!$C$86:$E$86,$B$4)
A10: Token cost multiplier | B10: =INDEX(Inputs!$C$87:$E$87,$B$4)
A11: Refund / reprint multiplier | B11: =INDEX(Inputs!$C$88:$E$88,$B$4)
A12: Marketing budget multiplier | B12: =INDEX(Inputs!$C$89:$E$89,$B$4)
A13: Print + shipping cost multiplier | B13: =INDEX(Inputs!$C$90:$E$90,$B$4)
A15: Headline KPIs (selected scenario) | B15: Value | C15: Note
A16: Break-even month (sustained: trailing-3M profit stays >= 0) | B16: =IF(COUNT(Forecast!$D$85:$AM$85)=0,"Not within 36 mo",MIN(Forecast!$D$85:$AM$85)) | C16: Month # from launch
A17: First profitable month | B17: =IF(COUNT(Forecast!$D$84:$AM$84)=0,"Not within 36 mo",MIN(Forecast!$D$84:$AM$84)) | C17: May be a seasonal one-off
A18: Cash payback month (cumulative net income >= 0) | B18: =IF(COUNT(Forecast!$D$86:$AM$86)=0,"Not within 36 mo",MIN(Forecast!$D$86:$AM$86))
A19: Month 12 net revenue | B19: =Forecast!O60
A20: Month 12 net income | B20: =Forecast!O77
A21: Month 36 net revenue | B21: =Forecast!AM60
A22: Month 36 net income | B22: =Forecast!AM77
A23: Year 1 net revenue | B23: =Forecast!AO60
A24: Year 1 net income | B24: =Forecast!AO77
A25: Year 3 net revenue | B25: =Forecast!AQ60
A26: Year 3 net income | B26: =Forecast!AQ77
A27: Cash balance, month 36 | B27: =Forecast!AM80
A28: Lowest cash balance | B28: =MIN(Forecast!C80:AM80)
A29: Peak funding need (opening cash minus lowest cash) | B29: =MAX(0,Inputs!$B$8-$B$28)
A30: Total orders, 36 months | B30: =SUM(Forecast!$D$43:$AM$43)
A31: Blended CAC, 36 months ($ per new customer) | B31: =IFERROR(SUM(Forecast!$D$74:$AM$74)/SUM(Forecast!$D$40:$AM$40),0)
A32: Paid CAC, steady state ($) | B32: ='Unit Economics'!$B$28
A33: LTV per customer (contribution $) | B33: ='Unit Economics'!$B$25
A34: LTV : blended CAC | B34: =IFERROR($B$33/$B$31,0) | C34: Healthy >= 3x
A35: LTV : paid CAC | B35: =IFERROR($B$33/$B$32,0)
A36: Blended contribution margin per order ($) | B36: ='Unit Economics'!$B$23
A37: Gross margin, Year 3 | B37: =Forecast!AQ72
A38: Guest preview cost, 36 months ($, no revenue) | B38: =SUM(Forecast!$D$63:$AM$63)

Sheet Dashboard
A1: GreetHub - Dashboard
A2: ="Scenario: "&Scenarios!B3&" (change on Scenarios sheet)"
A4: KPI | B4: Value
A5: Break-even month (sustained) | B5: =Scenarios!$B$16
A6: Cash payback month | B6: =Scenarios!$B$18
A7: Month 12 net revenue | B7: =Scenarios!$B$19
A8: Month 12 net income | B8: =Scenarios!$B$20
A9: Month 36 net revenue | B9: =Scenarios!$B$21
A10: Month 36 net income | B10: =Scenarios!$B$22
A11: Cash balance, month 36 | B11: =Scenarios!$B$27
A12: Peak funding need | B12: =Scenarios!$B$29
A13: Blended CAC | B13: =Scenarios!$B$31
A14: LTV per customer | B14: =Scenarios!$B$33
A15: LTV : blended CAC | B15: =Scenarios!$B$34
A16: Orders, 36 months | B16: =Scenarios!$B$30
A18: Annual summary | B18: Year 1 | C18: Year 2 | D18: Year 3
A19: Visits | B19: =Forecast!AO30 | C19: =Forecast!AP30 | D19: =Forecast!AQ30
A20: New-customer orders | B20: =Forecast!AO40 | C20: =Forecast!AP40 | D20: =Forecast!AQ40
A21: Total orders | B21: =Forecast!AO43 | C21: =Forecast!AP43 | D21: =Forecast!AQ43
A22: Net revenue | B22: =Forecast!AO60 | C22: =Forecast!AP60 | D22: =Forecast!AQ60
A23: Gross profit | B23: =Forecast!AO71 | C23: =Forecast!AP71 | D23: =Forecast!AQ71
A24: Marketing | B24: =Forecast!AO74 | C24: =Forecast!AP74 | D24: =Forecast!AQ74
A25: Operating costs | B25: =Forecast!AO75 | C25: =Forecast!AP75 | D25: =Forecast!AQ75
A26: Net income | B26: =Forecast!AO77 | C26: =Forecast!AP77 | D26: =Forecast!AQ77
A27: Ending cash | B27: =Forecast!AO80 | C27: =Forecast!AP80 | D27: =Forecast!AQ80
A29: Contribution margin per item | B29: CM $ | C29: CM %
A30: ='Unit Economics'!A5 | B30: ='Unit Economics'!N5 | C30: ='Unit Economics'!O5
A31: ='Unit Economics'!A6 | B31: ='Unit Economics'!N6 | C31: ='Unit Economics'!O6
A32: ='Unit Economics'!A7 | B32: ='Unit Economics'!N7 | C32: ='Unit Economics'!O7
A33: ='Unit Economics'!A8 | B33: ='Unit Economics'!N8 | C33: ='Unit Economics'!O8
A34: ='Unit Economics'!A9 | B34: ='Unit Economics'!N9 | C34: ='Unit Economics'!O9
